{
  "type": "Feature",
  "properties": {
    "gn:admin1_code":"6.0",
    "gn:admin2_code":"18147.0",
    "gn:asciiname":"Gomez Cue",
    "gn:country_code":"AR",
    "gn:dem":78,
    "gn:feature_class":"P",
    "gn:feature_code":"PPL",
    "gn:name":"G\u00f3mez Cu\u00e9",
    "gn:population":0,
    "gn:timezone":"America/Argentina/Cordoba",
    "iso:country":"AR",
    "wof:name":"Gomez Cue",
    "wof:placetype":"locality"
},
  "geometry": {"coordinates":[-56.53699,-28.329],"type":"Point"}
}