{
  "type": "Feature",
  "properties": {
    "gn:admin1_code":"24.0",
    "gn:admin2_code":"90105.0",
    "gn:asciiname":"Ingenio San Jose",
    "gn:country_code":"AR",
    "gn:dem":498,
    "gn:feature_class":"P",
    "gn:feature_code":"PPL",
    "gn:name":"Ingenio San Jos\u00e9",
    "gn:population":0,
    "gn:timezone":"America/Argentina/Tucuman",
    "iso:country":"AR",
    "wof:name":"Ingenio San Jose",
    "wof:placetype":"locality"
},
  "geometry": {"coordinates":[-65.23333000000001,-26.78333],"type":"Point"}
}