{
  "type": "Feature",
  "properties": {
    "gn:admin1_code":"18",
    "gn:admin2_code":"70084.0",
    "gn:asciiname":"Barrio Rivadavia",
    "gn:country_code":"AR",
    "gn:dem":650,
    "gn:feature_class":"P",
    "gn:feature_code":"PPL",
    "gn:name":"Barrio Rivadavia",
    "gn:population":0,
    "gn:timezone":"America/Argentina/San_Juan",
    "iso:country":"AR",
    "wof:name":"Barrio Rivadavia",
    "wof:placetype":"locality"
},
  "geometry": {"coordinates":[-68.55,-31.55],"type":"Point"}
}