{
  "type": "Feature",
  "properties": {
    "gn:admin1_code":"20",
    "gn:admin2_code":"78021.0",
    "gn:asciiname":"Capitan Eyroa",
    "gn:country_code":"AR",
    "gn:dem":164,
    "gn:feature_class":"P",
    "gn:feature_code":"PPL",
    "gn:name":"Capit\u00e1n Eyroa",
    "gn:population":0,
    "gn:timezone":"America/Argentina/Rio_Gallegos",
    "iso:country":"AR",
    "wof:name":"Capitan Eyroa",
    "wof:placetype":"locality"
},
  "geometry": {"coordinates":[-70.09999999999999,-51.75],"type":"Point"}
}