{
  "type": "Feature",
  "properties": {
    "gn:admin1_code":"04",
    "gn:admin2_code":"26035.0",
    "gn:asciiname":"Arroyo Pescado",
    "gn:country_code":"AR",
    "gn:dem":574,
    "gn:feature_class":"P",
    "gn:feature_code":"PPL",
    "gn:name":"Arroyo Pescado",
    "gn:population":0,
    "gn:timezone":"America/Argentina/Catamarca",
    "iso:country":"AR",
    "wof:name":"Arroyo Pescado",
    "wof:placetype":"locality"
},
  "geometry": {"coordinates":[-70.78426999999998,-43.00201],"type":"Point"}
}