{
  "type": "Feature",
  "properties": {
    "gn:admin1_code":"22.0",
    "gn:admin2_code":"86140.0",
    "gn:asciiname":"Paso a Paso",
    "gn:country_code":"AR",
    "gn:dem":95,
    "gn:feature_class":"P",
    "gn:feature_code":"PPL",
    "gn:name":"Paso a Paso",
    "gn:population":0,
    "gn:timezone":"America/Argentina/Cordoba",
    "iso:country":"AR",
    "wof:name":"Paso a Paso",
    "wof:placetype":"locality"
},
  "geometry": {"coordinates":[-63.31667,-29.21667],"type":"Point"}
}