{
  "type": "Feature",
  "properties": {
    "gn:admin1_code":"5.0",
    "gn:admin2_code":"14133.0",
    "gn:asciiname":"La Ramada",
    "gn:country_code":"AR",
    "gn:dem":814,
    "gn:feature_class":"P",
    "gn:feature_code":"PPL",
    "gn:name":"La Ramada",
    "gn:population":0,
    "gn:timezone":"America/Argentina/Cordoba",
    "iso:country":"AR",
    "wof:name":"La Ramada",
    "wof:placetype":"locality"
},
  "geometry": {"coordinates":[-65.03588000000001,-32.29616],"type":"Point"}
}