{
  "type": "Feature",
  "properties": {
    "gn:admin1_code":"8.0",
    "gn:admin2_code":"30015.0",
    "gn:asciiname":"Osvaldo Magnasco",
    "gn:country_code":"AR",
    "gn:dem":51,
    "gn:feature_class":"P",
    "gn:feature_code":"PPL",
    "gn:name":"Osvaldo Magnasco",
    "gn:population":0,
    "gn:timezone":"America/Argentina/Cordoba",
    "iso:country":"AR",
    "name:und_x_variant":[
        "O. Magnasco",
        "Osvaldo Magnasco"
    ],
    "wof:name":"Osvaldo Magnasco",
    "wof:placetype":"locality"
},
  "geometry": {"coordinates":[-58.05729,-31.31237],"type":"Point"}
}