{
  "type": "Feature",
  "properties": {
    "gn:admin1_code":"24.0",
    "gn:admin2_code":"90091.0",
    "gn:asciiname":"Yalapa",
    "gn:country_code":"AR",
    "gn:dem":282,
    "gn:feature_class":"P",
    "gn:feature_code":"PPL",
    "gn:name":"Yalapa",
    "gn:population":0,
    "gn:timezone":"America/Argentina/Cordoba",
    "iso:country":"AR",
    "wof:name":"Yalapa",
    "wof:placetype":"locality"
},
  "geometry": {"coordinates":[-65.05168,-27.46578],"type":"Point"}
}