{
  "type": "Feature",
  "properties": {
    "iso:country":"AR",
    "name:arn_x_preferred":[
        "Centenario"
    ],
    "name:ceb_x_preferred":[
        "Centenario"
    ],
    "name:eng_x_preferred":[
        "Centenario"
    ],
    "name:fra_x_preferred":[
        "Centenario"
    ],
    "name:hye_x_preferred":[
        "\u054d\u0565\u0576\u057f\u0565\u0576\u0561\u0580\u056b\u0578"
    ],
    "name:nld_x_preferred":[
        "Centenario"
    ],
    "name:pol_x_preferred":[
        "Centenario"
    ],
    "name:por_x_preferred":[
        "Centenario"
    ],
    "name:rus_x_preferred":[
        "\u0421\u0435\u043d\u0442\u0435\u043d\u0430\u0440\u0438\u043e"
    ],
    "name:spa_x_preferred":[
        "Centenario"
    ],
    "name:swe_x_preferred":[
        "Centenario"
    ],
    "name:ukr_x_preferred":[
        "\u0421\u0435\u043d\u0442\u0435\u043d\u0430\u0440\u0456\u043e"
    ],
    "name:und_x_variant":[
        "Colonia Centenario"
    ],
    "qs:gn_country":"AR",
    "qs:gn_fcode":"PPL",
    "qs:gn_pop":28956,
    "qs:name":"Centenario",
    "qs:name_adm0":"Argentina",
    "qs:name_adm1":"Neuqu\u00e9n",
    "qs:photos":735,
    "qs:photos_1k":149,
    "qs:photos_9k":3,
    "qs:photos_9r":5,
    "qs:photos_all":735,
    "qs:photos_sr":8,
    "qs:placetype":"Town",
    "qs:pop_sr":"7",
    "qs:woe_adm0":23424747,
    "wd:wordcount":17,
    "wof:name":"Centenario",
    "wof:placetype":"locality",
    "wof:population":28956
},
  "geometry": {"coordinates":[-68.1318,-38.82955],"type":"Point"}
}