{
  "type": "Feature",
  "properties": {
    "gn:admin1_code":"22",
    "gn:admin2_code":"86042.0",
    "gn:asciiname":"Bandera",
    "gn:country_code":"AR",
    "gn:dem":97,
    "gn:feature_class":"P",
    "gn:feature_code":"PPLA2",
    "gn:name":"Bandera",
    "gn:population":0,
    "gn:timezone":"America/Argentina/Cordoba",
    "iso:country":"AR",
    "name:deu_x_preferred":[
        "Bandera"
    ],
    "name:fra_x_preferred":[
        "Bandera"
    ],
    "name:ita_x_preferred":[
        "Bandera"
    ],
    "name:mlg_x_preferred":[
        "Bandera"
    ],
    "name:nld_x_preferred":[
        "Bandera"
    ],
    "name:spa_x_preferred":[
        "Bandera"
    ],
    "name:zho_x_preferred":[
        "\u73ed\u5fb7\u62c9"
    ],
    "wof:name":"Bandera",
    "wof:placetype":"locality"
},
  "geometry": {"coordinates":[-62.26600000000001,-28.8884],"type":"Point"}
}