{
  "type": "Feature",
  "properties": {
    "gn:admin1_code":"17.0",
    "gn:admin2_code":"66133.0",
    "gn:asciiname":"Pluma del Pato",
    "gn:country_code":"AR",
    "gn:dem":232,
    "gn:feature_class":"P",
    "gn:feature_code":"PPL",
    "gn:name":"Pluma del Pato",
    "gn:population":0,
    "gn:timezone":"America/Argentina/Salta",
    "iso:country":"AR",
    "name:ceb_x_preferred":[
        "Pluma del Pato"
    ],
    "name:swe_x_preferred":[
        "Pluma del Pato"
    ],
    "name:und_x_variant":[
        "Pluma de Pato"
    ],
    "wof:name":"Pluma del Pato",
    "wof:placetype":"locality"
},
  "geometry": {"coordinates":[-63.10038,-23.37369],"type":"Point"}
}