{
  "type": "Feature",
  "properties": {
    "iso:country":"AR",
    "name:azb_x_preferred":[
        "\u067e\u0647\u0648\u0627\u062e\u0648"
    ],
    "name:cym_x_preferred":[
        "Pehuaj\u00f3"
    ],
    "name:dan_x_preferred":[
        "Pehuaj\u00f3"
    ],
    "name:deu_x_preferred":[
        "Pehuaj\u00f3"
    ],
    "name:ell_x_preferred":[
        "\u03a0\u03b5\u03bf\u03c5\u03b1\u03c7\u03cc"
    ],
    "name:eng_x_preferred":[
        "Pehuaj\u00f3"
    ],
    "name:fas_x_preferred":[
        "\u067e\u0647\u0648\u0627\u062e\u0648"
    ],
    "name:fra_x_preferred":[
        "Pehuaj\u00f3"
    ],
    "name:ita_x_preferred":[
        "Pehuaj\u00f3"
    ],
    "name:jpn_x_preferred":[
        "\u30da\u30ef\u30db"
    ],
    "name:nld_x_preferred":[
        "Pehuaj\u00f3"
    ],
    "name:pol_x_preferred":[
        "Pehuaj\u00f3"
    ],
    "name:por_x_preferred":[
        "Pehuaj\u00f3"
    ],
    "name:ron_x_preferred":[
        "Pehuaj\u00f3"
    ],
    "name:spa_x_preferred":[
        "Pehuaj\u00f3"
    ],
    "name:ukr_x_preferred":[
        "\u041f\u0435\u0432\u0430\u0445\u043e"
    ],
    "name:zho_x_preferred":[
        "\u4f69\u74e6\u970d"
    ],
    "qs:gn_country":"AR",
    "qs:gn_fcode":"PPL",
    "qs:gn_pop":0,
    "qs:name":"Pehuaj\u00f3",
    "qs:name_adm0":"Argentina",
    "qs:name_adm1":"Buenos Aires",
    "qs:photos":28,
    "qs:photos_1k":6,
    "qs:photos_9k":1,
    "qs:photos_9r":2,
    "qs:photos_all":28,
    "qs:photos_sr":2,
    "qs:placetype":"Town",
    "qs:pop_sr":"7",
    "qs:woe_adm0":23424747,
    "wof:name":"Pehuaj\u00f3",
    "wof:placetype":"locality"
},
  "geometry": {"coordinates":[-61.8968,-35.81077],"type":"Point"}
}