{
  "type": "Feature",
  "properties": {
    "gn:admin1_code":"22.0",
    "gn:admin2_code":"86070.0",
    "gn:asciiname":"La Guardia",
    "gn:country_code":"AR",
    "gn:dem":170,
    "gn:feature_class":"P",
    "gn:feature_code":"PPL",
    "gn:name":"La Guardia",
    "gn:population":0,
    "gn:timezone":"America/Argentina/Cordoba",
    "iso:country":"AR",
    "wof:name":"La Guardia",
    "wof:placetype":"locality"
},
  "geometry": {"coordinates":[-63.69426,-27.19245],"type":"Point"}
}