{
  "type": "Feature",
  "properties": {
    "gn:admin1_code":"16",
    "gn:admin2_code":"62035.0",
    "gn:asciiname":"Aguada de Guzman",
    "gn:country_code":"AR",
    "gn:dem":772,
    "gn:feature_class":"P",
    "gn:feature_code":"PPL",
    "gn:name":"Aguada de Guzm\u00e1n",
    "gn:population":0,
    "gn:timezone":"America/Argentina/Salta",
    "iso:country":"AR",
    "name:fas_x_preferred":[
        "\u0627\u06af\u0648\u0627\u062f\u0627 \u06af\u0648\u0632\u0645\u0627\u0646"
    ],
    "name:spa_x_preferred":[
        "Aguada Guzm\u00e1n"
    ],
    "name:und_x_variant":[
        "Aguada de Guzm\u00e1n"
    ],
    "name:urd_x_preferred":[
        "\u0627\u06af\u0648\u0627\u062f\u0627 \u06af\u0648\u0632\u0645\u0627\u0646"
    ],
    "wof:name":"Aguada de Guzman",
    "wof:placetype":"locality"
},
  "geometry": {"coordinates":[-68.87043,-39.98157],"type":"Point"}
}