{
  "type": "Feature",
  "properties": {
    "gn:admin1_code":"19.0",
    "gn:admin2_code":"74007.0",
    "gn:asciiname":"El Retamo",
    "gn:country_code":"AR",
    "gn:dem":437,
    "gn:feature_class":"P",
    "gn:feature_code":"PPL",
    "gn:name":"El Retamo",
    "gn:population":0,
    "gn:timezone":"America/Argentina/San_Luis",
    "iso:country":"AR",
    "wof:name":"El Retamo",
    "wof:placetype":"locality"
},
  "geometry": {"coordinates":[-65.96094000000001,-32.10718],"type":"Point"}
}