{
  "type": "Feature",
  "properties": {
    "gn:admin1_code":"24.0",
    "gn:admin2_code":"90119.0",
    "gn:asciiname":"Marcos Paz",
    "gn:country_code":"AR",
    "gn:dem":477,
    "gn:feature_class":"P",
    "gn:feature_code":"PPL",
    "gn:name":"Marcos Paz",
    "gn:population":0,
    "gn:timezone":"America/Argentina/Tucuman",
    "iso:country":"AR",
    "wof:name":"Marcos Paz",
    "wof:placetype":"locality"
},
  "geometry": {"coordinates":[-65.28333000000001,-26.81667],"type":"Point"}
}