{
  "type": "Feature",
  "properties": {
    "gn:admin1_code":"24.0",
    "gn:admin2_code":"90119.0",
    "gn:asciiname":"Marcos Paz",
    "gn:country_code":"AR",
    "gn:dem":477,
    "gn:feature_class":"P",
    "gn:feature_code":"PPL",
    "gn:name":"Marcos Paz",
    "gn:population":0,
    "gn:timezone":"America/Argentina/Tucuman",
    "iso:country":"AR",
    "name:ara_x_preferred":[
        "\u0645\u0627\u0631\u0643\u0648\u0633 \u0628\u0627\u0632"
    ],
    "name:ast_x_preferred":[
        "Marcos Paz"
    ],
    "name:azb_x_preferred":[
        "\u0645\u0627\u0631\u06a9\u0648\u0633 \u067e\u0627\u0632"
    ],
    "name:ita_x_preferred":[
        "Marcos Paz"
    ],
    "name:spa_x_preferred":[
        "Marcos Paz"
    ],
    "wof:name":"Marcos Paz",
    "wof:placetype":"locality"
},
  "geometry": {"coordinates":[-65.28333000000001,-26.81667],"type":"Point"}
}