{
  "type": "Feature",
  "properties": {
    "gn:country":"AR",
    "gn:fcode":"PPL",
    "gn:population":1389,
    "iso:country":"AR",
    "name:ceb_x_preferred":[
        "La Maruja"
    ],
    "name:deu_x_preferred":[
        "La Maruja"
    ],
    "name:eng_x_preferred":[
        "La Maruja"
    ],
    "name:fra_x_preferred":[
        "La Maruja"
    ],
    "name:nld_x_preferred":[
        "La Maruja"
    ],
    "name:por_x_preferred":[
        "La Maruja"
    ],
    "name:spa_x_preferred":[
        "La Maruja"
    ],
    "name:swe_x_preferred":[
        "La Maruja"
    ],
    "name:urd_x_preferred":[
        "\u0644\u0627 \u0645\u0627\u0631\u0648\u062c\u0627"
    ],
    "qs:name":"La Maruja",
    "qs:photos_9r":0,
    "qs:photos_sr":0,
    "qs:pop_sr":"5",
    "wd:wordcount":36,
    "wof:name":"La Maruja",
    "wof:placetype":"locality",
    "wof:population":1389
},
  "geometry": {"coordinates":[-64.93997,-35.6736],"type":"Point"}
}