{
  "type": "Feature",
  "properties": {
    "gn:admin1_code":"1.0",
    "gn:admin2_code":"6392.0",
    "gn:asciiname":"Los Laureles",
    "gn:country_code":"AR",
    "gn:dem":111,
    "gn:feature_class":"P",
    "gn:feature_code":"PPL",
    "gn:name":"Los Laureles",
    "gn:population":0,
    "gn:timezone":"America/Argentina/Buenos_Aires",
    "iso:country":"AR",
    "name:por_x_preferred":[
        "Los Laureles"
    ],
    "name:spa_x_preferred":[
        "Los Laureles"
    ],
    "wof:name":"Los Laureles",
    "wof:placetype":"locality"
},
  "geometry": {"coordinates":[-62.90774,-35.11238],"type":"Point"}
}