{
  "type": "Feature",
  "properties": {
    "gn:admin1_code":"19.0",
    "gn:admin2_code":"74049.0",
    "gn:asciiname":"Rosario",
    "gn:country_code":"AR",
    "gn:dem":496,
    "gn:feature_class":"P",
    "gn:feature_code":"PPL",
    "gn:name":"Rosario",
    "gn:population":0,
    "gn:timezone":"America/Argentina/San_Luis",
    "iso:country":"AR",
    "wof:name":"Rosario",
    "wof:placetype":"locality"
},
  "geometry": {"coordinates":[-65.25,-32.11667],"type":"Point"}
}