{
  "type": "Feature",
  "properties": {
    "gn:admin1_code":"15.0",
    "gn:admin2_code":"58077.0",
    "gn:asciiname":"Nahueve",
    "gn:country_code":"AR",
    "gn:dem":1311,
    "gn:feature_class":"P",
    "gn:feature_code":"PPL",
    "gn:name":"Nahueve",
    "gn:population":0,
    "gn:timezone":"America/Argentina/Salta",
    "iso:country":"AR",
    "wof:name":"Nahueve",
    "wof:placetype":"locality"
},
  "geometry": {"coordinates":[-70.78333000000001,-37.06667],"type":"Point"}
}