{
  "type": "Feature",
  "properties": {
    "gn:admin1_code":"6.0",
    "gn:admin2_code":"18140.0",
    "gn:asciiname":"Campo Grande",
    "gn:country_code":"AR",
    "gn:dem":64,
    "gn:feature_class":"P",
    "gn:feature_code":"PPL",
    "gn:name":"Campo Grande",
    "gn:population":0,
    "gn:timezone":"America/Argentina/Cordoba",
    "iso:country":"AR",
    "wof:name":"Campo Grande",
    "wof:placetype":"locality"
},
  "geometry": {"coordinates":[-58.35895,-27.50954],"type":"Point"}
}