{
  "type": "Feature",
  "properties": {
    "iso:country":"AR",
    "name:ceb_x_preferred":[
        "El Colorado"
    ],
    "name:dan_x_preferred":[
        "El Colorado"
    ],
    "name:deu_x_preferred":[
        "El Colorado"
    ],
    "name:eng_x_preferred":[
        "El Colorado"
    ],
    "name:fra_x_preferred":[
        "El Colorado"
    ],
    "name:heb_x_preferred":[
        "\u05d0\u05dc \u05e7\u05d5\u05dc\u05d5\u05e8\u05d3\u05d5"
    ],
    "name:ita_x_preferred":[
        "El Colorado"
    ],
    "name:jpn_x_preferred":[
        "\u30a8\u30eb\u30fb\u30b3\u30ed\u30e9\u30c9"
    ],
    "name:nld_x_preferred":[
        "El Colorado"
    ],
    "name:pol_x_preferred":[
        "El Colorado"
    ],
    "name:por_x_preferred":[
        "El Colorado"
    ],
    "name:spa_x_preferred":[
        "El Colorado"
    ],
    "name:swe_x_preferred":[
        "El Colorado"
    ],
    "name:ukr_x_preferred":[
        "\u0415\u043b\u044c-\u041a\u043e\u043b\u043e\u0440\u0430\u0434\u043e"
    ],
    "qs:gn_country":"AR",
    "qs:gn_fcode":"PPL",
    "qs:gn_pop":12780,
    "qs:name":"El Colorado",
    "qs:name_adm0":"Argentina",
    "qs:name_adm1":"Formosa",
    "qs:photos":0,
    "qs:photos_1k":0,
    "qs:photos_9k":0,
    "qs:photos_9r":0,
    "qs:photos_all":0,
    "qs:photos_sr":0,
    "qs:placetype":"Town",
    "qs:pop_sr":"6",
    "qs:woe_adm0":23424747,
    "wd:wordcount":31,
    "wof:name":"El Colorado",
    "wof:placetype":"locality",
    "wof:population":12780
},
  "geometry": {"coordinates":[-59.37291,-26.30808],"type":"Point"}
}