{
  "type": "Feature",
  "properties": {
    "gn:admin1_code":"6.0",
    "gn:admin2_code":"18070.0",
    "gn:asciiname":"Pago Redondo",
    "gn:country_code":"AR",
    "gn:dem":42,
    "gn:feature_class":"P",
    "gn:feature_code":"PPL",
    "gn:name":"Pago Redondo",
    "gn:population":0,
    "gn:timezone":"America/Argentina/Cordoba",
    "iso:country":"AR",
    "wof:name":"Pago Redondo",
    "wof:placetype":"locality"
},
  "geometry": {"coordinates":[-59.21666999999999,-29.58333],"type":"Point"}
}