{
  "type": "Feature",
  "properties": {
    "gn:admin1_code":"01",
    "gn:admin2_code":"6560.0",
    "gn:asciiname":"San Serapio de la Loma",
    "gn:country_code":"AR",
    "gn:dem":25,
    "gn:feature_class":"P",
    "gn:feature_code":"PPL",
    "gn:name":"San Serapio de la Loma",
    "gn:population":0,
    "gn:timezone":"America/Argentina/Buenos_Aires",
    "iso:country":"AR",
    "name:spa_x_preferred":[
        "San Serapio de la Loma"
    ],
    "wof:name":"San Serapio de la Loma",
    "wof:placetype":"locality"
},
  "geometry": {"coordinates":[-58.76856,-34.60267],"type":"Point"}
}