{
  "type": "Feature",
  "properties": {
    "gn:admin1_code":"12",
    "gn:admin2_code":"46098.0",
    "gn:asciiname":"Yegua Quemada",
    "gn:country_code":"AR",
    "gn:dem":4021,
    "gn:feature_class":"P",
    "gn:feature_code":"PPL",
    "gn:name":"Yegua Quemada",
    "gn:population":0,
    "gn:timezone":"America/Argentina/La_Rioja",
    "iso:country":"AR",
    "wof:name":"Yegua Quemada",
    "wof:placetype":"locality"
},
  "geometry": {"coordinates":[-68.62139000000001,-28.22444],"type":"Point"}
}