{
  "type": "Feature",
  "properties": {
    "gn:admin1_code":"1.0",
    "gn:admin2_code":"6385.0",
    "gn:asciiname":"San Emilio",
    "gn:country_code":"AR",
    "gn:dem":65,
    "gn:feature_class":"P",
    "gn:feature_code":"PPL",
    "gn:name":"San Emilio",
    "gn:population":0,
    "gn:timezone":"America/Argentina/Buenos_Aires",
    "iso:country":"AR",
    "name:bcl_x_preferred":[
        "San Emilio"
    ],
    "name:ceb_x_preferred":[
        "San Emilio"
    ],
    "name:deu_x_preferred":[
        "San Emilio"
    ],
    "name:fra_x_preferred":[
        "San Emilio"
    ],
    "name:ilo_x_preferred":[
        "San Emilio"
    ],
    "name:ind_x_preferred":[
        "San Emilio"
    ],
    "name:ita_x_preferred":[
        "San Emilio"
    ],
    "name:nld_x_preferred":[
        "San Emilio"
    ],
    "name:pag_x_preferred":[
        "San Emilio"
    ],
    "name:pam_x_preferred":[
        "San Emilio"
    ],
    "name:spa_x_preferred":[
        "San Emilio"
    ],
    "name:swe_x_preferred":[
        "San Emilio"
    ],
    "name:tgl_x_preferred":[
        "San Emilio"
    ],
    "name:vie_x_preferred":[
        "San Emilio"
    ],
    "name:war_x_preferred":[
        "San Emilio"
    ],
    "wof:name":"San Emilio",
    "wof:placetype":"locality"
},
  "geometry": {"coordinates":[-60.86896,-35.02987],"type":"Point"}
}