{
  "type": "Feature",
  "properties": {
    "gn:admin1_code":"1.0",
    "gn:admin2_code":"6609.0",
    "gn:asciiname":"Pedro Gamen",
    "gn:country_code":"AR",
    "gn:dem":88,
    "gn:feature_class":"P",
    "gn:feature_code":"PPL",
    "gn:name":"Pedro Gamen",
    "gn:population":0,
    "gn:timezone":"America/Argentina/Buenos_Aires",
    "iso:country":"AR",
    "name:und_x_variant":[
        "P. Gamen",
        "Pedro Gamen"
    ],
    "wof:name":"Pedro Gamen",
    "wof:placetype":"locality"
},
  "geometry": {"coordinates":[-61.83841,-35.64818],"type":"Point"}
}