{
  "type": "Feature",
  "properties": {
    "gn:admin1_code":"1.0",
    "gn:admin2_code":"6098.0",
    "gn:asciiname":"Ensenada Berisso",
    "gn:country_code":"AR",
    "gn:dem":11,
    "gn:feature_class":"P",
    "gn:feature_code":"PPL",
    "gn:name":"Ensenada Berisso",
    "gn:population":0,
    "gn:timezone":"America/Argentina/Buenos_Aires",
    "iso:country":"AR",
    "wof:name":"Ensenada Berisso",
    "wof:placetype":"locality"
},
  "geometry": {"coordinates":[-57.89222,-34.86307],"type":"Point"}
}