{
  "type": "Feature",
  "properties": {
    "iso:country":"AR",
    "name:bre_x_preferred":[
        "Hern\u00e1ndez"
    ],
    "name:cat_x_preferred":[
        "Hern\u00e1ndez"
    ],
    "name:ces_x_preferred":[
        "Hern\u00e1ndez"
    ],
    "name:deu_x_preferred":[
        "Hern\u00e1ndez"
    ],
    "name:fra_x_preferred":[
        "Hern\u00e1ndez"
    ],
    "name:heb_x_preferred":[
        "\u05d0\u05e8\u05e0\u05e0\u05d3\u05e1"
    ],
    "name:ita_x_preferred":[
        "Hernandez"
    ],
    "name:jpn_x_preferred":[
        "\u30a8\u30eb\u30ca\u30f3\u30c7\u30b9"
    ],
    "name:kor_x_preferred":[
        "\uc5d0\ub974\ub09c\ub370\uc2a4"
    ],
    "name:nld_x_preferred":[
        "Hern\u00e1ndez"
    ],
    "name:spa_x_preferred":[
        "Hern\u00e1ndez"
    ],
    "qs:gn_country":"AR",
    "qs:gn_fcode":"PPL",
    "qs:gn_pop":1801,
    "qs:name":"Hern\u00e1ndez",
    "qs:name_adm0":"Argentina",
    "qs:name_adm1":"Entre R\u00edos",
    "qs:photos":0,
    "qs:photos_1k":0,
    "qs:photos_9k":1,
    "qs:photos_9r":1,
    "qs:photos_all":10,
    "qs:photos_sr":0,
    "qs:placetype":"Town",
    "qs:pop_sr":"6",
    "qs:woe_adm0":23424747,
    "wd:wordcount":1377,
    "wof:name":"Hern\u00e1ndez",
    "wof:placetype":"locality",
    "wof:population":1801
},
  "geometry": {"coordinates":[-60.0216,-32.3373],"type":"Point"}
}