{
  "type": "Feature",
  "properties": {
    "gn:admin1_code":"24.0",
    "gn:admin2_code":"90014.0",
    "gn:asciiname":"Naranjito",
    "gn:country_code":"AR",
    "gn:dem":374,
    "gn:feature_class":"P",
    "gn:feature_code":"PPL",
    "gn:name":"Naranjito",
    "gn:population":0,
    "gn:timezone":"America/Argentina/Tucuman",
    "iso:country":"AR",
    "wof:name":"Naranjito",
    "wof:placetype":"locality"
},
  "geometry": {"coordinates":[-65.08606999999999,-26.99802],"type":"Point"}
}