{
  "type": "Feature",
  "properties": {
    "gn:admin1_code":"21.0",
    "gn:asciiname":"Piloto Avila",
    "gn:country_code":"AR",
    "gn:dem":69,
    "gn:feature_class":"P",
    "gn:feature_code":"PPL",
    "gn:name":"Piloto \u00c1vila",
    "gn:population":0,
    "gn:timezone":"America/Argentina/Cordoba",
    "iso:country":"AR",
    "wof:name":"Piloto Avila",
    "wof:placetype":"locality"
},
  "geometry": {"coordinates":[-59.57442,-30.74516],"type":"Point"}
}