{
  "type": "Feature",
  "properties": {
    "gn:admin1_code":"22.0",
    "gn:admin2_code":"86091.0",
    "gn:asciiname":"Poleo Pozo",
    "gn:country_code":"AR",
    "gn:dem":342,
    "gn:feature_class":"P",
    "gn:feature_code":"PPL",
    "gn:name":"Poleo Pozo",
    "gn:population":0,
    "gn:timezone":"America/Argentina/Cordoba",
    "iso:country":"AR",
    "wof:name":"Poleo Pozo",
    "wof:placetype":"locality"
},
  "geometry": {"coordinates":[-64.72920000000001,-27.02482],"type":"Point"}
}