{
  "type": "Feature",
  "properties": {
    "gn:admin1_code":"5.0",
    "gn:admin2_code":"14070.0",
    "gn:asciiname":"Ojo de Agua",
    "gn:country_code":"AR",
    "gn:dem":976,
    "gn:feature_class":"P",
    "gn:feature_code":"PPL",
    "gn:name":"Ojo de Agua",
    "gn:population":0,
    "gn:timezone":"America/Argentina/Cordoba",
    "iso:country":"AR",
    "wof:name":"Ojo de Agua",
    "wof:placetype":"locality"
},
  "geometry": {"coordinates":[-65.2465,-31.21447],"type":"Point"}
}