{
  "type": "Feature",
  "properties": {
    "gn:admin1_code":"5.0",
    "gn:admin2_code":"14028.0",
    "gn:asciiname":"El Perchel",
    "gn:country_code":"AR",
    "gn:dem":1370,
    "gn:feature_class":"P",
    "gn:feature_code":"PPL",
    "gn:name":"El Perchel",
    "gn:population":0,
    "gn:timezone":"America/Argentina/Cordoba",
    "iso:country":"AR",
    "wof:name":"El Perchel",
    "wof:placetype":"locality"
},
  "geometry": {"coordinates":[-64.87363000000001,-31.13003],"type":"Point"}
}