{
  "type": "Feature",
  "properties": {
    "iso:country":"AR",
    "name:eng_x_preferred":[
        "Comandante Nicanor Otamendi"
    ],
    "name:nld_x_preferred":[
        "Comandante Nicanor Otamendi"
    ],
    "name:pol_x_preferred":[
        "Comandante Nicanor Otamendi"
    ],
    "name:spa_x_preferred":[
        "Walter Hern\u00e1ndez"
    ],
    "name:spa_x_variant":[
        "Comandante Nicanor Otamendi"
    ],
    "name:ukr_x_preferred":[
        "\u041a\u043e\u043c\u0430\u043d\u0434\u0430\u043d\u0442\u0435-\u041d\u0456\u043a\u0430\u043d\u043e\u0440-\u041e\u0442\u0430\u043c\u0435\u043d\u0434\u0456"
    ],
    "name:unk_x_variant":[
        "Dionisia"
    ],
    "qs:gn_country":"AR",
    "qs:gn_fcode":"PPL",
    "qs:gn_pop":0,
    "qs:name":"Comandante Nicanor Otamendi",
    "qs:name_adm0":"Argentina",
    "qs:name_adm1":"Buenos Aires",
    "qs:photos":0,
    "qs:photos_1k":0,
    "qs:photos_9k":1,
    "qs:photos_9r":1,
    "qs:photos_all":3,
    "qs:photos_sr":0,
    "qs:placetype":"Town",
    "qs:pop_sr":"0",
    "qs:woe_adm0":23424747,
    "wof:name":"Comandante Nicanor Otamendi",
    "wof:placetype":"locality"
},
  "geometry": {"coordinates":[-57.83809,-38.11415],"type":"Point"}
}