{
  "type": "Feature",
  "properties": {
    "gn:gn_country":"AR",
    "gn:gn_fcode":"PPLX",
    "gn:gn_pop":0,
    "iso:country":"AR",
    "name:spa_x_preferred":[
        "Sorrento"
    ],
    "name:spa_x_variant":[
        "Sarmiento",
        "Sorento"
    ],
    "name:unk_x_variant":[
        "Sarmiento",
        "Sorrento"
    ],
    "qs:gn_adm0_cc":"AR",
    "qs:gn_fcode":"PPLX",
    "qs:gn_local":3838583,
    "qs:gn_namadm1":"21",
    "qs:gn_name":"Sorrento",
    "qs:local_max":4639,
    "qs:local_sum":17736,
    "qs:localhoods":14,
    "qs:name":"Sorrento",
    "qs:name_adm0":"Argentina",
    "qs:name_adm1":"Santa Fe",
    "qs:name_adm2":"Rosario",
    "qs:name_local":"Rosario",
    "qs:photo_max":39,
    "qs:photo_sum":150,
    "qs:placetype":"Suburb",
    "qs:quad_count":12,
    "qs:woe_adm0":23424747,
    "qs:woe_adm1":2344695,
    "qs:woe_adm2":20070927,
    "qs:woe_lau":0,
    "qs:woe_local":466862,
    "qs:woe_ver":"7.10.0",
    "qs_pg:aaroncc":"AR",
    "qs_pg:gn_country":"AR",
    "qs_pg:gn_fcode":"PPLX",
    "qs_pg:gn_pop":0,
    "qs_pg:name":"Sorrento",
    "qs_pg:name_adm0":"Argentina",
    "qs_pg:name_adm1":"Santa Fe",
    "qs_pg:photos":151,
    "qs_pg:photos_1k":31,
    "qs_pg:photos_9k":1,
    "qs_pg:photos_9r":4,
    "qs_pg:photos_all":151,
    "qs_pg:photos_sr":4,
    "qs_pg:pop_sr":0,
    "qs_pg:qs_pg_placetype":"neighbourhood",
    "qs_pg:qs_pg_placetype_gp":"Suburb",
    "qs_pg:woe_adm0":23424747,
    "wof:lang":[
        "spa"
    ],
    "wof:name":"Sorrento",
    "wof:placetype":"neighbourhood"
},
  "geometry": {"coordinates":[-60.725128,-32.906866],"type":"Point"}
}