{
  "type": "Feature",
  "properties": {
    "gn:admin1_code":"05",
    "gn:admin2_code":"14105.0",
    "gn:asciiname":"Capilla de la Sagrada Familia",
    "gn:country_code":"AR",
    "gn:dem":193,
    "gn:feature_class":"P",
    "gn:feature_code":"PPL",
    "gn:name":"Capilla de la Sagrada Familia",
    "gn:population":0,
    "gn:timezone":"America/Argentina/Cordoba",
    "iso:country":"AR",
    "name:und_x_variant":[
        "Sagrada Familia",
        "Capilla de la Sagrada Familia"
    ],
    "wof:name":"Capilla de la Sagrada Familia",
    "wof:placetype":"locality"
},
  "geometry": {"coordinates":[-63.42746,-31.24749000000001],"type":"Point"}
}