{
  "type": "Feature",
  "properties": {
    "gn:admin1_code":"21",
    "gn:admin2_code":"82098.0",
    "gn:asciiname":"Paraje Pajaro Blanco",
    "gn:country_code":"AR",
    "gn:dem":36,
    "gn:feature_class":"P",
    "gn:feature_code":"PPL",
    "gn:name":"Paraje P\u00e1jaro Blanco",
    "gn:population":0,
    "gn:timezone":"America/Argentina/Cordoba",
    "iso:country":"AR",
    "wof:name":"Paraje Pajaro Blanco",
    "wof:placetype":"locality"
},
  "geometry": {"coordinates":[-59.7897,-29.78069],"type":"Point"}
}