{
  "type": "Feature",
  "properties": {
    "iso:country":"AR",
    "name:ceb_x_preferred":[
        "Ruiz de Montoya"
    ],
    "name:deu_x_preferred":[
        "Ruiz de Montoya"
    ],
    "name:eng_x_preferred":[
        "Ruiz de Montoya"
    ],
    "name:nld_x_preferred":[
        "Ruiz de Montoya"
    ],
    "name:por_x_preferred":[
        "Ruiz de Montoya"
    ],
    "name:spa_x_preferred":[
        "Ruiz de Montoya"
    ],
    "name:swe_x_preferred":[
        "Ruiz de Montoya"
    ],
    "qs:gn_country":"AR",
    "qs:gn_fcode":"PPL",
    "qs:gn_pop":3374,
    "qs:name":"Ruiz de Montoya",
    "qs:name_adm0":"Argentina",
    "qs:name_adm1":"Misiones",
    "qs:photos":0,
    "qs:photos_1k":0,
    "qs:photos_9k":0,
    "qs:photos_9r":0,
    "qs:photos_all":0,
    "qs:photos_sr":0,
    "qs:placetype":"Town",
    "qs:pop_sr":"4",
    "qs:woe_adm0":23424747,
    "wd:wordcount":38,
    "wof:name":"Ruiz de Montoya",
    "wof:placetype":"locality",
    "wof:population":3374
},
  "geometry": {"coordinates":[-55.05,-26.98333],"type":"Point"}
}