{
  "type": "Feature",
  "properties": {
    "gn:admin1_code":"1.0",
    "gn:admin2_code":"6392.0",
    "gn:asciiname":"General Villegas",
    "gn:country_code":"AR",
    "gn:dem":112,
    "gn:feature_class":"P",
    "gn:feature_code":"PPLA2",
    "gn:name":"General Villegas",
    "gn:population":16270,
    "gn:timezone":"America/Argentina/Buenos_Aires",
    "iso:country":"AR",
    "name:bul_x_preferred":[
        "\u0425\u0435\u043d\u0435\u0440\u0430\u043b \u0412\u0438\u043b\u0435\u0433\u0430\u0441"
    ],
    "wof:name":"General Villegas",
    "wof:placetype":"locality",
    "wof:population":16270
},
  "geometry": {"coordinates":[-63.01252,-35.03285],"type":"Point"}
}