{
  "type": "Feature",
  "properties": {
    "gn:admin1_code":"24.0",
    "gn:admin2_code":"90056.0",
    "gn:asciiname":"Mojon",
    "gn:country_code":"AR",
    "gn:dem":325,
    "gn:feature_class":"P",
    "gn:feature_code":"PPL",
    "gn:name":"Moj\u00f3n",
    "gn:population":0,
    "gn:timezone":"America/Argentina/Tucuman",
    "iso:country":"AR",
    "wof:name":"Mojon",
    "wof:placetype":"locality"
},
  "geometry": {"coordinates":[-64.93418,-27.23296],"type":"Point"}
}