{
  "type": "Feature",
  "properties": {
    "gn:admin1_code":"17.0",
    "gn:admin2_code":"66056.0",
    "gn:asciiname":"Luna Muerta",
    "gn:country_code":"AR",
    "gn:dem":267,
    "gn:feature_class":"P",
    "gn:feature_code":"PPL",
    "gn:name":"Luna Muerta",
    "gn:population":0,
    "gn:timezone":"America/Argentina/Salta",
    "iso:country":"AR",
    "wof:name":"Luna Muerta",
    "wof:placetype":"locality"
},
  "geometry": {"coordinates":[-63.65897,-23.33112],"type":"Point"}
}