{
  "type": "Feature",
  "properties": {
    "gn:admin1_code":"10",
    "gn:admin2_code":"38098.0",
    "gn:asciiname":"Huachichocana",
    "gn:country_code":"AR",
    "gn:dem":3773,
    "gn:elevation":"4000.0",
    "gn:feature_class":"P",
    "gn:feature_code":"PPL",
    "gn:name":"Huachichocana",
    "gn:population":0,
    "gn:timezone":"America/Argentina/Jujuy",
    "iso:country":"AR",
    "wof:name":"Huachichocana",
    "wof:placetype":"locality"
},
  "geometry": {"coordinates":[-65.6331,-23.71452],"type":"Point"}
}