{
  "type": "Feature",
  "properties": {
    "gn:admin1_code":"17.0",
    "gn:admin2_code":"66084.0",
    "gn:asciiname":"Los Mogotes",
    "gn:country_code":"AR",
    "gn:dem":905,
    "gn:feature_class":"P",
    "gn:feature_code":"PPL",
    "gn:name":"Los Mogotes",
    "gn:population":0,
    "gn:timezone":"America/Argentina/Salta",
    "iso:country":"AR",
    "wof:name":"Los Mogotes",
    "wof:placetype":"locality"
},
  "geometry": {"coordinates":[-65.17758000000001,-26.02699],"type":"Point"}
}