{
  "type": "Feature",
  "properties": {
    "gn:admin1_code":"1.0",
    "gn:admin2_code":"6357.0",
    "gn:asciiname":"Parque Camet",
    "gn:country_code":"AR",
    "gn:dem":9,
    "gn:feature_class":"P",
    "gn:feature_code":"PPL",
    "gn:name":"Parque Camet",
    "gn:population":0,
    "gn:timezone":"America/Argentina/Buenos_Aires",
    "iso:country":"AR",
    "wof:name":"Parque Camet",
    "wof:placetype":"locality"
},
  "geometry": {"coordinates":[-57.53816,-37.93746],"type":"Point"}
}