{
  "type": "Feature",
  "properties": {
    "iso:country":"AR",
    "name:eng_x_preferred":[
        "Chepes"
    ],
    "name:fra_x_preferred":[
        "Chepes"
    ],
    "name:ita_x_preferred":[
        "Chepes"
    ],
    "name:jpn_x_preferred":[
        "\u30c1\u30a7\u30da\u30b9"
    ],
    "name:nld_x_preferred":[
        "Chepes"
    ],
    "name:por_x_preferred":[
        "Chepes"
    ],
    "name:spa_x_preferred":[
        "Chepes"
    ],
    "name:swe_x_preferred":[
        "Chepes Viejo"
    ],
    "name:ukr_x_preferred":[
        "\u0427\u0435\u043f\u0435\u0441"
    ],
    "name:zho_x_preferred":[
        "\u5207\u4f69\u65af"
    ],
    "ne:ADM0CAP":0.0,
    "ne:ADM0NAME":"Argentina",
    "ne:ADM0_A3":"ARG",
    "ne:ADM1NAME":"La Rioja",
    "ne:ADMIN1_COD":0,
    "ne:CAPALT":0,
    "ne:CHANGED":0,
    "ne:CHECKME":0,
    "ne:COMPARE":0,
    "ne:DIFFASCII":0,
    "ne:ELEVATION":0.0,
    "ne:FEATURECLA":"Populated place",
    "ne:GEONAMEID":-1,
    "ne:GEONAMESNO":"No GeoNames match due to small population, not in GeoNames, or poor NEV placement.",
    "ne:GN_POP":0,
    "ne:GTOPO30":0.0,
    "ne:ISO_A2":"AR",
    "ne:LABELRANK":3,
    "ne:LATITUDE":-31.349987,
    "ne:LONGITUDE":-66.599951,
    "ne:LS_MATCH":1,
    "ne:LS_NAME":"Chepes",
    "ne:MAX_AREAKM":6.0,
    "ne:MAX_AREAMI":2.0,
    "ne:MAX_BBXMAX":-66.575,
    "ne:MAX_BBXMIN":-66.608333,
    "ne:MAX_BBYMAX":-31.325,
    "ne:MAX_BBYMIN":-31.35,
    "ne:MAX_NATSCA":10.0,
    "ne:MAX_PERKM":12.0,
    "ne:MAX_PERMI":8.0,
    "ne:MAX_POP10":6020,
    "ne:MAX_POP20":0,
    "ne:MAX_POP300":0,
    "ne:MAX_POP310":0,
    "ne:MAX_POP50":0,
    "ne:MEAN_BBXC":-66.589583,
    "ne:MEAN_BBYC":-31.340625,
    "ne:MEGACITY":0,
    "ne:MIN_AREAKM":6.0,
    "ne:MIN_AREAMI":2.0,
    "ne:MIN_BBXMAX":-66.575,
    "ne:MIN_BBXMIN":-66.608333,
    "ne:MIN_BBYMAX":-31.325,
    "ne:MIN_BBYMIN":-31.35,
    "ne:MIN_PERKM":12.0,
    "ne:MIN_PERMI":8.0,
    "ne:NAME":"Chepes",
    "ne:NAMEASCII":"Chepes",
    "ne:NAMEDIFF":0,
    "ne:NATSCALE":10,
    "ne:POP1950":0,
    "ne:POP1955":0,
    "ne:POP1960":0,
    "ne:POP1965":0,
    "ne:POP1970":0,
    "ne:POP1975":0,
    "ne:POP1980":0,
    "ne:POP1985":0,
    "ne:POP1990":0,
    "ne:POP1995":0,
    "ne:POP2000":0,
    "ne:POP2005":0,
    "ne:POP2010":0,
    "ne:POP2015":0,
    "ne:POP2020":0,
    "ne:POP2025":0,
    "ne:POP2050":0,
    "ne:POP_MAX":6020,
    "ne:POP_MIN":6020,
    "ne:POP_OTHER":6020,
    "ne:RANK_MAX":5,
    "ne:RANK_MIN":5,
    "ne:SCALERANK":8,
    "ne:SOV0NAME":"Argentina",
    "ne:SOV_A3":"ARG",
    "ne:UN_FID":0,
    "ne:UN_LAT":0.0,
    "ne:UN_LONG":0.0,
    "ne:WORLDCITY":0,
    "ne:min_zoom":7.0,
    "wof:name":"Chepes",
    "wof:placetype":"locality"
},
  "geometry": {"coordinates":[-66.59995060389457,-31.34998696006988],"type":"Point"}
}