{
  "type": "Feature",
  "properties": {
    "gn:admin1_code":"05",
    "gn:admin2_code":"14021.0",
    "gn:asciiname":"Cabana",
    "gn:country_code":"AR",
    "gn:dem":764,
    "gn:feature_class":"P",
    "gn:feature_code":"PPL",
    "gn:name":"Cabana",
    "gn:population":0,
    "gn:timezone":"America/Argentina/Cordoba",
    "iso:country":"AR",
    "wof:name":"Cabana",
    "wof:placetype":"locality"
},
  "geometry": {"coordinates":[-64.35311999999999,-31.20221],"type":"Point"}
}