{
  "type": "Feature",
  "properties": {
    "gn:admin1_code":"18.0",
    "gn:admin2_code":"70126.0",
    "gn:asciiname":"Punta del Medano",
    "gn:country_code":"AR",
    "gn:dem":500,
    "gn:feature_class":"P",
    "gn:feature_code":"PPL",
    "gn:name":"Punta del M\u00e9dano",
    "gn:population":0,
    "gn:timezone":"America/Argentina/San_Juan",
    "iso:country":"AR",
    "wof:name":"Punta del Medano",
    "wof:placetype":"locality"
},
  "geometry": {"coordinates":[-67.39466999999999,-32.25465],"type":"Point"}
}