{
  "type": "Feature",
  "properties": {
    "gn:admin1_code":"22",
    "gn:admin2_code":"86119.0",
    "gn:asciiname":"Arbol Blanco",
    "gn:country_code":"AR",
    "gn:dem":157,
    "gn:feature_class":"P",
    "gn:feature_code":"PPL",
    "gn:name":"\u00c1rbol Blanco",
    "gn:population":0,
    "gn:timezone":"America/Argentina/Cordoba",
    "iso:country":"AR",
    "wof:name":"Arbol Blanco",
    "wof:placetype":"locality"
},
  "geometry": {"coordinates":[-61.98333,-26.83333],"type":"Point"}
}