{
  "type": "Feature",
  "properties": {
    "gn:admin1_code":"22.0",
    "gn:admin2_code":"86042.0",
    "gn:asciiname":"Isla Baja",
    "gn:country_code":"AR",
    "gn:dem":89,
    "gn:feature_class":"P",
    "gn:feature_code":"PPL",
    "gn:name":"Isla Baja",
    "gn:population":0,
    "gn:timezone":"America/Argentina/Cordoba",
    "iso:country":"AR",
    "wof:name":"Isla Baja",
    "wof:placetype":"locality"
},
  "geometry": {"coordinates":[-62.33675,-29.04594],"type":"Point"}
}