{
  "type": "Feature",
  "properties": {
    "gn:admin1_code":"17.0",
    "gn:admin2_code":"66056.0",
    "gn:asciiname":"Hickmann",
    "gn:country_code":"AR",
    "gn:dem":258,
    "gn:feature_class":"P",
    "gn:feature_code":"PPL",
    "gn:name":"Hickmann",
    "gn:population":0,
    "gn:timezone":"America/Argentina/Salta",
    "iso:country":"AR",
    "name:und_x_variant":[
        "Hickman",
        "Hickmann"
    ],
    "wof:name":"Hickmann",
    "wof:placetype":"locality"
},
  "geometry": {"coordinates":[-63.56373000000001,-23.20761],"type":"Point"}
}