{
  "type": "Feature",
  "properties": {
    "iso:country":"AR",
    "name:ceb_x_preferred":[
        "Departamento de L\u00e1car"
    ],
    "name:deu_x_preferred":[
        "Departamento L\u00e1car"
    ],
    "name:fra_x_preferred":[
        "D\u00e9partement de L\u00e1car"
    ],
    "name:hun_x_preferred":[
        "L\u00e1car megye"
    ],
    "name:ita_x_preferred":[
        "Dipartimento di L\u00e1car"
    ],
    "name:kat_x_preferred":[
        "\u10da\u10d0\u10d9\u10d0\u10e0\u10d8\u10e1 \u10d3\u10d4\u10de\u10d0\u10e0\u10e2\u10d0\u10db\u10d4\u10dc\u10e2\u10d8"
    ],
    "name:nld_x_preferred":[
        "L\u00e1car"
    ],
    "name:por_x_preferred":[
        "L\u00e1car"
    ],
    "name:sco_x_preferred":[
        "L\u00e1car Depairtment"
    ],
    "name:spa_x_preferred":[
        "Departamento L\u00e1car"
    ],
    "name:unk_x_variant":[
        "Hua Hum"
    ],
    "qs:gn_country":"AR",
    "qs:gn_fcode":"PPL",
    "qs:gn_pop":0,
    "qs:name":"Puerto Hua Hum",
    "qs:name_adm0":"Argentina",
    "qs:name_adm1":"Neuqu\u00e9n",
    "qs:photos":136,
    "qs:photos_1k":28,
    "qs:photos_9k":1,
    "qs:photos_9r":3,
    "qs:photos_all":136,
    "qs:photos_sr":3,
    "qs:placetype":"Town",
    "qs:pop_sr":"0",
    "qs:woe_adm0":23424747,
    "wof:name":"Puerto Hua Hum",
    "wof:placetype":"locality"
},
  "geometry": {"coordinates":[-71.65267,-40.11514],"type":"Point"}
}