{
  "type": "Feature",
  "properties": {
    "gn:admin1_code":"09",
    "gn:admin2_code":"34063.0",
    "gn:asciiname":"El Chaquito",
    "gn:country_code":"AR",
    "gn:dem":222,
    "gn:feature_class":"P",
    "gn:feature_code":"PPL",
    "gn:name":"El Chaquito",
    "gn:population":0,
    "gn:timezone":"America/Argentina/Cordoba",
    "iso:country":"AR",
    "wof:name":"El Chaquito",
    "wof:placetype":"locality"
},
  "geometry": {"coordinates":[-62.08333,-22.85],"type":"Point"}
}