{
  "type": "Feature",
  "properties": {
    "iso:country":"AR",
    "name:und_x_variant":[
        "Rincon"
    ],
    "qs:gn_country":"AR",
    "qs:gn_fcode":"PPL",
    "qs:gn_pop":0,
    "qs:name":"Rinc\u00f3n de Nogoy\u00e1",
    "qs:name_adm0":"Argentina",
    "qs:name_adm1":"Entre R\u00edos",
    "qs:photos":0,
    "qs:photos_1k":0,
    "qs:photos_9k":0,
    "qs:photos_9r":0,
    "qs:photos_all":0,
    "qs:photos_sr":0,
    "qs:placetype":"Town",
    "qs:pop_sr":"0",
    "qs:woe_adm0":23424747,
    "wof:name":"Rinc\u00f3n de Nogoy\u00e1",
    "wof:placetype":"locality"
},
  "geometry": {"coordinates":[-59.93333,-32.75],"type":"Point"}
}