{
  "type": "Feature",
  "properties": {
    "gn:admin1_code":"1.0",
    "gn:admin2_code":"6357.0",
    "gn:asciiname":"La Estafeta",
    "gn:country_code":"AR",
    "gn:dem":14,
    "gn:feature_class":"P",
    "gn:feature_code":"PPL",
    "gn:name":"La Estafeta",
    "gn:population":0,
    "gn:timezone":"America/Argentina/Buenos_Aires",
    "iso:country":"AR",
    "wof:name":"La Estafeta",
    "wof:placetype":"locality"
},
  "geometry": {"coordinates":[-57.64007,-38.16236],"type":"Point"}
}