{
  "type": "Feature",
  "properties": {
    "gn:admin1_code":"18",
    "gn:admin2_code":"70119.0",
    "gn:asciiname":"Astica",
    "gn:country_code":"AR",
    "gn:dem":736,
    "gn:feature_class":"P",
    "gn:feature_code":"PPL",
    "gn:name":"Astica",
    "gn:population":0,
    "gn:timezone":"America/Argentina/San_Juan",
    "iso:country":"AR",
    "wof:name":"Astica",
    "wof:placetype":"locality"
},
  "geometry": {"coordinates":[-67.30396999999999,-30.95388],"type":"Point"}
}