{
  "type": "Feature",
  "properties": {
    "gn:admin1_code":"8.0",
    "gn:admin2_code":"30084.0",
    "gn:asciiname":"La Picada",
    "gn:country_code":"AR",
    "gn:dem":30,
    "gn:feature_class":"P",
    "gn:feature_code":"PPL",
    "gn:name":"La Picada",
    "gn:population":0,
    "gn:timezone":"America/Argentina/Cordoba",
    "iso:country":"AR",
    "wof:name":"La Picada",
    "wof:placetype":"locality"
},
  "geometry": {"coordinates":[-60.30861,-31.73481],"type":"Point"}
}