{
  "type": "Feature",
  "properties": {
    "gn:admin1_code":"12.0",
    "gn:admin2_code":"46119.0",
    "gn:asciiname":"Los Robles",
    "gn:country_code":"AR",
    "gn:dem":1043,
    "gn:feature_class":"P",
    "gn:feature_code":"PPL",
    "gn:name":"Los Robles",
    "gn:population":0,
    "gn:timezone":"America/Argentina/La_Rioja",
    "iso:country":"AR",
    "name:und_x_variant":[
        "Robles",
        "Los Robles"
    ],
    "wof:name":"Los Robles",
    "wof:placetype":"locality"
},
  "geometry": {"coordinates":[-67.11399,-28.43171],"type":"Point"}
}