{
  "type": "Feature",
  "properties": {
    "gn:admin1_code":"22.0",
    "gn:admin2_code":"86189.0",
    "gn:asciiname":"Sumamao",
    "gn:country_code":"AR",
    "gn:dem":150,
    "gn:feature_class":"P",
    "gn:feature_code":"PPL",
    "gn:name":"Sumamao",
    "gn:population":0,
    "gn:timezone":"America/Argentina/Cordoba",
    "iso:country":"AR",
    "name:und_x_variant":[
        "Villa Sumamao",
        "Sumamao"
    ],
    "wof:name":"Sumamao",
    "wof:placetype":"locality"
},
  "geometry": {"coordinates":[-64.10096,-28.16666],"type":"Point"}
}