{
  "type": "Feature",
  "properties": {
    "iso:country":"AR",
    "name:ceb_x_preferred":[
        "Soldini"
    ],
    "name:dut_x_preferred":[
        "Soldini"
    ],
    "name:eng_x_preferred":[
        "Soldini"
    ],
    "name:por_x_preferred":[
        "Soldini"
    ],
    "name:spa_x_preferred":[
        "Soldini"
    ],
    "name:swe_x_preferred":[
        "Soldini"
    ],
    "qs:gn_country":"AR",
    "qs:gn_fcode":"PPL",
    "qs:gn_pop":0,
    "qs:name":"Soldini",
    "qs:name_adm0":"Argentina",
    "qs:name_adm1":"Santa Fe",
    "qs:photos":0,
    "qs:photos_1k":0,
    "qs:photos_9k":1,
    "qs:photos_9r":3,
    "qs:photos_all":122,
    "qs:photos_sr":0,
    "qs:placetype":"Town",
    "qs:pop_sr":"0",
    "qs:woe_adm0":23424747,
    "wd:wordcount":89,
    "wof:name":"Soldini",
    "wof:placetype":"locality"
},
  "geometry": {"coordinates":[-60.75529,-33.0276],"type":"Point"}
}