{
  "type": "Feature",
  "properties": {
    "iso:country":"AR",
    "name:ceb_x_preferred":[
        "Nuestra Se\u00f1ora del Rosario de Caa Cat\u00ed"
    ],
    "name:chi_x_preferred":[
        "\u5361\u963f\u5361\u8482"
    ],
    "name:dut_x_preferred":[
        "Ca\u00e1 Cat\u00ed"
    ],
    "name:eng_x_preferred":[
        "Ca\u00e1 Cat\u00ed"
    ],
    "name:fra_x_preferred":[
        "Ca\u00e1 Cat\u00ed"
    ],
    "name:fre_x_preferred":[
        "Ca\u00e1 Cat\u00ed"
    ],
    "name:grn_x_preferred":[
        "Ka'a Kati"
    ],
    "name:nld_x_preferred":[
        "Ca\u00e1 Cat\u00ed"
    ],
    "name:por_x_preferred":[
        "Ca\u00e1 Cat\u00ed"
    ],
    "name:spa_x_preferred":[
        "Ca\u00e1 Cat\u00ed"
    ],
    "name:swe_x_preferred":[
        "Nuestra Se\u00f1ora del Rosario de Caa Cat\u00ed"
    ],
    "name:ukr_x_preferred":[
        "\u041a\u0430\u0430-\u041a\u0430\u0442\u0456"
    ],
    "name:unk_x_variant":[
        "Caa Cat\u00ed"
    ],
    "name:zho_x_preferred":[
        "\u5361\u963f\u5361\u8482"
    ],
    "qs:gn_country":"AR",
    "qs:gn_fcode":"PPL",
    "qs:gn_pop":7573,
    "qs:name":"Nuestra Se\u00f1ora del Rosario De Caa Cat\u00ed",
    "qs:name_adm0":"Argentina",
    "qs:name_adm1":"Corrientes",
    "qs:photos":0,
    "qs:photos_1k":0,
    "qs:photos_9k":1,
    "qs:photos_9r":1,
    "qs:photos_all":1,
    "qs:photos_sr":0,
    "qs:placetype":"Town",
    "qs:pop_sr":"5",
    "qs:woe_adm0":23424747,
    "wof:name":"Nuestra Se\u00f1ora del Rosario De Caa Cat\u00ed",
    "wof:placetype":"locality",
    "wof:population":7573
},
  "geometry": {"coordinates":[-57.62073,-27.75072],"type":"Point"}
}