{
  "type": "Feature",
  "properties": {
    "gn:admin1_code":"17",
    "gn:admin2_code":"66140.0",
    "gn:asciiname":"Almona",
    "gn:country_code":"AR",
    "gn:dem":452,
    "gn:feature_class":"P",
    "gn:feature_code":"PPL",
    "gn:name":"Almona",
    "gn:population":0,
    "gn:timezone":"America/Argentina/Salta",
    "iso:country":"AR",
    "wof:name":"Almona",
    "wof:placetype":"locality"
},
  "geometry": {"coordinates":[-64.51329,-25.96289],"type":"Point"}
}