{
  "type": "Feature",
  "properties": {
    "gn:admin1_code":"17.0",
    "gn:admin2_code":"66161.0",
    "gn:asciiname":"Lipeo",
    "gn:cc2":"AR",
    "gn:country_code":"AR",
    "gn:dem":1157,
    "gn:feature_class":"P",
    "gn:feature_code":"PPL",
    "gn:name":"Lipeo",
    "gn:population":0,
    "gn:timezone":"America/Argentina/Salta",
    "iso:country":"AR",
    "name:und_x_variant":[
        "Puerto Lipes Argentino",
        "Lipeo Argentino",
        "Lipeo"
    ],
    "wof:name":"Lipeo",
    "wof:placetype":"locality"
},
  "geometry": {"coordinates":[-64.73333000000001,-22.43333],"type":"Point"}
}