{
  "type": "Feature",
  "properties": {
    "gn:admin1_code":"1.0",
    "gn:admin2_code":"6462.0",
    "gn:asciiname":"Trigales",
    "gn:country_code":"AR",
    "gn:dem":105,
    "gn:feature_class":"P",
    "gn:feature_code":"PPL",
    "gn:name":"Trigales",
    "gn:population":0,
    "gn:timezone":"America/Argentina/Buenos_Aires",
    "iso:country":"AR",
    "wof:name":"Trigales",
    "wof:placetype":"locality"
},
  "geometry": {"coordinates":[-61.93333000000001,-34.53333],"type":"Point"}
}