{
  "type": "Feature",
  "properties": {
    "gn:admin1_code":"2.0",
    "gn:admin2_code":"10084.0",
    "gn:asciiname":"Sebila",
    "gn:country_code":"AR",
    "gn:dem":1089,
    "gn:feature_class":"P",
    "gn:feature_code":"PPL",
    "gn:name":"S\u00e9bila",
    "gn:population":0,
    "gn:timezone":"America/Argentina/Catamarca",
    "iso:country":"AR",
    "wof:name":"Sebila",
    "wof:placetype":"locality"
},
  "geometry": {"coordinates":[-66.36667,-28.71667],"type":"Point"}
}