{
  "type": "Feature",
  "properties": {
    "iso:country":"AR",
    "name:ceb_x_preferred":[
        "General Alvear"
    ],
    "name:deu_x_preferred":[
        "General Alvear"
    ],
    "name:ita_x_preferred":[
        "General Alvear"
    ],
    "name:nld_x_preferred":[
        "General Alvear"
    ],
    "name:por_x_preferred":[
        "General Alvear"
    ],
    "name:sco_x_preferred":[
        "General Alvear"
    ],
    "name:slk_x_preferred":[
        "General Alvear"
    ],
    "name:spa_x_preferred":[
        "General Alvear"
    ],
    "name:swe_x_preferred":[
        "General Alvear"
    ],
    "qs:gn_country":"AR",
    "qs:gn_fcode":"PPL",
    "qs:gn_pop":0,
    "qs:name":"General Alvear",
    "qs:name_adm0":"Argentina",
    "qs:name_adm1":"Entre R\u00edos",
    "qs:photos":8,
    "qs:photos_1k":2,
    "qs:photos_9k":1,
    "qs:photos_9r":1,
    "qs:photos_all":8,
    "qs:photos_sr":1,
    "qs:placetype":"Town",
    "qs:pop_sr":"0",
    "qs:woe_adm0":23424747,
    "wof:name":"General Alvear",
    "wof:placetype":"locality"
},
  "geometry": {"coordinates":[-60.66903,-31.94594],"type":"Point"}
}