{
  "type": "Feature",
  "properties": {
    "gn:admin1_code":"11.0",
    "gn:admin2_code":"42105.0",
    "gn:asciiname":"Speluzzi",
    "gn:country_code":"AR",
    "gn:dem":143,
    "gn:feature_class":"P",
    "gn:feature_code":"PPL",
    "gn:name":"Speluzzi",
    "gn:population":0,
    "gn:timezone":"America/Argentina/Salta",
    "iso:country":"AR",
    "name:ceb_x_preferred":[
        "Speluzzi"
    ],
    "name:por_x_preferred":[
        "Speluzzi"
    ],
    "name:spa_x_preferred":[
        "Speluzzi"
    ],
    "name:swe_x_preferred":[
        "Speluzzi"
    ],
    "wof:name":"Speluzzi",
    "wof:placetype":"locality"
},
  "geometry": {"coordinates":[-63.81811,-35.54829],"type":"Point"}
}