{
  "type": "Feature",
  "properties": {
    "gn:admin1_code":"23.0",
    "gn:admin2_code":"94007.0",
    "gn:asciiname":"La Marina",
    "gn:cc2":"AR",
    "gn:country_code":"AR",
    "gn:dem":301,
    "gn:feature_class":"P",
    "gn:feature_code":"PPL",
    "gn:name":"La Marina",
    "gn:population":0,
    "gn:timezone":"America/Argentina/Ushuaia",
    "iso:country":"AR",
    "name:ceb_x_preferred":[
        "La Marina"
    ],
    "name:spa_x_preferred":[
        "La Marina"
    ],
    "name:swe_x_preferred":[
        "La Marina"
    ],
    "name:und_x_variant":[
        "Estancia La Marina",
        "La Marina"
    ],
    "wof:name":"La Marina",
    "wof:placetype":"locality"
},
  "geometry": {"coordinates":[-68.55,-54.31667],"type":"Point"}
}