{
  "type": "Feature",
  "properties": {
    "gn:admin1_code":"17.0",
    "gn:admin2_code":"66007.0",
    "gn:asciiname":"El Yeso",
    "gn:country_code":"AR",
    "gn:dem":586,
    "gn:feature_class":"P",
    "gn:feature_code":"PPL",
    "gn:name":"El Yeso",
    "gn:population":0,
    "gn:timezone":"America/Argentina/Salta",
    "iso:country":"AR",
    "wof:name":"El Yeso",
    "wof:placetype":"locality"
},
  "geometry": {"coordinates":[-64.42871,-24.97383],"type":"Point"}
}