{
  "type": "Feature",
  "properties": {
    "gn:admin1_code":"20.0",
    "gn:admin2_code":"78014.0",
    "gn:asciiname":"Jaramillo",
    "gn:country_code":"AR",
    "gn:dem":190,
    "gn:feature_class":"P",
    "gn:feature_code":"PPL",
    "gn:name":"Jaramillo",
    "gn:population":0,
    "gn:timezone":"America/Argentina/Rio_Gallegos",
    "iso:country":"AR",
    "name:ceb_x_preferred":[
        "Jaramillo"
    ],
    "name:ita_x_preferred":[
        "Jaramillo"
    ],
    "name:spa_x_preferred":[
        "Jaramillo"
    ],
    "name:urd_x_preferred":[
        "\u062c\u0631\u0627\u0645\u0644\u0648"
    ],
    "wof:name":"Jaramillo",
    "wof:placetype":"locality"
},
  "geometry": {"coordinates":[-67.14256999999999,-47.18311],"type":"Point"}
}