{
  "type": "Feature",
  "properties": {
    "gn:admin1_code":"9.0",
    "gn:asciiname":"La Sirena",
    "gn:country_code":"AR",
    "gn:dem":166,
    "gn:feature_class":"P",
    "gn:feature_code":"PPL",
    "gn:name":"La Sirena",
    "gn:population":0,
    "gn:timezone":"America/Argentina/Cordoba",
    "iso:country":"AR",
    "wof:name":"La Sirena",
    "wof:placetype":"locality"
},
  "geometry": {"coordinates":[-61.53333000000001,-24.51667],"type":"Point"}
}