{
  "type": "Feature",
  "properties": {
    "gn:admin1_code":"01",
    "gn:admin2_code":"6007.0",
    "gn:asciiname":"Canonigo Gorriti",
    "gn:country_code":"AR",
    "gn:dem":180,
    "gn:feature_class":"P",
    "gn:feature_code":"PPL",
    "gn:name":"Can\u00f3nigo Gorriti",
    "gn:population":0,
    "gn:timezone":"America/Argentina/Buenos_Aires",
    "iso:country":"AR",
    "wof:name":"Canonigo Gorriti",
    "wof:placetype":"locality"
},
  "geometry": {"coordinates":[-63.24302,-37.54761],"type":"Point"}
}