{
  "type": "Feature",
  "properties": {
    "gn:admin1_code":"12",
    "gn:admin2_code":"46063.0",
    "gn:asciiname":"Bajo Grande",
    "gn:country_code":"AR",
    "gn:dem":432,
    "gn:feature_class":"P",
    "gn:feature_code":"PPL",
    "gn:name":"Bajo Grande",
    "gn:population":0,
    "gn:timezone":"America/Argentina/La_Rioja",
    "iso:country":"AR",
    "wof:name":"Bajo Grande",
    "wof:placetype":"locality"
},
  "geometry": {"coordinates":[-66.15000000000001,-30.56667],"type":"Point"}
}