{
  "type": "Feature",
  "properties": {
    "gn:admin1_code":"01",
    "gn:admin2_code":"6056.0",
    "gn:asciiname":"Corti",
    "gn:country_code":"AR",
    "gn:dem":106,
    "gn:feature_class":"P",
    "gn:feature_code":"PPL",
    "gn:name":"Corti",
    "gn:population":0,
    "gn:timezone":"America/Argentina/Buenos_Aires",
    "iso:country":"AR",
    "name:und_x_variant":[
        "Adela Corti",
        "A. Corti",
        "Corti"
    ],
    "wof:name":"Corti",
    "wof:placetype":"locality"
},
  "geometry": {"coordinates":[-62.06023,-38.62161],"type":"Point"}
}