{
  "type": "Feature",
  "properties": {
    "iso:country":"AR",
    "name:ara_x_preferred":[
        "\u0633\u0627\u0646 \u062c\u0648\u0633\u062a\u0648"
    ],
    "name:ben_x_preferred":[
        "\u09b8\u09be\u09a8 \u099c\u09c1\u09b8\u09cd\u09a4\u09cb"
    ],
    "name:cat_x_preferred":[
        "Sant Just"
    ],
    "name:ceb_x_preferred":[
        "San Justo"
    ],
    "name:deu_x_preferred":[
        "San Justo"
    ],
    "name:ell_x_preferred":[
        "\u03a3\u03b1\u03bd \u03a7\u03bf\u03cd\u03c3\u03c4\u03bf"
    ],
    "name:eus_x_preferred":[
        "San Justo"
    ],
    "name:fas_x_preferred":[
        "\u0633\u0646 \u062c\u0627\u0633\u062a\u0648"
    ],
    "name:fra_x_preferred":[
        "San Justo"
    ],
    "name:heb_x_preferred":[
        "\u05e1\u05df \u05d7\u05d5\u05e1\u05d8\u05d5"
    ],
    "name:hin_x_preferred":[
        "\u0938\u0948\u0928 \u091c\u0938\u094d\u091f\u094b"
    ],
    "name:hun_x_preferred":[
        "San Justo"
    ],
    "name:ind_x_preferred":[
        "San Justo"
    ],
    "name:ita_x_preferred":[
        "San Justo"
    ],
    "name:kor_x_preferred":[
        "\uc0b0 \ud6c4\uc2a4\ud1a0"
    ],
    "name:nld_x_preferred":[
        "San Justo"
    ],
    "name:pol_x_preferred":[
        "San Justo"
    ],
    "name:sco_x_preferred":[
        "San Justo"
    ],
    "name:spa_x_preferred":[
        "San Justo"
    ],
    "name:swe_x_preferred":[
        "San Justo"
    ],
    "name:tur_x_preferred":[
        "San Justo"
    ],
    "name:ukr_x_preferred":[
        "\u0421\u0430\u043d-\u0425\u0443\u0441\u0442\u043e"
    ],
    "name:und_x_variant":[
        "Villa San Justo"
    ],
    "name:urd_x_preferred":[
        "\u0633\u0627\u0646 \u062c\u0648\u0633\u0679\u0648"
    ],
    "name:vie_x_preferred":[
        "San Justo"
    ],
    "qs:gn_country":"AR",
    "qs:gn_fcode":"PPL",
    "qs:gn_pop":1473,
    "qs:name":"San Justo",
    "qs:name_adm0":"Argentina",
    "qs:name_adm1":"Entre R\u00edos",
    "qs:photos":0,
    "qs:photos_1k":0,
    "qs:photos_9k":1,
    "qs:photos_9r":1,
    "qs:photos_all":3,
    "qs:photos_sr":0,
    "qs:placetype":"Town",
    "qs:pop_sr":"3",
    "qs:woe_adm0":23424747,
    "wof:name":"San Justo",
    "wof:placetype":"locality",
    "wof:population":1473
},
  "geometry": {"coordinates":[-58.43569,-32.44654],"type":"Point"}
}