{
  "type": "Feature",
  "properties": {
    "iso:country":"AR",
    "name:cat_x_preferred":[
        "Sant Just"
    ],
    "name:ceb_x_preferred":[
        "San Justo"
    ],
    "name:deu_x_preferred":[
        "San Justo"
    ],
    "name:eus_x_preferred":[
        "San Justo"
    ],
    "name:fra_x_preferred":[
        "San Justo"
    ],
    "name:ita_x_preferred":[
        "San Justo"
    ],
    "name:nld_x_preferred":[
        "San Justo"
    ],
    "name:pol_x_preferred":[
        "San Justo"
    ],
    "name:sco_x_preferred":[
        "San Justo"
    ],
    "name:spa_x_preferred":[
        "San Justo"
    ],
    "name:swe_x_preferred":[
        "San Justo"
    ],
    "name:ukr_x_preferred":[
        "\u0421\u0430\u043d-\u0425\u0443\u0441\u0442\u043e"
    ],
    "name:und_x_variant":[
        "Villa San Justo"
    ],
    "qs:gn_country":"AR",
    "qs:gn_fcode":"PPL",
    "qs:gn_pop":1473,
    "qs:name":"San Justo",
    "qs:name_adm0":"Argentina",
    "qs:name_adm1":"Entre R\u00edos",
    "qs:photos":0,
    "qs:photos_1k":0,
    "qs:photos_9k":1,
    "qs:photos_9r":1,
    "qs:photos_all":3,
    "qs:photos_sr":0,
    "qs:placetype":"Town",
    "qs:pop_sr":"3",
    "qs:woe_adm0":23424747,
    "wof:name":"San Justo",
    "wof:placetype":"locality",
    "wof:population":1473
},
  "geometry": {"coordinates":[-58.43569,-32.44654],"type":"Point"}
}