{
  "type": "Feature",
  "properties": {
    "gn:admin1_code":"16.0",
    "gn:admin2_code":"62035.0",
    "gn:asciiname":"Rivadavia",
    "gn:country_code":"AR",
    "gn:dem":234,
    "gn:feature_class":"P",
    "gn:feature_code":"PPL",
    "gn:name":"Rivadavia",
    "gn:population":0,
    "gn:timezone":"America/Argentina/Salta",
    "iso:country":"AR",
    "wof:name":"Rivadavia",
    "wof:placetype":"locality"
},
  "geometry": {"coordinates":[-67.33333,-39.11667],"type":"Point"}
}