{
  "type": "Feature",
  "properties": {
    "gn:admin1_code":"18.0",
    "gn:admin2_code":"70049.0",
    "gn:asciiname":"La Jarilla",
    "gn:cc2":"AR",
    "gn:country_code":"AR",
    "gn:dem":2863,
    "gn:feature_class":"P",
    "gn:feature_code":"PPL",
    "gn:name":"La Jarilla",
    "gn:population":0,
    "gn:timezone":"America/Argentina/San_Juan",
    "iso:country":"AR",
    "name:und_x_variant":[
        "Jarillito",
        "La Jarilla"
    ],
    "wof:name":"La Jarilla",
    "wof:placetype":"locality"
},
  "geometry": {"coordinates":[-69.06667,-29.15],"type":"Point"}
}