{
  "type": "Feature",
  "properties": {
    "gn:admin1_code":"5.0",
    "gn:admin2_code":"14077.0",
    "gn:asciiname":"Villa Viso",
    "gn:country_code":"AR",
    "gn:dem":990,
    "gn:feature_class":"P",
    "gn:feature_code":"PPL",
    "gn:name":"Villa Viso",
    "gn:population":0,
    "gn:timezone":"America/Argentina/Cordoba",
    "iso:country":"AR",
    "wof:name":"Villa Viso",
    "wof:placetype":"locality"
},
  "geometry": {"coordinates":[-65.10531999999999,-31.36416],"type":"Point"}
}