{
  "type": "Feature",
  "properties": {
    "gn:admin1_code":"15",
    "gn:admin2_code":"58063.0",
    "gn:asciiname":"Coihueco",
    "gn:country_code":"AR",
    "gn:dem":899,
    "gn:feature_class":"P",
    "gn:feature_code":"PPL",
    "gn:name":"Coihueco",
    "gn:population":0,
    "gn:timezone":"America/Argentina/Salta",
    "iso:country":"AR",
    "wof:name":"Coihueco",
    "wof:placetype":"locality"
},
  "geometry": {"coordinates":[-70.16667,-38.06667],"type":"Point"}
}