{
  "type": "Feature",
  "properties": {
    "gn:admin1_code":"15",
    "gn:admin2_code":"58063.0",
    "gn:asciiname":"Coihueco",
    "gn:country_code":"AR",
    "gn:dem":899,
    "gn:feature_class":"P",
    "gn:feature_code":"PPL",
    "gn:name":"Coihueco",
    "gn:population":0,
    "gn:timezone":"America/Argentina/Salta",
    "iso:country":"AR",
    "name:ara_x_preferred":[
        "\u0643\u0648\u0627\u064a\u0647\u064a\u0648\u0643\u0648"
    ],
    "name:ceb_x_preferred":[
        "Coihueco"
    ],
    "name:eus_x_preferred":[
        "Coihueco"
    ],
    "name:fas_x_preferred":[
        "\u06a9\u0648\u0627\u06cc\u0647\u06cc\u0648\u06a9\u0648"
    ],
    "name:fra_x_preferred":[
        "Coihueco"
    ],
    "name:ita_x_preferred":[
        "Coihueco"
    ],
    "name:kor_x_preferred":[
        "\ucf54\uc774\uc6b0\uc5d0\ucf54"
    ],
    "name:nld_x_preferred":[
        "Coihueco"
    ],
    "name:por_x_preferred":[
        "Coihueco"
    ],
    "name:ron_x_preferred":[
        "Coihueco"
    ],
    "name:rus_x_preferred":[
        "\u041a\u043e\u0439\u0443\u044d\u043a\u043e"
    ],
    "name:spa_x_preferred":[
        "Coihueco"
    ],
    "name:swe_x_preferred":[
        "Coihueco"
    ],
    "name:zho_x_preferred":[
        "\u79d1\u4f0a\u97cb\u79d1"
    ],
    "wof:name":"Coihueco",
    "wof:placetype":"locality"
},
  "geometry": {"coordinates":[-70.16667,-38.06667],"type":"Point"}
}