{
  "type": "Feature",
  "properties": {
    "gn:admin1_code":"2.0",
    "gn:admin2_code":"10035.0",
    "gn:asciiname":"Nacimientos de Abajo",
    "gn:country_code":"AR",
    "gn:dem":2053,
    "gn:feature_class":"P",
    "gn:feature_code":"PPL",
    "gn:name":"Nacimientos de Abajo",
    "gn:population":0,
    "gn:timezone":"America/Argentina/Catamarca",
    "iso:country":"AR",
    "name:und_x_variant":[
        "Nacimientos Abajo",
        "Nacimiento",
        "Nacimientos de Abajo"
    ],
    "wof:name":"Nacimientos de Abajo",
    "wof:placetype":"locality"
},
  "geometry": {"coordinates":[-66.73235,-27.165],"type":"Point"}
}