{
  "type": "Feature",
  "properties": {
    "gn:admin1_code":"19.0",
    "gn:admin2_code":"74056.0",
    "gn:asciiname":"Las Barrancas",
    "gn:country_code":"AR",
    "gn:dem":722,
    "gn:feature_class":"P",
    "gn:feature_code":"PPL",
    "gn:name":"Las Barrancas",
    "gn:population":0,
    "gn:timezone":"America/Argentina/San_Luis",
    "iso:country":"AR",
    "wof:name":"Las Barrancas",
    "wof:placetype":"locality"
},
  "geometry": {"coordinates":[-66.2668,-33.62512],"type":"Point"}
}