{
  "type": "Feature",
  "properties": {
    "iso:country":"AR",
    "name:ceb_x_preferred":[
        "San Pedro"
    ],
    "name:fas_x_preferred":[
        "\u0633\u0627\u0646 \u067e\u062f\u0631\u0648"
    ],
    "name:fra_x_preferred":[
        "San Pedro"
    ],
    "name:hye_x_preferred":[
        "\u054d\u0561\u0576 \u054a\u0565\u0564\u0580\u0578"
    ],
    "name:nld_x_preferred":[
        "San Pedro"
    ],
    "name:pol_x_preferred":[
        "San Pedro"
    ],
    "name:por_x_preferred":[
        "San Pedro"
    ],
    "name:rus_x_preferred":[
        "\u0421\u0430\u043d-\u041f\u0435\u0434\u0440\u043e"
    ],
    "name:spa_x_preferred":[
        "San Pedro"
    ],
    "name:swe_x_preferred":[
        "San Pedro"
    ],
    "name:zho_x_preferred":[
        "\u8056\u4f69\u5fb7\u7f85"
    ],
    "qs:gn_country":"AR",
    "qs:gn_fcode":"PPL",
    "qs:gn_pop":0,
    "qs:name":"San Pedro",
    "qs:name_adm0":"Argentina",
    "qs:name_adm1":"Buenos Aires",
    "qs:photos":682,
    "qs:photos_1k":138,
    "qs:photos_9k":3,
    "qs:photos_9r":5,
    "qs:photos_all":682,
    "qs:photos_sr":8,
    "qs:placetype":"Town",
    "qs:pop_sr":"6",
    "qs:woe_adm0":23424747,
    "wd:elevation":31.0,
    "wd:population":47452,
    "wd:wordcount":926,
    "wof:name":"San Pedro",
    "wof:placetype":"locality",
    "wof:population":47452
},
  "geometry": {"coordinates":[-59.66664,-33.67913],"type":"Point"}
}