{
  "type": "Feature",
  "properties": {
    "gn:admin1_code":"1.0",
    "gn:admin2_code":"6525.0",
    "gn:asciiname":"Elias Romero",
    "gn:cc2":"AR",
    "gn:country_code":"AR",
    "gn:dem":29,
    "gn:feature_class":"P",
    "gn:feature_code":"PPL",
    "gn:name":"El\u00edas Romero",
    "gn:population":0,
    "gn:timezone":"America/Argentina/Buenos_Aires",
    "iso:country":"AR",
    "name:und_x_variant":[
        "E. Romero",
        "El\u00edas Romero"
    ],
    "wof:name":"Elias Romero",
    "wof:placetype":"locality"
},
  "geometry": {"coordinates":[-58.86666999999999,-34.76667],"type":"Point"}
}