{
  "type": "Feature",
  "properties": {
    "gn:country":"AR",
    "gn:fcode":"PPL",
    "gn:pop":1672,
    "iso:country":"AR",
    "name:eng_x_preferred":[
        "Lonquimay"
    ],
    "name:por_x_preferred":[
        "Lonquimay"
    ],
    "name:spa_x_preferred":[
        "Lonquimay"
    ],
    "name:swe_x_preferred":[
        "Lonquimay"
    ],
    "name:unk_x_variant":[
        "Pueblo Quintana"
    ],
    "qs:name":"Lonquimay",
    "qs:photos_9r":0,
    "qs:photos_sr":0,
    "qs:pop_sr":"6",
    "wd:wordcount":431,
    "wof:name":"Lonquimay",
    "wof:placetype":"locality",
    "wof:population":1672
},
  "geometry": {"coordinates":[-63.62429,-36.46546],"type":"Point"}
}