{
  "type": "Feature",
  "properties": {
    "gn:country":"AR",
    "gn:fcode":"PPL",
    "gn:population":1672,
    "iso:country":"AR",
    "name:ara_x_preferred":[
        "\u0644\u0648\u0646\u0643\u064a\u0645\u064a"
    ],
    "name:arg_x_preferred":[
        "Lonquimay"
    ],
    "name:ast_x_preferred":[
        "Lonquimay"
    ],
    "name:ben_x_preferred":[
        "\u09b2\u09a8\u0995\u09c1\u0987\u09ae\u09c7"
    ],
    "name:cat_x_preferred":[
        "Lonquimay"
    ],
    "name:ceb_x_preferred":[
        "Lonquimay"
    ],
    "name:deu_x_preferred":[
        "Lonquimay"
    ],
    "name:ell_x_preferred":[
        "\u039b\u03bf\u03bd\u03ba\u03b9\u03bc\u03ac\u03b9"
    ],
    "name:eng_x_preferred":[
        "Lonquimay"
    ],
    "name:eus_x_preferred":[
        "Lonquimay"
    ],
    "name:fas_x_preferred":[
        "\u0644\u0648\u0646\u06a9\u06cc\u0645\u0627\u06cc"
    ],
    "name:fra_x_preferred":[
        "Lonquimay"
    ],
    "name:glg_x_preferred":[
        "Lonquimay"
    ],
    "name:heb_x_preferred":[
        "\u05dc\u05e0\u05e7\u05d5\u05d5\u05d9\u05de\u05d0\u05d9"
    ],
    "name:hin_x_preferred":[
        "\u0932\u094b\u0902\u0915\u094d\u0935\u093f\u092e\u0947"
    ],
    "name:hun_x_preferred":[
        "Lonquimay"
    ],
    "name:ind_x_preferred":[
        "Lonquimay"
    ],
    "name:ita_x_preferred":[
        "Lonquimay"
    ],
    "name:kor_x_preferred":[
        "\ub871\ud0a4\ub9c8\uc774"
    ],
    "name:nld_x_preferred":[
        "Lonquimay"
    ],
    "name:oci_x_preferred":[
        "Lonquimay"
    ],
    "name:por_x_preferred":[
        "Lonquimay"
    ],
    "name:ron_x_preferred":[
        "Lonquimay"
    ],
    "name:rus_x_preferred":[
        "\u041b\u043e\u043d\u043a\u0438\u043c\u0430\u0439"
    ],
    "name:spa_x_preferred":[
        "Lonquimay"
    ],
    "name:swe_x_preferred":[
        "Lonquimay"
    ],
    "name:tur_x_preferred":[
        "Lonquimay"
    ],
    "name:ukr_x_preferred":[
        "\u041b\u043e\u043d\u043a\u0456\u043c\u0430\u0439"
    ],
    "name:und_x_variant":[
        "Pueblo Quintana"
    ],
    "name:urd_x_preferred":[
        "\u0644\u0648\u0646\u06a9\u06cc\u0645\u06d2"
    ],
    "name:vie_x_preferred":[
        "Lonquimay"
    ],
    "name:zho_x_preferred":[
        "\u9686\u57fa\u9081"
    ],
    "qs:name":"Lonquimay",
    "qs:photos_9r":0,
    "qs:photos_sr":0,
    "qs:pop_sr":"6",
    "wd:wordcount":431,
    "wof:name":"Lonquimay",
    "wof:placetype":"locality",
    "wof:population":1672
},
  "geometry": {"coordinates":[-63.62429,-36.46546],"type":"Point"}
}