{
  "type": "Feature",
  "properties": {
    "gn:country":"AR",
    "gn:fcode":"PPL",
    "gn:population":1672,
    "iso:country":"AR",
    "name:arg_x_preferred":[
        "Lonquimay"
    ],
    "name:ast_x_preferred":[
        "Lonquimay"
    ],
    "name:cat_x_preferred":[
        "Lonquimay"
    ],
    "name:ceb_x_preferred":[
        "Lonquimay"
    ],
    "name:deu_x_preferred":[
        "Lonquimay"
    ],
    "name:eng_x_preferred":[
        "Lonquimay"
    ],
    "name:eus_x_preferred":[
        "Lonquimay"
    ],
    "name:fra_x_preferred":[
        "Lonquimay"
    ],
    "name:glg_x_preferred":[
        "Lonquimay"
    ],
    "name:ita_x_preferred":[
        "Lonquimay"
    ],
    "name:kor_x_preferred":[
        "\ub871\ud0a4\ub9c8\uc774"
    ],
    "name:nld_x_preferred":[
        "Lonquimay"
    ],
    "name:oci_x_preferred":[
        "Lonquimay"
    ],
    "name:por_x_preferred":[
        "Lonquimay"
    ],
    "name:ron_x_preferred":[
        "Lonquimay"
    ],
    "name:rus_x_preferred":[
        "\u041b\u043e\u043d\u043a\u0438\u043c\u0430\u0439"
    ],
    "name:spa_x_preferred":[
        "Lonquimay"
    ],
    "name:swe_x_preferred":[
        "Lonquimay"
    ],
    "name:und_x_variant":[
        "Pueblo Quintana"
    ],
    "name:zho_x_preferred":[
        "\u9686\u57fa\u9081"
    ],
    "qs:name":"Lonquimay",
    "qs:photos_9r":0,
    "qs:photos_sr":0,
    "qs:pop_sr":"6",
    "wd:wordcount":431,
    "wof:name":"Lonquimay",
    "wof:placetype":"locality",
    "wof:population":1672
},
  "geometry": {"coordinates":[-63.62429,-36.46546],"type":"Point"}
}