{
  "type": "Feature",
  "properties": {
    "gn:admin1_code":"02",
    "gn:admin2_code":"10014.0",
    "gn:asciiname":"Comedero",
    "gn:country_code":"AR",
    "gn:dem":1297,
    "gn:feature_class":"P",
    "gn:feature_code":"PPL",
    "gn:name":"Comedero",
    "gn:population":0,
    "gn:timezone":"America/Argentina/Catamarca",
    "iso:country":"AR",
    "wof:name":"Comedero",
    "wof:placetype":"locality"
},
  "geometry": {"coordinates":[-65.58497,-28.91749],"type":"Point"}
}