{
  "type": "Feature",
  "properties": {
    "gn:admin1_code":"5.0",
    "gn:admin2_code":"14105.0",
    "gn:asciiname":"Las Saladas",
    "gn:country_code":"AR",
    "gn:dem":91,
    "gn:feature_class":"P",
    "gn:feature_code":"PPL",
    "gn:name":"Las Saladas",
    "gn:population":0,
    "gn:timezone":"America/Argentina/Cordoba",
    "iso:country":"AR",
    "wof:name":"Las Saladas",
    "wof:placetype":"locality"
},
  "geometry": {"coordinates":[-63.20313,-30.75992],"type":"Point"}
}