{
  "type": "Feature",
  "properties": {
    "gn:admin1_code":"6.0",
    "gn:admin2_code":"18091.0",
    "gn:asciiname":"Puerto Lavalle",
    "gn:country_code":"AR",
    "gn:dem":47,
    "gn:feature_class":"P",
    "gn:feature_code":"PPL",
    "gn:name":"Puerto Lavalle",
    "gn:population":0,
    "gn:timezone":"America/Argentina/Cordoba",
    "iso:country":"AR",
    "name:spa_x_preferred":[
        "Puerto Lavalle"
    ],
    "wof:name":"Puerto Lavalle",
    "wof:placetype":"locality"
},
  "geometry": {"coordinates":[-59.18333000000001,-29.03333],"type":"Point"}
}