{
  "type": "Feature",
  "properties": {
    "gn:admin1_code":"21.0",
    "gn:admin2_code":"82056.0",
    "gn:asciiname":"San Ricardo",
    "gn:country_code":"AR",
    "gn:dem":74,
    "gn:feature_class":"P",
    "gn:feature_code":"PPL",
    "gn:name":"San Ricardo",
    "gn:population":0,
    "gn:timezone":"America/Argentina/Cordoba",
    "iso:country":"AR",
    "wof:name":"San Ricardo",
    "wof:placetype":"locality"
},
  "geometry": {"coordinates":[-61.60168,-33.03026],"type":"Point"}
}