{
  "type": "Feature",
  "properties": {
    "gn:admin1_code":"5.0",
    "gn:admin2_code":"14119.0",
    "gn:asciiname":"Impira",
    "gn:country_code":"AR",
    "gn:dem":274,
    "gn:feature_class":"P",
    "gn:feature_code":"PPL",
    "gn:name":"Impira",
    "gn:population":0,
    "gn:timezone":"America/Argentina/Cordoba",
    "iso:country":"AR",
    "wof:name":"Impira",
    "wof:placetype":"locality"
},
  "geometry": {"coordinates":[-63.66667,-31.78333],"type":"Point"}
}