{
  "type": "Feature",
  "properties": {
    "gn:admin1_code":"10.0",
    "gn:admin2_code":"38112.0",
    "gn:asciiname":"San Juancito",
    "gn:country_code":"AR",
    "gn:dem":3498,
    "gn:feature_class":"P",
    "gn:feature_code":"PPL",
    "gn:name":"San Juancito",
    "gn:population":0,
    "gn:timezone":"America/Argentina/Jujuy",
    "iso:country":"AR",
    "wof:name":"San Juancito",
    "wof:placetype":"locality"
},
  "geometry": {"coordinates":[-65.55,-22.18333],"type":"Point"}
}