{
  "type": "Feature",
  "properties": {
    "gn:admin1_code":"19.0",
    "gn:admin2_code":"74014.0",
    "gn:asciiname":"Socoscora",
    "gn:country_code":"AR",
    "gn:dem":675,
    "gn:feature_class":"P",
    "gn:feature_code":"PPL",
    "gn:name":"Socoscora",
    "gn:population":0,
    "gn:timezone":"America/Argentina/San_Luis",
    "iso:country":"AR",
    "wof:name":"Socoscora",
    "wof:placetype":"locality"
},
  "geometry": {"coordinates":[-66.26666999999999,-32.56667],"type":"Point"}
}