{
  "type": "Feature",
  "properties": {
    "gn:admin1_code":"19",
    "gn:admin2_code":"74007.0",
    "gn:asciiname":"Balde de los Torres",
    "gn:country_code":"AR",
    "gn:dem":398,
    "gn:feature_class":"P",
    "gn:feature_code":"PPL",
    "gn:name":"Balde de los Torres",
    "gn:population":0,
    "gn:timezone":"America/Argentina/San_Luis",
    "iso:country":"AR",
    "name:und_x_variant":[
        "Torres",
        "Balde de Torres",
        "Balde Los Torres",
        "Balde de los Torres"
    ],
    "wof:name":"Balde de los Torres",
    "wof:placetype":"locality"
},
  "geometry": {"coordinates":[-66.10179000000001,-32.02564],"type":"Point"}
}