{
  "type": "Feature",
  "properties": {
    "gn:admin1_code":"21.0",
    "gn:admin2_code":"82021.0",
    "gn:asciiname":"Tacural",
    "gn:country_code":"AR",
    "gn:dem":100,
    "gn:feature_class":"P",
    "gn:feature_code":"PPL",
    "gn:name":"Tacural",
    "gn:population":0,
    "gn:timezone":"America/Argentina/Cordoba",
    "iso:country":"AR",
    "name:und_x_variant":[
        "Tacura",
        "Tacural"
    ],
    "wof:name":"Tacural",
    "wof:placetype":"locality"
},
  "geometry": {"coordinates":[-61.59192,-30.84633],"type":"Point"}
}