{
  "type": "Feature",
  "properties": {
    "gn:admin1_code":"21.0",
    "gn:admin2_code":"82063.0",
    "gn:asciiname":"Sauce Viejo",
    "gn:country_code":"AR",
    "gn:dem":19,
    "gn:feature_class":"P",
    "gn:feature_code":"PPL",
    "gn:name":"Sauce Viejo",
    "gn:population":0,
    "gn:timezone":"America/Argentina/Cordoba",
    "iso:country":"AR",
    "name:ceb_x_preferred":[
        "Sauce Viejo"
    ],
    "name:nld_x_preferred":[
        "Sauce Viejo"
    ],
    "name:por_x_preferred":[
        "Sauce Viejo"
    ],
    "name:spa_x_preferred":[
        "Sauce Viejo"
    ],
    "name:swe_x_preferred":[
        "Sauce Viejo"
    ],
    "name:und_x_variant":[
        "San Viejo",
        "Sauce Viejo"
    ],
    "wof:name":"Sauce Viejo",
    "wof:placetype":"locality"
},
  "geometry": {"coordinates":[-60.83666,-31.77125],"type":"Point"}
}