{
  "type": "Feature",
  "properties": {
    "iso:country":"AR",
    "name:ceb_x_preferred":[
        "Riachuelo"
    ],
    "name:deu_x_preferred":[
        "Riachuelo"
    ],
    "name:eng_x_preferred":[
        "Riachuelo"
    ],
    "name:fra_x_preferred":[
        "Riachuelo"
    ],
    "name:ita_x_preferred":[
        "Riachuelo"
    ],
    "name:nld_x_preferred":[
        "Riachuelo"
    ],
    "name:nor_x_preferred":[
        "Riachuelo"
    ],
    "name:por_x_preferred":[
        "Riachuelo"
    ],
    "name:rus_x_preferred":[
        "\u0420\u0438\u0430\u0448\u0443\u044d\u043b\u0443"
    ],
    "name:spa_x_preferred":[
        "Riachuelo"
    ],
    "name:swe_x_preferred":[
        "Riachuelo"
    ],
    "name:vol_x_preferred":[
        "Riachuelo"
    ],
    "qs:gn_country":"AR",
    "qs:gn_fcode":"PPL",
    "qs:gn_pop":3668,
    "qs:name":"Riachuelo",
    "qs:name_adm0":"Argentina",
    "qs:name_adm1":"Corrientes",
    "qs:photos":0,
    "qs:photos_1k":0,
    "qs:photos_9k":1,
    "qs:photos_9r":1,
    "qs:photos_all":12,
    "qs:photos_sr":0,
    "qs:placetype":"Town",
    "qs:pop_sr":"4",
    "qs:woe_adm0":23424747,
    "wof:name":"Riachuelo",
    "wof:placetype":"locality",
    "wof:population":3668
},
  "geometry": {"coordinates":[-58.73945,-27.57754],"type":"Point"}
}