{
  "type": "Feature",
  "properties": {
    "gn:admin1_code":"5.0",
    "gn:admin2_code":"14077.0",
    "gn:asciiname":"Piedritas Rosadas",
    "gn:country_code":"AR",
    "gn:dem":1150,
    "gn:feature_class":"P",
    "gn:feature_code":"PPL",
    "gn:name":"Piedritas Rosadas",
    "gn:population":0,
    "gn:timezone":"America/Argentina/Cordoba",
    "iso:country":"AR",
    "wof:name":"Piedritas Rosadas",
    "wof:placetype":"locality"
},
  "geometry": {"coordinates":[-65.31667,-31.33333],"type":"Point"}
}