{
  "type": "Feature",
  "properties": {
    "gn:gn_country":"AR",
    "gn:gn_fcode":"PPLX",
    "gn:gn_pop":0,
    "iso:country":"AR",
    "name:spa_x_preferred":[
        "Rivadavia"
    ],
    "name:unk_x_variant":[
        "Rivadavia"
    ],
    "qs:gn_adm0_cc":"AR",
    "qs:gn_fcode":"PPLX",
    "qs:gn_local":3838583,
    "qs:gn_namadm1":"21",
    "qs:gn_name":"Rivadavia",
    "qs:local_max":4639,
    "qs:local_sum":17736,
    "qs:localhoods":14,
    "qs:name":"Rivadavia",
    "qs:name_adm0":"Argentina",
    "qs:name_adm1":"Santa Fe",
    "qs:name_adm2":"Rosario",
    "qs:name_local":"Rosario",
    "qs:photo_max":416,
    "qs:photo_sum":2116,
    "qs:placetype":"Suburb",
    "qs:quad_count":62,
    "qs:woe_adm0":23424747,
    "qs:woe_adm1":2344695,
    "qs:woe_adm2":20070927,
    "qs:woe_lau":0,
    "qs:woe_local":466862,
    "qs:woe_ver":"7.10.0",
    "qs_pg:aaroncc":"AR",
    "qs_pg:gn_country":"AR",
    "qs_pg:gn_fcode":"PPLX",
    "qs_pg:gn_pop":0,
    "qs_pg:name":"Rivadavia",
    "qs_pg:name_adm0":"Argentina",
    "qs_pg:name_adm1":"Santa Fe",
    "qs_pg:photos":1829,
    "qs_pg:photos_1k":371,
    "qs_pg:photos_9k":8,
    "qs_pg:photos_9r":9,
    "qs_pg:photos_all":1829,
    "qs_pg:photos_sr":14,
    "qs_pg:pop_sr":0,
    "qs_pg:qs_pg_placetype":"neighbourhood",
    "qs_pg:qs_pg_placetype_gp":"Suburb",
    "qs_pg:woe_adm0":23424747,
    "wof:lang":[
        "spa"
    ],
    "wof:name":"Rivadavia",
    "wof:placetype":"neighbourhood"
},
  "geometry": {"coordinates":[-60.666836,-32.921682],"type":"Point"}
}