{
  "type": "Feature",
  "properties": {
    "gn:admin1_code":"02",
    "gn:admin2_code":"10105.0",
    "gn:asciiname":"Antinaco",
    "gn:country_code":"AR",
    "gn:dem":2042,
    "gn:feature_class":"P",
    "gn:feature_code":"PPL",
    "gn:name":"Antinaco",
    "gn:population":0,
    "gn:timezone":"America/Argentina/Catamarca",
    "iso:country":"AR",
    "name:ceb_x_preferred":[
        "Antinaco"
    ],
    "name:deu_x_preferred":[
        "Antinaco"
    ],
    "name:spa_x_preferred":[
        "Antinaco"
    ],
    "name:swe_x_preferred":[
        "Antinaco"
    ],
    "wof:name":"Antinaco",
    "wof:placetype":"locality"
},
  "geometry": {"coordinates":[-67.60755999999999,-27.2128],"type":"Point"}
}