{
  "type": "Feature",
  "properties": {
    "gn:admin1_code":"1.0",
    "gn:asciiname":"Solano",
    "gn:country_code":"AR",
    "gn:dem":168,
    "gn:feature_class":"P",
    "gn:feature_code":"PPL",
    "gn:name":"Solano",
    "gn:population":0,
    "gn:timezone":"America/Argentina/Catamarca",
    "iso:country":"AR",
    "wof:name":"Solano",
    "wof:placetype":"locality"
},
  "geometry": {"coordinates":[-67.45634,-45.69209],"type":"Point"}
}