{
  "type": "Feature",
  "properties": {
    "gn:admin1_code":"21",
    "gn:admin2_code":"82084.0",
    "gn:asciiname":"Arminda",
    "gn:country_code":"AR",
    "gn:dem":68,
    "gn:feature_class":"P",
    "gn:feature_code":"PPL",
    "gn:name":"Arminda",
    "gn:population":0,
    "gn:timezone":"America/Argentina/Cordoba",
    "iso:country":"AR",
    "name:und_x_variant":[
        "Armindo",
        "Arminda"
    ],
    "wof:name":"Arminda",
    "wof:placetype":"locality"
},
  "geometry": {"coordinates":[-60.96655,-33.26414],"type":"Point"}
}