{
  "type": "Feature",
  "properties": {
    "gn:admin1_code":"5.0",
    "gn:admin2_code":"14007.0",
    "gn:asciiname":"El Parador",
    "gn:country_code":"AR",
    "gn:dem":763,
    "gn:feature_class":"P",
    "gn:feature_code":"PPL",
    "gn:name":"El Parador",
    "gn:population":0,
    "gn:timezone":"America/Argentina/Cordoba",
    "iso:country":"AR",
    "wof:name":"El Parador",
    "wof:placetype":"locality"
},
  "geometry": {"coordinates":[-64.48333000000001,-32.11667],"type":"Point"}
}