{
  "type": "Feature",
  "properties": {
    "gn:admin1_code":"1.0",
    "gn:admin2_code":"6392.0",
    "gn:asciiname":"Emilio V. Bunge",
    "gn:country_code":"AR",
    "gn:dem":131,
    "gn:feature_class":"P",
    "gn:feature_code":"PPL",
    "gn:name":"Emilio V. Bunge",
    "gn:population":0,
    "gn:timezone":"America/Argentina/Buenos_Aires",
    "iso:country":"AR",
    "name:und_x_variant":[
        "Bunge",
        "E.V. Bunge",
        "Emilio V. Bunge"
    ],
    "wof:name":"Emilio V. Bunge",
    "wof:placetype":"locality"
},
  "geometry": {"coordinates":[-63.19557,-34.77982],"type":"Point"}
}