{
  "type": "Feature",
  "properties": {
    "gn:admin1_code":"20.0",
    "gn:admin2_code":"78007.0",
    "gn:asciiname":"Le Marchand",
    "gn:country_code":"AR",
    "gn:dem":279,
    "gn:feature_class":"P",
    "gn:feature_code":"PPL",
    "gn:name":"Le Marchand",
    "gn:population":0,
    "gn:timezone":"America/Argentina/Rio_Gallegos",
    "iso:country":"AR",
    "name:und_x_variant":[
        "Hotel de Marchand",
        "Hotel de Lemarchand"
    ],
    "wof:name":"Le Marchand",
    "wof:placetype":"locality"
},
  "geometry": {"coordinates":[-69.43129999999999,-50.75951],"type":"Point"}
}