{
  "type": "Feature",
  "properties": {
    "gn:admin1_code":"01",
    "gn:admin2_code":"6882.0",
    "gn:asciiname":"La Plata Chica",
    "gn:country_code":"AR",
    "gn:dem":20,
    "gn:feature_class":"P",
    "gn:feature_code":"PPL",
    "gn:name":"La Plata Chica",
    "gn:population":0,
    "gn:timezone":"America/Argentina/Buenos_Aires",
    "iso:country":"AR",
    "name:spa_x_preferred":[
        "La Plata Chica"
    ],
    "wof:name":"La Plata Chica",
    "wof:placetype":"locality"
},
  "geometry": {"coordinates":[-59.10914,-34.18906],"type":"Point"}
}