{
  "type": "Feature",
  "properties": {
    "gn:admin1_code":"13.0",
    "gn:admin2_code":"50105.0",
    "gn:asciiname":"Punta del Agua",
    "gn:country_code":"AR",
    "gn:dem":771,
    "gn:feature_class":"P",
    "gn:feature_code":"PPL",
    "gn:name":"Punta del Agua",
    "gn:population":0,
    "gn:timezone":"America/Argentina/Mendoza",
    "iso:country":"AR",
    "wof:name":"Punta del Agua",
    "wof:placetype":"locality"
},
  "geometry": {"coordinates":[-68.07805,-35.52737],"type":"Point"}
}