{
  "type": "Feature",
  "properties": {
    "gn:admin1_code":"5.0",
    "gn:asciiname":"El Mojon",
    "gn:country_code":"AR",
    "gn:dem":74,
    "gn:feature_class":"P",
    "gn:feature_code":"PPL",
    "gn:name":"El Moj\u00f3n",
    "gn:population":0,
    "gn:timezone":"America/Argentina/Cordoba",
    "iso:country":"AR",
    "wof:name":"El Mojon",
    "wof:placetype":"locality"
},
  "geometry": {"coordinates":[-62.52769,-30.01266],"type":"Point"}
}