{
  "type": "Feature",
  "properties": {
    "gn:admin1_code":"21",
    "gn:admin2_code":"82119.0",
    "gn:asciiname":"Aldao",
    "gn:country_code":"AR",
    "gn:dem":36,
    "gn:feature_class":"P",
    "gn:feature_code":"PPL",
    "gn:name":"Aldao",
    "gn:population":0,
    "gn:timezone":"America/Argentina/Cordoba",
    "iso:country":"AR",
    "name:ceb_x_preferred":[
        "Aldao"
    ],
    "name:fas_x_preferred":[
        "\u0627\u0644\u062f\u0627\u0626\u0648"
    ],
    "wof:name":"Aldao",
    "wof:placetype":"locality"
},
  "geometry": {"coordinates":[-60.81416,-32.70305],"type":"Point"}
}