{
  "type": "Feature",
  "properties": {
    "iso:country":"AR",
    "name:ara_x_preferred":[
        "\u0625\u0633\u0645\u0627\u0639\u064a\u0644 \u063a\u0648\u0646\u0632\u0627\u0644\u064a\u0633"
    ],
    "name:ast_x_preferred":[
        "Ismael Gonz\u00e1lez Moreno"
    ],
    "name:cat_x_preferred":[
        "Ismael Gonz\u00e1lez Moreno"
    ],
    "name:deu_x_preferred":[
        "Ismael Gonz\u00e1lez Moreno"
    ],
    "name:eng_x_preferred":[
        "Ismael Gonz\u00e1lez Moreno"
    ],
    "name:fra_x_preferred":[
        "Ismael Gonz\u00e1lez Moreno"
    ],
    "name:nld_x_preferred":[
        "Ismael Gonz\u00e1lez Moreno"
    ],
    "name:slv_x_preferred":[
        "Ismael Gonz\u00e1lez Moreno"
    ],
    "name:spa_x_preferred":[
        "Ismael Gonz\u00e1lez Moreno"
    ],
    "name:und_x_variant":[
        "Meridiano Quinto"
    ],
    "qs:gn_country":"AR",
    "qs:gn_fcode":"PPL",
    "qs:gn_pop":0,
    "qs:name":"Gonz\u00e1lez Moreno",
    "qs:name_adm0":"Argentina",
    "qs:name_adm1":"Buenos Aires",
    "qs:photos":0,
    "qs:photos_1k":0,
    "qs:photos_9k":1,
    "qs:photos_9r":1,
    "qs:photos_all":2,
    "qs:photos_sr":0,
    "qs:placetype":"Town",
    "qs:pop_sr":"6",
    "qs:woe_adm0":23424747,
    "wd:wordcount":106,
    "wof:name":"Gonz\u00e1lez Moreno",
    "wof:placetype":"locality"
},
  "geometry": {"coordinates":[-63.36667,-35.55],"type":"Point"}
}