{
  "type": "Feature",
  "properties": {
    "iso:country":"AR",
    "name:unk_x_variant":[
        "Meridiano Quinto"
    ],
    "qs:gn_country":"AR",
    "qs:gn_fcode":"PPL",
    "qs:gn_pop":0,
    "qs:name":"Gonz\u00e1lez Moreno",
    "qs:name_adm0":"Argentina",
    "qs:name_adm1":"Buenos Aires",
    "qs:photos":0,
    "qs:photos_1k":0,
    "qs:photos_9k":1,
    "qs:photos_9r":1,
    "qs:photos_all":2,
    "qs:photos_sr":0,
    "qs:placetype":"Town",
    "qs:pop_sr":"6",
    "qs:woe_adm0":23424747,
    "wd:wordcount":106,
    "wof:name":"Gonz\u00e1lez Moreno",
    "wof:placetype":"locality"
},
  "geometry": {"coordinates":[-63.36667,-35.55],"type":"Point"}
}