{
  "type": "Feature",
  "properties": {
    "iso:country":"AR",
    "qs:gn_pop":0,
    "qs:name":"Deseado",
    "qs:name_adm0":"Argentina",
    "qs:name_adm1":"Santa Cruz",
    "qs:photos":152,
    "qs:photos_1k":31,
    "qs:photos_9k":1,
    "qs:photos_9r":4,
    "qs:photos_all":152,
    "qs:photos_sr":4,
    "qs:placetype":"Town",
    "qs:pop_sr":"0",
    "qs:woe_adm0":23424747,
    "wof:name":"Deseado",
    "wof:placetype":"locality"
},
  "geometry": {"coordinates":[-65.90612400000001,-47.752597],"type":"Point"}
}