{
  "type": "Feature",
  "properties": {
    "iso:country":"AR",
    "name:ara_x_preferred":[
        "\u062f\u064a\u0633\u0627\u062f\u0648"
    ],
    "name:ben_x_preferred":[
        "\u09a6\u09c7\u09b8\u09c0\u09df\u09be\u09a6\u09cb"
    ],
    "name:ell_x_preferred":[
        "\u039d\u03c4\u03b5\u03c3\u03b5\u03ac\u03bd\u03c4\u03bf"
    ],
    "name:heb_x_preferred":[
        "\u05d3\u05b6\u05e1\u05b6\u05d0\u05b8\u05d3\u05d5\u05b9"
    ],
    "name:hin_x_preferred":[
        "\u0921\u0947\u0938\u0940\u0921\u094b"
    ],
    "name:hun_x_preferred":[
        "Deseado"
    ],
    "name:ind_x_preferred":[
        "Deseado"
    ],
    "name:ita_x_preferred":[
        "Deseado"
    ],
    "name:kor_x_preferred":[
        "\ub370\uc2dc\ub3c4"
    ],
    "name:tur_x_preferred":[
        "Deseado"
    ],
    "name:urd_x_preferred":[
        "\u0688\u06cc\u0633\u06cc\u0627\u0688\u0648"
    ],
    "name:vie_x_preferred":[
        "S\u00f4ng Deseado"
    ],
    "qs:gn_pop":0,
    "qs:name":"Deseado",
    "qs:name_adm0":"Argentina",
    "qs:name_adm1":"Santa Cruz",
    "qs:photos":152,
    "qs:photos_1k":31,
    "qs:photos_9k":1,
    "qs:photos_9r":4,
    "qs:photos_all":152,
    "qs:photos_sr":4,
    "qs:placetype":"Town",
    "qs:pop_sr":"0",
    "qs:woe_adm0":23424747,
    "wof:name":"Deseado",
    "wof:placetype":"locality"
},
  "geometry": {"coordinates":[-65.90612400000001,-47.752597],"type":"Point"}
}