{
  "type": "Feature",
  "properties": {
    "gn:admin1_code":"22.0",
    "gn:admin2_code":"86168.0",
    "gn:asciiname":"Pozo del Simbol",
    "gn:country_code":"AR",
    "gn:dem":110,
    "gn:feature_class":"P",
    "gn:feature_code":"PPL",
    "gn:name":"Pozo del Simbol",
    "gn:population":0,
    "gn:timezone":"America/Argentina/Cordoba",
    "iso:country":"AR",
    "name:und_x_variant":[
        "Pozo del Rimbol",
        "Pozo del Simbol"
    ],
    "wof:name":"Pozo del Simbol",
    "wof:placetype":"locality"
},
  "geometry": {"coordinates":[-63.55494,-28.96663],"type":"Point"}
}