{
  "type": "Feature",
  "properties": {
    "gn:admin1_code":"21.0",
    "gn:admin2_code":"82091.0",
    "gn:asciiname":"Santurce",
    "gn:country_code":"AR",
    "gn:dem":70,
    "gn:feature_class":"P",
    "gn:feature_code":"PPL",
    "gn:name":"Santurce",
    "gn:population":0,
    "gn:timezone":"America/Argentina/Cordoba",
    "iso:country":"AR",
    "name:por_x_preferred":[
        "Santurce"
    ],
    "name:sco_x_preferred":[
        "Santurce"
    ],
    "name:spa_x_preferred":[
        "Santurce"
    ],
    "wof:name":"Santurce",
    "wof:placetype":"locality"
},
  "geometry": {"coordinates":[-61.18135,-30.18985],"type":"Point"}
}