{
  "type": "Feature",
  "properties": {
    "gn:admin1_code":"19.0",
    "gn:asciiname":"Toscal",
    "gn:country_code":"AR",
    "gn:dem":342,
    "gn:feature_class":"P",
    "gn:feature_code":"PPL",
    "gn:name":"Toscal",
    "gn:population":0,
    "gn:timezone":"America/Argentina/Mendoza",
    "iso:country":"AR",
    "wof:name":"Toscal",
    "wof:placetype":"locality"
},
  "geometry": {"coordinates":[-66.58757,-35.69589000000001],"type":"Point"}
}