{
  "type": "Feature",
  "properties": {
    "gn:admin1_code":"08",
    "gn:admin2_code":"30015.0",
    "gn:asciiname":"Chacra Viuda de Diaz",
    "gn:country_code":"AR",
    "gn:dem":23,
    "gn:feature_class":"P",
    "gn:feature_code":"PPL",
    "gn:name":"Chacra Viuda de D\u00edaz",
    "gn:population":0,
    "gn:timezone":"America/Argentina/Cordoba",
    "iso:country":"AR",
    "wof:name":"Chacra Viuda de Diaz",
    "wof:placetype":"locality"
},
  "geometry": {"coordinates":[-58.04769,-31.60624],"type":"Point"}
}