{
  "type": "Feature",
  "properties": {
    "gn:admin1_code":"5.0",
    "gn:admin2_code":"14105.0",
    "gn:asciiname":"La Buena Parada",
    "gn:country_code":"AR",
    "gn:dem":218,
    "gn:feature_class":"P",
    "gn:feature_code":"PPL",
    "gn:name":"La Buena Parada",
    "gn:population":0,
    "gn:timezone":"America/Argentina/Cordoba",
    "iso:country":"AR",
    "name:und_x_variant":[
        "Yegua Muerta",
        "La Buena Parada"
    ],
    "wof:name":"La Buena Parada",
    "wof:placetype":"locality"
},
  "geometry": {"coordinates":[-63.60636,-31.17113],"type":"Point"}
}