{
  "type": "Feature",
  "properties": {
    "gn:admin1_code":"19.0",
    "gn:admin2_code":"74035.0",
    "gn:asciiname":"Molino Chico",
    "gn:country_code":"AR",
    "gn:dem":962,
    "gn:feature_class":"P",
    "gn:feature_code":"PPL",
    "gn:name":"Molino Chico",
    "gn:population":0,
    "gn:timezone":"America/Argentina/San_Luis",
    "iso:country":"AR",
    "wof:name":"Molino Chico",
    "wof:placetype":"locality"
},
  "geometry": {"coordinates":[-65.48333000000001,-33.03333],"type":"Point"}
}