{
  "type": "Feature",
  "properties": {
    "iso:country":"AR",
    "name:ara_x_preferred":[
        "\u0644\u0648\u0645\u0627\u0633 \u062f\u064a\u0644 \u0645\u064a\u0631\u0627\u062f\u0648\u0631"
    ],
    "name:arz_x_preferred":[
        "\u0644\u0648\u0645\u0627\u0633 \u062f\u064a\u0644 \u0645\u064a\u0631\u0627\u062f\u0648\u0631"
    ],
    "name:azb_x_preferred":[
        "\u0644\u0648\u0645\u0627\u0633 \u062f\u0644 \u0645\u06cc\u0631\u0627\u062f\u0648\u0631"
    ],
    "name:ceb_x_preferred":[
        "Lomas del Mirador"
    ],
    "name:eng_x_preferred":[
        "Lomas del Mirador"
    ],
    "name:fas_x_preferred":[
        "\u0644\u0648\u0645\u0627\u0633 \u062f\u0644 \u0645\u06cc\u0631\u0627\u062f\u0648\u0631"
    ],
    "name:fra_x_preferred":[
        "Lomas del Mirador"
    ],
    "name:ita_x_preferred":[
        "Lomas del Mirador"
    ],
    "name:nld_x_preferred":[
        "Lomas del Mirador"
    ],
    "name:por_x_preferred":[
        "Lomas del Mirador"
    ],
    "name:rus_x_preferred":[
        "\u041b\u043e\u043c\u0430\u0441-\u0434\u0435-\u041c\u0438\u0440\u0430\u0434\u043e\u0440"
    ],
    "name:sco_x_preferred":[
        "Lomas del Mirador"
    ],
    "name:spa_x_preferred":[
        "Lomas del Mirador"
    ],
    "name:swe_x_preferred":[
        "Lomas del Mirador"
    ],
    "name:ukr_x_preferred":[
        "\u041b\u043e\u043c\u0430\u0441-\u0434\u0435\u043b\u044c-\u041c\u0456\u0440\u0430\u0434\u043e\u0440"
    ],
    "name:zho_x_preferred":[
        "\u6d1b\u99ac\u65af\u5fb7\u723e\u7c73\u62c9\u591a\u723e"
    ],
    "qs:gn_country":"AR",
    "qs:gn_fcode":"PPL",
    "qs:gn_pop":0,
    "qs:name":"Lomas del Mirador",
    "qs:name_adm0":"Argentina",
    "qs:name_adm1":"Buenos Aires",
    "qs:photos":177,
    "qs:photos_1k":36,
    "qs:photos_9k":1,
    "qs:photos_9r":4,
    "qs:photos_all":177,
    "qs:photos_sr":4,
    "qs:placetype":"Town",
    "qs:pop_sr":"0",
    "qs:woe_adm0":23424747,
    "wd:elevation":22.0,
    "wd:wordcount":179,
    "wof:name":"Lomas del Mirador",
    "wof:placetype":"locality"
},
  "geometry": {"coordinates":[-58.53196,-34.66484],"type":"Point"}
}