{
  "type": "Feature",
  "properties": {
    "gn:admin1_code":"1.0",
    "gn:admin2_code":"6462.0",
    "gn:asciiname":"Leandro N. Alem",
    "gn:country_code":"AR",
    "gn:dem":90,
    "gn:feature_class":"P",
    "gn:feature_code":"PPL",
    "gn:name":"Leandro N. Alem",
    "gn:population":0,
    "gn:timezone":"America/Argentina/Buenos_Aires",
    "iso:country":"AR",
    "name:spa_x_preferred":[
        "Leandro N. Alem"
    ],
    "name:und_x_variant":[
        "Alem",
        "L.N. Alem",
        "Leandro Alem"
    ],
    "wof:name":"Leandro N. Alem",
    "wof:placetype":"locality"
},
  "geometry": {"coordinates":[-61.39029,-34.52109],"type":"Point"}
}