{
  "type": "Feature",
  "properties": {
    "gn:admin1_code":"1.0",
    "gn:admin2_code":"6266.0",
    "gn:asciiname":"Chenaut",
    "gn:country_code":"AR",
    "gn:dem":38,
    "gn:feature_class":"P",
    "gn:feature_code":"PPL",
    "gn:name":"Chenaut",
    "gn:population":0,
    "gn:timezone":"America/Argentina/Buenos_Aires",
    "iso:country":"AR",
    "wof:name":"Chenaut",
    "wof:placetype":"locality"
},
  "geometry": {"coordinates":[-59.21903,-34.24967],"type":"Point"}
}