{
  "type": "Feature",
  "properties": {
    "gn:admin1_code":"22.0",
    "gn:admin2_code":"86063.0",
    "gn:asciiname":"La Punta",
    "gn:country_code":"AR",
    "gn:dem":390,
    "gn:feature_class":"P",
    "gn:feature_code":"PPL",
    "gn:name":"La Punta",
    "gn:population":0,
    "gn:timezone":"America/Argentina/Cordoba",
    "iso:country":"AR",
    "name:cat_x_preferred":[
        "La Punta"
    ],
    "name:ceb_x_preferred":[
        "La Punta"
    ],
    "name:deu_x_preferred":[
        "La Punta"
    ],
    "name:jpn_x_preferred":[
        "\u30e9\u30fb\u30d7\u30f3\u30bf"
    ],
    "name:nld_x_preferred":[
        "La Punta"
    ],
    "name:srp_x_preferred":[
        "La Punta"
    ],
    "name:swe_x_preferred":[
        "La Punta"
    ],
    "name:und_x_variant":[
        "Villa La Punta"
    ],
    "wof:name":"La Punta",
    "wof:placetype":"locality"
},
  "geometry": {"coordinates":[-64.79347,-28.37054],"type":"Point"}
}