{
  "type": "Feature",
  "properties": {
    "gn:admin1_code":"12",
    "gn:admin2_code":"46084.0",
    "gn:asciiname":"Agua Colorada",
    "gn:country_code":"AR",
    "gn:dem":512,
    "gn:feature_class":"P",
    "gn:feature_code":"PPL",
    "gn:name":"Agua Colorada",
    "gn:population":0,
    "gn:timezone":"America/Argentina/La_Rioja",
    "iso:country":"AR",
    "wof:name":"Agua Colorada",
    "wof:placetype":"locality"
},
  "geometry": {"coordinates":[-66.19561999999999,-30.8672],"type":"Point"}
}