{
  "type": "Feature",
  "properties": {
    "gn:admin1_code":"13.0",
    "gn:admin2_code":"50028.0",
    "gn:asciiname":"El Sauce",
    "gn:country_code":"AR",
    "gn:dem":673,
    "gn:feature_class":"P",
    "gn:feature_code":"PPL",
    "gn:name":"El Sauce",
    "gn:population":0,
    "gn:timezone":"America/Argentina/Mendoza",
    "iso:country":"AR",
    "wof:name":"El Sauce",
    "wof:placetype":"locality"
},
  "geometry": {"coordinates":[-68.74313000000001,-32.86314],"type":"Point"}
}