{
  "type": "Feature",
  "properties": {
    "gn:admin1_code":"8.0",
    "gn:admin2_code":"30056.0",
    "gn:asciiname":"Colonia Gobernador Basavilbaso",
    "gn:country_code":"AR",
    "gn:dem":64,
    "gn:feature_class":"P",
    "gn:feature_code":"PPL",
    "gn:name":"Colonia Gobernador Basavilbaso",
    "gn:population":0,
    "gn:timezone":"America/Argentina/Cordoba",
    "iso:country":"AR",
    "wof:name":"Colonia Gobernador Basavilbaso",
    "wof:placetype":"locality"
},
  "geometry": {"coordinates":[-58.90594,-32.77008],"type":"Point"}
}