{
  "type": "Feature",
  "properties": {
    "gn:admin1_code":"12",
    "gn:admin2_code":"46056.0",
    "gn:asciiname":"Alcazar",
    "gn:country_code":"AR",
    "gn:dem":553,
    "gn:feature_class":"P",
    "gn:feature_code":"PPL",
    "gn:name":"Alc\u00e1zar",
    "gn:population":0,
    "gn:timezone":"America/Argentina/La_Rioja",
    "iso:country":"AR",
    "name:ceb_x_preferred":[
        "Alc\u00e1zar"
    ],
    "name:deu_x_preferred":[
        "Alc\u00e1zar"
    ],
    "name:ell_x_preferred":[
        "\u0391\u03bb\u03ba\u03b1\u03b6\u03ac\u03c1"
    ],
    "name:fra_x_preferred":[
        "Alcazar"
    ],
    "name:glg_x_preferred":[
        "Alc\u00e1zar"
    ],
    "name:ita_x_preferred":[
        "Alcazar"
    ],
    "name:jpn_x_preferred":[
        "\u30a2\u30eb\u30ab\u30b5\u30eb"
    ],
    "name:kor_x_preferred":[
        "\uc54c\uce74\uc0ac\ub974"
    ],
    "name:nld_x_preferred":[
        "Alcazar"
    ],
    "name:nor_x_preferred":[
        "Alcazar"
    ],
    "name:pol_x_preferred":[
        "Alkazar"
    ],
    "name:rus_x_preferred":[
        "\u0410\u043b\u044c\u043a\u0430\u0441\u0430\u0440"
    ],
    "name:sco_x_preferred":[
        "Alcazar"
    ],
    "name:slv_x_preferred":[
        "Alcazar"
    ],
    "name:spa_x_preferred":[
        "Alc\u00e1zar"
    ],
    "name:srp_x_preferred":[
        "\u0410\u043b\u043a\u0430\u0437\u0430\u0440"
    ],
    "name:swe_x_preferred":[
        "Alcazar"
    ],
    "name:tur_x_preferred":[
        "Alkazar"
    ],
    "wof:name":"Alcazar",
    "wof:placetype":"locality"
},
  "geometry": {"coordinates":[-66.54701,-30.3652],"type":"Point"}
}