{
  "type": "Feature",
  "properties": {
    "gn:admin1_code":"12",
    "gn:admin2_code":"46056.0",
    "gn:asciiname":"Alcazar",
    "gn:country_code":"AR",
    "gn:dem":553,
    "gn:feature_class":"P",
    "gn:feature_code":"PPL",
    "gn:name":"Alc\u00e1zar",
    "gn:population":0,
    "gn:timezone":"America/Argentina/La_Rioja",
    "iso:country":"AR",
    "wof:name":"Alcazar",
    "wof:placetype":"locality"
},
  "geometry": {"coordinates":[-66.54701,-30.3652],"type":"Point"}
}