{
  "type": "Feature",
  "properties": {
    "gn:country":"AR",
    "gn:fcode":"PPL",
    "gn:population":1619,
    "iso:country":"AR",
    "name:ceb_x_preferred":[
        "Bernardo Larroud\u00e9"
    ],
    "name:eng_x_preferred":[
        "Bernardo Larroud\u00e9"
    ],
    "name:nld_x_preferred":[
        "Bernardo Larroud\u00e9"
    ],
    "name:por_x_preferred":[
        "Bernardo Larroud\u00e9"
    ],
    "name:spa_x_preferred":[
        "Bernardo Larroud\u00e9"
    ],
    "name:swe_x_preferred":[
        "Bernardo Larroud\u00e9"
    ],
    "name:und_x_variant":[
        "Larroude"
    ],
    "qs:name":"Bernardo Larroud\u00e9",
    "qs:photos_9r":0,
    "qs:photos_sr":0,
    "qs:pop_sr":"3",
    "wd:wordcount":36,
    "wof:name":"Bernardo Larroud\u00e9",
    "wof:placetype":"locality",
    "wof:population":1619
},
  "geometry": {"coordinates":[-63.58253,-35.02449],"type":"Point"}
}