{
  "type": "Feature",
  "properties": {
    "gn:admin1_code":"5.0",
    "gn:admin2_code":"14084.0",
    "gn:asciiname":"Gavilan",
    "gn:country_code":"AR",
    "gn:dem":165,
    "gn:feature_class":"P",
    "gn:feature_code":"PPL",
    "gn:name":"Gavil\u00e1n",
    "gn:population":0,
    "gn:timezone":"America/Argentina/Cordoba",
    "iso:country":"AR",
    "name:ceb_x_preferred":[
        "Gavilan"
    ],
    "name:ita_x_preferred":[
        "Gavilan"
    ],
    "name:swe_x_preferred":[
        "Gavilan"
    ],
    "wof:name":"Gavilan",
    "wof:placetype":"locality"
},
  "geometry": {"coordinates":[-63.85,-34.01667],"type":"Point"}
}