{
  "type": "Feature",
  "properties": {
    "gn:admin1_code":"12.0",
    "gn:admin2_code":"46042.0",
    "gn:asciiname":"El Pique",
    "gn:cc2":"AR",
    "gn:country_code":"AR",
    "gn:dem":1936,
    "gn:feature_class":"P",
    "gn:feature_code":"PPL",
    "gn:name":"El Pique",
    "gn:population":0,
    "gn:timezone":"America/Argentina/La_Rioja",
    "iso:country":"AR",
    "name:und_x_variant":[
        "Pique",
        "El Pique"
    ],
    "wof:name":"El Pique",
    "wof:placetype":"locality"
},
  "geometry": {"coordinates":[-67.65000000000001,-29.15],"type":"Point"}
}