{
  "type": "Feature",
  "properties": {
    "iso:country":"AR",
    "name:cat_x_preferred":[
        "Pico Truncado"
    ],
    "name:ceb_x_preferred":[
        "Pico Truncado"
    ],
    "name:deu_x_preferred":[
        "Pico Truncado"
    ],
    "name:eng_x_preferred":[
        "Pico Truncado"
    ],
    "name:fra_x_preferred":[
        "Pico Truncado"
    ],
    "name:heb_x_preferred":[
        "\u05e4\u05d9\u05e7\u05d5 \u05d8\u05e8\u05d5\u05e0\u05e7\u05d3\u05d5"
    ],
    "name:hye_x_preferred":[
        "\u054a\u056b\u056f\u0578 \u054f\u0580\u0578\u0582\u0576\u056f\u0561\u0564\u0578"
    ],
    "name:ita_x_preferred":[
        "Pico Truncado"
    ],
    "name:lit_x_preferred":[
        "Piko Trunkadas"
    ],
    "name:nld_x_preferred":[
        "Pico Truncado"
    ],
    "name:oci_x_preferred":[
        "Pico Truncado"
    ],
    "name:rus_x_preferred":[
        "\u041f\u0438\u043a\u043e \u0422\u0440\u0443\u043d\u043a\u0430\u0434\u043e"
    ],
    "name:spa_x_preferred":[
        "Pico Truncado"
    ],
    "name:swe_x_preferred":[
        "Pico Truncado"
    ],
    "name:ukr_x_preferred":[
        "\u041f\u0456\u043a\u043e-\u0422\u0440\u0443\u043d\u043a\u0430\u0434\u043e"
    ],
    "name:unk_x_variant":[
        "Pico Troncado"
    ],
    "qs:gn_country":"AR",
    "qs:gn_fcode":"PPL",
    "qs:gn_pop":14985,
    "qs:name":"Pico Truncado",
    "qs:name_adm0":"Argentina",
    "qs:name_adm1":"Santa Cruz",
    "qs:photos":0,
    "qs:photos_1k":0,
    "qs:photos_9k":1,
    "qs:photos_9r":1,
    "qs:photos_all":1,
    "qs:photos_sr":0,
    "qs:placetype":"Town",
    "qs:pop_sr":"6",
    "qs:woe_adm0":23424747,
    "wd:wordcount":133,
    "wof:name":"Pico Truncado",
    "wof:placetype":"locality",
    "wof:population":14985
},
  "geometry": {"coordinates":[-67.95731000000001,-46.7949],"type":"Point"}
}