{
  "type": "Feature",
  "properties": {
    "gn:admin1_code":"24",
    "gn:admin2_code":"90007.0",
    "gn:asciiname":"Chorrillos",
    "gn:country_code":"AR",
    "gn:dem":1266,
    "gn:feature_class":"P",
    "gn:feature_code":"PPL",
    "gn:name":"Chorrillos",
    "gn:population":0,
    "gn:timezone":"America/Argentina/Tucuman",
    "iso:country":"AR",
    "name:ceb_x_preferred":[
        "Chorrillos"
    ],
    "name:swe_x_preferred":[
        "Chorrillos"
    ],
    "wof:name":"Chorrillos",
    "wof:placetype":"locality"
},
  "geometry": {"coordinates":[-64.94953000000001,-26.33809],"type":"Point"}
}