{
  "type": "Feature",
  "properties": {
    "gn:admin1_code":"21.0",
    "gn:admin2_code":"82077.0",
    "gn:asciiname":"Nueva Italia",
    "gn:country_code":"AR",
    "gn:dem":67,
    "gn:feature_class":"P",
    "gn:feature_code":"PPL",
    "gn:name":"Nueva Italia",
    "gn:population":0,
    "gn:timezone":"America/Argentina/Cordoba",
    "iso:country":"AR",
    "name:ceb_x_preferred":[
        "Nueva Italia"
    ],
    "name:sco_x_preferred":[
        "Nueva Italia"
    ],
    "name:srp_x_preferred":[
        "\u041d\u0443\u0435\u0432\u0430 \u0418\u0442\u0430\u043b\u0438\u0458\u0430"
    ],
    "name:swe_x_preferred":[
        "Nueva Italia"
    ],
    "wof:name":"Nueva Italia",
    "wof:placetype":"locality"
},
  "geometry": {"coordinates":[-61.41667,-29.81667],"type":"Point"}
}