{
  "type": "Feature",
  "properties": {
    "gn:admin1_code":"15.0",
    "gn:admin2_code":"58007.0",
    "gn:asciiname":"Sainuco",
    "gn:country_code":"AR",
    "gn:dem":1605,
    "gn:feature_class":"P",
    "gn:feature_code":"PPL",
    "gn:name":"Sainuco",
    "gn:population":0,
    "gn:timezone":"America/Argentina/Salta",
    "iso:country":"AR",
    "wof:name":"Sainuco",
    "wof:placetype":"locality"
},
  "geometry": {"coordinates":[-70.74079,-38.92196],"type":"Point"}
}