{
  "type": "Feature",
  "properties": {
    "gn:admin1_code":"21",
    "gn:admin2_code":"82042.0",
    "gn:asciiname":"Diego de Alvear",
    "gn:country_code":"AR",
    "gn:dem":119,
    "gn:feature_class":"P",
    "gn:feature_code":"PPL",
    "gn:name":"Diego de Alvear",
    "gn:population":0,
    "gn:timezone":"America/Argentina/Cordoba",
    "iso:country":"AR",
    "name:und_x_variant":[
        "Mayor Jos\u00e9 Orellanos",
        "D. de Alvear",
        "Diego de Alvear"
    ],
    "wof:name":"Diego de Alvear",
    "wof:placetype":"locality"
},
  "geometry": {"coordinates":[-62.12859,-34.37256],"type":"Point"}
}