{
  "type": "Feature",
  "properties": {
    "gn:admin1_code":"16",
    "gn:admin2_code":"62091.0",
    "gn:asciiname":"Aguada de Guerra",
    "gn:country_code":"AR",
    "gn:dem":947,
    "gn:feature_class":"P",
    "gn:feature_code":"PPL",
    "gn:name":"Aguada de Guerra",
    "gn:population":0,
    "gn:timezone":"America/Argentina/Salta",
    "iso:country":"AR",
    "name:fas_x_preferred":[
        "\u0627\u06af\u0648\u0627\u062f\u0627 \u062f\u0648 \u06af\u0631\u0648"
    ],
    "name:und_x_variant":[
        "Aguada de Guerro",
        "Aguada de Guerra"
    ],
    "name:urd_x_preferred":[
        "\u0627\u06af\u0648\u0627\u062f\u0627 \u062f \u06af\u0631\u0627"
    ],
    "wof:name":"Aguada de Guerra",
    "wof:placetype":"locality"
},
  "geometry": {"coordinates":[-68.35861,-41.05982],"type":"Point"}
}