{
  "type": "Feature",
  "properties": {
    "gn:country":"AR",
    "gn:fcode":"PPL",
    "gn:population":2902,
    "iso:country":"AR",
    "name:ceb_x_preferred":[
        "Winifreda"
    ],
    "name:eng_x_preferred":[
        "Winifreda"
    ],
    "name:fra_x_preferred":[
        "Winifreda"
    ],
    "name:nld_x_preferred":[
        "Winifreda"
    ],
    "name:por_x_preferred":[
        "Winifreda"
    ],
    "name:spa_x_preferred":[
        "Winifreda"
    ],
    "name:swe_x_preferred":[
        "Winifreda"
    ],
    "name:ukr_x_preferred":[
        "\u0412\u0456\u043d\u0456\u0444\u0440\u0435\u0434\u0430"
    ],
    "qs_pg:aaroncc":"AR",
    "qs_pg:gn_country":"AR",
    "qs_pg:gn_fcode":"PPL",
    "qs_pg:gn_pop":2902,
    "qs_pg:name":"Winifreda",
    "qs_pg:photos_9r":0,
    "qs_pg:photos_sr":0,
    "qs_pg:pop_sr":7,
    "qs_pg:qs_pg_placetype":"locality",
    "wof:name":"Winifreda",
    "wof:placetype":"locality",
    "wof:population":2902
},
  "geometry": {"coordinates":[-64.23388,-36.22643],"type":"Point"}
}