{
  "type": "Feature",
  "properties": {
    "gn:admin1_code":"10",
    "gn:admin2_code":"38112.0",
    "gn:asciiname":"Caracara",
    "gn:country_code":"AR",
    "gn:dem":3585,
    "gn:feature_class":"P",
    "gn:feature_code":"PPL",
    "gn:name":"Caracara",
    "gn:population":0,
    "gn:timezone":"America/Argentina/Jujuy",
    "iso:country":"AR",
    "wof:name":"Caracara",
    "wof:placetype":"locality"
},
  "geometry": {"coordinates":[-65.65000000000001,-22.31667],"type":"Point"}
}