{
  "type": "Feature",
  "properties": {
    "iso:country":"AR",
    "name:ceb_x_preferred":[
        "Villa del Rosario"
    ],
    "name:eng_x_preferred":[
        "Villa del Rosario"
    ],
    "name:nld_x_preferred":[
        "Villa del Rosario"
    ],
    "name:por_x_preferred":[
        "Villa del Rosario"
    ],
    "name:spa_x_preferred":[
        "Villa del Rosario"
    ],
    "name:swe_x_preferred":[
        "Villa del Rosario"
    ],
    "name:ukr_x_preferred":[
        "\u0412\u0456\u043b\u044c\u044f-\u0434\u0435\u043b\u044c-\u0420\u043e\u0441\u0430\u0440\u0456\u043e"
    ],
    "name:unk_x_variant":[
        "Villa Rosario"
    ],
    "qs:gn_country":"AR",
    "qs:gn_fcode":"PPL",
    "qs:gn_pop":3488,
    "qs:name":"Villa del Rosario",
    "qs:name_adm0":"Argentina",
    "qs:name_adm1":"Entre R\u00edos",
    "qs:photos":0,
    "qs:photos_1k":0,
    "qs:photos_9k":1,
    "qs:photos_9r":1,
    "qs:photos_all":1,
    "qs:photos_sr":0,
    "qs:placetype":"Town",
    "qs:pop_sr":"4",
    "qs:woe_adm0":23424747,
    "wd:wordcount":87,
    "wof:name":"Villa del Rosario",
    "wof:placetype":"locality",
    "wof:population":3488
},
  "geometry": {"coordinates":[-57.91257,-30.79567],"type":"Point"}
}