{
  "type": "Feature",
  "properties": {
    "gn:admin1_code":"1.0",
    "gn:admin2_code":"6413.0",
    "gn:asciiname":"Saforcada",
    "gn:country_code":"AR",
    "gn:dem":82,
    "gn:feature_class":"P",
    "gn:feature_code":"PPL",
    "gn:name":"Saforcada",
    "gn:population":0,
    "gn:timezone":"America/Argentina/Buenos_Aires",
    "iso:country":"AR",
    "wof:name":"Saforcada",
    "wof:placetype":"locality"
},
  "geometry": {"coordinates":[-61.07366999999999,-34.5724],"type":"Point"}
}