{
  "type": "Feature",
  "properties": {
    "gn:admin1_code":"1.0",
    "gn:admin2_code":"6833.0",
    "gn:asciiname":"Orense",
    "gn:country_code":"AR",
    "gn:dem":33,
    "gn:feature_class":"P",
    "gn:feature_code":"PPL",
    "gn:name":"Orense",
    "gn:population":0,
    "gn:timezone":"America/Argentina/Buenos_Aires",
    "iso:country":"AR",
    "wof:name":"Orense",
    "wof:placetype":"locality"
},
  "geometry": {"coordinates":[-59.77618,-38.682],"type":"Point"}
}