{
  "type": "Feature",
  "properties": {
    "gn:country":"AR",
    "gn:fcode":"PPL",
    "gn:pop":2333,
    "iso:country":"AR",
    "name:ceb_x_preferred":[
        "Herradura"
    ],
    "name:eng_x_preferred":[
        "Herradura"
    ],
    "name:nld_x_preferred":[
        "Herradura"
    ],
    "name:por_x_preferred":[
        "Herradura"
    ],
    "name:spa_x_preferred":[
        "Herradura"
    ],
    "name:swe_x_preferred":[
        "Herradura"
    ],
    "name:ukr_x_preferred":[
        "\u0415\u0440\u0440\u0430\u0434\u0443\u0440\u0430"
    ],
    "name:unk_x_variant":[
        "Colonia Herradura"
    ],
    "qs:name":"Herradura",
    "qs:photos_9r":0,
    "qs:photos_sr":0,
    "qs:pop_sr":"6",
    "wof:name":"Herradura",
    "wof:placetype":"locality",
    "wof:population":2333
},
  "geometry": {"coordinates":[-58.31198,-26.48705],"type":"Point"}
}