{
  "type": "Feature",
  "properties": {
    "gn:country":"AR",
    "gn:fcode":"PPL",
    "gn:pop":5174,
    "iso:country":"AR",
    "name:cat_x_preferred":[
        "Calilegua"
    ],
    "name:deu_x_preferred":[
        "Calilegua"
    ],
    "name:eng_x_preferred":[
        "Calilegua"
    ],
    "name:fra_x_preferred":[
        "Calilegua"
    ],
    "name:ita_x_preferred":[
        "Calilegua"
    ],
    "name:nld_x_preferred":[
        "Calilegua"
    ],
    "name:spa_x_preferred":[
        "Calilegua"
    ],
    "name:swe_x_preferred":[
        "Calilegua"
    ],
    "name:ukr_x_preferred":[
        "\u041a\u0430\u043b\u0456\u043b\u0435\u0433\u0432\u0430"
    ],
    "qs:name":"Calilegua",
    "qs:photos_9r":0,
    "qs:photos_sr":0,
    "qs:pop_sr":"6",
    "wof:name":"Calilegua",
    "wof:placetype":"locality",
    "wof:population":5174
},
  "geometry": {"coordinates":[-64.77002,-23.77368],"type":"Point"}
}