{
  "type": "Feature",
  "properties": {
    "gn:admin1_code":"13.0",
    "gn:admin2_code":"50070.0",
    "gn:asciiname":"Russell",
    "gn:country_code":"AR",
    "gn:dem":830,
    "gn:feature_class":"P",
    "gn:feature_code":"PPL",
    "gn:name":"Russell",
    "gn:population":0,
    "gn:timezone":"America/Argentina/Mendoza",
    "iso:country":"AR",
    "wof:name":"Russell",
    "wof:placetype":"locality"
},
  "geometry": {"coordinates":[-68.78504000000001,-33.00652],"type":"Point"}
}