{
  "type": "Feature",
  "properties": {
    "gn:admin1_code":"01",
    "gn:admin2_code":"6798.0",
    "gn:asciiname":"Crotto",
    "gn:country_code":"AR",
    "gn:dem":122,
    "gn:feature_class":"P",
    "gn:feature_code":"PPL",
    "gn:name":"Crotto",
    "gn:population":0,
    "gn:timezone":"America/Argentina/Buenos_Aires",
    "iso:country":"AR",
    "wof:name":"Crotto",
    "wof:placetype":"locality"
},
  "geometry": {"coordinates":[-60.17289,-36.57591],"type":"Point"}
}