{
  "type": "Feature",
  "properties": {
    "gn:admin1_code":"01",
    "gn:admin2_code":"6700.0",
    "gn:asciiname":"Dufaur",
    "gn:country_code":"AR",
    "gn:dem":320,
    "gn:feature_class":"P",
    "gn:feature_code":"PPL",
    "gn:name":"Dufaur",
    "gn:population":0,
    "gn:timezone":"America/Argentina/Buenos_Aires",
    "iso:country":"AR",
    "wof:name":"Dufaur",
    "wof:placetype":"locality"
},
  "geometry": {"coordinates":[-62.28486,-37.94371],"type":"Point"}
}