{
  "type": "Feature",
  "properties": {
    "gn:admin1_code":"22.0",
    "gn:admin2_code":"86140.0",
    "gn:asciiname":"Ramirez de Velazco",
    "gn:country_code":"AR",
    "gn:dem":223,
    "gn:feature_class":"P",
    "gn:feature_code":"PPL",
    "gn:name":"Ram\u00edrez de Velazco",
    "gn:population":0,
    "gn:timezone":"America/Argentina/Cordoba",
    "iso:country":"AR",
    "name:und_x_variant":[
        "Ram\u00edrez de Velasco",
        "Ram\u00edrez de Velazco"
    ],
    "wof:name":"Ramirez de Velazco",
    "wof:placetype":"locality"
},
  "geometry": {"coordinates":[-63.47212,-29.23026],"type":"Point"}
}