{
  "type": "Feature",
  "properties": {
    "iso:country":"AR",
    "name:cat_x_preferred":[
        "T\u00edo Pujio"
    ],
    "name:dut_x_preferred":[
        "T\u00edo Pujio"
    ],
    "name:eng_x_preferred":[
        "T\u00edo Pujio"
    ],
    "name:glg_x_preferred":[
        "T\u00edo Pujio"
    ],
    "name:por_x_preferred":[
        "T\u00edo Pujio"
    ],
    "name:spa_x_preferred":[
        "T\u00edo Pujio"
    ],
    "name:swe_x_preferred":[
        "T\u00edo Pujio"
    ],
    "name:ukr_x_preferred":[
        "\u0422\u0456\u043e-\u041f\u0443\u0445\u0456\u043e"
    ],
    "qs:gn_country":"AR",
    "qs:gn_fcode":"PPL",
    "qs:gn_pop":2383,
    "qs:name":"T\u00edo Pujio",
    "qs:name_adm0":"Argentina",
    "qs:name_adm1":"C\u00f3rdoba",
    "qs:photos":0,
    "qs:photos_1k":0,
    "qs:photos_9k":0,
    "qs:photos_9r":0,
    "qs:photos_all":0,
    "qs:photos_sr":0,
    "qs:placetype":"Town",
    "qs:pop_sr":"4",
    "qs:woe_adm0":23424747,
    "wof:name":"T\u00edo Pujio",
    "wof:placetype":"locality",
    "wof:population":2383
},
  "geometry": {"coordinates":[-63.35598,-32.2879],"type":"Point"}
}