{
  "type": "Feature",
  "properties": {
    "iso:country":"AR",
    "name:ceb_x_preferred":[
        "Aldea San Antonio"
    ],
    "name:eng_x_preferred":[
        "Aldea San Antonio"
    ],
    "name:fas_x_preferred":[
        "\u0627\u0644\u062f\u06cc\u0627 \u0633\u0627\u0646 \u0627\u0646\u062a\u0648\u0646\u06cc\u0648"
    ],
    "name:fra_x_preferred":[
        "Aldea San Antonio"
    ],
    "name:nld_x_preferred":[
        "Aldea San Antonio"
    ],
    "name:por_x_preferred":[
        "Aldea San Antonio"
    ],
    "name:spa_x_preferred":[
        "Aldea San Antonio"
    ],
    "name:swe_x_preferred":[
        "Aldea San Antonio"
    ],
    "name:und_x_variant":[
        "San Antonio"
    ],
    "qs:gn_country":"AR",
    "qs:gn_fcode":"PPL",
    "qs:gn_pop":1127,
    "qs:name":"Aldea San Antonio",
    "qs:name_adm0":"Argentina",
    "qs:name_adm1":"Entre R\u00edos",
    "qs:photos":0,
    "qs:photos_1k":0,
    "qs:photos_9k":1,
    "qs:photos_9r":1,
    "qs:photos_all":2,
    "qs:photos_sr":0,
    "qs:placetype":"Town",
    "qs:pop_sr":"7",
    "qs:woe_adm0":23424747,
    "wd:wordcount":93,
    "wof:name":"Aldea San Antonio",
    "wof:placetype":"locality",
    "wof:population":1127
},
  "geometry": {"coordinates":[-58.70333,-32.62376],"type":"Point"}
}