{
  "type": "Feature",
  "properties": {
    "gn:admin1_code":"13.0",
    "gn:admin2_code":"50119.0",
    "gn:asciiname":"Villa Seca",
    "gn:country_code":"AR",
    "gn:dem":998,
    "gn:feature_class":"P",
    "gn:feature_code":"PPL",
    "gn:name":"Villa Seca",
    "gn:population":0,
    "gn:timezone":"America/Argentina/Mendoza",
    "iso:country":"AR",
    "wof:name":"Villa Seca",
    "wof:placetype":"locality"
},
  "geometry": {"coordinates":[-69.17324000000001,-33.56699],"type":"Point"}
}