{
  "type": "Feature",
  "properties": {
    "gn:admin1_code":"1.0",
    "gn:admin2_code":"6056.0",
    "gn:asciiname":"Villa Pronsato",
    "gn:country_code":"AR",
    "gn:dem":17,
    "gn:feature_class":"P",
    "gn:feature_code":"PPL",
    "gn:name":"Villa Pronsato",
    "gn:population":0,
    "gn:timezone":"America/Argentina/Buenos_Aires",
    "iso:country":"AR",
    "wof:name":"Villa Pronsato",
    "wof:placetype":"locality"
},
  "geometry": {"coordinates":[-62.31667,-38.71667],"type":"Point"}
}