{
  "type": "Feature",
  "properties": {
    "iso:country":"AR",
    "name:kor_x_preferred":[
        "\ub77c\uc2a4 \ucf58\ucc28\uc2a4 \ud654\uc7ac"
    ],
    "qs:gn_country":"AR",
    "qs:gn_fcode":"PPL",
    "qs:gn_pop":0,
    "qs:name":"Las Conchas",
    "qs:name_adm0":"Argentina",
    "qs:name_adm1":"Salta",
    "qs:photos":466,
    "qs:photos_1k":94,
    "qs:photos_9k":2,
    "qs:photos_9r":5,
    "qs:photos_all":466,
    "qs:photos_sr":7,
    "qs:placetype":"Town",
    "qs:pop_sr":"0",
    "qs:woe_adm0":23424747,
    "wd:wordcount":868,
    "wof:name":"Las Conchas",
    "wof:placetype":"locality"
},
  "geometry": {"coordinates":[-65.82487999999999,-25.99764],"type":"Point"}
}