{
  "type": "Feature",
  "properties": {
    "gn:admin1_code":"6.0",
    "gn:admin2_code":"18063.0",
    "gn:asciiname":"Paso Florentin",
    "gn:country_code":"AR",
    "gn:dem":75,
    "gn:feature_class":"P",
    "gn:feature_code":"PPL",
    "gn:name":"Paso Florent\u00edn",
    "gn:population":0,
    "gn:timezone":"America/Argentina/Cordoba",
    "iso:country":"AR",
    "wof:name":"Paso Florentin",
    "wof:placetype":"locality"
},
  "geometry": {"coordinates":[-57.77631,-27.74432],"type":"Point"}
}