{
  "type": "Feature",
  "properties": {
    "gn:admin1_code":"8.0",
    "gn:admin2_code":"30098.0",
    "gn:asciiname":"Villa San Marcial",
    "gn:country_code":"AR",
    "gn:dem":56,
    "gn:feature_class":"P",
    "gn:feature_code":"PPL",
    "gn:name":"Villa San Marcial",
    "gn:population":0,
    "gn:timezone":"America/Argentina/Cordoba",
    "iso:country":"AR",
    "name:spa_x_preferred":[
        "Villa San Marcial"
    ],
    "wof:name":"Villa San Marcial",
    "wof:placetype":"locality"
},
  "geometry": {"coordinates":[-58.93333000000001,-32.16667],"type":"Point"}
}