{
  "type": "Feature",
  "properties": {
    "gn:admin1_code":"05",
    "gn:admin2_code":"14126.0",
    "gn:asciiname":"Ambul",
    "gn:country_code":"AR",
    "gn:dem":1125,
    "gn:feature_class":"P",
    "gn:feature_code":"PPL",
    "gn:name":"Ambul",
    "gn:population":0,
    "gn:timezone":"America/Argentina/Cordoba",
    "iso:country":"AR",
    "wof:name":"Ambul",
    "wof:placetype":"locality"
},
  "geometry": {"coordinates":[-65.05494,-31.4902],"type":"Point"}
}