{
  "type": "Feature",
  "properties": {
    "gn:admin1_code":"5.0",
    "gn:admin2_code":"14056.0",
    "gn:asciiname":"Pacheco de Melo",
    "gn:country_code":"AR",
    "gn:dem":138,
    "gn:feature_class":"P",
    "gn:feature_code":"PPL",
    "gn:name":"Pacheco de Melo",
    "gn:population":0,
    "gn:timezone":"America/Argentina/Cordoba",
    "iso:country":"AR",
    "wof:name":"Pacheco de Melo",
    "wof:placetype":"locality"
},
  "geometry": {"coordinates":[-63.4933,-33.76222],"type":"Point"}
}