{
  "type": "Feature",
  "properties": {
    "iso:country":"AR",
    "name:ast_x_preferred":[
        "Villanueva"
    ],
    "name:bre_x_preferred":[
        "Villanueva"
    ],
    "name:cat_x_preferred":[
        "Villanueva"
    ],
    "name:ceb_x_preferred":[
        "Villanueva"
    ],
    "name:deu_x_preferred":[
        "Villanueva"
    ],
    "name:eus_x_preferred":[
        "Villanueva"
    ],
    "name:fas_x_preferred":[
        "\u0648\u06cc\u0644\u0627\u0646\u0648\u0626\u0632\u0627"
    ],
    "name:fas_x_variant":[
        "\u0648\u06cc\u06cc\u0627\u0646\u0648\u0626\u0648\u0627"
    ],
    "name:fra_x_preferred":[
        "Villanueva"
    ],
    "name:heb_x_preferred":[
        "\u05d5\u05d9\u05dc\u05d0\u05e0\u05d5\u05d0\u05d1\u05d4"
    ],
    "name:hin_x_preferred":[
        "\u0935\u093f\u0932\u093e\u0928\u094d\u092f\u0942\u0935\u093e"
    ],
    "name:hun_x_preferred":[
        "Villanueva"
    ],
    "name:ind_x_preferred":[
        "Villanueva"
    ],
    "name:ita_x_preferred":[
        "Villanueva"
    ],
    "name:jpn_x_preferred":[
        "\u30d3\u30b8\u30e3\u30cc\u30a8\u30d0"
    ],
    "name:kor_x_preferred":[
        "\ube4c\ub77c\ub204\uc5d0\ubc14"
    ],
    "name:nds_x_preferred":[
        "Villanueva"
    ],
    "name:nld_x_preferred":[
        "Villanueva"
    ],
    "name:pol_x_preferred":[
        "Villanueva"
    ],
    "name:por_x_preferred":[
        "Villanueva"
    ],
    "name:rus_x_preferred":[
        "\u0412\u0438\u043b\u044c\u044f\u043d\u0443\u044d\u0432\u0430"
    ],
    "name:sco_x_preferred":[
        "Villanueva"
    ],
    "name:spa_x_preferred":[
        "Villanueva"
    ],
    "name:swe_x_preferred":[
        "Villanueva"
    ],
    "name:tur_x_preferred":[
        "Villanueva"
    ],
    "name:ukr_x_preferred":[
        "\u0412\u0456\u043b\u0430\u043d\u0443\u0435\u0432\u0430"
    ],
    "name:urd_x_preferred":[
        "\u0648\u0644\u0627\u0646\u06cc\u0648\u0627"
    ],
    "name:vie_x_preferred":[
        "Villanueva"
    ],
    "name:war_x_preferred":[
        "Villanueva"
    ],
    "name:zho_cn_x_preferred":[
        "\u6bd4\u4e9a\u52aa\u57c3\u74e6"
    ],
    "name:zho_tw_x_preferred":[
        "\u7dad\u62c9\u7d10\u74e6"
    ],
    "qs:gn_country":"AR",
    "qs:gn_fcode":"PPL",
    "qs:gn_pop":0,
    "qs:name":"Villanueva",
    "qs:name_adm0":"Argentina",
    "qs:name_adm1":"Buenos Aires",
    "qs:photos":0,
    "qs:photos_1k":0,
    "qs:photos_9k":0,
    "qs:photos_9r":0,
    "qs:photos_all":0,
    "qs:photos_sr":0,
    "qs:placetype":"Town",
    "qs:pop_sr":"6",
    "qs:woe_adm0":23424747,
    "wof:name":"Villanueva",
    "wof:placetype":"locality"
},
  "geometry": {"coordinates":[-58.43456,-35.67502],"type":"Point"}
}