{
  "type": "Feature",
  "properties": {
    "gn:admin1_code":"22",
    "gn:admin2_code":"86126.0",
    "gn:asciiname":"El Barrial",
    "gn:country_code":"AR",
    "gn:dem":96,
    "gn:feature_class":"P",
    "gn:feature_code":"PPL",
    "gn:name":"El Barrial",
    "gn:population":0,
    "gn:timezone":"America/Argentina/Cordoba",
    "iso:country":"AR",
    "name:spa_x_preferred":[
        "El Barrial"
    ],
    "wof:name":"El Barrial",
    "wof:placetype":"locality"
},
  "geometry": {"coordinates":[-63.35247,-29.74485],"type":"Point"}
}