{
  "type": "Feature",
  "properties": {
    "gn:admin1_code":"08",
    "gn:admin2_code":"30008.0",
    "gn:asciiname":"El Palmarito",
    "gn:country_code":"AR",
    "gn:dem":59,
    "gn:feature_class":"P",
    "gn:feature_code":"PPLL",
    "gn:name":"El Palmarito",
    "gn:population":0,
    "gn:timezone":"America/Argentina/Cordoba",
    "iso:country":"AR",
    "wof:name":"El Palmarito",
    "wof:placetype":"locality"
},
  "geometry": {"coordinates":[-58.37371,-31.8819],"type":"Point"}
}