{
  "type": "Feature",
  "properties": {
    "gn:admin1_code":"5.0",
    "gn:admin2_code":"14049.0",
    "gn:asciiname":"La Juanita",
    "gn:country_code":"AR",
    "gn:dem":610,
    "gn:feature_class":"P",
    "gn:feature_code":"PPL",
    "gn:name":"La Juanita",
    "gn:population":0,
    "gn:timezone":"America/Argentina/Cordoba",
    "iso:country":"AR",
    "wof:name":"La Juanita",
    "wof:placetype":"locality"
},
  "geometry": {"coordinates":[-64.63333,-30.53333],"type":"Point"}
}