{
  "type": "Feature",
  "properties": {
    "gn:admin1_code":"13",
    "gn:admin2_code":"50063.0",
    "gn:asciiname":"Banos Lunlunta",
    "gn:country_code":"AR",
    "gn:dem":903,
    "gn:feature_class":"P",
    "gn:feature_code":"PPL",
    "gn:name":"Ba\u00f1os Lunlunta",
    "gn:population":0,
    "gn:timezone":"America/Argentina/Mendoza",
    "iso:country":"AR",
    "wof:name":"Banos Lunlunta",
    "wof:placetype":"locality"
},
  "geometry": {"coordinates":[-68.82939,-33.06394],"type":"Point"}
}