{
  "type": "Feature",
  "properties": {
    "gn:admin1_code":"3.0",
    "gn:admin2_code":"22077.0",
    "gn:asciiname":"Colonia Popular",
    "gn:country_code":"AR",
    "gn:dem":65,
    "gn:feature_class":"P",
    "gn:feature_code":"PPL",
    "gn:name":"Colonia Popular",
    "gn:population":0,
    "gn:timezone":"America/Argentina/Cordoba",
    "iso:country":"AR",
    "name:ceb_x_preferred":[
        "Colonia Popular"
    ],
    "name:fra_x_preferred":[
        "Colonia Popular"
    ],
    "name:por_x_preferred":[
        "Colonia Popular"
    ],
    "name:spa_x_preferred":[
        "Colonia Popular"
    ],
    "name:swe_x_preferred":[
        "Colonia Popular"
    ],
    "wof:name":"Colonia Popular",
    "wof:placetype":"locality"
},
  "geometry": {"coordinates":[-59.15,-27.28333],"type":"Point"}
}