{
  "type": "Feature",
  "properties": {
    "gn:admin1_code":"3.0",
    "gn:admin2_code":"22077.0",
    "gn:asciiname":"Fortin Cardoso",
    "gn:country_code":"AR",
    "gn:dem":57,
    "gn:feature_class":"P",
    "gn:feature_code":"PPL",
    "gn:name":"Fort\u00edn Cardoso",
    "gn:population":0,
    "gn:timezone":"America/Argentina/Cordoba",
    "iso:country":"AR",
    "name:und_x_variant":[
        "Cardoso",
        "Fort\u00edn Cardozo",
        "Fort\u00edn Cardoso"
    ],
    "wof:name":"Fortin Cardoso",
    "wof:placetype":"locality"
},
  "geometry": {"coordinates":[-59.22344,-27.41017],"type":"Point"}
}