{
  "type": "Feature",
  "properties": {
    "gn:admin1_code":"05",
    "gn:admin2_code":"14147.0",
    "gn:asciiname":"Cosme Sud",
    "gn:country_code":"AR",
    "gn:dem":408,
    "gn:feature_class":"P",
    "gn:feature_code":"PPL",
    "gn:name":"Cosme Sud",
    "gn:population":0,
    "gn:timezone":"America/Argentina/Cordoba",
    "iso:country":"AR",
    "wof:name":"Cosme Sud",
    "wof:placetype":"locality"
},
  "geometry": {"coordinates":[-64.11667,-31.88333],"type":"Point"}
}