{
  "type": "Feature",
  "properties": {
    "iso:country":"AR",
    "name:arm_x_preferred":[
        "\u054d\u0565\u056b\u0562\u0561\u057d"
    ],
    "name:ceb_x_preferred":[
        "Ceibas"
    ],
    "name:dut_x_preferred":[
        "Ceibas"
    ],
    "name:eng_x_preferred":[
        "Ceibas"
    ],
    "name:spa_x_preferred":[
        "Ceibas"
    ],
    "name:swe_x_preferred":[
        "Ceibas"
    ],
    "qs:gn_country":"AR",
    "qs:gn_fcode":"PPL",
    "qs:gn_pop":1405,
    "qs:name":"Ceibas",
    "qs:name_adm0":"Argentina",
    "qs:name_adm1":"Entre R\u00edos",
    "qs:photos":0,
    "qs:photos_1k":0,
    "qs:photos_9k":1,
    "qs:photos_9r":1,
    "qs:photos_all":6,
    "qs:photos_sr":0,
    "qs:placetype":"Town",
    "qs:pop_sr":"4",
    "qs:woe_adm0":23424747,
    "wd:elevation":17.0,
    "wd:wordcount":304,
    "wof:name":"Ceibas",
    "wof:placetype":"locality",
    "wof:population":1405
},
  "geometry": {"coordinates":[-58.75,-33.43333],"type":"Point"}
}