{
  "type": "Feature",
  "properties": {
    "gn:admin1_code":"2.0",
    "gn:admin2_code":"10042.0",
    "gn:asciiname":"La Aguada",
    "gn:country_code":"AR",
    "gn:dem":632,
    "gn:feature_class":"P",
    "gn:feature_code":"PPL",
    "gn:name":"La Aguada",
    "gn:population":0,
    "gn:timezone":"America/Argentina/Catamarca",
    "iso:country":"AR",
    "wof:name":"La Aguada",
    "wof:placetype":"locality"
},
  "geometry": {"coordinates":[-65.88436999999999,-28.55012],"type":"Point"}
}