{
  "type": "Feature",
  "properties": {
    "gn:admin1_code":"18.0",
    "gn:admin2_code":"70035.0",
    "gn:asciiname":"Nikizanga",
    "gn:cc2":"AR",
    "gn:country_code":"AR",
    "gn:dem":772,
    "gn:feature_class":"P",
    "gn:feature_code":"PPL",
    "gn:name":"Nikizanga",
    "gn:population":0,
    "gn:timezone":"America/Argentina/San_Juan",
    "iso:country":"AR",
    "name:und_x_variant":[
        "Niq-uisanga",
        "Nikizanga"
    ],
    "wof:name":"Nikizanga",
    "wof:placetype":"locality"
},
  "geometry": {"coordinates":[-67.84999999999999,-31.56667],"type":"Point"}
}