{
  "type": "Feature",
  "properties": {
    "gn:admin1_code":"05",
    "gn:admin2_code":"14049.0",
    "gn:asciiname":"Delicia",
    "gn:country_code":"AR",
    "gn:dem":789,
    "gn:feature_class":"P",
    "gn:feature_code":"PPL",
    "gn:name":"Delicia",
    "gn:population":0,
    "gn:timezone":"America/Argentina/Cordoba",
    "iso:country":"AR",
    "wof:name":"Delicia",
    "wof:placetype":"locality"
},
  "geometry": {"coordinates":[-64.24016,-30.64058],"type":"Point"}
}