{
  "type": "Feature",
  "properties": {
    "gn:admin1_code":"11",
    "gn:admin2_code":"42063.0",
    "gn:asciiname":"Aguada Chos Malal",
    "gn:country_code":"AR",
    "gn:dem":808,
    "gn:feature_class":"P",
    "gn:feature_code":"PPL",
    "gn:name":"Aguada Chos Malal",
    "gn:population":0,
    "gn:timezone":"America/Argentina/Salta",
    "iso:country":"AR",
    "wof:name":"Aguada Chos Malal",
    "wof:placetype":"locality"
},
  "geometry": {"coordinates":[-68.15000000000001,-36.76667],"type":"Point"}
}