{
  "type": "Feature",
  "properties": {
    "gn:admin1_code":"01",
    "gn:admin2_code":"6588.0",
    "gn:asciiname":"Dudignac",
    "gn:country_code":"AR",
    "gn:dem":79,
    "gn:feature_class":"P",
    "gn:feature_code":"PPL",
    "gn:name":"Dudignac",
    "gn:population":0,
    "gn:timezone":"America/Argentina/Buenos_Aires",
    "iso:country":"AR",
    "wof:name":"Dudignac",
    "wof:placetype":"locality"
},
  "geometry": {"coordinates":[-60.70522,-35.64906],"type":"Point"}
}