{
  "type": "Feature",
  "properties": {
    "iso:country":"AR",
    "name:ceb_x_preferred":[
        "Villa del Dique"
    ],
    "name:eng_x_preferred":[
        "Villa del Dique"
    ],
    "name:nld_x_preferred":[
        "Villa del Dique"
    ],
    "name:por_x_preferred":[
        "Villa del Dique"
    ],
    "name:rus_x_preferred":[
        "\u0412\u0438\u043b\u044c\u044f-\u0434\u0435\u043b\u044c-\u0414\u0438\u043a\u0435"
    ],
    "name:spa_x_preferred":[
        "Villa del Dique"
    ],
    "name:swe_x_preferred":[
        "Villa del Dique"
    ],
    "name:ukr_x_preferred":[
        "\u0412\u0456\u043b\u044c\u044f-\u0434\u0435\u043b\u044c-\u0414\u0456\u043a\u0435"
    ],
    "name:unk_x_variant":[
        "Villa Dique"
    ],
    "qs:gn_country":"AR",
    "qs:gn_fcode":"PPL",
    "qs:gn_pop":2829,
    "qs:name":"Villa del Dique",
    "qs:name_adm0":"Argentina",
    "qs:name_adm1":"C\u00f3rdoba",
    "qs:photos":24,
    "qs:photos_1k":5,
    "qs:photos_9k":1,
    "qs:photos_9r":1,
    "qs:photos_all":24,
    "qs:photos_sr":1,
    "qs:placetype":"Town",
    "qs:pop_sr":"4",
    "qs:woe_adm0":23424747,
    "wd:wordcount":36,
    "wof:name":"Villa del Dique",
    "wof:placetype":"locality",
    "wof:population":2829
},
  "geometry": {"coordinates":[-64.45543000000001,-32.17667],"type":"Point"}
}