{
  "type": "Feature",
  "properties": {
    "gn:admin1_code":"24",
    "gn:admin2_code":"90056.0",
    "gn:asciiname":"Cachi Yaco",
    "gn:country_code":"AR",
    "gn:dem":340,
    "gn:feature_class":"P",
    "gn:feature_code":"PPL",
    "gn:name":"Cach\u00ed Yaco",
    "gn:population":0,
    "gn:timezone":"America/Argentina/Tucuman",
    "iso:country":"AR",
    "wof:name":"Cachi Yaco",
    "wof:placetype":"locality"
},
  "geometry": {"coordinates":[-64.99127,-27.16543],"type":"Point"}
}