{
  "type": "Feature",
  "properties": {
    "iso:country":"AR",
    "name:deu_x_preferred":[
        "Malague\u00f1o"
    ],
    "name:ell_x_preferred":[
        "\u0391\u03c4\u03bb\u03ad\u03c4\u03b9\u03ba\u03bf \u039c\u03b1\u03bb\u03b1\u03b3\u03ba\u03ad\u03bd\u03b9\u03bf"
    ],
    "name:eng_x_preferred":[
        "Malague\u00f1o"
    ],
    "name:fra_x_preferred":[
        "Atl\u00e9tico Malague\u00f1o"
    ],
    "name:glg_x_preferred":[
        "Atl\u00e9tico Malague\u00f1o"
    ],
    "name:hun_x_preferred":[
        "Atl\u00e9tico Malague\u00f1o"
    ],
    "name:nld_x_preferred":[
        "Atl\u00e9tico Malague\u00f1o"
    ],
    "name:nld_x_variant":[
        "Malague\u00f1o"
    ],
    "name:rus_x_preferred":[
        "\u0410\u0442\u043b\u0435\u0442\u0438\u043a\u043e \u041c\u0430\u043b\u0430\u0433\u0435\u043d\u044c\u043e"
    ],
    "name:spa_x_preferred":[
        "Atl\u00e9tico Malague\u00f1o"
    ],
    "name:ukr_x_preferred":[
        "\u041c\u0430\u043b\u0430\u0433\u0435\u043d\u044c\u0439\u043e"
    ],
    "qs:gn_country":"AR",
    "qs:gn_fcode":"PPL",
    "qs:gn_pop":9364,
    "qs:name":"Malague\u00f1o",
    "qs:name_adm0":"Argentina",
    "qs:name_adm1":"C\u00f3rdoba",
    "qs:photos":0,
    "qs:photos_1k":0,
    "qs:photos_9k":1,
    "qs:photos_9r":1,
    "qs:photos_all":5,
    "qs:photos_sr":0,
    "qs:placetype":"Town",
    "qs:pop_sr":"5",
    "qs:woe_adm0":23424747,
    "wof:name":"Malague\u00f1o",
    "wof:placetype":"locality",
    "wof:population":9364
},
  "geometry": {"coordinates":[-64.3584,-31.46467],"type":"Point"}
}