{
  "type": "Feature",
  "properties": {
    "gn:admin1_code":"12.0",
    "gn:admin2_code":"46014.0",
    "gn:asciiname":"Puerto Alegre",
    "gn:country_code":"AR",
    "gn:dem":435,
    "gn:feature_class":"P",
    "gn:feature_code":"PPL",
    "gn:name":"Puerto Alegre",
    "gn:population":0,
    "gn:timezone":"America/Argentina/La_Rioja",
    "iso:country":"AR",
    "wof:name":"Puerto Alegre",
    "wof:placetype":"locality"
},
  "geometry": {"coordinates":[-66.77005,-29.31946],"type":"Point"}
}