{
  "type": "Feature",
  "properties": {
    "gn:admin1_code":"19.0",
    "gn:admin2_code":"74007.0",
    "gn:asciiname":"Talita",
    "gn:country_code":"AR",
    "gn:dem":437,
    "gn:feature_class":"P",
    "gn:feature_code":"PPL",
    "gn:name":"Talita",
    "gn:population":0,
    "gn:timezone":"America/Argentina/San_Luis",
    "iso:country":"AR",
    "name:spa_x_preferred":[
        "Talita"
    ],
    "wof:name":"Talita",
    "wof:placetype":"locality"
},
  "geometry": {"coordinates":[-66.70286,-32.34083],"type":"Point"}
}