{
  "type": "Feature",
  "properties": {
    "iso:country":"AR",
    "name:ceb_x_preferred":[
        "Buenos Aires Chico"
    ],
    "name:eng_x_preferred":[
        "Buenos Aires Chico"
    ],
    "name:nld_x_preferred":[
        "Buenos Aires Chico"
    ],
    "name:spa_x_preferred":[
        "Buenos Aires Chico"
    ],
    "name:swe_x_preferred":[
        "Buenos Aires Chico"
    ],
    "name:unk_x_variant":[
        "Buenas Aires Chico"
    ],
    "qs:gn_country":"AR",
    "qs:gn_fcode":"PPL",
    "qs:gn_pop":0,
    "qs:name":"Buenos Aires Chico",
    "qs:name_adm0":"Argentina",
    "qs:name_adm1":"Chubut",
    "qs:photos":5,
    "qs:photos_1k":1,
    "qs:photos_9k":1,
    "qs:photos_9r":1,
    "qs:photos_all":5,
    "qs:photos_sr":1,
    "qs:placetype":"Town",
    "qs:pop_sr":"0",
    "qs:woe_adm0":23424747,
    "wd:wordcount":35,
    "wof:name":"Buenos Aires Chico",
    "wof:placetype":"locality"
},
  "geometry": {"coordinates":[-71.21729000000001,-42.06802],"type":"Point"}
}