{
  "type": "Feature",
  "properties": {
    "gn:admin1_code":"1.0",
    "gn:admin2_code":"6875.0",
    "gn:asciiname":"Paraje Santa Catalina",
    "gn:country_code":"AR",
    "gn:dem":21,
    "gn:feature_class":"P",
    "gn:feature_code":"PPL",
    "gn:name":"Paraje Santa Catalina",
    "gn:population":0,
    "gn:timezone":"America/Argentina/Buenos_Aires",
    "iso:country":"AR",
    "wof:name":"Paraje Santa Catalina",
    "wof:placetype":"locality"
},
  "geometry": {"coordinates":[-62.70738000000001,-39.32479],"type":"Point"}
}