{
  "type": "Feature",
  "properties": {
    "iso:country":"AR",
    "name:arz_x_preferred":[
        "\u062c\u0628\u0644 \u062a\u0634\u0627\u067e\u064a\u0644\u0643\u0648"
    ],
    "name:ceb_x_preferred":[
        "Cerro Chapelco"
    ],
    "name:eng_x_preferred":[
        "Chapelco"
    ],
    "name:fas_x_preferred":[
        "\u0686\u0627\u067e\u0644\u06a9\u0648"
    ],
    "name:jpn_x_preferred":[
        "\u30c1\u30e3\u30da\u30eb\u30b3"
    ],
    "name:lld_x_preferred":[
        "Chapelco"
    ],
    "name:nld_x_preferred":[
        "Chapelco"
    ],
    "name:pol_x_preferred":[
        "Chapelco"
    ],
    "name:por_x_preferred":[
        "Chapelco"
    ],
    "name:spa_x_preferred":[
        "Chapelco"
    ],
    "name:swe_x_preferred":[
        "Chapelco"
    ],
    "name:und_x_variant":[
        "Bazan"
    ],
    "qs:gn_country":"AR",
    "qs:gn_fcode":"PPL",
    "qs:gn_pop":0,
    "qs:name":"Chapelco",
    "qs:name_adm0":"Argentina",
    "qs:name_adm1":"Neuqu\u00e9n",
    "qs:photos":854,
    "qs:photos_1k":173,
    "qs:photos_9k":4,
    "qs:photos_9r":6,
    "qs:photos_all":854,
    "qs:photos_sr":10,
    "qs:placetype":"Town",
    "qs:pop_sr":"0",
    "qs:woe_adm0":23424747,
    "wd:wordcount":213,
    "wof:name":"Chapelco",
    "wof:placetype":"locality"
},
  "geometry": {"coordinates":[-71.21769,-40.12662],"type":"Point"}
}