{
  "type": "Feature",
  "properties": {
    "gn:admin1_code":"9.0",
    "gn:admin2_code":"34007.0",
    "gn:asciiname":"Rio Muerto",
    "gn:country_code":"AR",
    "gn:dem":177,
    "gn:feature_class":"P",
    "gn:feature_code":"PPL",
    "gn:name":"R\u00edo Muerto",
    "gn:population":0,
    "gn:timezone":"America/Argentina/Cordoba",
    "iso:country":"AR",
    "wof:name":"Rio Muerto",
    "wof:placetype":"locality"
},
  "geometry": {"coordinates":[-61.31667,-23.61667000000001],"type":"Point"}
}