{
  "type": "Feature",
  "properties": {
    "gn:admin1_code":"11.0",
    "gn:admin2_code":"42049.0",
    "gn:asciiname":"Paso de los Algarrobos",
    "gn:country_code":"AR",
    "gn:dem":284,
    "gn:feature_class":"P",
    "gn:feature_code":"PPL",
    "gn:name":"Paso de los Algarrobos",
    "gn:population":0,
    "gn:timezone":"America/Argentina/Salta",
    "iso:country":"AR",
    "wof:name":"Paso de los Algarrobos",
    "wof:placetype":"locality"
},
  "geometry": {"coordinates":[-66.9378,-36.71525],"type":"Point"}
}