{
  "type": "Feature",
  "properties": {
    "gn:admin1_code":"19",
    "gn:admin2_code":"74028.0",
    "gn:asciiname":"Balcarce",
    "gn:country_code":"AR",
    "gn:dem":904,
    "gn:feature_class":"P",
    "gn:feature_code":"PPL",
    "gn:name":"Balcarce",
    "gn:population":0,
    "gn:timezone":"America/Argentina/San_Luis",
    "iso:country":"AR",
    "wof:name":"Balcarce",
    "wof:placetype":"locality"
},
  "geometry": {"coordinates":[-65.03175,-32.56329],"type":"Point"}
}