{
  "type": "Feature",
  "properties": {
    "gn:admin1_code":"19",
    "gn:admin2_code":"74028.0",
    "gn:asciiname":"Balcarce",
    "gn:country_code":"AR",
    "gn:dem":904,
    "gn:feature_class":"P",
    "gn:feature_code":"PPL",
    "gn:name":"Balcarce",
    "gn:population":0,
    "gn:timezone":"America/Argentina/San_Luis",
    "iso:country":"AR",
    "name:ben_x_preferred":[
        "\u09ac\u09be\u09b2\u0995\u09be\u09b0\u0995\u09c7"
    ],
    "name:ceb_x_preferred":[
        "Balcarce"
    ],
    "name:deu_x_preferred":[
        "Balcarce"
    ],
    "name:ell_x_preferred":[
        "\u039c\u03c0\u03b1\u03bb\u03ba\u03ac\u03c1\u03c4\u03c3\u03b5"
    ],
    "name:heb_x_preferred":[
        "\u05d1\u05dc\u05e7\u05e8\u05e1\u05d4"
    ],
    "name:hin_x_preferred":[
        "\u092c\u093e\u0932\u0915\u093e\u0930\u094d\u0915\u0947"
    ],
    "name:hun_x_preferred":[
        "Balcarce"
    ],
    "name:ind_x_preferred":[
        "Balcarce"
    ],
    "name:jpn_x_preferred":[
        "\u30d0\u30eb\u30ab\u30eb\u30bb"
    ],
    "name:kor_x_preferred":[
        "\ubc1c\uce74\ub974\uc2a4"
    ],
    "name:nds_x_preferred":[
        "Balcarce"
    ],
    "name:nld_x_preferred":[
        "Balcarce"
    ],
    "name:por_x_preferred":[
        "Balcarce"
    ],
    "name:rus_x_preferred":[
        "\u0411\u0430\u043b\u044c\u043a\u0430\u0440\u0441\u0435"
    ],
    "name:spa_x_preferred":[
        "Balcarce"
    ],
    "name:swe_x_preferred":[
        "Balcarce"
    ],
    "name:ukr_x_preferred":[
        "\u0411\u0430\u043b\u044c\u043a\u0430\u0440\u0441\u0435"
    ],
    "name:urd_x_preferred":[
        "\u0628\u06cc\u0644\u06a9\u0627\u0631\u0633\u06cc"
    ],
    "name:vie_x_preferred":[
        "Balcarce"
    ],
    "wof:name":"Balcarce",
    "wof:placetype":"locality"
},
  "geometry": {"coordinates":[-65.03175,-32.56329],"type":"Point"}
}