{
  "type": "Feature",
  "properties": {
    "gn:admin1_code":"19",
    "gn:admin2_code":"74028.0",
    "gn:asciiname":"Balcarce",
    "gn:country_code":"AR",
    "gn:dem":904,
    "gn:feature_class":"P",
    "gn:feature_code":"PPL",
    "gn:name":"Balcarce",
    "gn:population":0,
    "gn:timezone":"America/Argentina/San_Luis",
    "iso:country":"AR",
    "name:ceb_x_preferred":[
        "Balcarce"
    ],
    "name:deu_x_preferred":[
        "Balcarce"
    ],
    "name:nds_x_preferred":[
        "Balcarce"
    ],
    "name:nld_x_preferred":[
        "Balcarce"
    ],
    "name:por_x_preferred":[
        "Balcarce"
    ],
    "name:rus_x_preferred":[
        "\u0411\u0430\u043b\u044c\u043a\u0430\u0440\u0441\u0435"
    ],
    "name:spa_x_preferred":[
        "Balcarce"
    ],
    "name:swe_x_preferred":[
        "Balcarce"
    ],
    "name:ukr_x_preferred":[
        "\u0411\u0430\u043b\u044c\u043a\u0430\u0440\u0441\u0435"
    ],
    "wof:name":"Balcarce",
    "wof:placetype":"locality"
},
  "geometry": {"coordinates":[-65.03175,-32.56329],"type":"Point"}
}