{
  "type": "Feature",
  "properties": {
    "gn:admin1_code":"14.0",
    "gn:admin2_code":"54063.0",
    "gn:asciiname":"Pilon",
    "gn:country_code":"AR",
    "gn:dem":305,
    "gn:feature_class":"P",
    "gn:feature_code":"PPL",
    "gn:name":"Pil\u00f3n",
    "gn:population":0,
    "gn:timezone":"America/Argentina/Cordoba",
    "iso:country":"AR",
    "name:ceb_x_preferred":[
        "Pilon"
    ],
    "name:deu_x_preferred":[
        "Pilon"
    ],
    "name:fra_x_preferred":[
        "Pilon"
    ],
    "name:hun_x_preferred":[
        "Pilon"
    ],
    "name:nds_x_preferred":[
        "Pilon"
    ],
    "name:pol_x_preferred":[
        "Pilon"
    ],
    "name:slv_x_preferred":[
        "Pilon"
    ],
    "name:swe_x_preferred":[
        "Pilon"
    ],
    "wof:name":"Pilon",
    "wof:placetype":"locality"
},
  "geometry": {"coordinates":[-54.33333,-26.03333],"type":"Point"}
}