{
  "type": "Feature",
  "properties": {
    "iso:country":"AR",
    "name:ceb_x_preferred":[
        "Quem\u00fa Quem\u00fa"
    ],
    "name:eng_x_preferred":[
        "Quem\u00fa Quem\u00fa"
    ],
    "name:fra_x_preferred":[
        "Quem\u00fa Quem\u00fa"
    ],
    "name:ita_x_preferred":[
        "Quem\u00fa Quem\u00fa"
    ],
    "name:nld_x_preferred":[
        "Quem\u00fa Quem\u00fa"
    ],
    "name:por_x_preferred":[
        "Quem\u00fa Quem\u00fa"
    ],
    "name:spa_x_preferred":[
        "Quem\u00fa Quem\u00fa"
    ],
    "name:swe_x_preferred":[
        "Quem\u00fa Quem\u00fa"
    ],
    "name:ukr_x_preferred":[
        "\u041a\u0435\u043c\u0443-\u041a\u0435\u043c\u0443"
    ],
    "name:zho_x_preferred":[
        "\u514b\u7a46\u514b\u7a46"
    ],
    "qs:gn_country":"AR",
    "qs:gn_fcode":"PPL",
    "qs:gn_pop":3851,
    "qs:name":"Quem\u00fa Quem\u00fa",
    "qs:name_adm0":"Argentina",
    "qs:name_adm1":"La Pampa",
    "qs:photos":0,
    "qs:photos_1k":0,
    "qs:photos_9k":1,
    "qs:photos_9r":1,
    "qs:photos_all":2,
    "qs:photos_sr":0,
    "qs:placetype":"Town",
    "qs:pop_sr":"4",
    "qs:woe_adm0":23424747,
    "wd:wordcount":32,
    "wof:name":"Quem\u00fa Quem\u00fa",
    "wof:placetype":"locality",
    "wof:population":3851
},
  "geometry": {"coordinates":[-63.56428,-36.05463],"type":"Point"}
}