{
  "type": "Feature",
  "properties": {
    "gn:admin1_code":"21.0",
    "gn:admin2_code":"82126.0",
    "gn:asciiname":"Traill",
    "gn:country_code":"AR",
    "gn:dem":78,
    "gn:feature_class":"P",
    "gn:feature_code":"PPL",
    "gn:name":"Traill",
    "gn:population":0,
    "gn:timezone":"America/Argentina/Cordoba",
    "iso:country":"AR",
    "name:deu_x_preferred":[
        "Traill"
    ],
    "name:por_x_preferred":[
        "Traill"
    ],
    "name:und_x_variant":[
        "Traili",
        "Traill"
    ],
    "wof:name":"Traill",
    "wof:placetype":"locality"
},
  "geometry": {"coordinates":[-61.70137,-31.92067],"type":"Point"}
}