{
  "type": "Feature",
  "properties": {
    "gn:admin1_code":"24.0",
    "gn:admin2_code":"90056.0",
    "gn:asciiname":"Palmitas",
    "gn:country_code":"AR",
    "gn:dem":324,
    "gn:feature_class":"P",
    "gn:feature_code":"PPL",
    "gn:name":"Palmitas",
    "gn:population":0,
    "gn:timezone":"America/Argentina/Tucuman",
    "iso:country":"AR",
    "name:cat_x_preferred":[
        "Palmitas"
    ],
    "name:deu_x_preferred":[
        "Palmitas"
    ],
    "name:fra_x_preferred":[
        "Palmitas"
    ],
    "name:hye_x_preferred":[
        "\u054a\u0561\u056c\u0574\u056b\u057f\u0561\u057d"
    ],
    "name:ita_x_preferred":[
        "Palmitas"
    ],
    "name:nds_x_preferred":[
        "Palmitas"
    ],
    "name:nor_x_preferred":[
        "Palmitas"
    ],
    "name:rus_x_preferred":[
        "\u041f\u0430\u043b\u044c\u043c\u0438\u0442\u0430\u0441"
    ],
    "name:spa_x_preferred":[
        "Palmitas"
    ],
    "name:und_x_variant":[
        "Palomitas",
        "Palmitas"
    ],
    "wof:name":"Palmitas",
    "wof:placetype":"locality"
},
  "geometry": {"coordinates":[-64.93482,-27.24959],"type":"Point"}
}