{
  "type": "Feature",
  "properties": {
    "gn:admin1_code":"24.0",
    "gn:admin2_code":"90056.0",
    "gn:asciiname":"Palmitas",
    "gn:country_code":"AR",
    "gn:dem":324,
    "gn:feature_class":"P",
    "gn:feature_code":"PPL",
    "gn:name":"Palmitas",
    "gn:population":0,
    "gn:timezone":"America/Argentina/Tucuman",
    "iso:country":"AR",
    "name:und_x_variant":[
        "Palomitas",
        "Palmitas"
    ],
    "wof:name":"Palmitas",
    "wof:placetype":"locality"
},
  "geometry": {"coordinates":[-64.93482,-27.24959],"type":"Point"}
}