{
  "type": "Feature",
  "properties": {
    "gn:admin1_code":"1.0",
    "gn:admin2_code":"6049.0",
    "gn:asciiname":"Campodonico",
    "gn:country_code":"AR",
    "gn:dem":84,
    "gn:feature_class":"P",
    "gn:feature_code":"PPL",
    "gn:name":"Campod\u00f3nico",
    "gn:population":0,
    "gn:timezone":"America/Argentina/Buenos_Aires",
    "iso:country":"AR",
    "name:und_x_variant":[
        "Arroyo de los Heros",
        "Campod\u00f3nico"
    ],
    "wof:name":"Campodonico",
    "wof:placetype":"locality"
},
  "geometry": {"coordinates":[-59.79286,-36.34753],"type":"Point"}
}