{
  "type": "Feature",
  "properties": {
    "gn:admin1_code":"24",
    "gn:admin2_code":"90014.0",
    "gn:asciiname":"Canete",
    "gn:country_code":"AR",
    "gn:dem":426,
    "gn:feature_class":"P",
    "gn:feature_code":"PPL",
    "gn:name":"Ca\u00f1ete",
    "gn:population":0,
    "gn:timezone":"America/Argentina/Tucuman",
    "iso:country":"AR",
    "wof:name":"Canete",
    "wof:placetype":"locality"
},
  "geometry": {"coordinates":[-64.85589,-26.89299],"type":"Point"}
}