{
  "type": "Feature",
  "properties": {
    "iso:country":"AR",
    "name:ceb_x_preferred":[
        "Loro Huasi"
    ],
    "name:eng_x_preferred":[
        "Loro Huasi"
    ],
    "name:spa_x_preferred":[
        "Loro Huasi"
    ],
    "name:swe_x_preferred":[
        "Loro Huasi"
    ],
    "name:und_x_variant":[
        "Lora Huasi"
    ],
    "qs:gn_country":"AR",
    "qs:gn_fcode":"PPL",
    "qs:gn_pop":0,
    "qs:name":"Loro Huasi",
    "qs:name_adm0":"Argentina",
    "qs:name_adm1":"Salta",
    "qs:photos":193,
    "qs:photos_1k":39,
    "qs:photos_9k":1,
    "qs:photos_9r":4,
    "qs:photos_all":193,
    "qs:photos_sr":4,
    "qs:placetype":"Town",
    "qs:pop_sr":"0",
    "qs:woe_adm0":23424747,
    "wd:wordcount":36,
    "wof:name":"Loro Huasi",
    "wof:placetype":"locality"
},
  "geometry": {"coordinates":[-65.97049,-26.1125],"type":"Point"}
}