{
  "type": "Feature",
  "properties": {
    "gn:admin1_code":"1.0",
    "gn:admin2_code":"6707.0",
    "gn:asciiname":"La Barrancosa",
    "gn:country_code":"AR",
    "gn:dem":48,
    "gn:feature_class":"P",
    "gn:feature_code":"PPL",
    "gn:name":"La Barrancosa",
    "gn:population":0,
    "gn:timezone":"America/Argentina/Buenos_Aires",
    "iso:country":"AR",
    "wof:name":"La Barrancosa",
    "wof:placetype":"locality"
},
  "geometry": {"coordinates":[-59.86819000000001,-35.73779000000001],"type":"Point"}
}