{
  "type": "Feature",
  "properties": {
    "gn:admin1_code":"18.0",
    "gn:admin2_code":"70035.0",
    "gn:asciiname":"Vallecito",
    "gn:country_code":"AR",
    "gn:dem":801,
    "gn:feature_class":"P",
    "gn:feature_code":"PPL",
    "gn:name":"Vallecito",
    "gn:population":0,
    "gn:timezone":"America/Argentina/San_Juan",
    "iso:country":"AR",
    "name:ceb_x_preferred":[
        "Vallecito"
    ],
    "name:deu_x_preferred":[
        "Vallecito"
    ],
    "name:swe_x_preferred":[
        "Vallecito"
    ],
    "wof:name":"Vallecito",
    "wof:placetype":"locality"
},
  "geometry": {"coordinates":[-67.99148000000001,-31.73946],"type":"Point"}
}