{
  "type": "Feature",
  "properties": {
    "gn:admin1_code":"9.0",
    "gn:admin2_code":"34042.0",
    "gn:asciiname":"Villa Real",
    "gn:country_code":"AR",
    "gn:dem":87,
    "gn:feature_class":"P",
    "gn:feature_code":"PPL",
    "gn:name":"Villa Real",
    "gn:population":0,
    "gn:timezone":"America/Argentina/Cordoba",
    "iso:country":"AR",
    "wof:name":"Villa Real",
    "wof:placetype":"locality"
},
  "geometry": {"coordinates":[-58.54183,-25.06225],"type":"Point"}
}