{
  "type": "Feature",
  "properties": {
    "iso:country":"AR",
    "name:ell_x_preferred":[
        "\u039c\u03b1\u03bb\u03ac\u03c1\u03b3\u03bf\u03c5\u03b5"
    ],
    "name:eng_x_preferred":[
        "Malarg\u00fce"
    ],
    "name:lit_x_preferred":[
        "Malarguj\u0117"
    ],
    "name:unk_x_variant":[
        "Villa Malarg\u00fce"
    ],
    "name:zho_x_preferred":[
        "\u9a6c\u62c9\u572d"
    ],
    "qs:gn_country":"AR",
    "qs:gn_fcode":"PPL",
    "qs:gn_pop":0,
    "qs:name":"Malarg\u00fce",
    "qs:name_adm0":"Argentina",
    "qs:name_adm1":"Mendoza",
    "qs:photos":195,
    "qs:photos_1k":40,
    "qs:photos_9k":1,
    "qs:photos_9r":4,
    "qs:photos_all":195,
    "qs:photos_sr":4,
    "qs:placetype":"Town",
    "qs:pop_sr":"6",
    "qs:woe_adm0":23424747,
    "wd:wordcount":534,
    "wof:name":"Malarg\u00fce",
    "wof:placetype":"locality"
},
  "geometry": {"coordinates":[-69.58427,-35.47546],"type":"Point"}
}