{
  "type": "Feature",
  "properties": {
    "iso:country":"AR",
    "name:ast_x_preferred":[
        "Malarg\u00fce"
    ],
    "name:ces_x_preferred":[
        "Malarg\u00fce"
    ],
    "name:deu_x_preferred":[
        "Malarg\u00fce"
    ],
    "name:ell_x_preferred":[
        "\u039c\u03b1\u03bb\u03ac\u03c1\u03b3\u03bf\u03c5\u03b5"
    ],
    "name:eng_x_preferred":[
        "Malarg\u00fce"
    ],
    "name:fas_x_preferred":[
        "\u0645\u0627\u0644\u0627\u0631\u06af\u0648\u06cc\u06cc"
    ],
    "name:fra_x_preferred":[
        "Malarg\u00fce"
    ],
    "name:heb_x_preferred":[
        "\u05de\u05dc\u05e8\u05d2\u05d5\u05d0\u05d4"
    ],
    "name:jpn_x_preferred":[
        "\u30de\u30e9\u30eb\u30b2"
    ],
    "name:lit_x_preferred":[
        "Malarguj\u0117"
    ],
    "name:nld_x_preferred":[
        "Malarg\u00fce"
    ],
    "name:pol_x_preferred":[
        "Malarg\u00fce"
    ],
    "name:por_x_preferred":[
        "Malarg\u00fce"
    ],
    "name:spa_x_preferred":[
        "El Cruce"
    ],
    "name:spa_x_variant":[
        "Malarg\u00fce"
    ],
    "name:tur_x_preferred":[
        "Malarg\u00fce"
    ],
    "name:ukr_x_preferred":[
        "\u041c\u0430\u043b\u0430\u0440\u0433\u0432\u0435"
    ],
    "name:und_x_variant":[
        "Villa Malarg\u00fce"
    ],
    "name:zho_x_preferred":[
        "\u9a6c\u62c9\u572d"
    ],
    "qs:gn_country":"AR",
    "qs:gn_fcode":"PPL",
    "qs:gn_pop":0,
    "qs:name":"Malarg\u00fce",
    "qs:name_adm0":"Argentina",
    "qs:name_adm1":"Mendoza",
    "qs:photos":195,
    "qs:photos_1k":40,
    "qs:photos_9k":1,
    "qs:photos_9r":4,
    "qs:photos_all":195,
    "qs:photos_sr":4,
    "qs:placetype":"Town",
    "qs:pop_sr":"6",
    "qs:woe_adm0":23424747,
    "wd:wordcount":534,
    "wof:name":"Malarg\u00fce",
    "wof:placetype":"locality"
},
  "geometry": {"coordinates":[-69.58427,-35.47546],"type":"Point"}
}