{
  "type": "Feature",
  "properties": {
    "gn:admin1_code":"6.0",
    "gn:admin2_code":"18056.0",
    "gn:asciiname":"Las Palmitas",
    "gn:country_code":"AR",
    "gn:dem":73,
    "gn:feature_class":"P",
    "gn:feature_code":"PPL",
    "gn:name":"Las Palmitas",
    "gn:population":0,
    "gn:timezone":"America/Argentina/Cordoba",
    "iso:country":"AR",
    "name:und_x_variant":[
        "Palmitas",
        "Las Palmitas"
    ],
    "wof:name":"Las Palmitas",
    "wof:placetype":"locality"
},
  "geometry": {"coordinates":[-56.51243,-28.99777000000001],"type":"Point"}
}