{
  "type": "Feature",
  "properties": {
    "gn:country":"AR",
    "gn:fcode":"PPL",
    "gn:population":8237,
    "iso:country":"AR",
    "name:ast_x_preferred":[
        "Brinkmann"
    ],
    "name:cat_x_preferred":[
        "Brinkmann"
    ],
    "name:ceb_x_preferred":[
        "Brinkmann"
    ],
    "name:deu_x_preferred":[
        "Brinkmann"
    ],
    "name:eng_x_preferred":[
        "Brinkmann"
    ],
    "name:fra_x_preferred":[
        "Brinkmann"
    ],
    "name:glg_x_preferred":[
        "Brinkmann"
    ],
    "name:ita_x_preferred":[
        "Brinkmann"
    ],
    "name:jpn_x_preferred":[
        "\u30d6\u30ea\u30f3\u30af\u30de\u30f3"
    ],
    "name:nld_x_preferred":[
        "Brinkmann"
    ],
    "name:nld_x_variant":[
        "Brinkman"
    ],
    "name:por_x_preferred":[
        "Brinkmann"
    ],
    "name:sco_x_preferred":[
        "Brinkmann"
    ],
    "name:spa_x_preferred":[
        "Brinkmann"
    ],
    "name:swe_x_preferred":[
        "Brinkmann"
    ],
    "name:ukr_x_preferred":[
        "\u0411\u0440\u0456\u043d\u043a\u043c\u0430\u043d\u043d"
    ],
    "qs:name":"Brinkmann",
    "qs:photos_9r":0,
    "qs:photos_sr":0,
    "qs:pop_sr":"7",
    "wd:wordcount":267,
    "wof:name":"Brinkmann",
    "wof:placetype":"locality",
    "wof:population":8237
},
  "geometry": {"coordinates":[-62.03742,-30.8659],"type":"Point"}
}