{
  "type": "Feature",
  "properties": {
    "iso:country":"AR",
    "name:ceb_x_preferred":[
        "Guavirav\u00ed"
    ],
    "name:dut_x_preferred":[
        "Guavirav\u00ed"
    ],
    "name:eng_x_preferred":[
        "Guavirav\u00ed"
    ],
    "name:swe_x_preferred":[
        "Guavirav\u00ed"
    ],
    "qs:gn_country":"AR",
    "qs:gn_fcode":"PPL",
    "qs:gn_pop":641,
    "qs:name":"Guavirav\u00ed",
    "qs:name_adm0":"Argentina",
    "qs:name_adm1":"Corrientes",
    "qs:photos":0,
    "qs:photos_1k":0,
    "qs:photos_9k":0,
    "qs:photos_9r":0,
    "qs:photos_all":0,
    "qs:photos_sr":0,
    "qs:placetype":"Town",
    "qs:pop_sr":"5",
    "qs:woe_adm0":23424747,
    "wd:wordcount":35,
    "wof:name":"Guavirav\u00ed",
    "wof:placetype":"locality",
    "wof:population":641
},
  "geometry": {"coordinates":[-56.82868,-29.36816],"type":"Point"}
}