{
  "type": "Feature",
  "properties": {
    "iso:country":"AR",
    "name:unk_x_variant":[
        "Balneario Reta"
    ],
    "qs:gn_country":"AR",
    "qs:gn_fcode":"PPL",
    "qs:gn_pop":0,
    "qs:name":"Balneario Oc\u00e9ano",
    "qs:name_adm0":"Argentina",
    "qs:name_adm1":"Buenos Aires",
    "qs:photos":63,
    "qs:photos_1k":13,
    "qs:photos_9k":1,
    "qs:photos_9r":2,
    "qs:photos_all":63,
    "qs:photos_sr":2,
    "qs:placetype":"Town",
    "qs:pop_sr":"0",
    "qs:woe_adm0":23424747,
    "wof:name":"Balneario Oc\u00e9ano",
    "wof:placetype":"locality"
},
  "geometry": {"coordinates":[-60.33948,-38.89564],"type":"Point"}
}