{
  "type": "Feature",
  "properties": {
    "gn:admin1_code":"1.0",
    "gn:admin2_code":"6547.0",
    "gn:asciiname":"Zenon Videla Dorna",
    "gn:country_code":"AR",
    "gn:dem":26,
    "gn:feature_class":"P",
    "gn:feature_code":"PPL",
    "gn:name":"Zen\u00f3n Videla Dorna",
    "gn:population":0,
    "gn:timezone":"America/Argentina/Buenos_Aires",
    "iso:country":"AR",
    "name:und_x_variant":[
        "Z. Videla Dorna",
        "Zen\u00f3n Videla Dorna"
    ],
    "wof:name":"Zenon Videla Dorna",
    "wof:placetype":"locality"
},
  "geometry": {"coordinates":[-58.8862,-35.54257],"type":"Point"}
}