{
  "type": "Feature",
  "properties": {
    "gn:admin1_code":"1.0",
    "gn:admin2_code":"6434.0",
    "gn:asciiname":"Caraza",
    "gn:country_code":"AR",
    "gn:dem":7,
    "gn:feature_class":"P",
    "gn:feature_code":"PPL",
    "gn:name":"Caraza",
    "gn:population":0,
    "gn:timezone":"America/Argentina/Buenos_Aires",
    "iso:country":"AR",
    "name:spa_x_preferred":[
        "Caraza"
    ],
    "wof:name":"Caraza",
    "wof:placetype":"locality"
},
  "geometry": {"coordinates":[-58.42983,-34.69676],"type":"Point"}
}