{
  "type": "Feature",
  "properties": {
    "iso:country":"AR",
    "name:eng_x_preferred":[
        "La Paz"
    ],
    "name:por_x_preferred":[
        "La Paz"
    ],
    "name:spa_x_preferred":[
        "La Paz"
    ],
    "name:urd_x_preferred":[
        "\u0644\u0627 \u067e\u0627\u0632\u060c \u0642\u0631\u0637\u0628\u06c1"
    ],
    "name:urd_x_variant":[
        "\u0644\u0627 \u067e\u0627\u0632"
    ],
    "qs:gn_country":"AR",
    "qs:gn_fcode":"PPL",
    "qs:gn_pop":0,
    "qs:name":"La Paz",
    "qs:name_adm0":"Argentina",
    "qs:name_adm1":"C\u00f3rdoba",
    "qs:photos":57,
    "qs:photos_1k":12,
    "qs:photos_9k":1,
    "qs:photos_9r":2,
    "qs:photos_all":57,
    "qs:photos_sr":2,
    "qs:placetype":"Town",
    "qs:pop_sr":"6",
    "qs:woe_adm0":23424747,
    "wd:wordcount":97,
    "wof:name":"La Paz",
    "wof:placetype":"locality"
},
  "geometry": {"coordinates":[-65.04831,-32.21659],"type":"Point"}
}