{
  "type": "Feature",
  "properties": {
    "iso:country":"AR",
    "name:ben_x_preferred":[
        "\u09b2\u09be \u09aa\u09be\u099c"
    ],
    "name:ell_x_preferred":[
        "\u039b\u03b1 \u03a0\u03b1\u03b6"
    ],
    "name:eng_x_preferred":[
        "La Paz"
    ],
    "name:fra_x_preferred":[
        "La Paz"
    ],
    "name:heb_x_preferred":[
        "\u05dc\u05d4 \u05e4\u05d6"
    ],
    "name:hin_x_preferred":[
        "\u0932\u093e \u092a\u093e\u091c\u093c"
    ],
    "name:hun_x_preferred":[
        "La Paz"
    ],
    "name:ind_x_preferred":[
        "La Paz"
    ],
    "name:kor_x_preferred":[
        "\ub77c\ud30c\uc2a4"
    ],
    "name:por_x_preferred":[
        "La Paz"
    ],
    "name:rus_x_preferred":[
        "\u041b\u0430-\u041f\u0430\u0441"
    ],
    "name:spa_x_preferred":[
        "La Paz"
    ],
    "name:swe_x_preferred":[
        "La Paz"
    ],
    "name:tur_x_preferred":[
        "La Paz"
    ],
    "name:urd_x_preferred":[
        "\u0644\u0627 \u067e\u0627\u0632\u060c \u0642\u0631\u0637\u0628\u06c1"
    ],
    "name:urd_x_variant":[
        "\u0644\u0627 \u067e\u0627\u0632"
    ],
    "name:vie_x_preferred":[
        "La Paz"
    ],
    "name:zho_cn_x_preferred":[
        "\u62c9\u5df4\u65af"
    ],
    "name:zho_tw_x_preferred":[
        "\u62c9\u5df4\u65af"
    ],
    "qs:gn_country":"AR",
    "qs:gn_fcode":"PPL",
    "qs:gn_pop":0,
    "qs:name":"La Paz",
    "qs:name_adm0":"Argentina",
    "qs:name_adm1":"C\u00f3rdoba",
    "qs:photos":57,
    "qs:photos_1k":12,
    "qs:photos_9k":1,
    "qs:photos_9r":2,
    "qs:photos_all":57,
    "qs:photos_sr":2,
    "qs:placetype":"Town",
    "qs:pop_sr":"6",
    "qs:woe_adm0":23424747,
    "wd:wordcount":97,
    "wof:name":"La Paz",
    "wof:placetype":"locality"
},
  "geometry": {"coordinates":[-65.04831,-32.21659],"type":"Point"}
}