{
  "type": "Feature",
  "properties": {
    "gn:admin1_code":"21.0",
    "gn:admin2_code":"82084.0",
    "gn:asciiname":"Los Muchachos",
    "gn:country_code":"AR",
    "gn:dem":44,
    "gn:feature_class":"P",
    "gn:feature_code":"PPL",
    "gn:name":"Los Muchachos",
    "gn:population":0,
    "gn:timezone":"America/Argentina/Cordoba",
    "iso:country":"AR",
    "wof:name":"Los Muchachos",
    "wof:placetype":"locality"
},
  "geometry": {"coordinates":[-60.7579,-33.0902],"type":"Point"}
}