{
  "type": "Feature",
  "properties": {
    "gn:admin1_code":"22.0",
    "gn:admin2_code":"86035.0",
    "gn:asciiname":"Palmitas",
    "gn:country_code":"AR",
    "gn:dem":180,
    "gn:feature_class":"P",
    "gn:feature_code":"PPL",
    "gn:name":"Palmitas",
    "gn:population":0,
    "gn:timezone":"America/Argentina/Cordoba",
    "iso:country":"AR",
    "wof:name":"Palmitas",
    "wof:placetype":"locality"
},
  "geometry": {"coordinates":[-64.12961999999999,-27.62377],"type":"Point"}
}