{
  "type": "Feature",
  "properties": {
    "gn:admin1_code":"1.0",
    "gn:admin2_code":"6483.0",
    "gn:asciiname":"Elvira",
    "gn:country_code":"AR",
    "gn:dem":36,
    "gn:feature_class":"P",
    "gn:feature_code":"PPL",
    "gn:name":"Elvira",
    "gn:population":0,
    "gn:timezone":"America/Argentina/Buenos_Aires",
    "iso:country":"AR",
    "name:deu_x_preferred":[
        "Elvira"
    ],
    "name:hun_x_preferred":[
        "Elvira"
    ],
    "name:ita_x_preferred":[
        "Elvira"
    ],
    "name:nld_x_preferred":[
        "Elvira"
    ],
    "name:nor_x_preferred":[
        "Elvira"
    ],
    "name:rus_x_preferred":[
        "\u042d\u043b\u044c\u0432\u0438\u0440\u0430"
    ],
    "name:slv_x_preferred":[
        "Elvira"
    ],
    "name:spa_x_preferred":[
        "Elvira"
    ],
    "name:srp_x_preferred":[
        "\u0415\u043b\u0432\u0438\u0440\u0430"
    ],
    "name:swe_x_preferred":[
        "Elvira"
    ],
    "wof:name":"Elvira",
    "wof:placetype":"locality"
},
  "geometry": {"coordinates":[-59.48399000000001,-35.24429],"type":"Point"}
}