{
  "type": "Feature",
  "properties": {
    "iso:country":"AR",
    "name:eng_x_preferred":[
        "Ramallo Partido"
    ],
    "name:fra_x_preferred":[
        "Ramallo"
    ],
    "name:hun_x_preferred":[
        "Ramallo partido"
    ],
    "name:nld_x_preferred":[
        "Ramallo"
    ],
    "name:por_x_preferred":[
        "Ramallo"
    ],
    "name:rus_x_preferred":[
        "\u0420\u0430\u043c\u0430\u043b\u044c\u043e"
    ],
    "name:spa_x_preferred":[
        "Ramallo"
    ],
    "qs:gn_country":"AR",
    "qs:gn_fcode":"PPL",
    "qs:gn_pop":0,
    "qs:name":"Ramallo",
    "qs:name_adm0":"Argentina",
    "qs:name_adm1":"Buenos Aires",
    "qs:photos":45,
    "qs:photos_1k":9,
    "qs:photos_9k":1,
    "qs:photos_9r":2,
    "qs:photos_all":45,
    "qs:photos_sr":2,
    "qs:placetype":"Town",
    "qs:pop_sr":"5",
    "qs:woe_adm0":23424747,
    "wof:name":"Ramallo",
    "wof:placetype":"locality"
},
  "geometry": {"coordinates":[-60.00707,-33.48482],"type":"Point"}
}