{
  "type": "Feature",
  "properties": {
    "gn:admin1_code":"01",
    "gn:admin2_code":"6182.0",
    "gn:asciiname":"Barrio Cuidad Atlantida",
    "gn:country_code":"AR",
    "gn:dem":6,
    "gn:feature_class":"P",
    "gn:feature_code":"PPL",
    "gn:name":"Barrio Cuidad Atl\u00e1ntida",
    "gn:population":0,
    "gn:timezone":"America/Argentina/Buenos_Aires",
    "iso:country":"AR",
    "wof:name":"Barrio Cuidad Atlantida",
    "wof:placetype":"locality"
},
  "geometry": {"coordinates":[-62.06375,-38.88723],"type":"Point"}
}