{
  "type": "Feature",
  "properties": {
    "gn:admin1_code":"17",
    "gn:admin2_code":"66105.0",
    "gn:asciiname":"Agua Blanca",
    "gn:country_code":"AR",
    "gn:dem":4190,
    "gn:feature_class":"P",
    "gn:feature_code":"PPL",
    "gn:name":"Agua Blanca",
    "gn:population":0,
    "gn:timezone":"America/Argentina/Salta",
    "iso:country":"AR",
    "name:bre_x_preferred":[
        "Agua Blanca"
    ],
    "name:ceb_x_preferred":[
        "Agua Blanca"
    ],
    "name:deu_x_preferred":[
        "Agua Blanca"
    ],
    "name:fra_x_preferred":[
        "Agua Blanca"
    ],
    "name:nld_x_preferred":[
        "Agua Blanca"
    ],
    "name:por_x_preferred":[
        "Agua Blanca"
    ],
    "name:sco_x_preferred":[
        "Agua Blanca"
    ],
    "name:spa_x_preferred":[
        "Agua Blanca"
    ],
    "name:swe_x_preferred":[
        "Agua Blanca"
    ],
    "wof:name":"Agua Blanca",
    "wof:placetype":"locality"
},
  "geometry": {"coordinates":[-66.87701,-24.2438],"type":"Point"}
}