{
  "type": "Feature",
  "properties": {
    "gn:admin1_code":"24",
    "gn:admin2_code":"90035.0",
    "gn:asciiname":"Arboles Grandes",
    "gn:country_code":"AR",
    "gn:dem":294,
    "gn:feature_class":"P",
    "gn:feature_code":"PPL",
    "gn:name":"\u00c1rboles Grandes",
    "gn:population":0,
    "gn:timezone":"America/Argentina/Cordoba",
    "iso:country":"AR",
    "wof:name":"Arboles Grandes",
    "wof:placetype":"locality"
},
  "geometry": {"coordinates":[-65.01193000000001,-27.68278],"type":"Point"}
}