{
  "type": "Feature",
  "properties": {
    "iso:country":"AR",
    "qs:gn_country":"AR",
    "qs:gn_fcode":"PPL",
    "qs:gn_pop":0,
    "qs:name":"Isla de Los Castillos",
    "qs:name_adm0":"Argentina",
    "qs:name_adm1":"Santiago del Estero",
    "qs:photos":31,
    "qs:photos_1k":6,
    "qs:photos_9k":1,
    "qs:photos_9r":2,
    "qs:photos_all":31,
    "qs:photos_sr":2,
    "qs:placetype":"Town",
    "qs:pop_sr":"0",
    "qs:woe_adm0":23424747,
    "wof:name":"Isla de Los Castillos",
    "wof:placetype":"locality"
},
  "geometry": {"coordinates":[-64.88333,-27.53333],"type":"Point"}
}