{
  "type": "Feature",
  "properties": {
    "gn:admin1_code":"15.0",
    "gn:admin2_code":"58105.0",
    "gn:asciiname":"La Buitrera",
    "gn:country_code":"AR",
    "gn:dem":762,
    "gn:feature_class":"P",
    "gn:feature_code":"PPL",
    "gn:name":"La Buitrera",
    "gn:population":0,
    "gn:timezone":"America/Argentina/Salta",
    "iso:country":"AR",
    "name:ceb_x_preferred":[
        "La Buitrera"
    ],
    "name:spa_x_preferred":[
        "La Buitrera"
    ],
    "name:urd_x_preferred":[
        "\u0644\u0627 \u0628\u0648\u06cc\u0679\u0631\u06cc\u0631\u0627"
    ],
    "wof:name":"La Buitrera",
    "wof:placetype":"locality"
},
  "geometry": {"coordinates":[-70.37801,-38.55653],"type":"Point"}
}