{
  "type": "Feature",
  "properties": {
    "gn:admin1_code":"15.0",
    "gn:admin2_code":"58105.0",
    "gn:asciiname":"La Buitrera",
    "gn:country_code":"AR",
    "gn:dem":762,
    "gn:feature_class":"P",
    "gn:feature_code":"PPL",
    "gn:name":"La Buitrera",
    "gn:population":0,
    "gn:timezone":"America/Argentina/Salta",
    "iso:country":"AR",
    "wof:name":"La Buitrera",
    "wof:placetype":"locality"
},
  "geometry": {"coordinates":[-70.37801,-38.55653],"type":"Point"}
}