{
  "type": "Feature",
  "properties": {
    "gn:admin1_code":"9.0",
    "gn:admin2_code":"34035.0",
    "gn:asciiname":"Posta General San Martin",
    "gn:country_code":"AR",
    "gn:dem":115,
    "gn:feature_class":"P",
    "gn:feature_code":"PPL",
    "gn:name":"Posta General San Mart\u00edn",
    "gn:population":0,
    "gn:timezone":"America/Argentina/Cordoba",
    "iso:country":"AR",
    "name:und_x_variant":[
        "Posta San Mart\u00edn",
        "Posta General San Mart\u00edn"
    ],
    "wof:name":"Posta General San Martin",
    "wof:placetype":"locality"
},
  "geometry": {"coordinates":[-59.65315,-24.43308],"type":"Point"}
}