{
  "type": "Feature",
  "properties": {
    "iso:country":"AR",
    "name:eng_x_preferred":[
        "Sebasti\u00e1n Elcano"
    ],
    "name:nld_x_preferred":[
        "Sebasti\u00e1n Elcano"
    ],
    "name:por_x_preferred":[
        "Sebasti\u00e1n Elcano"
    ],
    "name:spa_x_preferred":[
        "Sebasti\u00e1n Elcano"
    ],
    "name:ukr_x_preferred":[
        "\u0421\u0435\u0431\u0430\u0441\u0442\u044c\u044f\u043d-\u0415\u043b\u044c\u043a\u0430\u043d\u043e"
    ],
    "qs:gn_country":"AR",
    "qs:gn_fcode":"PPL",
    "qs:gn_pop":2042,
    "qs:name":"Sebasti\u00e1n Elcano",
    "qs:name_adm0":"Argentina",
    "qs:name_adm1":"C\u00f3rdoba",
    "qs:photos":0,
    "qs:photos_1k":0,
    "qs:photos_9k":0,
    "qs:photos_9r":0,
    "qs:photos_all":0,
    "qs:photos_sr":0,
    "qs:placetype":"Town",
    "qs:pop_sr":"7",
    "qs:woe_adm0":23424747,
    "wd:wordcount":1043,
    "wof:name":"Sebasti\u00e1n Elcano",
    "wof:placetype":"locality",
    "wof:population":2042
},
  "geometry": {"coordinates":[-63.5936,-30.16105],"type":"Point"}
}