{
  "type": "Feature",
  "properties": {
    "iso:country":"AR",
    "name:eng_x_preferred":[
        "Ezpeleta"
    ],
    "name:kat_x_preferred":[
        "\u10d4\u10e1\u10de\u10d4\u10da\u10d4\u10e2\u10d0"
    ],
    "name:nld_x_preferred":[
        "Ezpeleta"
    ],
    "name:por_x_preferred":[
        "Ezpeleta"
    ],
    "name:spa_x_preferred":[
        "Ezpeleta"
    ],
    "name:ukr_x_preferred":[
        "\u0415\u0441\u043f\u0435\u043b\u0435\u0442\u0430"
    ],
    "name:unk_x_variant":[
        "Espeleta"
    ],
    "qs:gn_country":"AR",
    "qs:gn_fcode":"PPL",
    "qs:gn_pop":0,
    "qs:name":"Ezpeleta",
    "qs:name_adm0":"Argentina",
    "qs:name_adm1":"Buenos Aires",
    "qs:photos":28,
    "qs:photos_1k":6,
    "qs:photos_9k":1,
    "qs:photos_9r":2,
    "qs:photos_all":28,
    "qs:photos_sr":2,
    "qs:placetype":"Town",
    "qs:pop_sr":"0",
    "qs:woe_adm0":23424747,
    "wof:name":"Ezpeleta",
    "wof:placetype":"locality"
},
  "geometry": {"coordinates":[-58.23078,-34.74849],"type":"Point"}
}