{
  "type": "Feature",
  "properties": {
    "iso:country":"AR",
    "name:fra_x_preferred":[
        "Bol\u00edvar"
    ],
    "name:hun_x_preferred":[
        "Bol\u00edvar partido"
    ],
    "name:ita_x_preferred":[
        "Partido di Bol\u00edvar"
    ],
    "name:nld_x_preferred":[
        "Bol\u00edvar"
    ],
    "name:pol_x_preferred":[
        "San Carlos de Bol\u00edvar"
    ],
    "name:por_x_preferred":[
        "Bol\u00edvar"
    ],
    "name:sco_x_preferred":[
        "Bol\u00edvar Partido"
    ],
    "name:spa_x_preferred":[
        "Partido de Bol\u00edvar"
    ],
    "name:unk_x_variant":[
        "La Torrecita"
    ],
    "name:urd_x_preferred":[
        "\u0628\u0648\u0644\u06cc\u0648\u0631 \u067e\u0627\u0631\u062a\u06cc\u062f\u0648"
    ],
    "qs:gn_country":"AR",
    "qs:gn_fcode":"PPL",
    "qs:gn_pop":0,
    "qs:name":"Urdampilleta",
    "qs:name_adm0":"Argentina",
    "qs:name_adm1":"Buenos Aires",
    "qs:photos":5,
    "qs:photos_1k":1,
    "qs:photos_9k":1,
    "qs:photos_9r":1,
    "qs:photos_all":5,
    "qs:photos_sr":1,
    "qs:placetype":"Town",
    "qs:pop_sr":"6",
    "qs:woe_adm0":23424747,
    "wof:name":"Urdampilleta",
    "wof:placetype":"locality"
},
  "geometry": {"coordinates":[-61.43333,-36.45],"type":"Point"}
}