{
  "type": "Feature",
  "properties": {
    "gn:admin1_code":"18.0",
    "gn:admin2_code":"70105.0",
    "gn:asciiname":"Ramblon",
    "gn:country_code":"AR",
    "gn:dem":611,
    "gn:feature_class":"P",
    "gn:feature_code":"PPL",
    "gn:name":"Rambl\u00f3n",
    "gn:population":0,
    "gn:timezone":"America/Argentina/Mendoza",
    "iso:country":"AR",
    "wof:name":"Ramblon",
    "wof:placetype":"locality"
},
  "geometry": {"coordinates":[-68.6609,-32.3097],"type":"Point"}
}