{
  "type": "Feature",
  "properties": {
    "gn:admin1_code":"3.0",
    "gn:admin2_code":"22028.0",
    "gn:asciiname":"Pampa del Cielo",
    "gn:country_code":"AR",
    "gn:dem":103,
    "gn:feature_class":"P",
    "gn:feature_code":"PPL",
    "gn:name":"Pampa del Cielo",
    "gn:population":0,
    "gn:timezone":"America/Argentina/Cordoba",
    "iso:country":"AR",
    "wof:name":"Pampa del Cielo",
    "wof:placetype":"locality"
},
  "geometry": {"coordinates":[-61.14221,-27.15582],"type":"Point"}
}