{
  "type": "Feature",
  "properties": {
    "gn:admin1_code":"1.0",
    "gn:admin2_code":"6672.0",
    "gn:asciiname":"Villa San Pedro",
    "gn:country_code":"AR",
    "gn:dem":92,
    "gn:feature_class":"P",
    "gn:feature_code":"PPL",
    "gn:name":"Villa San Pedro",
    "gn:population":0,
    "gn:timezone":"America/Argentina/Buenos_Aires",
    "iso:country":"AR",
    "wof:name":"Villa San Pedro",
    "wof:placetype":"locality"
},
  "geometry": {"coordinates":[-59.04643000000001,-36.79245],"type":"Point"}
}