{
  "type": "Feature",
  "properties": {
    "gn:admin1_code":"24.0",
    "gn:admin2_code":"90070.0",
    "gn:asciiname":"Villa Quinteros",
    "gn:country_code":"AR",
    "gn:dem":377,
    "gn:feature_class":"P",
    "gn:feature_code":"PPL",
    "gn:name":"Villa Quinteros",
    "gn:population":0,
    "gn:timezone":"America/Argentina/Tucuman",
    "iso:country":"AR",
    "wof:name":"Villa Quinteros",
    "wof:placetype":"locality"
},
  "geometry": {"coordinates":[-65.54859,-27.25259],"type":"Point"}
}