{
  "type": "Feature",
  "properties": {
    "gn:admin1_code":"2.0",
    "gn:admin2_code":"10042.0",
    "gn:asciiname":"Los Angeles",
    "gn:country_code":"AR",
    "gn:dem":2647,
    "gn:feature_class":"P",
    "gn:feature_code":"PPL",
    "gn:name":"Los \u00c1ngeles",
    "gn:population":0,
    "gn:timezone":"America/Argentina/Catamarca",
    "iso:country":"AR",
    "name:ceb_x_preferred":[
        "Los \u00c1ngeles"
    ],
    "name:spa_x_preferred":[
        "Los \u00c1ngeles"
    ],
    "wof:name":"Los Angeles",
    "wof:placetype":"locality"
},
  "geometry": {"coordinates":[-65.98333000000001,-28.48333],"type":"Point"}
}