{
  "type": "Feature",
  "properties": {
    "gn:admin1_code":"13",
    "gn:asciiname":"Colonia Gobernador Ayala",
    "gn:country_code":"AR",
    "gn:dem":434,
    "gn:feature_class":"P",
    "gn:feature_code":"PPL",
    "gn:name":"Colonia Gobernador Ayala",
    "gn:population":0,
    "gn:timezone":"America/Argentina/Salta",
    "iso:country":"AR",
    "name:und_x_variant":[
        "Gobernador Ayala",
        "Colonia Gobernador Ayala"
    ],
    "wof:name":"Colonia Gobernador Ayala",
    "wof:placetype":"locality"
},
  "geometry": {"coordinates":[-68.09499,-37.58492],"type":"Point"}
}