{
  "type": "Feature",
  "properties": {
    "gn:admin1_code":"10.0",
    "gn:admin2_code":"38049.0",
    "gn:asciiname":"Pairique Chico",
    "gn:country_code":"AR",
    "gn:dem":4554,
    "gn:feature_class":"P",
    "gn:feature_code":"PPL",
    "gn:name":"Pairique Chico",
    "gn:population":0,
    "gn:timezone":"America/Argentina/Jujuy",
    "iso:country":"AR",
    "name:spa_x_preferred":[
        "Pairique Chico"
    ],
    "name:und_x_variant":[
        "Pairiqui Chico"
    ],
    "wof:name":"Pairique Chico",
    "wof:placetype":"locality"
},
  "geometry": {"coordinates":[-66.75949,-22.87792],"type":"Point"}
}