{
  "type": "Feature",
  "properties": {
    "gn:admin1_code":"2.0",
    "gn:admin2_code":"10105.0",
    "gn:asciiname":"Tambillo",
    "gn:country_code":"AR",
    "gn:dem":3871,
    "gn:feature_class":"P",
    "gn:feature_code":"PPL",
    "gn:name":"Tambillo",
    "gn:population":0,
    "gn:timezone":"America/Argentina/Catamarca",
    "iso:country":"AR",
    "wof:name":"Tambillo",
    "wof:placetype":"locality"
},
  "geometry": {"coordinates":[-68.16667,-28.06667],"type":"Point"}
}