{
  "type": "Feature",
  "properties": {
    "gn:admin1_code":"1.0",
    "gn:admin2_code":"6763.0",
    "gn:asciiname":"Erescano",
    "gn:country_code":"AR",
    "gn:dem":53,
    "gn:feature_class":"P",
    "gn:feature_code":"PPL",
    "gn:name":"Er\u00e9scano",
    "gn:population":0,
    "gn:timezone":"America/Argentina/Buenos_Aires",
    "iso:country":"AR",
    "wof:name":"Erescano",
    "wof:placetype":"locality"
},
  "geometry": {"coordinates":[-60.31691,-33.52132],"type":"Point"}
}