{
  "type": "Feature",
  "properties": {
    "gn:admin1_code":"04",
    "gn:admin2_code":"26028.0",
    "gn:asciiname":"Cabo Raso",
    "gn:country_code":"AR",
    "gn:dem":30,
    "gn:feature_class":"P",
    "gn:feature_code":"PPL",
    "gn:name":"Cabo Raso",
    "gn:population":0,
    "gn:timezone":"America/Argentina/Catamarca",
    "iso:country":"AR",
    "name:und_x_variant":[
        "Puerto Raso",
        "Cabo Raso"
    ],
    "wof:name":"Cabo Raso",
    "wof:placetype":"locality"
},
  "geometry": {"coordinates":[-65.23829000000001,-44.3424],"type":"Point"}
}