{
  "type": "Feature",
  "properties": {
    "iso:country":"AR",
    "name:ceb_x_preferred":[
        "Capit\u00e1n Berm\u00fadez"
    ],
    "name:eng_x_preferred":[
        "Capit\u00e1n Berm\u00fadez"
    ],
    "name:fra_x_preferred":[
        "Capit\u00e1n Berm\u00fadez"
    ],
    "name:heb_x_preferred":[
        "\u05e7\u05e4\u05d9\u05d8\u05df \u05d1\u05e8\u05de\u05d5\u05d3\u05e1"
    ],
    "name:ita_x_preferred":[
        "Capit\u00e1n Berm\u00fadez"
    ],
    "name:jpn_x_preferred":[
        "\u30ab\u30d4\u30bf\u30f3\u30fb\u30d9\u30eb\u30e0\u30c7\u30b9"
    ],
    "name:nld_x_preferred":[
        "Capit\u00e1n Berm\u00fadez"
    ],
    "name:por_x_preferred":[
        "Capit\u00e1n Berm\u00fadez"
    ],
    "name:spa_x_preferred":[
        "Capit\u00e1n Berm\u00fadez"
    ],
    "name:swe_x_preferred":[
        "Capit\u00e1n Berm\u00fadez"
    ],
    "name:unk_x_variant":[
        "Juan Ort\u00edz"
    ],
    "qs:gn_country":"AR",
    "qs:gn_fcode":"PPL",
    "qs:gn_pop":27060,
    "qs:name":"Capit\u00e1n Berm\u00fadez",
    "qs:name_adm0":"Argentina",
    "qs:name_adm1":"Santa Fe",
    "qs:photos":343,
    "qs:photos_1k":70,
    "qs:photos_9k":2,
    "qs:photos_9r":5,
    "qs:photos_all":343,
    "qs:photos_sr":5,
    "qs:placetype":"Town",
    "qs:pop_sr":"7",
    "qs:woe_adm0":23424747,
    "wd:wordcount":262,
    "wof:name":"Capit\u00e1n Berm\u00fadez",
    "wof:placetype":"locality",
    "wof:population":27060
},
  "geometry": {"coordinates":[-60.71852,-32.82262],"type":"Point"}
}