{
  "type": "Feature",
  "properties": {
    "gn:admin1_code":"21",
    "gn:admin2_code":"82091.0",
    "gn:asciiname":"Colonia Bossi",
    "gn:country_code":"AR",
    "gn:dem":98,
    "gn:feature_class":"P",
    "gn:feature_code":"PPL",
    "gn:name":"Colonia Bossi",
    "gn:population":0,
    "gn:timezone":"America/Argentina/Cordoba",
    "iso:country":"AR",
    "name:und_x_variant":[
        "Rossi",
        "Colonia B. Rossi",
        "Bossi",
        "Colonia Bossi"
    ],
    "wof:name":"Colonia Bossi",
    "wof:placetype":"locality"
},
  "geometry": {"coordinates":[-61.78941999999999,-30.66786],"type":"Point"}
}