{
  "type": "Feature",
  "properties": {
    "gn:admin1_code":"02",
    "gn:admin2_code":"10105.0",
    "gn:asciiname":"Cienaguita",
    "gn:country_code":"AR",
    "gn:dem":1450,
    "gn:feature_class":"P",
    "gn:feature_code":"PPL",
    "gn:name":"Cienaguita",
    "gn:population":0,
    "gn:timezone":"America/Argentina/Catamarca",
    "iso:country":"AR",
    "name:und_x_variant":[
        "Cieneguita",
        "Cienaguita"
    ],
    "wof:name":"Cienaguita",
    "wof:placetype":"locality"
},
  "geometry": {"coordinates":[-67.68267,-28.18186],"type":"Point"}
}