{
  "type": "Feature",
  "properties": {
    "gn:admin1_code":"5.0",
    "gn:admin2_code":"14098.0",
    "gn:asciiname":"Los Jagueeles",
    "gn:country_code":"AR",
    "gn:dem":424,
    "gn:feature_class":"P",
    "gn:feature_code":"PPL",
    "gn:name":"Los Jag\u00fceles",
    "gn:population":0,
    "gn:timezone":"America/Argentina/Cordoba",
    "iso:country":"AR",
    "wof:name":"Los Jagueeles",
    "wof:placetype":"locality"
},
  "geometry": {"coordinates":[-64.53241,-33.40255],"type":"Point"}
}