{
  "type": "Feature",
  "properties": {
    "gn:admin1_code":"22",
    "gn:admin2_code":"86035.0",
    "gn:asciiname":"Alto Pozo",
    "gn:country_code":"AR",
    "gn:dem":266,
    "gn:feature_class":"P",
    "gn:feature_code":"PPL",
    "gn:name":"Alto Pozo",
    "gn:population":0,
    "gn:timezone":"America/Argentina/Cordoba",
    "iso:country":"AR",
    "wof:name":"Alto Pozo",
    "wof:placetype":"locality"
},
  "geometry": {"coordinates":[-64.46666999999999,-27.36667000000001],"type":"Point"}
}