{
  "type": "Feature",
  "properties": {
    "gn:admin1_code":"24.0",
    "gn:admin2_code":"90084.0",
    "gn:asciiname":"Gobernador Nougues",
    "gn:country_code":"AR",
    "gn:dem":407,
    "gn:feature_class":"P",
    "gn:feature_code":"PPL",
    "gn:name":"Gobernador Nougues",
    "gn:population":0,
    "gn:timezone":"America/Argentina/Tucuman",
    "iso:country":"AR",
    "name:und_x_variant":[
        "Gobernador Niniqu\u00e9s",
        "Gobernador Nougues"
    ],
    "wof:name":"Gobernador Nougues",
    "wof:placetype":"locality"
},
  "geometry": {"coordinates":[-65.22230999999999,-26.88605],"type":"Point"}
}