{
  "type": "Feature",
  "properties": {
    "gn:admin1_code":"17.0",
    "gn:admin2_code":"66098.0",
    "gn:asciiname":"Talapampa",
    "gn:country_code":"AR",
    "gn:dem":1123,
    "gn:feature_class":"P",
    "gn:feature_code":"PPL",
    "gn:name":"Talapampa",
    "gn:population":0,
    "gn:timezone":"America/Argentina/Salta",
    "iso:country":"AR",
    "name:ceb_x_preferred":[
        "Talapampa"
    ],
    "name:spa_x_preferred":[
        "Talapampa"
    ],
    "name:swe_x_preferred":[
        "Talapampa"
    ],
    "wof:name":"Talapampa",
    "wof:placetype":"locality"
},
  "geometry": {"coordinates":[-65.55789,-25.53636],"type":"Point"}
}