{
  "type": "Feature",
  "properties": {
    "iso:country":"AR",
    "name:ceb_x_preferred":[
        "Huinca Renanc\u00f3"
    ],
    "name:dut_x_preferred":[
        "Huinca Renanc\u00f3"
    ],
    "name:eng_x_preferred":[
        "Huinca Renanc\u00f3"
    ],
    "name:nld_x_preferred":[
        "Huinca Renanc\u00f3"
    ],
    "name:por_x_preferred":[
        "Huinca Renanc\u00f3"
    ],
    "name:spa_x_preferred":[
        "Huinca Renanc\u00f3"
    ],
    "name:swe_x_preferred":[
        "Huinca Renanc\u00f3"
    ],
    "name:ukr_x_preferred":[
        "\u0412\u0456\u043d\u043a\u0430-\u0420\u0435\u043d\u0430\u043d\u043a\u043e"
    ],
    "qs:gn_country":"AR",
    "qs:gn_fcode":"PPL",
    "qs:gn_pop":8637,
    "qs:name":"Huinca Renanc\u00f3",
    "qs:name_adm0":"Argentina",
    "qs:name_adm1":"C\u00f3rdoba",
    "qs:photos":159,
    "qs:photos_1k":32,
    "qs:photos_9k":1,
    "qs:photos_9r":4,
    "qs:photos_all":159,
    "qs:photos_sr":4,
    "qs:placetype":"Town",
    "qs:pop_sr":"7",
    "qs:woe_adm0":23424747,
    "wd:wordcount":13,
    "wof:name":"Huinca Renanc\u00f3",
    "wof:placetype":"locality",
    "wof:population":8637
},
  "geometry": {"coordinates":[-64.3758,-34.84038],"type":"Point"}
}