{
  "type": "Feature",
  "properties": {
    "gn:admin1_code":"19",
    "gn:admin2_code":"74014.0",
    "gn:asciiname":"Algarrobo Grande",
    "gn:country_code":"AR",
    "gn:dem":568,
    "gn:feature_class":"P",
    "gn:feature_code":"PPL",
    "gn:name":"Algarrobo Grande",
    "gn:population":0,
    "gn:timezone":"America/Argentina/San_Luis",
    "iso:country":"AR",
    "wof:name":"Algarrobo Grande",
    "wof:placetype":"locality"
},
  "geometry": {"coordinates":[-66.76289,-32.58069],"type":"Point"}
}