{
  "type": "Feature",
  "properties": {
    "gn:admin1_code":"15.0",
    "gn:admin2_code":"58084.0",
    "gn:asciiname":"Vilu Mallin",
    "gn:country_code":"AR",
    "gn:dem":1264,
    "gn:feature_class":"P",
    "gn:feature_code":"PPL",
    "gn:name":"Vil\u00fa Mall\u00edn",
    "gn:population":0,
    "gn:timezone":"America/Argentina/Salta",
    "iso:country":"AR",
    "name:und_x_variant":[
        "Bilo Mallin",
        "Vil\u00fa Mall\u00edn"
    ],
    "wof:name":"Vilu Mallin",
    "wof:placetype":"locality"
},
  "geometry": {"coordinates":[-70.74106999999999,-37.47808],"type":"Point"}
}