{
  "type": "Feature",
  "properties": {
    "gn:admin1_code":"01",
    "gn:admin2_code":"6532.0",
    "gn:asciiname":"La Florida",
    "gn:country_code":"AR",
    "gn:dem":39,
    "gn:feature_class":"P",
    "gn:feature_code":"PPL",
    "gn:name":"La Florida",
    "gn:population":0,
    "gn:timezone":"America/Argentina/Buenos_Aires",
    "iso:country":"AR",
    "name:spa_x_preferred":[
        "La Florida"
    ],
    "wof:name":"La Florida",
    "wof:placetype":"locality"
},
  "geometry": {"coordinates":[-59.42138000000001,-34.59326],"type":"Point"}
}