{
  "type": "Feature",
  "properties": {
    "iso:country":"AR",
    "name:fra_x_preferred":[
        "Thea"
    ],
    "name:ita_x_preferred":[
        "Thea"
    ],
    "name:pol_x_preferred":[
        "Thea"
    ],
    "name:por_x_preferred":[
        "Thea"
    ],
    "name:rus_x_preferred":[
        "\u0422\u0438\u044f"
    ],
    "name:swe_x_preferred":[
        "Thea"
    ],
    "name:urd_x_preferred":[
        "Thea"
    ],
    "qs:gn_country":"AR",
    "qs:gn_fcode":"PPL",
    "qs:gn_pop":0,
    "qs:name":"Thea",
    "qs:name_adm0":"Argentina",
    "qs:name_adm1":"C\u00f3rdoba",
    "qs:photos":10,
    "qs:photos_1k":2,
    "qs:photos_9k":1,
    "qs:photos_9r":1,
    "qs:photos_all":10,
    "qs:photos_sr":1,
    "qs:placetype":"Town",
    "qs:pop_sr":"0",
    "qs:woe_adm0":23424747,
    "wd:wordcount":127,
    "wof:name":"Thea",
    "wof:placetype":"locality"
},
  "geometry": {"coordinates":[-64.49927,-31.05061],"type":"Point"}
}