{
  "type": "Feature",
  "properties": {
    "gn:admin1_code":"18.0",
    "gn:admin2_code":"70105.0",
    "gn:asciiname":"Retamito",
    "gn:country_code":"AR",
    "gn:dem":603,
    "gn:feature_class":"P",
    "gn:feature_code":"PPL",
    "gn:name":"Retamito",
    "gn:population":0,
    "gn:timezone":"America/Argentina/San_Juan",
    "iso:country":"AR",
    "wof:name":"Retamito",
    "wof:placetype":"locality"
},
  "geometry": {"coordinates":[-68.60178000000001,-32.1022],"type":"Point"}
}