{
  "type": "Feature",
  "properties": {
    "iso:country":"AR",
    "name:ceb_x_preferred":[
        "Taf\u00ed del Valle"
    ],
    "name:chi_x_preferred":[
        "\u5854\u83f2\u5fb7\u723e\u74e6\u52d2"
    ],
    "name:deu_x_preferred":[
        "Taf\u00ed del Valle"
    ],
    "name:dut_x_preferred":[
        "Taf\u00ed del Valle"
    ],
    "name:eng_x_preferred":[
        "Taf\u00ed del Valle"
    ],
    "name:fra_x_preferred":[
        "Taf\u00ed del Valle"
    ],
    "name:fre_x_preferred":[
        "Taf\u00ed del Valle"
    ],
    "name:ger_x_preferred":[
        "Taf\u00ed del Valle"
    ],
    "name:ita_x_preferred":[
        "Taf\u00ed del Valle"
    ],
    "name:nld_x_preferred":[
        "Taf\u00ed del Valle"
    ],
    "name:por_x_preferred":[
        "Taf\u00ed del Valle"
    ],
    "name:spa_x_preferred":[
        "Taf\u00ed del Valle"
    ],
    "name:swe_x_preferred":[
        "Taf\u00ed del Valle"
    ],
    "name:ukr_x_preferred":[
        "\u0422\u0430\u0444\u0456-\u0434\u0435\u043b\u044c-\u0412\u0430\u043b\u044c\u0454"
    ],
    "name:unk_x_variant":[
        "Taf\u00ed"
    ],
    "name:zho_x_preferred":[
        "\u5854\u83f2\u5fb7\u723e\u74e6\u52d2"
    ],
    "qs:gn_country":"AR",
    "qs:gn_fcode":"PPL",
    "qs:gn_pop":4028,
    "qs:name":"Taf\u00ed del Valle",
    "qs:name_adm0":"Argentina",
    "qs:name_adm1":"Tucum\u00e1n",
    "qs:photos":536,
    "qs:photos_1k":109,
    "qs:photos_9k":2,
    "qs:photos_9r":5,
    "qs:photos_all":536,
    "qs:photos_sr":7,
    "qs:placetype":"Town",
    "qs:pop_sr":"4",
    "qs:woe_adm0":23424747,
    "wof:name":"Taf\u00ed del Valle",
    "wof:placetype":"locality",
    "wof:population":4028
},
  "geometry": {"coordinates":[-65.70983,-26.85275],"type":"Point"}
}