{
  "type": "Feature",
  "properties": {
    "gn:admin1_code":"1.0",
    "gn:admin2_code":"6595.0",
    "gn:asciiname":"Pourtale",
    "gn:country_code":"AR",
    "gn:dem":187,
    "gn:feature_class":"P",
    "gn:feature_code":"PPL",
    "gn:name":"Pourtal\u00e9",
    "gn:population":0,
    "gn:timezone":"America/Argentina/Buenos_Aires",
    "iso:country":"AR",
    "wof:name":"Pourtale",
    "wof:placetype":"locality"
},
  "geometry": {"coordinates":[-60.58939,-37.02024],"type":"Point"}
}