{
  "type": "Feature",
  "properties": {
    "iso:country":"AR",
    "name:ceb_x_preferred":[
        "San Pedro de Colalao"
    ],
    "name:eng_x_preferred":[
        "San Pedro de Colalao"
    ],
    "name:nld_x_preferred":[
        "San Pedro de Colalao"
    ],
    "name:por_x_preferred":[
        "San Pedro de Colalao"
    ],
    "name:spa_x_preferred":[
        "San Pedro de Colalao"
    ],
    "name:swe_x_preferred":[
        "San Pedro de Colalao"
    ],
    "name:ukr_x_preferred":[
        "\u0421\u0430\u043d-\u041f\u0435\u0434\u0440\u043e-\u0434\u0435-\u041a\u043e\u043b\u0430\u043b\u0430\u043e"
    ],
    "qs:gn_country":"AR",
    "qs:gn_fcode":"PPL",
    "qs:gn_pop":0,
    "qs:name":"San Pedro de Colalao",
    "qs:name_adm0":"Argentina",
    "qs:name_adm1":"Tucum\u00e1n",
    "qs:photos":244,
    "qs:photos_1k":49,
    "qs:photos_9k":1,
    "qs:photos_9r":4,
    "qs:photos_all":244,
    "qs:photos_sr":4,
    "qs:placetype":"Town",
    "qs:pop_sr":"0",
    "qs:woe_adm0":23424747,
    "wd:wordcount":413,
    "wof:name":"San Pedro de Colalao",
    "wof:placetype":"locality"
},
  "geometry": {"coordinates":[-65.49575,-26.23814],"type":"Point"}
}