{
  "type": "Feature",
  "properties": {
    "gn:admin1_code":"5.0",
    "gn:admin2_code":"14140.0",
    "gn:asciiname":"Trinchera",
    "gn:country_code":"AR",
    "gn:dem":87,
    "gn:feature_class":"P",
    "gn:feature_code":"PPL",
    "gn:name":"Trinchera",
    "gn:population":0,
    "gn:timezone":"America/Argentina/Cordoba",
    "iso:country":"AR",
    "wof:name":"Trinchera",
    "wof:placetype":"locality"
},
  "geometry": {"coordinates":[-62.49601,-31.07823],"type":"Point"}
}