{
  "type": "Feature",
  "properties": {
    "gn:admin1_code":"17.0",
    "gn:admin2_code":"66042.0",
    "gn:asciiname":"Tipal",
    "gn:country_code":"AR",
    "gn:dem":1219,
    "gn:feature_class":"P",
    "gn:feature_code":"PPL",
    "gn:name":"Tipal",
    "gn:population":0,
    "gn:timezone":"America/Argentina/Salta",
    "iso:country":"AR",
    "name:und_x_variant":[
        "El Tipal",
        "Tipal"
    ],
    "wof:name":"Tipal",
    "wof:placetype":"locality"
},
  "geometry": {"coordinates":[-65.52972,-25.06823],"type":"Point"}
}