{
  "type": "Feature",
  "properties": {
    "iso:country":"AR",
    "name:ceb_x_preferred":[
        "Ceres"
    ],
    "name:eng_x_preferred":[
        "Ceres"
    ],
    "name:fra_x_preferred":[
        "Ceres"
    ],
    "name:ita_x_preferred":[
        "Ceres"
    ],
    "name:jpn_x_preferred":[
        "\u30bb\u30ec\u30b9"
    ],
    "name:nld_x_preferred":[
        "Ceres"
    ],
    "name:spa_x_preferred":[
        "Ceres"
    ],
    "name:swe_x_preferred":[
        "Ceres"
    ],
    "name:ukr_x_preferred":[
        "\u0421\u0435\u0440\u0435\u0441"
    ],
    "name:zho_x_preferred":[
        "\u585e\u96f7\u65af"
    ],
    "qs:gn_country":"AR",
    "qs:gn_fcode":"PPL",
    "qs:gn_pop":13063,
    "qs:name":"Ceres",
    "qs:name_adm0":"Argentina",
    "qs:name_adm1":"Santa Fe",
    "qs:photos":0,
    "qs:photos_1k":0,
    "qs:photos_9k":1,
    "qs:photos_9r":1,
    "qs:photos_all":7,
    "qs:photos_sr":0,
    "qs:placetype":"Town",
    "qs:pop_sr":"7",
    "qs:woe_adm0":23424747,
    "wd:wordcount":373,
    "wof:name":"Ceres",
    "wof:placetype":"locality",
    "wof:population":13063
},
  "geometry": {"coordinates":[-61.94504,-29.881],"type":"Point"}
}