{
  "type": "Feature",
  "properties": {
    "iso:country":"AR",
    "name:ben_x_preferred":[
        "\u0995\u09c7\u09b0\u09c7\u09b8"
    ],
    "name:ceb_x_preferred":[
        "Ceres"
    ],
    "name:ell_x_preferred":[
        "\u03a3\u03ad\u03c1\u03b5\u03c2"
    ],
    "name:eng_x_preferred":[
        "Ceres"
    ],
    "name:fas_x_preferred":[
        "\u06a9\u0631\u0633"
    ],
    "name:fra_x_preferred":[
        "Ceres"
    ],
    "name:heb_x_preferred":[
        "\u05e1\u05e8\u05e1"
    ],
    "name:hin_x_preferred":[
        "\u0938\u0947\u0930\u0947\u0938"
    ],
    "name:ind_x_preferred":[
        "Ceres"
    ],
    "name:ita_x_preferred":[
        "Ceres"
    ],
    "name:jpn_x_preferred":[
        "\u30bb\u30ec\u30b9"
    ],
    "name:kor_x_preferred":[
        "\ucf00\ub808\uc2a4"
    ],
    "name:nld_x_preferred":[
        "Ceres"
    ],
    "name:rus_x_preferred":[
        "\u0421\u0435\u0440\u0435\u0441"
    ],
    "name:spa_x_preferred":[
        "Ceres"
    ],
    "name:swe_x_preferred":[
        "Ceres"
    ],
    "name:tur_x_preferred":[
        "Ceres"
    ],
    "name:ukr_x_preferred":[
        "\u0421\u0435\u0440\u0435\u0441"
    ],
    "name:urd_x_preferred":[
        "\u0633\u06cc\u0631\u0633"
    ],
    "name:vie_x_preferred":[
        "Ceres"
    ],
    "name:zho_x_preferred":[
        "\u585e\u96f7\u65af"
    ],
    "qs:gn_country":"AR",
    "qs:gn_fcode":"PPL",
    "qs:gn_pop":13063,
    "qs:name":"Ceres",
    "qs:name_adm0":"Argentina",
    "qs:name_adm1":"Santa Fe",
    "qs:photos":0,
    "qs:photos_1k":0,
    "qs:photos_9k":1,
    "qs:photos_9r":1,
    "qs:photos_all":7,
    "qs:photos_sr":0,
    "qs:placetype":"Town",
    "qs:pop_sr":"7",
    "qs:woe_adm0":23424747,
    "wd:wordcount":373,
    "wof:name":"Ceres",
    "wof:placetype":"locality",
    "wof:population":13063
},
  "geometry": {"coordinates":[-61.94504,-29.881],"type":"Point"}
}