{
  "type": "Feature",
  "properties": {
    "gn:admin1_code":"17",
    "gn:admin2_code":"66056.0",
    "gn:asciiname":"Dragones",
    "gn:country_code":"AR",
    "gn:dem":245,
    "gn:feature_class":"P",
    "gn:feature_code":"PPL",
    "gn:name":"Dragones",
    "gn:population":0,
    "gn:timezone":"America/Argentina/Salta",
    "iso:country":"AR",
    "name:und_x_variant":[
        "Fortin Dragones",
        "Dragones"
    ],
    "wof:name":"Dragones",
    "wof:placetype":"locality"
},
  "geometry": {"coordinates":[-63.33831,-23.24923],"type":"Point"}
}