{
  "type": "Feature",
  "properties": {
    "gn:admin1_code":"12.0",
    "gn:admin2_code":"46014.0",
    "gn:asciiname":"Santo Domingo",
    "gn:country_code":"AR",
    "gn:dem":339,
    "gn:feature_class":"P",
    "gn:feature_code":"PPL",
    "gn:name":"Santo Domingo",
    "gn:population":0,
    "gn:timezone":"America/Argentina/La_Rioja",
    "iso:country":"AR",
    "wof:name":"Santo Domingo",
    "wof:placetype":"locality"
},
  "geometry": {"coordinates":[-66.28471,-29.29427],"type":"Point"}
}