{
  "type": "Feature",
  "properties": {
    "gn:admin1_code":"1.0",
    "gn:admin2_code":"6609.0",
    "gn:asciiname":"Juan Jose Paso",
    "gn:country_code":"AR",
    "gn:dem":87,
    "gn:feature_class":"P",
    "gn:feature_code":"PPL",
    "gn:name":"Juan Jos\u00e9 Paso",
    "gn:population":0,
    "gn:timezone":"America/Argentina/Buenos_Aires",
    "iso:country":"AR",
    "name:und_x_variant":[
        "Passo",
        "J.J. Paso",
        "Paso",
        "Juan J. Paso",
        "Juan Jos\u00e9 Paso"
    ],
    "wof:name":"Juan Jose Paso",
    "wof:placetype":"locality"
},
  "geometry": {"coordinates":[-62.29783000000001,-35.85055],"type":"Point"}
}