{
  "type": "Feature",
  "properties": {
    "gn:admin1_code":"2.0",
    "gn:admin2_code":"10091.0",
    "gn:asciiname":"Las Mojarras",
    "gn:country_code":"AR",
    "gn:dem":1879,
    "gn:feature_class":"P",
    "gn:feature_code":"PPL",
    "gn:name":"Las Mojarras",
    "gn:population":0,
    "gn:timezone":"America/Argentina/Catamarca",
    "iso:country":"AR",
    "wof:name":"Las Mojarras",
    "wof:placetype":"locality"
},
  "geometry": {"coordinates":[-66.06168000000001,-26.65326],"type":"Point"}
}