{
  "type": "Feature",
  "properties": {
    "gn:admin1_code":"22.0",
    "gn:admin2_code":"86133.0",
    "gn:asciiname":"La Puerta",
    "gn:country_code":"AR",
    "gn:dem":222,
    "gn:feature_class":"P",
    "gn:feature_code":"PPL",
    "gn:name":"La Puerta",
    "gn:population":0,
    "gn:timezone":"America/Argentina/Cordoba",
    "iso:country":"AR",
    "wof:name":"La Puerta",
    "wof:placetype":"locality"
},
  "geometry": {"coordinates":[-64.17619999999999,-26.71942],"type":"Point"}
}