{
  "type": "Feature",
  "properties": {
    "gn:admin1_code":"17.0",
    "gn:admin2_code":"66056.0",
    "gn:asciiname":"Padre Lozano",
    "gn:country_code":"AR",
    "gn:dem":273,
    "gn:feature_class":"P",
    "gn:feature_code":"PPL",
    "gn:name":"Padre Lozano",
    "gn:population":0,
    "gn:timezone":"America/Argentina/Salta",
    "iso:country":"AR",
    "name:ceb_x_preferred":[
        "Padre Lozano"
    ],
    "name:spa_x_preferred":[
        "Padre Lozano"
    ],
    "name:und_x_variant":[
        "Milagro",
        "Padre Pedro Lozano",
        "Padre Lozana"
    ],
    "wof:name":"Padre Lozano",
    "wof:placetype":"locality"
},
  "geometry": {"coordinates":[-63.87519,-23.21492000000001],"type":"Point"}
}