{
  "type": "Feature",
  "properties": {
    "gn:admin1_code":"8.0",
    "gn:admin2_code":"30008.0",
    "gn:asciiname":"Liebig",
    "gn:cc2":"AR",
    "gn:country_code":"AR",
    "gn:dem":26,
    "gn:feature_class":"P",
    "gn:feature_code":"PPL",
    "gn:name":"Liebig",
    "gn:population":0,
    "gn:timezone":"America/Argentina/Cordoba",
    "iso:country":"AR",
    "name:und_x_variant":[
        "Yatay",
        "Liebig"
    ],
    "wof:name":"Liebig",
    "wof:placetype":"locality"
},
  "geometry": {"coordinates":[-58.26667,-32.13333],"type":"Point"}
}