{
  "type": "Feature",
  "properties": {
    "gn:admin1_code":"16.0",
    "gn:admin2_code":"62063.0",
    "gn:asciiname":"Juan de Garay",
    "gn:country_code":"AR",
    "gn:dem":109,
    "gn:feature_class":"P",
    "gn:feature_code":"PPL",
    "gn:name":"Juan de Garay",
    "gn:population":0,
    "gn:timezone":"America/Argentina/Salta",
    "iso:country":"AR",
    "name:bul_x_preferred":[
        "\u0425\u0443\u0430\u043d \u0434\u0435 \u0413\u0430\u0440\u0430\u0439"
    ],
    "name:eus_x_preferred":[
        "Juan Garai"
    ],
    "name:jpn_x_preferred":[
        "\u30d5\u30a2\u30f3\u30fb\u30c7\u30fb\u30ac\u30e9\u30a4"
    ],
    "name:kor_x_preferred":[
        "\ud6c4\uc548 \ub370 \uac00\ub77c\uc774"
    ],
    "name:rus_x_preferred":[
        "\u0425\u0443\u0430\u043d \u0434\u0435 \u0413\u0430\u0440\u0430\u0439"
    ],
    "name:ukr_x_preferred":[
        "\u0425\u0443\u0430\u043d \u0434\u0435 \u0490\u0430\u0440\u0430\u0439"
    ],
    "name:und_x_variant":[
        "J. de Garay",
        "Juan de Garay"
    ],
    "name:zho_x_preferred":[
        "\u80e1\u5b89\u00b7\u5fb7\u00b7\u52a0\u96f7"
    ],
    "wof:name":"Juan de Garay",
    "wof:placetype":"locality"
},
  "geometry": {"coordinates":[-64.55153,-38.86973],"type":"Point"}
}