{
  "type": "Feature",
  "properties": {
    "gn:admin1_code":"16.0",
    "gn:admin2_code":"62063.0",
    "gn:asciiname":"Juan de Garay",
    "gn:country_code":"AR",
    "gn:dem":109,
    "gn:feature_class":"P",
    "gn:feature_code":"PPL",
    "gn:name":"Juan de Garay",
    "gn:population":0,
    "gn:timezone":"America/Argentina/Salta",
    "iso:country":"AR",
    "name:und_x_variant":[
        "J. de Garay",
        "Juan de Garay"
    ],
    "wof:name":"Juan de Garay",
    "wof:placetype":"locality"
},
  "geometry": {"coordinates":[-64.55153,-38.86973],"type":"Point"}
}