{
  "type": "Feature",
  "properties": {
    "iso:country":"AR",
    "name:ceb_x_preferred":[
        "Hualf\u00edn"
    ],
    "name:eng_x_preferred":[
        "Hualf\u00edn"
    ],
    "name:fra_x_preferred":[
        "Hualf\u00edn"
    ],
    "name:ita_x_preferred":[
        "Hualf\u00edn"
    ],
    "name:nld_x_preferred":[
        "Hualf\u00edn"
    ],
    "name:por_x_preferred":[
        "Hualf\u00edn"
    ],
    "name:spa_x_preferred":[
        "Hualf\u00edn"
    ],
    "name:swe_x_preferred":[
        "Hualf\u00edn"
    ],
    "qs:gn_country":"AR",
    "qs:gn_fcode":"PPL",
    "qs:gn_pop":2304,
    "qs:name":"Hualf\u00edn",
    "qs:name_adm0":"Argentina",
    "qs:name_adm1":"Catamarca",
    "qs:photos":0,
    "qs:photos_1k":0,
    "qs:photos_9k":1,
    "qs:photos_9r":2,
    "qs:photos_all":35,
    "qs:photos_sr":0,
    "qs:placetype":"Town",
    "qs:pop_sr":"4",
    "qs:woe_adm0":23424747,
    "wd:wordcount":33,
    "wof:name":"Hualf\u00edn",
    "wof:placetype":"locality",
    "wof:population":2304
},
  "geometry": {"coordinates":[-66.83131,-27.22896],"type":"Point"}
}