{
  "type": "Feature",
  "properties": {
    "gn:admin1_code":"9.0",
    "gn:admin2_code":"34049.0",
    "gn:asciiname":"Primera Punta",
    "gn:country_code":"AR",
    "gn:dem":84,
    "gn:feature_class":"P",
    "gn:feature_code":"PPL",
    "gn:name":"Primera Punta",
    "gn:population":0,
    "gn:timezone":"America/Argentina/Cordoba",
    "iso:country":"AR",
    "wof:name":"Primera Punta",
    "wof:placetype":"locality"
},
  "geometry": {"coordinates":[-58.35144,-25.11477],"type":"Point"}
}