{
  "type": "Feature",
  "properties": {
    "gn:admin1_code":"17",
    "gn:admin2_code":"66035.0",
    "gn:asciiname":"El Ceibalito",
    "gn:country_code":"AR",
    "gn:dem":1178,
    "gn:feature_class":"P",
    "gn:feature_code":"PPL",
    "gn:name":"El Ceibalito",
    "gn:population":0,
    "gn:timezone":"America/Argentina/Salta",
    "iso:country":"AR",
    "name:und_x_variant":[
        "Estancia El Ceibalito",
        "El Ceibalito"
    ],
    "wof:name":"El Ceibalito",
    "wof:placetype":"locality"
},
  "geometry": {"coordinates":[-65.37266,-24.97022],"type":"Point"}
}