{
  "type": "Feature",
  "properties": {
    "gn:admin1_code":"5.0",
    "gn:admin2_code":"14161.0",
    "gn:asciiname":"Pampayasta Norte",
    "gn:country_code":"AR",
    "gn:dem":284,
    "gn:feature_class":"P",
    "gn:feature_code":"PPL",
    "gn:name":"Pampayasta Norte",
    "gn:population":0,
    "gn:timezone":"America/Argentina/Cordoba",
    "iso:country":"AR",
    "wof:name":"Pampayasta Norte",
    "wof:placetype":"locality"
},
  "geometry": {"coordinates":[-63.64346,-32.24093],"type":"Point"}
}