{
  "type": "Feature",
  "properties": {
    "iso:country":"AR",
    "name:cat_x_preferred":[
        "Santa Gertrudis"
    ],
    "name:ceb_x_preferred":[
        "Santa Gertrudis"
    ],
    "name:deu_x_preferred":[
        "Santa Gertrudis"
    ],
    "name:sco_x_preferred":[
        "Santa Gertrudis"
    ],
    "name:spa_x_preferred":[
        "Santa Gertrudis"
    ],
    "name:swe_x_preferred":[
        "Santa Gertrudis"
    ],
    "name:und_x_variant":[
        "San Gertrudis"
    ],
    "qs:gn_country":"AR",
    "qs:gn_fcode":"PPL",
    "qs:gn_pop":0,
    "qs:name":"Santa Gertrudis",
    "qs:name_adm0":"Argentina",
    "qs:name_adm1":"Salta",
    "qs:photos":13,
    "qs:photos_1k":3,
    "qs:photos_9k":1,
    "qs:photos_9r":1,
    "qs:photos_all":13,
    "qs:photos_sr":1,
    "qs:placetype":"Town",
    "qs:pop_sr":"0",
    "qs:woe_adm0":23424747,
    "wof:name":"Santa Gertrudis",
    "wof:placetype":"locality"
},
  "geometry": {"coordinates":[-65.51501,-25.1185],"type":"Point"}
}