{
  "type": "Feature",
  "properties": {
    "iso:country":"AR",
    "qs:gn_pop":0,
    "qs:name":"Puerto la Uni\u00f3n",
    "qs:name_adm0":"Argentina",
    "qs:name_adm1":"Neuqu\u00e9n",
    "qs:photos":71,
    "qs:photos_1k":14,
    "qs:photos_9k":1,
    "qs:photos_9r":2,
    "qs:photos_all":71,
    "qs:photos_sr":2,
    "qs:placetype":"Town",
    "qs:pop_sr":"0",
    "qs:woe_adm0":23424747,
    "wof:name":"Puerto la Uni\u00f3n",
    "wof:placetype":"locality"
},
  "geometry": {"coordinates":[-71.514987,-39.74125],"type":"Point"}
}