{
  "type": "Feature",
  "properties": {
    "gn:admin1_code":"11",
    "gn:admin2_code":"42154.0",
    "gn:asciiname":"Chacharramendi",
    "gn:country_code":"AR",
    "gn:dem":283,
    "gn:feature_class":"P",
    "gn:feature_code":"PPL",
    "gn:name":"Chacharramendi",
    "gn:population":0,
    "gn:timezone":"America/Argentina/Salta",
    "iso:country":"AR",
    "wof:name":"Chacharramendi",
    "wof:placetype":"locality"
},
  "geometry": {"coordinates":[-65.65134,-37.33133],"type":"Point"}
}