{
  "type": "Feature",
  "properties": {
    "gn:admin1_code":"1.0",
    "gn:admin2_code":"6539.0",
    "gn:asciiname":"Puente Cascallares",
    "gn:country_code":"AR",
    "gn:dem":17,
    "gn:feature_class":"P",
    "gn:feature_code":"PPL",
    "gn:name":"Puente Cascallares",
    "gn:population":0,
    "gn:timezone":"America/Argentina/Buenos_Aires",
    "iso:country":"AR",
    "wof:name":"Puente Cascallares",
    "wof:placetype":"locality"
},
  "geometry": {"coordinates":[-58.81961999999999,-34.68622],"type":"Point"}
}