{
  "type": "Feature",
  "properties": {
    "gn:admin1_code":"2.0",
    "gn:admin2_code":"10014.0",
    "gn:asciiname":"Tacana",
    "gn:country_code":"AR",
    "gn:dem":1406,
    "gn:feature_class":"P",
    "gn:feature_code":"PPL",
    "gn:name":"Tacana",
    "gn:population":0,
    "gn:timezone":"America/Argentina/Catamarca",
    "iso:country":"AR",
    "wof:name":"Tacana",
    "wof:placetype":"locality"
},
  "geometry": {"coordinates":[-65.5856,-28.63025],"type":"Point"}
}