{
  "type": "Feature",
  "properties": {
    "gn:admin1_code":"17",
    "gn:admin2_code":"66063.0",
    "gn:asciiname":"El Cevillar",
    "gn:country_code":"AR",
    "gn:dem":1763,
    "gn:feature_class":"P",
    "gn:feature_code":"PPL",
    "gn:name":"El Cevillar",
    "gn:population":0,
    "gn:timezone":"America/Argentina/Salta",
    "iso:country":"AR",
    "name:und_x_variant":[
        "El Cebillar",
        "El Cevillar"
    ],
    "wof:name":"El Cevillar",
    "wof:placetype":"locality"
},
  "geometry": {"coordinates":[-65.47242,-25.62779],"type":"Point"}
}