{
  "type": "Feature",
  "properties": {
    "gn:admin1_code":"5.0",
    "gn:admin2_code":"14175.0",
    "gn:asciiname":"San Jose de las Salinas",
    "gn:country_code":"AR",
    "gn:dem":196,
    "gn:feature_class":"P",
    "gn:feature_code":"PPL",
    "gn:name":"San Jos\u00e9 de las Salinas",
    "gn:population":0,
    "gn:timezone":"America/Argentina/Cordoba",
    "iso:country":"AR",
    "name:und_x_variant":[
        "San Jos\u00e9",
        "San Jos\u00e9 de las Salinas"
    ],
    "wof:name":"San Jose de las Salinas",
    "wof:placetype":"locality"
},
  "geometry": {"coordinates":[-64.62398,-30.00787],"type":"Point"}
}