{
  "type": "Feature",
  "properties": {
    "gn:admin1_code":"23.0",
    "gn:admin2_code":"94007.0",
    "gn:asciiname":"Puerto San Pablo",
    "gn:country_code":"AR",
    "gn:dem":77,
    "gn:feature_class":"P",
    "gn:feature_code":"PPL",
    "gn:name":"Puerto San Pablo",
    "gn:population":0,
    "gn:timezone":"America/Argentina/Ushuaia",
    "iso:country":"AR",
    "wof:name":"Puerto San Pablo",
    "wof:placetype":"locality"
},
  "geometry": {"coordinates":[-66.76666999999999,-54.26667],"type":"Point"}
}