{
  "type": "Feature",
  "properties": {
    "gn:admin1_code":"22.0",
    "gn:admin2_code":"86028.0",
    "gn:asciiname":"Mailin",
    "gn:country_code":"AR",
    "gn:dem":114,
    "gn:feature_class":"P",
    "gn:feature_code":"PPL",
    "gn:name":"Mail\u00edn",
    "gn:population":0,
    "gn:timezone":"America/Argentina/Cordoba",
    "iso:country":"AR",
    "name:und_x_variant":[
        "Mail\u00edn"
    ],
    "wof:name":"Mailin",
    "wof:placetype":"locality"
},
  "geometry": {"coordinates":[-63.27624,-28.48262],"type":"Point"}
}