{
  "type": "Feature",
  "properties": {
    "gn:admin1_code":"24.0",
    "gn:admin2_code":"90063.0",
    "gn:asciiname":"La Reduccion",
    "gn:country_code":"AR",
    "gn:dem":398,
    "gn:feature_class":"P",
    "gn:feature_code":"PPL",
    "gn:name":"La Reducci\u00f3n",
    "gn:population":0,
    "gn:timezone":"America/Argentina/Tucuman",
    "iso:country":"AR",
    "wof:name":"La Reduccion",
    "wof:placetype":"locality"
},
  "geometry": {"coordinates":[-65.35053000000001,-26.95529],"type":"Point"}
}