{
  "type": "Feature",
  "properties": {
    "gn:admin1_code":"22.0",
    "gn:admin2_code":"86133.0",
    "gn:asciiname":"Rapelli",
    "gn:country_code":"AR",
    "gn:dem":399,
    "gn:feature_class":"P",
    "gn:feature_code":"PPL",
    "gn:name":"Rapelli",
    "gn:population":0,
    "gn:timezone":"America/Argentina/Cordoba",
    "iso:country":"AR",
    "wof:name":"Rapelli",
    "wof:placetype":"locality"
},
  "geometry": {"coordinates":[-64.50010999999999,-26.3922],"type":"Point"}
}