{
  "type": "Feature",
  "properties": {
    "gn:admin1_code":"16.0",
    "gn:admin2_code":"62077.0",
    "gn:asciiname":"Mancha Blanca",
    "gn:country_code":"AR",
    "gn:dem":158,
    "gn:feature_class":"P",
    "gn:feature_code":"PPL",
    "gn:name":"Mancha Blanca",
    "gn:population":0,
    "gn:timezone":"America/Argentina/Salta",
    "iso:country":"AR",
    "name:ceb_x_preferred":[
        "Tinguat\u00f3n"
    ],
    "name:deu_x_preferred":[
        "Mancha Blanca"
    ],
    "name:fra_x_preferred":[
        "Mancha Blanca"
    ],
    "name:nld_x_preferred":[
        "Mancha Blanca"
    ],
    "name:swe_x_preferred":[
        "Tinguat\u00f3n"
    ],
    "wof:name":"Mancha Blanca",
    "wof:placetype":"locality"
},
  "geometry": {"coordinates":[-65.45017,-40.77632],"type":"Point"}
}