{
  "type": "Feature",
  "properties": {
    "gn:admin1_code":"21.0",
    "gn:admin2_code":"82070.0",
    "gn:asciiname":"Santa Clara de Buena Vista",
    "gn:country_code":"AR",
    "gn:dem":55,
    "gn:feature_class":"P",
    "gn:feature_code":"PPL",
    "gn:name":"Santa Clara de Buena Vista",
    "gn:population":0,
    "gn:timezone":"America/Argentina/Cordoba",
    "iso:country":"AR",
    "name:und_x_variant":[
        "Santa Clara",
        "Santa Clara de Buena Vista"
    ],
    "wof:name":"Santa Clara de Buena Vista",
    "wof:placetype":"locality"
},
  "geometry": {"coordinates":[-61.31981999999999,-31.7639],"type":"Point"}
}