{
  "type": "Feature",
  "properties": {
    "gn:country":"AR",
    "gn:fcode":"PPLS",
    "gn:pop":1600,
    "iso:country":"AR",
    "qs:name":"Santa Catalina - Dique Lujan",
    "qs:photos_9r":0,
    "qs:photos_sr":0,
    "qs:pop_sr":"3",
    "wof:name":"Santa Catalina - Dique Lujan",
    "wof:placetype":"locality",
    "wof:population":1600
},
  "geometry": {"coordinates":[-58.70673,-34.38375],"type":"Point"}
}