{
  "type": "Feature",
  "properties": {
    "gn:admin1_code":"5.0",
    "gn:admin2_code":"14161.0",
    "gn:asciiname":"Los Zorros",
    "gn:country_code":"AR",
    "gn:dem":202,
    "gn:feature_class":"P",
    "gn:feature_code":"PPL",
    "gn:name":"Los Zorros",
    "gn:population":0,
    "gn:timezone":"America/Argentina/Cordoba",
    "iso:country":"AR",
    "wof:name":"Los Zorros",
    "wof:placetype":"locality"
},
  "geometry": {"coordinates":[-63.2014,-32.04571],"type":"Point"}
}