{
  "type": "Feature",
  "properties": {
    "iso:country":"AR",
    "name:eng_x_preferred":[
        "Contralmirante Cordero"
    ],
    "name:nld_x_preferred":[
        "Contralmirante Cordero"
    ],
    "name:spa_x_preferred":[
        "Contralmirante Cordero"
    ],
    "name:unk_x_variant":[
        "Contralmirante Cordero"
    ],
    "qs:gn_country":"AR",
    "qs:gn_fcode":"PPL",
    "qs:gn_pop":2782,
    "qs:name":"Contraalmirante Cordero",
    "qs:name_adm0":"Argentina",
    "qs:name_adm1":"R\u00edo Negro",
    "qs:photos":0,
    "qs:photos_1k":0,
    "qs:photos_9k":1,
    "qs:photos_9r":3,
    "qs:photos_all":112,
    "qs:photos_sr":0,
    "qs:placetype":"Town",
    "qs:pop_sr":"4",
    "qs:woe_adm0":23424747,
    "wof:name":"Contraalmirante Cordero",
    "wof:placetype":"locality",
    "wof:population":2782
},
  "geometry": {"coordinates":[-68.15284,-38.72423],"type":"Point"}
}