{
  "type": "Feature",
  "properties": {
    "gn:admin1_code":"1.0",
    "gn:admin2_code":"6826.0",
    "gn:asciiname":"La Portena",
    "gn:country_code":"AR",
    "gn:dem":109,
    "gn:feature_class":"P",
    "gn:feature_code":"PPL",
    "gn:name":"La Porte\u00f1a",
    "gn:population":0,
    "gn:timezone":"America/Argentina/Buenos_Aires",
    "iso:country":"AR",
    "wof:name":"La Portena",
    "wof:placetype":"locality"
},
  "geometry": {"coordinates":[-62.72001,-36.36443],"type":"Point"}
}