{
  "type": "Feature",
  "properties": {
    "gn:admin1_code":"6.0",
    "gn:admin2_code":"18021.0",
    "gn:asciiname":"Santa Ana",
    "gn:country_code":"AR",
    "gn:dem":72,
    "gn:feature_class":"P",
    "gn:feature_code":"PPL",
    "gn:name":"Santa Ana",
    "gn:population":0,
    "gn:timezone":"America/Argentina/Cordoba",
    "iso:country":"AR",
    "wof:name":"Santa Ana",
    "wof:placetype":"locality"
},
  "geometry": {"coordinates":[-58.65389,-27.45519],"type":"Point"}
}