{
  "type": "Feature",
  "properties": {
    "gn:admin1_code":"2.0",
    "gn:admin2_code":"10042.0",
    "gn:asciiname":"Los Pinos",
    "gn:country_code":"AR",
    "gn:dem":1225,
    "gn:feature_class":"P",
    "gn:feature_code":"PPL",
    "gn:name":"Los Pinos",
    "gn:population":0,
    "gn:timezone":"America/Argentina/Catamarca",
    "iso:country":"AR",
    "wof:name":"Los Pinos",
    "wof:placetype":"locality"
},
  "geometry": {"coordinates":[-65.95631,-28.5428],"type":"Point"}
}