{
  "type": "Feature",
  "properties": {
    "iso:country":"AR",
    "name:ceb_x_preferred":[
        "Santa Florentina"
    ],
    "name:eng_x_preferred":[
        "Santa Florentina"
    ],
    "name:spa_x_preferred":[
        "Santa Florentina"
    ],
    "name:swe_x_preferred":[
        "Santa Florentina"
    ],
    "name:unk_x_variant":[
        "Florentina"
    ],
    "qs:gn_country":"AR",
    "qs:gn_fcode":"PPL",
    "qs:gn_pop":0,
    "qs:name":"Santa Florentina",
    "qs:name_adm0":"Argentina",
    "qs:name_adm1":"La Rioja",
    "qs:photos":215,
    "qs:photos_1k":44,
    "qs:photos_9k":1,
    "qs:photos_9r":4,
    "qs:photos_all":215,
    "qs:photos_sr":4,
    "qs:placetype":"Town",
    "qs:pop_sr":"0",
    "qs:woe_adm0":23424747,
    "wd:wordcount":37,
    "wof:name":"Santa Florentina",
    "wof:placetype":"locality"
},
  "geometry": {"coordinates":[-67.55634000000001,-29.12985],"type":"Point"}
}