{
  "type": "Feature",
  "properties": {
    "iso:country":"AR",
    "name:dut_x_preferred":[
        "Fray Luis Beltr\u00e1n"
    ],
    "name:eng_x_preferred":[
        "Fray Luis Beltr\u00e1n"
    ],
    "name:spa_x_preferred":[
        "Fray Luis Beltr\u00e1n"
    ],
    "name:ukr_x_preferred":[
        "\u0424\u0440\u0430\u0439-\u041b\u0443\u0457\u0441-\u0411\u0435\u043b\u044c\u0442\u0440\u0430\u043d"
    ],
    "name:unk_x_variant":[
        "Fray L. Beltr\u00e1n"
    ],
    "qs:gn_country":"AR",
    "qs:gn_fcode":"PPL",
    "qs:gn_pop":0,
    "qs:name":"Fray Luis Beltr\u00e1n",
    "qs:name_adm0":"Argentina",
    "qs:name_adm1":"Mendoza",
    "qs:photos":0,
    "qs:photos_1k":0,
    "qs:photos_9k":1,
    "qs:photos_9r":1,
    "qs:photos_all":2,
    "qs:photos_sr":0,
    "qs:placetype":"Town",
    "qs:pop_sr":"0",
    "qs:woe_adm0":23424747,
    "wd:wordcount":169,
    "wof:name":"Fray Luis Beltr\u00e1n",
    "wof:placetype":"locality"
},
  "geometry": {"coordinates":[-68.65062,-33.00724],"type":"Point"}
}