{
  "type": "Feature",
  "properties": {
    "gn:admin1_code":"17.0",
    "gn:admin2_code":"66147.0",
    "gn:asciiname":"San Ramon",
    "gn:country_code":"AR",
    "gn:dem":1235,
    "gn:feature_class":"P",
    "gn:feature_code":"PPL",
    "gn:name":"San Ram\u00f3n",
    "gn:population":0,
    "gn:timezone":"America/Argentina/Salta",
    "iso:country":"AR",
    "wof:name":"San Ramon",
    "wof:placetype":"locality"
},
  "geometry": {"coordinates":[-65.52735,-25.01833],"type":"Point"}
}