{
  "type": "Feature",
  "properties": {
    "iso:country":"AR",
    "name:spa_x_preferred":[
        "Quebrada de los Pozos"
    ],
    "name:unk_x_variant":[
        "Quebrada de los Pozos"
    ],
    "qs:gn_country":"AR",
    "qs:gn_fcode":"PPL",
    "qs:gn_pop":0,
    "qs:name":"Quebrada de Los Pozos",
    "qs:name_adm0":"Argentina",
    "qs:name_adm1":"C\u00f3rdoba",
    "qs:photos":78,
    "qs:photos_1k":16,
    "qs:photos_9k":1,
    "qs:photos_9r":3,
    "qs:photos_all":78,
    "qs:photos_sr":3,
    "qs:placetype":"Town",
    "qs:pop_sr":"0",
    "qs:woe_adm0":23424747,
    "wof:name":"Quebrada de Los Pozos",
    "wof:placetype":"locality"
},
  "geometry": {"coordinates":[-65.03797,-31.91788],"type":"Point"}
}