{
  "type": "Feature",
  "properties": {
    "gn:admin1_code":"1.0",
    "gn:admin2_code":"6770.0",
    "gn:asciiname":"La Bolsa",
    "gn:country_code":"AR",
    "gn:dem":53,
    "gn:feature_class":"P",
    "gn:feature_code":"PPL",
    "gn:name":"La Bolsa",
    "gn:population":0,
    "gn:timezone":"America/Argentina/Buenos_Aires",
    "iso:country":"AR",
    "wof:name":"La Bolsa",
    "wof:placetype":"locality"
},
  "geometry": {"coordinates":[-59.9922,-33.78145],"type":"Point"}
}