{
  "type": "Feature",
  "properties": {
    "gn:admin1_code":"22.0",
    "gn:admin2_code":"86119.0",
    "gn:asciiname":"Girardet",
    "gn:country_code":"AR",
    "gn:dem":171,
    "gn:feature_class":"P",
    "gn:feature_code":"PPL",
    "gn:name":"Girardet",
    "gn:population":0,
    "gn:timezone":"America/Argentina/Cordoba",
    "iso:country":"AR",
    "wof:name":"Girardet",
    "wof:placetype":"locality"
},
  "geometry": {"coordinates":[-62.16667,-27.61667000000001],"type":"Point"}
}