{
  "type": "Feature",
  "properties": {
    "gn:admin1_code":"21",
    "gn:admin2_code":"82098.0",
    "gn:asciiname":"Campo Kaufmann",
    "gn:country_code":"AR",
    "gn:dem":55,
    "gn:feature_class":"P",
    "gn:feature_code":"PPLF",
    "gn:name":"Campo Kaufmann",
    "gn:population":0,
    "gn:timezone":"America/Argentina/Buenos_Aires",
    "iso:country":"AR",
    "name:und_x_variant":[
        "Escuela Nro 6376"
    ],
    "wof:name":"Campo Kaufmann",
    "wof:placetype":"locality"
},
  "geometry": {"coordinates":[-59.87167,-29.42036],"type":"Point"}
}