{
  "type": "Feature",
  "properties": {
    "iso:country":"AR",
    "name:eng_x_preferred":[
        "General Pir\u00e1n"
    ],
    "name:nld_x_preferred":[
        "General Pir\u00e1n"
    ],
    "name:spa_x_preferred":[
        "General Pir\u00e1n"
    ],
    "name:ukr_x_preferred":[
        "\u0425\u0435\u043d\u0435\u0440\u0430\u043b\u044c-\u041f\u0456\u0440\u0430\u043d"
    ],
    "qs:gn_country":"AR",
    "qs:gn_fcode":"PPL",
    "qs:gn_pop":0,
    "qs:name":"General Pir\u00e1n",
    "qs:name_adm0":"Argentina",
    "qs:name_adm1":"Buenos Aires",
    "qs:photos":0,
    "qs:photos_1k":0,
    "qs:photos_9k":1,
    "qs:photos_9r":1,
    "qs:photos_all":1,
    "qs:photos_sr":0,
    "qs:placetype":"Town",
    "qs:pop_sr":"5",
    "qs:woe_adm0":23424747,
    "wof:name":"General Pir\u00e1n",
    "wof:placetype":"locality"
},
  "geometry": {"coordinates":[-57.77375,-37.27455],"type":"Point"}
}