{
  "type": "Feature",
  "properties": {
    "gn:admin1_code":"16.0",
    "gn:admin2_code":"62021.0",
    "gn:asciiname":"Puerto Frias",
    "gn:country_code":"AR",
    "gn:dem":788,
    "gn:feature_class":"P",
    "gn:feature_code":"PPL",
    "gn:name":"Puerto Fr\u00edas",
    "gn:population":0,
    "gn:timezone":"America/Argentina/Salta",
    "iso:country":"AR",
    "wof:name":"Puerto Frias",
    "wof:placetype":"locality"
},
  "geometry": {"coordinates":[-71.80853,-41.07845],"type":"Point"}
}