{
  "type": "Feature",
  "properties": {
    "gn:admin1_code":"12.0",
    "gn:admin2_code":"46035.0",
    "gn:asciiname":"Esquina",
    "gn:country_code":"AR",
    "gn:dem":384,
    "gn:feature_class":"P",
    "gn:feature_code":"PPL",
    "gn:name":"Esquina",
    "gn:population":0,
    "gn:timezone":"America/Argentina/La_Rioja",
    "iso:country":"AR",
    "name:ceb_x_preferred":[
        "Esquina"
    ],
    "name:deu_x_preferred":[
        "Esquina"
    ],
    "name:nld_x_preferred":[
        "Esquina"
    ],
    "name:por_x_preferred":[
        "Esquina"
    ],
    "name:slk_x_preferred":[
        "Esquina"
    ],
    "name:spa_x_preferred":[
        "Esquina"
    ],
    "name:swe_x_preferred":[
        "Esquina"
    ],
    "wof:name":"Esquina",
    "wof:placetype":"locality"
},
  "geometry": {"coordinates":[-66.09173,-30.42313],"type":"Point"}
}