{
  "type": "Feature",
  "properties": {
    "gn:admin1_code":"1.0",
    "gn:admin2_code":"6049.0",
    "gn:asciiname":"Vicente Pereda",
    "gn:country_code":"AR",
    "gn:dem":128,
    "gn:feature_class":"P",
    "gn:feature_code":"PPL",
    "gn:name":"Vicente Pereda",
    "gn:population":0,
    "gn:timezone":"America/Argentina/Buenos_Aires",
    "iso:country":"AR",
    "name:deu_x_preferred":[
        "Vicente Pereda"
    ],
    "name:fra_x_preferred":[
        "Vicente Pereda"
    ],
    "name:ita_x_preferred":[
        "Vicente Pereda"
    ],
    "name:rus_x_preferred":[
        "\u041f\u0435\u0440\u0435\u0434\u0430"
    ],
    "name:spa_x_preferred":[
        "Vicente Pereda"
    ],
    "name:ukr_x_preferred":[
        "\u0412\u0456\u0441\u0435\u043d\u0442\u0435 \u041f\u0435\u0440\u0435\u0434\u0430"
    ],
    "wof:name":"Vicente Pereda",
    "wof:placetype":"locality"
},
  "geometry": {"coordinates":[-59.78248000000001,-36.69856],"type":"Point"}
}