{
  "type": "Feature",
  "properties": {
    "gn:admin1_code":"1.0",
    "gn:admin2_code":"6049.0",
    "gn:asciiname":"Vicente Pereda",
    "gn:country_code":"AR",
    "gn:dem":128,
    "gn:feature_class":"P",
    "gn:feature_code":"PPL",
    "gn:name":"Vicente Pereda",
    "gn:population":0,
    "gn:timezone":"America/Argentina/Buenos_Aires",
    "iso:country":"AR",
    "wof:name":"Vicente Pereda",
    "wof:placetype":"locality"
},
  "geometry": {"coordinates":[-59.78248000000001,-36.69856],"type":"Point"}
}