{
  "type": "Feature",
  "properties": {
    "iso:country":"AR",
    "name:ceb_x_preferred":[
        "San Isidro"
    ],
    "name:eng_x_preferred":[
        "San Isidro"
    ],
    "name:fas_x_preferred":[
        "\u0633\u0646 \u0627\u06cc\u0633\u06cc\u062f\u0631\u0648"
    ],
    "name:fra_x_preferred":[
        "San Isidro"
    ],
    "name:ita_x_preferred":[
        "San Isidro"
    ],
    "name:nld_x_preferred":[
        "San Isidro"
    ],
    "name:pol_x_preferred":[
        "San Isidro"
    ],
    "name:por_x_preferred":[
        "San Isidro"
    ],
    "name:sco_x_preferred":[
        "San Isidro"
    ],
    "name:spa_x_preferred":[
        "San Isidro"
    ],
    "name:tur_x_preferred":[
        "San Isidro"
    ],
    "name:zho_x_preferred":[
        "\u8056\u4f0a\u897f\u5fb7\u7f85"
    ],
    "qs:gn_country":"AR",
    "qs:gn_fcode":"PPL",
    "qs:gn_pop":0,
    "qs:name":"San Isidro",
    "qs:name_adm0":"Argentina",
    "qs:name_adm1":"Catamarca",
    "qs:photos":0,
    "qs:photos_1k":0,
    "qs:photos_9k":1,
    "qs:photos_9r":1,
    "qs:photos_all":9,
    "qs:photos_sr":0,
    "qs:placetype":"Town",
    "qs:pop_sr":"0",
    "qs:woe_adm0":23424747,
    "wd:wordcount":48,
    "wof:name":"San Isidro",
    "wof:placetype":"locality"
},
  "geometry": {"coordinates":[-65.72586,-28.46265],"type":"Point"}
}