{
  "type": "Feature",
  "properties": {
    "gn:admin1_code":"05",
    "gn:admin2_code":"14007.0",
    "gn:asciiname":"Intiyaco",
    "gn:country_code":"AR",
    "gn:dem":1061,
    "gn:feature_class":"P",
    "gn:feature_code":"PPL",
    "gn:name":"Intiyaco",
    "gn:population":0,
    "gn:timezone":"America/Argentina/Cordoba",
    "iso:country":"AR",
    "wof:name":"Intiyaco",
    "wof:placetype":"locality"
},
  "geometry": {"coordinates":[-64.71621,-31.95893],"type":"Point"}
}