{
  "type": "Feature",
  "properties": {
    "gn:admin1_code":"3.0",
    "gn:admin2_code":"22063.0",
    "gn:asciiname":"Simbolar",
    "gn:country_code":"AR",
    "gn:dem":180,
    "gn:feature_class":"P",
    "gn:feature_code":"PPL",
    "gn:name":"Simbolar",
    "gn:population":0,
    "gn:timezone":"America/Argentina/Cordoba",
    "iso:country":"AR",
    "wof:name":"Simbolar",
    "wof:placetype":"locality"
},
  "geometry": {"coordinates":[-62.04121,-24.58081],"type":"Point"}
}