{
  "type": "Feature",
  "properties": {
    "iso:country":"AR",
    "name:ceb_x_preferred":[
        "Tapebicu\u00e1"
    ],
    "name:eng_x_preferred":[
        "Tapebicu\u00e1"
    ],
    "name:nld_x_preferred":[
        "Tapebicu\u00e1"
    ],
    "name:por_x_preferred":[
        "Tapebicu\u00e1"
    ],
    "name:spa_x_preferred":[
        "Tapebicu\u00e1"
    ],
    "name:swe_x_preferred":[
        "Tapebicu\u00e1"
    ],
    "qs:gn_country":"AR",
    "qs:gn_fcode":"PPL",
    "qs:gn_pop":698,
    "qs:name":"Tapebicu\u00e1",
    "qs:name_adm0":"Argentina",
    "qs:name_adm1":"Corrientes",
    "qs:photos":0,
    "qs:photos_1k":0,
    "qs:photos_9k":1,
    "qs:photos_9r":1,
    "qs:photos_all":2,
    "qs:photos_sr":0,
    "qs:placetype":"Town",
    "qs:pop_sr":"2",
    "qs:woe_adm0":23424747,
    "wof:name":"Tapebicu\u00e1",
    "wof:placetype":"locality",
    "wof:population":698
},
  "geometry": {"coordinates":[-56.97488,-29.50616],"type":"Point"}
}