{
  "type": "Feature",
  "properties": {
    "gn:admin1_code":"18.0",
    "gn:admin2_code":"70056.0",
    "gn:asciiname":"La Cienaga de Cumillango",
    "gn:country_code":"AR",
    "gn:dem":1004,
    "gn:feature_class":"P",
    "gn:feature_code":"PPL",
    "gn:name":"La Ci\u00e9naga de Cumillango",
    "gn:population":0,
    "gn:timezone":"America/Argentina/San_Juan",
    "iso:country":"AR",
    "wof:name":"La Cienaga de Cumillango",
    "wof:placetype":"locality"
},
  "geometry": {"coordinates":[-68.71666999999999,-30.48333],"type":"Point"}
}