{
  "type": "Feature",
  "properties": {
    "gn:admin1_code":"02",
    "gn:asciiname":"Copetonas",
    "gn:country_code":"AR",
    "gn:dem":46,
    "gn:feature_class":"P",
    "gn:feature_code":"PPL",
    "gn:name":"Copetonas",
    "gn:population":0,
    "gn:timezone":"America/Argentina/Buenos_Aires",
    "iso:country":"AR",
    "wof:name":"Copetonas",
    "wof:placetype":"locality"
},
  "geometry": {"coordinates":[-60.45293,-38.72255],"type":"Point"}
}