{
  "type": "Feature",
  "properties": {
    "gn:admin1_code":"22.0",
    "gn:admin2_code":"86063.0",
    "gn:asciiname":"La Portena",
    "gn:country_code":"AR",
    "gn:dem":297,
    "gn:feature_class":"P",
    "gn:feature_code":"PPL",
    "gn:name":"La Porte\u00f1a",
    "gn:population":0,
    "gn:timezone":"America/Argentina/Cordoba",
    "iso:country":"AR",
    "wof:name":"La Portena",
    "wof:placetype":"locality"
},
  "geometry": {"coordinates":[-64.80388000000001,-28.70423],"type":"Point"}
}