{
  "type": "Feature",
  "properties": {
    "gn:admin1_code":"15.0",
    "gn:admin2_code":"58063.0",
    "gn:asciiname":"Mulichinco",
    "gn:country_code":"AR",
    "gn:dem":1266,
    "gn:feature_class":"P",
    "gn:feature_code":"PPL",
    "gn:name":"Mulichinc\u00f3",
    "gn:population":0,
    "gn:timezone":"America/Argentina/Salta",
    "iso:country":"AR",
    "wof:name":"Mulichinco",
    "wof:placetype":"locality"
},
  "geometry": {"coordinates":[-70.4372,-38.07836],"type":"Point"}
}