{
  "type": "Feature",
  "properties": {
    "gn:admin1_code":"22.0",
    "gn:admin2_code":"86168.0",
    "gn:asciiname":"Los Cerrillos",
    "gn:country_code":"AR",
    "gn:dem":104,
    "gn:feature_class":"P",
    "gn:feature_code":"PPL",
    "gn:name":"Los Cerrillos",
    "gn:population":0,
    "gn:timezone":"America/Argentina/Cordoba",
    "iso:country":"AR",
    "name:ceb_x_preferred":[
        "Los Cerrillos"
    ],
    "name:spa_x_preferred":[
        "Los Cerrillos"
    ],
    "name:swe_x_preferred":[
        "Los Cerrillos"
    ],
    "wof:name":"Los Cerrillos",
    "wof:placetype":"locality"
},
  "geometry": {"coordinates":[-63.3456,-28.98557000000001],"type":"Point"}
}