{
  "type": "Feature",
  "properties": {
    "gn:admin1_code":"01",
    "gn:admin2_code":"6210.0",
    "gn:asciiname":"Cucha Cucha",
    "gn:country_code":"AR",
    "gn:dem":71,
    "gn:feature_class":"P",
    "gn:feature_code":"PPL",
    "gn:name":"Cucha Cucha",
    "gn:population":0,
    "gn:timezone":"America/Argentina/Buenos_Aires",
    "iso:country":"AR",
    "wof:name":"Cucha Cucha",
    "wof:placetype":"locality"
},
  "geometry": {"coordinates":[-60.41559,-34.62173],"type":"Point"}
}