{
  "type": "Feature",
  "properties": {
    "gn:admin1_code":"1.0",
    "gn:admin2_code":"6147.0",
    "gn:asciiname":"Moctezuma",
    "gn:country_code":"AR",
    "gn:dem":88,
    "gn:feature_class":"P",
    "gn:feature_code":"PPL",
    "gn:name":"Moctezuma",
    "gn:population":0,
    "gn:timezone":"America/Argentina/Buenos_Aires",
    "iso:country":"AR",
    "wof:name":"Moctezuma",
    "wof:placetype":"locality"
},
  "geometry": {"coordinates":[-61.49361,-35.47724],"type":"Point"}
}