{
  "type": "Feature",
  "properties": {
    "gn:country":"AR",
    "gn:fcode":"PPL",
    "gn:pop":2291,
    "iso:country":"AR",
    "name:eng_x_preferred":[
        "Serrezuela"
    ],
    "name:ita_x_preferred":[
        "Serrezuela"
    ],
    "name:nld_x_preferred":[
        "Serrezuela"
    ],
    "name:por_x_preferred":[
        "Serrezuela"
    ],
    "name:spa_x_preferred":[
        "Serrezuela"
    ],
    "name:ukr_x_preferred":[
        "\u0421\u0435\u0440\u0440\u0435\u0441\u0443\u0435\u043b\u0430"
    ],
    "qs:name":"Serrezuela",
    "qs:photos_9r":0,
    "qs:photos_sr":0,
    "qs:pop_sr":"6",
    "wof:name":"Serrezuela",
    "wof:placetype":"locality",
    "wof:population":2291
},
  "geometry": {"coordinates":[-65.38692,-30.63761],"type":"Point"}
}