{
  "type": "Feature",
  "properties": {
    "iso:country":"AR",
    "name:eng_x_preferred":[
        "It\u00e1 Ibat\u00e9"
    ],
    "name:nld_x_preferred":[
        "It\u00e1 Ibat\u00e9"
    ],
    "name:spa_x_preferred":[
        "It\u00e1 Ibat\u00e9"
    ],
    "name:swe_x_preferred":[
        "It\u00e1 Ibat\u00e9"
    ],
    "name:ukr_x_preferred":[
        "\u0406\u0442\u0430-\u0406\u0431\u0430\u0442\u0435"
    ],
    "name:unk_x_variant":[
        "Italbate"
    ],
    "qs:gn_country":"AR",
    "qs:gn_fcode":"PPL",
    "qs:gn_pop":4115,
    "qs:name":"It\u00e1 Ibat\u00e9",
    "qs:name_adm0":"Argentina",
    "qs:name_adm1":"Corrientes",
    "qs:photos":0,
    "qs:photos_1k":0,
    "qs:photos_9k":1,
    "qs:photos_9r":1,
    "qs:photos_all":10,
    "qs:photos_sr":0,
    "qs:placetype":"Town",
    "qs:pop_sr":"4",
    "qs:woe_adm0":23424747,
    "wof:name":"It\u00e1 Ibat\u00e9",
    "wof:placetype":"locality",
    "wof:population":4115
},
  "geometry": {"coordinates":[-57.33758,-27.42573],"type":"Point"}
}