{
  "type": "Feature",
  "properties": {
    "gn:admin1_code":"16",
    "gn:admin2_code":"62084.0",
    "gn:asciiname":"Arroyo de la Ventana",
    "gn:country_code":"AR",
    "gn:dem":447,
    "gn:feature_class":"P",
    "gn:feature_code":"PPL",
    "gn:name":"Arroyo de la Ventana",
    "gn:population":0,
    "gn:timezone":"America/Argentina/Salta",
    "iso:country":"AR",
    "wof:name":"Arroyo de la Ventana",
    "wof:placetype":"locality"
},
  "geometry": {"coordinates":[-66.09012,-41.66508],"type":"Point"}
}