{
  "type": "Feature",
  "properties": {
    "gn:admin1_code":"15.0",
    "gn:admin2_code":"58077.0",
    "gn:asciiname":"Huinganco",
    "gn:country_code":"AR",
    "gn:dem":1188,
    "gn:feature_class":"P",
    "gn:feature_code":"PPL",
    "gn:name":"Huinganco",
    "gn:population":0,
    "gn:timezone":"America/Argentina/Salta",
    "iso:country":"AR",
    "name:ceb_x_preferred":[
        "Huinganco"
    ],
    "name:spa_x_preferred":[
        "Huinganco"
    ],
    "wof:name":"Huinganco",
    "wof:placetype":"locality"
},
  "geometry": {"coordinates":[-70.61832,-37.16139],"type":"Point"}
}