{
  "type": "Feature",
  "properties": {
    "gn:admin1_code":"01",
    "gn:admin2_code":"6189.0",
    "gn:asciiname":"Balneario Oriente",
    "gn:country_code":"AR",
    "gn:dem":4,
    "gn:feature_class":"P",
    "gn:feature_code":"PPL",
    "gn:name":"Balneario Oriente",
    "gn:population":0,
    "gn:timezone":"America/Argentina/Buenos_Aires",
    "iso:country":"AR",
    "wof:name":"Balneario Oriente",
    "wof:placetype":"locality"
},
  "geometry": {"coordinates":[-60.53333000000001,-38.91667],"type":"Point"}
}