{
  "type": "Feature",
  "properties": {
    "gn:admin1_code":"12.0",
    "gn:admin2_code":"46091.0",
    "gn:asciiname":"Ulapes",
    "gn:country_code":"AR",
    "gn:dem":411,
    "gn:feature_class":"P",
    "gn:feature_code":"PPLA2",
    "gn:name":"Ulapes",
    "gn:population":0,
    "gn:timezone":"America/Argentina/La_Rioja",
    "iso:country":"AR",
    "name:ceb_x_preferred":[
        "Ulapes"
    ],
    "name:fra_x_preferred":[
        "Ulapes"
    ],
    "name:ita_x_preferred":[
        "Ulapes"
    ],
    "name:por_x_preferred":[
        "Ulapes"
    ],
    "name:spa_x_preferred":[
        "Ulapes"
    ],
    "name:swe_x_preferred":[
        "Ulapes"
    ],
    "name:zho_x_preferred":[
        "\u70cf\u62c9\u4f69\u65af"
    ],
    "wof:name":"Ulapes",
    "wof:placetype":"locality"
},
  "geometry": {"coordinates":[-66.23650000000001,-31.57362],"type":"Point"}
}