{
  "type": "Feature",
  "properties": {
    "gn:admin1_code":"8.0",
    "gn:admin2_code":"30028.0",
    "gn:asciiname":"San Jaime",
    "gn:country_code":"AR",
    "gn:dem":82,
    "gn:feature_class":"P",
    "gn:feature_code":"PPL",
    "gn:name":"San Jaime",
    "gn:population":0,
    "gn:timezone":"America/Argentina/Cordoba",
    "iso:country":"AR",
    "name:und_x_variant":[
        "Juan B. Arruabarrena",
        "J.B. Arruabarrena",
        "Juan Bautista Arruabarrena",
        "San Jaime"
    ],
    "wof:name":"San Jaime",
    "wof:placetype":"locality"
},
  "geometry": {"coordinates":[-58.30707,-30.34098],"type":"Point"}
}