{
  "type": "Feature",
  "properties": {
    "gn:admin1_code":"01",
    "gn:admin2_code":"6609.0",
    "gn:asciiname":"Alagon",
    "gn:country_code":"AR",
    "gn:dem":87,
    "gn:feature_class":"P",
    "gn:feature_code":"PPL",
    "gn:name":"Alag\u00f3n",
    "gn:population":0,
    "gn:timezone":"America/Argentina/Buenos_Aires",
    "iso:country":"AR",
    "wof:name":"Alagon",
    "wof:placetype":"locality"
},
  "geometry": {"coordinates":[-61.96695,-35.94562],"type":"Point"}
}