{
  "type": "Feature",
  "properties": {
    "gn:admin1_code":"9.0",
    "gn:admin2_code":"34042.0",
    "gn:asciiname":"Punta Pora",
    "gn:country_code":"AR",
    "gn:dem":87,
    "gn:feature_class":"P",
    "gn:feature_code":"PPL",
    "gn:name":"Punta Por\u00e1",
    "gn:population":0,
    "gn:timezone":"America/Argentina/Cordoba",
    "iso:country":"AR",
    "wof:name":"Punta Pora",
    "wof:placetype":"locality"
},
  "geometry": {"coordinates":[-58.5115,-25.21594],"type":"Point"}
}