{
  "type": "Feature",
  "properties": {
    "gn:admin1_code":"24.0",
    "gn:admin2_code":"90091.0",
    "gn:asciiname":"Ingas",
    "gn:country_code":"AR",
    "gn:dem":316,
    "gn:feature_class":"P",
    "gn:feature_code":"PPL",
    "gn:name":"Ingas",
    "gn:population":0,
    "gn:timezone":"America/Argentina/Tucuman",
    "iso:country":"AR",
    "wof:name":"Ingas",
    "wof:placetype":"locality"
},
  "geometry": {"coordinates":[-65.34931999999999,-27.44922],"type":"Point"}
}