{
  "type": "Feature",
  "properties": {
    "iso:country":"AR",
    "name:ceb_x_preferred":[
        "Colonia El\u00eda"
    ],
    "name:eng_x_preferred":[
        "Colonia El\u00eda"
    ],
    "name:nld_x_preferred":[
        "Colonia El\u00eda"
    ],
    "name:por_x_preferred":[
        "Colonia El\u00eda"
    ],
    "name:spa_x_preferred":[
        "Colonia El\u00eda"
    ],
    "name:swe_x_preferred":[
        "Colonia El\u00eda"
    ],
    "qs:gn_country":"AR",
    "qs:gn_fcode":"PPL",
    "qs:gn_pop":1620,
    "qs:name":"Colonia El\u00eda",
    "qs:name_adm0":"Argentina",
    "qs:name_adm1":"Entre R\u00edos",
    "qs:photos":0,
    "qs:photos_1k":0,
    "qs:photos_9k":0,
    "qs:photos_9r":0,
    "qs:photos_all":0,
    "qs:photos_sr":0,
    "qs:placetype":"Town",
    "qs:pop_sr":"5",
    "qs:woe_adm0":23424747,
    "wof:name":"Colonia El\u00eda",
    "wof:placetype":"locality",
    "wof:population":1620
},
  "geometry": {"coordinates":[-58.32148,-32.66625],"type":"Point"}
}