{
  "type": "Feature",
  "properties": {
    "iso:country":"AR",
    "name:azb_x_preferred":[
        "\u0633\u0627\u0646 \u0644\u0648\u0631\u0646\u0633\u0648"
    ],
    "name:bul_x_preferred":[
        "\u0421\u0430\u043d \u041b\u043e\u0440\u0435\u043d\u0441\u043e"
    ],
    "name:cat_x_preferred":[
        "San Lorenzo"
    ],
    "name:dan_x_preferred":[
        "San Lorenzo"
    ],
    "name:eng_x_preferred":[
        "San Lorenzo"
    ],
    "name:fas_x_preferred":[
        "\u0633\u0627\u0646 \u0644\u0648\u0631\u0646\u0633\u0648"
    ],
    "name:fra_x_preferred":[
        "San Lorenzo"
    ],
    "name:heb_x_preferred":[
        "\u05e1\u05df \u05dc\u05d5\u05e8\u05e0\u05e6\u05d5"
    ],
    "name:ita_x_preferred":[
        "San Lorenzo"
    ],
    "name:jpn_x_preferred":[
        "\u30b5\u30f3\u30ed\u30ec\u30f3\u30bd"
    ],
    "name:kor_x_preferred":[
        "\uc0b0\ub85c\ub80c\uc18c"
    ],
    "name:lit_x_preferred":[
        "San Lorensas"
    ],
    "name:nld_x_preferred":[
        "San Lorenzo"
    ],
    "name:pol_x_preferred":[
        "San Lorenzo"
    ],
    "name:por_x_preferred":[
        "San Lorenzo"
    ],
    "name:rus_x_preferred":[
        "\u0421\u0430\u043d-\u041b\u043e\u0440\u0435\u043d\u0446\u043e"
    ],
    "name:rus_x_variant":[
        "\u0421\u0430\u043d-\u041b\u043e\u0440\u0435\u043d\u0441\u043e"
    ],
    "name:spa_x_preferred":[
        "San Lorenzo"
    ],
    "name:ukr_x_preferred":[
        "\u0421\u0430\u043d-\u041b\u043e\u0440\u0435\u043d\u0441\u043e"
    ],
    "name:zho_x_preferred":[
        "\u5723\u6d1b\u4f26\u7d22"
    ],
    "qs:gn_country":"AR",
    "qs:gn_fcode":"PPL",
    "qs:gn_pop":0,
    "qs:name":"San Lorenzo",
    "qs:name_adm0":"Argentina",
    "qs:name_adm1":"Santa Fe",
    "qs:photos":727,
    "qs:photos_1k":147,
    "qs:photos_9k":3,
    "qs:photos_9r":5,
    "qs:photos_all":727,
    "qs:photos_sr":8,
    "qs:placetype":"Town",
    "qs:pop_sr":"0",
    "qs:woe_adm0":23424747,
    "wd:wordcount":270,
    "wof:name":"San Lorenzo",
    "wof:placetype":"locality"
},
  "geometry": {"coordinates":[-60.745,-32.74139],"type":"Point"}
}