{
  "type": "Feature",
  "properties": {
    "gn:admin1_code":"21.0",
    "gn:admin2_code":"82112.0",
    "gn:asciiname":"Gobernador Crespo",
    "gn:country_code":"AR",
    "gn:dem":58,
    "gn:feature_class":"P",
    "gn:feature_code":"PPL",
    "gn:name":"Gobernador Crespo",
    "gn:population":0,
    "gn:timezone":"America/Argentina/Cordoba",
    "iso:country":"AR",
    "wof:name":"Gobernador Crespo",
    "wof:placetype":"locality"
},
  "geometry": {"coordinates":[-60.40162,-30.3627],"type":"Point"}
}