{
  "type": "Feature",
  "properties": {
    "gn:admin1_code":"1.0",
    "gn:admin2_code":"6434.0",
    "gn:asciiname":"Villa Diamante",
    "gn:country_code":"AR",
    "gn:dem":7,
    "gn:feature_class":"P",
    "gn:feature_code":"PPL",
    "gn:name":"Villa Diamante",
    "gn:population":0,
    "gn:timezone":"America/Argentina/Buenos_Aires",
    "iso:country":"AR",
    "name:spa_x_preferred":[
        "Villa Diamante"
    ],
    "wof:name":"Villa Diamante",
    "wof:placetype":"locality"
},
  "geometry": {"coordinates":[-58.43297,-34.68189],"type":"Point"}
}