{
  "type": "Feature",
  "properties": {
    "gn:admin1_code":"1.0",
    "gn:admin2_code":"6147.0",
    "gn:asciiname":"Smith",
    "gn:country_code":"AR",
    "gn:dem":88,
    "gn:feature_class":"P",
    "gn:feature_code":"PPL",
    "gn:name":"Smith",
    "gn:population":0,
    "gn:timezone":"America/Argentina/Buenos_Aires",
    "iso:country":"AR",
    "name:bel_x_preferred":[
        "\u0421\u043c\u0456\u0442"
    ],
    "name:bul_x_preferred":[
        "\u0421\u043c\u0438\u0442"
    ],
    "name:cat_x_preferred":[
        "Smith"
    ],
    "name:ceb_x_preferred":[
        "Smith"
    ],
    "name:ces_x_preferred":[
        "Smith"
    ],
    "name:deu_x_preferred":[
        "Smith"
    ],
    "name:fas_x_preferred":[
        "\u0627\u0633\u0645\u06cc\u062a"
    ],
    "name:fin_x_preferred":[
        "Smith"
    ],
    "name:fra_x_preferred":[
        "Smith"
    ],
    "name:heb_x_preferred":[
        "\u05e1\u05de\u05d9\u05ea'"
    ],
    "name:ita_x_preferred":[
        "Smith"
    ],
    "name:jpn_x_preferred":[
        "\u30b9\u30df\u30b9"
    ],
    "name:kor_x_preferred":[
        "\uc2a4\ubbf8\uc2a4"
    ],
    "name:lit_x_preferred":[
        "Smith"
    ],
    "name:nds_x_preferred":[
        "Smith"
    ],
    "name:nld_x_preferred":[
        "Smith"
    ],
    "name:nor_x_preferred":[
        "Smith"
    ],
    "name:pol_x_preferred":[
        "Smith"
    ],
    "name:por_x_preferred":[
        "Smith"
    ],
    "name:ron_x_preferred":[
        "Smith"
    ],
    "name:rus_x_preferred":[
        "Smith"
    ],
    "name:spa_x_preferred":[
        "Smith"
    ],
    "name:srp_x_preferred":[
        "\u0421\u043c\u0438\u0442"
    ],
    "name:swa_x_preferred":[
        "Smith"
    ],
    "name:swe_x_preferred":[
        "Smith"
    ],
    "name:tur_x_preferred":[
        "Smith"
    ],
    "name:ukr_x_preferred":[
        "\u0421\u043c\u0456\u0442"
    ],
    "name:vie_x_preferred":[
        "Smith"
    ],
    "name:zho_x_preferred":[
        "\u53f2\u5bc6\u65af"
    ],
    "wof:name":"Smith",
    "wof:placetype":"locality"
},
  "geometry": {"coordinates":[-61.59299,-35.49365],"type":"Point"}
}