{
  "type": "Feature",
  "properties": {
    "gn:admin1_code":"1.0",
    "gn:admin2_code":"6791.0",
    "gn:asciiname":"Azucena",
    "gn:country_code":"AR",
    "gn:dem":234,
    "gn:feature_class":"P",
    "gn:feature_code":"PPL",
    "gn:name":"Azucena",
    "gn:population":0,
    "gn:timezone":"America/Argentina/Buenos_Aires",
    "iso:country":"AR",
    "name:arg_x_preferred":[
        "Azuzena"
    ],
    "name:ceb_x_preferred":[
        "A\u00e7ucena"
    ],
    "name:por_x_preferred":[
        "A\u00e7ucena"
    ],
    "name:spa_x_preferred":[
        "Azucena"
    ],
    "name:swe_x_preferred":[
        "A\u00e7ucena"
    ],
    "wof:name":"Azucena",
    "wof:placetype":"locality"
},
  "geometry": {"coordinates":[-59.29221999999999,-37.48665],"type":"Point"}
}