{
  "type": "Feature",
  "properties": {
    "gn:admin1_code":"17",
    "gn:admin2_code":"66126.0",
    "gn:asciiname":"Chaguaral",
    "gn:country_code":"AR",
    "gn:dem":388,
    "gn:feature_class":"P",
    "gn:feature_code":"PPL",
    "gn:name":"Chaguaral",
    "gn:population":0,
    "gn:timezone":"America/Argentina/Salta",
    "iso:country":"AR",
    "wof:name":"Chaguaral",
    "wof:placetype":"locality"
},
  "geometry": {"coordinates":[-64.00112,-24.06537],"type":"Point"}
}