{
  "type": "Feature",
  "properties": {
    "gn:admin1_code":"01",
    "gn:admin2_code":"6126.0",
    "gn:asciiname":"Irupe",
    "gn:country_code":"AR",
    "gn:dem":6,
    "gn:feature_class":"P",
    "gn:feature_code":"PPL",
    "gn:name":"Irup\u00e9",
    "gn:population":0,
    "gn:timezone":"America/Argentina/Buenos_Aires",
    "iso:country":"AR",
    "name:spa_x_preferred":[
        "Irup\u00e9"
    ],
    "wof:name":"Irupe",
    "wof:placetype":"locality"
},
  "geometry": {"coordinates":[-59.00278,-34.15628],"type":"Point"}
}