{
  "type": "Feature",
  "properties": {
    "gn:admin1_code":"19.0",
    "gn:admin2_code":"74042.0",
    "gn:asciiname":"Ranquelco",
    "gn:country_code":"AR",
    "gn:dem":334,
    "gn:feature_class":"P",
    "gn:feature_code":"PPL",
    "gn:name":"Ranquelc\u00f3",
    "gn:population":0,
    "gn:timezone":"America/Argentina/San_Luis",
    "iso:country":"AR",
    "wof:name":"Ranquelco",
    "wof:placetype":"locality"
},
  "geometry": {"coordinates":[-65.43333,-35.26667],"type":"Point"}
}