{
  "type": "Feature",
  "properties": {
    "gn:admin1_code":"10.0",
    "gn:admin2_code":"38021.0",
    "gn:asciiname":"Termas de Reyes",
    "gn:country_code":"AR",
    "gn:dem":1962,
    "gn:feature_class":"P",
    "gn:feature_code":"PPL",
    "gn:name":"Termas de Reyes",
    "gn:population":0,
    "gn:timezone":"America/Argentina/Jujuy",
    "iso:country":"AR",
    "wof:name":"Termas de Reyes",
    "wof:placetype":"locality"
},
  "geometry": {"coordinates":[-65.48413000000001,-24.17668],"type":"Point"}
}