{
  "type": "Feature",
  "properties": {
    "gn:admin1_code":"5.0",
    "gn:admin2_code":"14021.0",
    "gn:asciiname":"El Manzano",
    "gn:country_code":"AR",
    "gn:dem":787,
    "gn:feature_class":"P",
    "gn:feature_code":"PPL",
    "gn:name":"El Manzano",
    "gn:population":0,
    "gn:timezone":"America/Argentina/Cordoba",
    "iso:country":"AR",
    "wof:name":"El Manzano",
    "wof:placetype":"locality"
},
  "geometry": {"coordinates":[-64.29831999999999,-31.07779],"type":"Point"}
}