{
  "type": "Feature",
  "properties": {
    "gn:admin1_code":"24.0",
    "gn:admin2_code":"90014.0",
    "gn:asciiname":"Ingenio San Miguel",
    "gn:country_code":"AR",
    "gn:dem":405,
    "gn:feature_class":"P",
    "gn:feature_code":"PPL",
    "gn:name":"Ingenio San Miguel",
    "gn:population":0,
    "gn:timezone":"America/Argentina/Tucuman",
    "iso:country":"AR",
    "wof:name":"Ingenio San Miguel",
    "wof:placetype":"locality"
},
  "geometry": {"coordinates":[-65.11667,-26.91667],"type":"Point"}
}