{
  "type": "Feature",
  "properties": {
    "gn:admin1_code":"22",
    "gn:admin2_code":"86098.0",
    "gn:asciiname":"Colonia Josefina",
    "gn:country_code":"AR",
    "gn:dem":123,
    "gn:feature_class":"P",
    "gn:feature_code":"PPL",
    "gn:name":"Colonia Josefina",
    "gn:population":0,
    "gn:timezone":"America/Argentina/Cordoba",
    "iso:country":"AR",
    "wof:name":"Colonia Josefina",
    "wof:placetype":"locality"
},
  "geometry": {"coordinates":[-62.26667,-27.96667],"type":"Point"}
}