{
  "type": "Feature",
  "properties": {
    "gn:admin1_code":"21.0",
    "gn:admin2_code":"82049.0",
    "gn:asciiname":"La Reserva",
    "gn:country_code":"AR",
    "gn:dem":53,
    "gn:feature_class":"P",
    "gn:feature_code":"PPL",
    "gn:name":"La Reserva",
    "gn:population":0,
    "gn:timezone":"America/Argentina/Cordoba",
    "iso:country":"AR",
    "wof:name":"La Reserva",
    "wof:placetype":"locality"
},
  "geometry": {"coordinates":[-59.51667,-28.48333],"type":"Point"}
}