{
  "type": "Feature",
  "properties": {
    "iso:country":"AR",
    "name:ceb_x_preferred":[
        "Villa de Soto Airport"
    ],
    "name:dut_x_preferred":[
        "Villa de Soto"
    ],
    "name:eng_x_preferred":[
        "Villa de Soto"
    ],
    "name:por_x_preferred":[
        "Villa de Soto"
    ],
    "name:spa_x_preferred":[
        "Villa de Soto"
    ],
    "name:swe_x_preferred":[
        "Villa de Soto Airport"
    ],
    "name:ukr_x_preferred":[
        "\u0412\u0456\u043b\u044c\u044f-\u0434\u0435-\u0421\u043e\u0442\u043e"
    ],
    "name:unk_x_variant":[
        "Soto"
    ],
    "qs:gn_country":"AR",
    "qs:gn_fcode":"PPL",
    "qs:gn_pop":7303,
    "qs:name":"Villa de Soto",
    "qs:name_adm0":"Argentina",
    "qs:name_adm1":"C\u00f3rdoba",
    "qs:photos":0,
    "qs:photos_1k":0,
    "qs:photos_9k":0,
    "qs:photos_9r":0,
    "qs:photos_all":0,
    "qs:photos_sr":0,
    "qs:placetype":"Town",
    "qs:pop_sr":"7",
    "qs:woe_adm0":23424747,
    "wd:wordcount":69,
    "wof:name":"Villa de Soto",
    "wof:placetype":"locality",
    "wof:population":7303
},
  "geometry": {"coordinates":[-64.99947,-30.85523],"type":"Point"}
}