{
  "type": "Feature",
  "properties": {
    "gn:admin1_code":"15",
    "gn:admin2_code":"58042.0",
    "gn:asciiname":"Cancha Huinganco",
    "gn:country_code":"AR",
    "gn:dem":1236,
    "gn:feature_class":"P",
    "gn:feature_code":"PPL",
    "gn:name":"Cancha Huinganco",
    "gn:population":0,
    "gn:timezone":"America/Argentina/Salta",
    "iso:country":"AR",
    "wof:name":"Cancha Huinganco",
    "wof:placetype":"locality"
},
  "geometry": {"coordinates":[-70.42166999999998,-37.02914000000001],"type":"Point"}
}