{
  "type": "Feature",
  "properties": {
    "gn:admin1_code":"1.0",
    "gn:admin2_code":"6707.0",
    "gn:asciiname":"Alvarez de Toledo",
    "gn:country_code":"AR",
    "gn:dem":41,
    "gn:feature_class":"P",
    "gn:feature_code":"PPL",
    "gn:name":"\u00c1lvarez de Toledo",
    "gn:population":0,
    "gn:timezone":"America/Argentina/Buenos_Aires",
    "iso:country":"AR",
    "name:und_x_variant":[
        "A. de Toledo",
        "Desv\u00edo Toledo",
        "\u00c1lvarez de Toledo"
    ],
    "wof:name":"Alvarez de Toledo",
    "wof:placetype":"locality"
},
  "geometry": {"coordinates":[-59.62951,-35.63775],"type":"Point"}
}