{
  "type": "Feature",
  "properties": {
    "gn:admin1_code":"17",
    "gn:admin2_code":"66084.0",
    "gn:asciiname":"El Brete",
    "gn:country_code":"AR",
    "gn:dem":857,
    "gn:feature_class":"P",
    "gn:feature_code":"PPL",
    "gn:name":"El Brete",
    "gn:population":0,
    "gn:timezone":"America/Argentina/Salta",
    "iso:country":"AR",
    "name:und_x_variant":[
        "Brete",
        "El Brete"
    ],
    "wof:name":"El Brete",
    "wof:placetype":"locality"
},
  "geometry": {"coordinates":[-65.33731,-26.06245],"type":"Point"}
}