{
  "type": "Feature",
  "properties": {
    "gn:admin1_code":"13.0",
    "gn:admin2_code":"50070.0",
    "gn:asciiname":"Villa Edelmira",
    "gn:country_code":"AR",
    "gn:dem":825,
    "gn:feature_class":"P",
    "gn:feature_code":"PPL",
    "gn:name":"Villa Edelmira",
    "gn:population":0,
    "gn:timezone":"America/Argentina/Mendoza",
    "iso:country":"AR",
    "wof:name":"Villa Edelmira",
    "wof:placetype":"locality"
},
  "geometry": {"coordinates":[-68.8184,-32.95495],"type":"Point"}
}