{
  "type": "Feature",
  "properties": {
    "gn:admin1_code":"21",
    "gn:admin2_code":"82042.0",
    "gn:asciiname":"Carreras",
    "gn:country_code":"AR",
    "gn:dem":103,
    "gn:feature_class":"P",
    "gn:feature_code":"PPL",
    "gn:name":"Carreras",
    "gn:population":0,
    "gn:timezone":"America/Argentina/Cordoba",
    "iso:country":"AR",
    "wof:name":"Carreras",
    "wof:placetype":"locality"
},
  "geometry": {"coordinates":[-61.30982,-33.59704],"type":"Point"}
}