{
  "type": "Feature",
  "properties": {
    "gn:admin1_code":"01",
    "gn:admin2_code":"6609.0",
    "gn:asciiname":"Asturias",
    "gn:country_code":"AR",
    "gn:dem":94,
    "gn:feature_class":"P",
    "gn:feature_code":"PPL",
    "gn:name":"Asturias",
    "gn:population":0,
    "gn:timezone":"America/Argentina/Buenos_Aires",
    "iso:country":"AR",
    "wof:name":"Asturias",
    "wof:placetype":"locality"
},
  "geometry": {"coordinates":[-61.88333000000001,-36.16667],"type":"Point"}
}