{
  "type": "Feature",
  "properties": {
    "gn:admin1_code":"14.0",
    "gn:admin2_code":"54098.0",
    "gn:asciiname":"Puerto Naranjito",
    "gn:country_code":"AR",
    "gn:dem":97,
    "gn:feature_class":"P",
    "gn:feature_code":"PPL",
    "gn:name":"Puerto Naranjito",
    "gn:population":0,
    "gn:timezone":"America/Argentina/Cordoba",
    "iso:country":"AR",
    "wof:name":"Puerto Naranjito",
    "wof:placetype":"locality"
},
  "geometry": {"coordinates":[-55.2913,-26.95982],"type":"Point"}
}