{
  "type": "Feature",
  "properties": {
    "gn:admin1_code":"22.0",
    "gn:admin2_code":"86161.0",
    "gn:asciiname":"Taco Pujio",
    "gn:country_code":"AR",
    "gn:dem":171,
    "gn:feature_class":"P",
    "gn:feature_code":"PPL",
    "gn:name":"Taco Pujio",
    "gn:population":0,
    "gn:timezone":"America/Argentina/Cordoba",
    "iso:country":"AR",
    "wof:name":"Taco Pujio",
    "wof:placetype":"locality"
},
  "geometry": {"coordinates":[-64.06667,-27.85],"type":"Point"}
}