{
  "type": "Feature",
  "properties": {
    "gn:country":"AR",
    "gn:fcode":"PPL",
    "gn:pop":3317,
    "iso:country":"AR",
    "name:deu_x_preferred":[
        "Colonia Bar\u00f3n"
    ],
    "name:eng_x_preferred":[
        "Colonia Bar\u00f3n"
    ],
    "name:fra_x_preferred":[
        "Colonia Bar\u00f3n"
    ],
    "name:nld_x_preferred":[
        "Colonia Bar\u00f3n"
    ],
    "name:por_x_preferred":[
        "Colonia Bar\u00f3n"
    ],
    "name:spa_x_preferred":[
        "Colonia Bar\u00f3n"
    ],
    "name:swe_x_preferred":[
        "Colonia Bar\u00f3n"
    ],
    "name:ukr_x_preferred":[
        "\u041a\u043e\u043b\u043e\u043d\u0456\u044f-\u0411\u0430\u0440\u043e\u043d"
    ],
    "qs:name":"Colonia Bar\u00f3n",
    "qs:photos_9r":0,
    "qs:photos_sr":0,
    "qs:pop_sr":"6",
    "wd:wordcount":32,
    "wof:name":"Colonia Bar\u00f3n",
    "wof:placetype":"locality",
    "wof:population":3317
},
  "geometry": {"coordinates":[-63.85404,-36.15152],"type":"Point"}
}