{
  "type": "Feature",
  "properties": {
    "gn:admin1_code":"1.0",
    "gn:admin2_code":"6455.0",
    "gn:asciiname":"Doctor Domingo Harosteguy",
    "gn:country_code":"AR",
    "gn:dem":50,
    "gn:feature_class":"P",
    "gn:feature_code":"PPL",
    "gn:name":"Doctor Domingo Harosteguy",
    "gn:population":0,
    "gn:timezone":"America/Argentina/Buenos_Aires",
    "iso:country":"AR",
    "name:und_x_variant":[
        "Naranja",
        "D. Harosteguy",
        "Doctor Domingo Harosteguy"
    ],
    "wof:name":"Doctor Domingo Harosteguy",
    "wof:placetype":"locality"
},
  "geometry": {"coordinates":[-59.26832,-36.14902],"type":"Point"}
}