{
  "type": "Feature",
  "properties": {
    "gn:admin1_code":"12",
    "gn:admin2_code":"46091.0",
    "gn:asciiname":"Bajo Hondo",
    "gn:country_code":"AR",
    "gn:dem":289,
    "gn:feature_class":"P",
    "gn:feature_code":"PPL",
    "gn:name":"Bajo Hondo",
    "gn:population":0,
    "gn:timezone":"America/Argentina/La_Rioja",
    "iso:country":"AR",
    "wof:name":"Bajo Hondo",
    "wof:placetype":"locality"
},
  "geometry": {"coordinates":[-66.01042,-31.68339000000001],"type":"Point"}
}