{
  "type": "Feature",
  "properties": {
    "gn:admin1_code":"24",
    "gn:admin2_code":"90112.0",
    "gn:asciiname":"Benjamin Paz",
    "gn:country_code":"AR",
    "gn:dem":767,
    "gn:feature_class":"P",
    "gn:feature_code":"PPL",
    "gn:name":"Benjam\u00edn Paz",
    "gn:population":0,
    "gn:timezone":"America/Argentina/Tucuman",
    "iso:country":"AR",
    "wof:name":"Benjamin Paz",
    "wof:placetype":"locality"
},
  "geometry": {"coordinates":[-65.29297,-26.37082],"type":"Point"}
}