{
  "type": "Feature",
  "properties": {
    "gn:admin1_code":"12.0",
    "gn:admin2_code":"46105.0",
    "gn:asciiname":"Vilgo",
    "gn:country_code":"AR",
    "gn:dem":1479,
    "gn:feature_class":"P",
    "gn:feature_code":"PPL",
    "gn:name":"Vilgo",
    "gn:population":0,
    "gn:timezone":"America/Argentina/La_Rioja",
    "iso:country":"AR",
    "wof:name":"Vilgo",
    "wof:placetype":"locality"
},
  "geometry": {"coordinates":[-67.36667,-29.95],"type":"Point"}
}