{
  "type": "Feature",
  "properties": {
    "gn:admin1_code":"1.0",
    "gn:admin2_code":"6168.0",
    "gn:asciiname":"Guerrero",
    "gn:country_code":"AR",
    "gn:dem":13,
    "gn:feature_class":"P",
    "gn:feature_code":"PPL",
    "gn:name":"Guerrero",
    "gn:population":0,
    "gn:timezone":"America/Argentina/Buenos_Aires",
    "iso:country":"AR",
    "wof:name":"Guerrero",
    "wof:placetype":"locality"
},
  "geometry": {"coordinates":[-57.84798000000001,-35.96991],"type":"Point"}
}