{
  "type": "Feature",
  "properties": {
    "gn:admin1_code":"21",
    "gn:admin2_code":"82091.0",
    "gn:asciiname":"Colonia Portugalete",
    "gn:cc2":"AR",
    "gn:country_code":"AR",
    "gn:dem":81,
    "gn:feature_class":"P",
    "gn:feature_code":"PPL",
    "gn:name":"Colonia Portugalete",
    "gn:population":0,
    "gn:timezone":"America/Argentina/Cordoba",
    "iso:country":"AR",
    "name:und_x_variant":[
        "Portugalete",
        "Colonia Portugalete"
    ],
    "wof:name":"Colonia Portugalete",
    "wof:placetype":"locality"
},
  "geometry": {"coordinates":[-61.36666999999999,-30.26667],"type":"Point"}
}