{
  "type": "Feature",
  "properties": {
    "gn:admin1_code":"19",
    "gn:admin2_code":"74056.0",
    "gn:asciiname":"El Chorrillo",
    "gn:country_code":"AR",
    "gn:dem":826,
    "gn:feature_class":"P",
    "gn:feature_code":"PPL",
    "gn:name":"El Chorrillo",
    "gn:population":0,
    "gn:timezone":"America/Argentina/San_Luis",
    "iso:country":"AR",
    "name:ita_x_preferred":[
        "El Chorrillo"
    ],
    "name:spa_x_preferred":[
        "El Chorrillo"
    ],
    "name:und_x_variant":[
        "Chorrillo",
        "Chorrillos"
    ],
    "name:zho_x_preferred":[
        "\u57c3\u723e\u55ac\u91cc\u7565"
    ],
    "wof:name":"El Chorrillo",
    "wof:placetype":"locality"
},
  "geometry": {"coordinates":[-66.25334000000001,-33.28642],"type":"Point"}
}