{
  "type": "Feature",
  "properties": {
    "gn:admin1_code":"5.0",
    "gn:admin2_code":"14049.0",
    "gn:asciiname":"Jaime Peter",
    "gn:country_code":"AR",
    "gn:dem":556,
    "gn:feature_class":"P",
    "gn:feature_code":"PPL",
    "gn:name":"Jaime Peter",
    "gn:population":0,
    "gn:timezone":"America/Argentina/Cordoba",
    "iso:country":"AR",
    "name:und_x_variant":[
        "Jaime Perez",
        "Jaime Peter"
    ],
    "wof:name":"Jaime Peter",
    "wof:placetype":"locality"
},
  "geometry": {"coordinates":[-64.54161999999999,-30.41253],"type":"Point"}
}