{
  "type": "Feature",
  "properties": {
    "gn:admin1_code":"01",
    "gn:admin2_code":"6616.0",
    "gn:asciiname":"De Bary",
    "gn:country_code":"AR",
    "gn:dem":117,
    "gn:feature_class":"P",
    "gn:feature_code":"PPL",
    "gn:name":"De Bary",
    "gn:population":0,
    "gn:timezone":"America/Argentina/Buenos_Aires",
    "iso:country":"AR",
    "wof:name":"De Bary",
    "wof:placetype":"locality"
},
  "geometry": {"coordinates":[-63.2606,-36.3406],"type":"Point"}
}