{
  "type": "Feature",
  "properties": {
    "gn:gn_country":"AR",
    "gn:gn_fcode":"PPL",
    "gn:gn_pop":9151,
    "gn:population":9151,
    "iso:country":"AR",
    "name:deu_x_preferred":[
        "Las Lajitas"
    ],
    "name:eng_x_preferred":[
        "Las Lajitas"
    ],
    "name:fra_x_preferred":[
        "Las Lajitas"
    ],
    "name:nld_x_preferred":[
        "Las Lajitas"
    ],
    "name:por_x_preferred":[
        "Las Lajitas"
    ],
    "name:spa_x_preferred":[
        "Las Lajitas"
    ],
    "name:swe_x_preferred":[
        "Las Lajitas"
    ],
    "name:ukr_x_preferred":[
        "\u041b\u0430\u0441-\u041b\u0430\u0445\u0456\u0442\u0430\u0441"
    ],
    "name:urd_x_preferred":[
        "\u0644\u0627\u0633 \u0644\u0627\u062c\u06cc\u0679\u0627\u0633"
    ],
    "qs_pg:aaroncc":"AR",
    "qs_pg:gn_country":"AR",
    "qs_pg:gn_fcode":"PPL",
    "qs_pg:gn_pop":9151,
    "qs_pg:name":"Las Lajitas",
    "qs_pg:photos_9r":0,
    "qs_pg:photos_sr":0,
    "qs_pg:pop_sr":5,
    "qs_pg:qs_pg_placetype":"locality",
    "wof:name":"Las Lajitas",
    "wof:placetype":"locality",
    "wof:population":9151
},
  "geometry": {"coordinates":[-64.25,-24.68333],"type":"Point"}
}