{
  "type": "Feature",
  "properties": {
    "gn:admin1_code":"10",
    "gn:admin2_code":"38035.0",
    "gn:asciiname":"Chalican",
    "gn:country_code":"AR",
    "gn:dem":429,
    "gn:feature_class":"P",
    "gn:feature_code":"PPL",
    "gn:name":"Chalic\u00e1n",
    "gn:population":0,
    "gn:timezone":"America/Argentina/Jujuy",
    "iso:country":"AR",
    "name:ceb_x_preferred":[
        "Chalic\u00e1n"
    ],
    "name:spa_x_preferred":[
        "Chalic\u00e1n"
    ],
    "name:swe_x_preferred":[
        "Chalic\u00e1n"
    ],
    "name:und_x_variant":[
        "Chalic\u00e1n"
    ],
    "wof:name":"Chalican",
    "wof:placetype":"locality"
},
  "geometry": {"coordinates":[-64.80530999999999,-24.06842],"type":"Point"}
}