{
  "type": "Feature",
  "properties": {
    "gn:admin1_code":"5.0",
    "gn:admin2_code":"14098.0",
    "gn:asciiname":"Las Canitas",
    "gn:country_code":"AR",
    "gn:dem":679,
    "gn:feature_class":"P",
    "gn:feature_code":"PPL",
    "gn:name":"Las Ca\u00f1itas",
    "gn:population":0,
    "gn:timezone":"America/Argentina/Cordoba",
    "iso:country":"AR",
    "wof:name":"Las Canitas",
    "wof:placetype":"locality"
},
  "geometry": {"coordinates":[-64.75,-32.86667],"type":"Point"}
}