{
  "type": "Feature",
  "properties": {
    "gn:admin1_code":"1.0",
    "gn:admin2_code":"6385.0",
    "gn:asciiname":"Quirno Costa",
    "gn:country_code":"AR",
    "gn:dem":80,
    "gn:feature_class":"P",
    "gn:feature_code":"PPL",
    "gn:name":"Quirno Costa",
    "gn:population":0,
    "gn:timezone":"America/Argentina/Buenos_Aires",
    "iso:country":"AR",
    "wof:name":"Quirno Costa",
    "wof:placetype":"locality"
},
  "geometry": {"coordinates":[-61.13887,-34.87566],"type":"Point"}
}