{
  "type": "Feature",
  "properties": {
    "gn:admin1_code":"5.0",
    "gn:admin2_code":"14119.0",
    "gn:asciiname":"Lagunilla",
    "gn:country_code":"AR",
    "gn:dem":352,
    "gn:feature_class":"P",
    "gn:feature_code":"PPL",
    "gn:name":"Lagunilla",
    "gn:population":0,
    "gn:timezone":"America/Argentina/Cordoba",
    "iso:country":"AR",
    "wof:name":"Lagunilla",
    "wof:placetype":"locality"
},
  "geometry": {"coordinates":[-63.9498,-31.72498],"type":"Point"}
}