{
  "type": "Feature",
  "properties": {
    "iso:country":"AR",
    "name:ceb_x_preferred":[
        "Turdera"
    ],
    "name:deu_x_preferred":[
        "Turdera"
    ],
    "name:eng_x_preferred":[
        "Turdera"
    ],
    "name:fas_x_preferred":[
        "\u062a\u0648\u0631\u062f\u0631\u0627"
    ],
    "name:ita_x_preferred":[
        "Turdera"
    ],
    "name:nld_x_preferred":[
        "Turdera"
    ],
    "name:sco_x_preferred":[
        "Turdera"
    ],
    "name:spa_x_preferred":[
        "Turdera"
    ],
    "name:spa_x_variant":[
        "Villa Turdera"
    ],
    "name:urd_x_preferred":[
        "\u062a\u0648\u0631\u062f\u0631\u0627"
    ],
    "qs:gn_country":"AR",
    "qs:gn_fcode":"PPL",
    "qs:gn_pop":0,
    "qs:name":"Turdera",
    "qs:name_adm0":"Argentina",
    "qs:name_adm1":"Buenos Aires",
    "qs:photos":311,
    "qs:photos_1k":63,
    "qs:photos_9k":1,
    "qs:photos_9r":5,
    "qs:photos_all":311,
    "qs:photos_sr":5,
    "qs:placetype":"Town",
    "qs:pop_sr":"0",
    "qs:woe_adm0":23424747,
    "wd:wordcount":63,
    "wof:name":"Turdera",
    "wof:placetype":"locality"
},
  "geometry": {"coordinates":[-58.40277,-34.79045],"type":"Point"}
}