{
  "type": "Feature",
  "properties": {
    "gn:admin1_code":"17.0",
    "gn:admin2_code":"66126.0",
    "gn:asciiname":"Quenoal",
    "gn:country_code":"AR",
    "gn:dem":2099,
    "gn:feature_class":"P",
    "gn:feature_code":"PPL",
    "gn:name":"Que\u00f1oal",
    "gn:population":0,
    "gn:timezone":"America/Argentina/Salta",
    "iso:country":"AR",
    "wof:name":"Quenoal",
    "wof:placetype":"locality"
},
  "geometry": {"coordinates":[-64.88621999999999,-23.12275],"type":"Point"}
}