{
  "type": "Feature",
  "properties": {
    "gn:admin1_code":"21.0",
    "gn:admin2_code":"82070.0",
    "gn:asciiname":"Ombu",
    "gn:country_code":"AR",
    "gn:dem":55,
    "gn:feature_class":"P",
    "gn:feature_code":"PPL",
    "gn:name":"Omb\u00fa",
    "gn:population":0,
    "gn:timezone":"America/Argentina/Cordoba",
    "iso:country":"AR",
    "wof:name":"Ombu",
    "wof:placetype":"locality"
},
  "geometry": {"coordinates":[-60.91087,-31.01163],"type":"Point"}
}