{
  "type": "Feature",
  "properties": {
    "gn:admin1_code":"17.0",
    "gn:admin2_code":"66133.0",
    "gn:asciiname":"Santa Rosa",
    "gn:country_code":"AR",
    "gn:dem":204,
    "gn:feature_class":"P",
    "gn:feature_code":"PPL",
    "gn:name":"Santa Rosa",
    "gn:population":0,
    "gn:timezone":"America/Argentina/Salta",
    "iso:country":"AR",
    "name:ara_x_preferred":[
        "\u0633\u0627\u0646\u062a \u0631\u0648\u0632\u0627"
    ],
    "name:ben_x_preferred":[
        "\u09b8\u09be\u09a8\u09cd\u09a4\u09be \u09b0\u09cb\u09b8\u09be"
    ],
    "name:ell_x_preferred":[
        "\u03a3\u03ac\u03bd\u03c4\u03b1 \u03a1\u03cc\u03c3\u03b1"
    ],
    "name:fas_x_preferred":[
        "\u0633\u0627\u0646\u062a\u0627 \u0631\u0632\u0627"
    ],
    "name:heb_x_preferred":[
        "\u05e1\u05e0\u05d8\u05d4 \u05e8\u05d5\u05d6\u05d4"
    ],
    "name:hin_x_preferred":[
        "\u0938\u0948\u0902\u091f\u093e \u0930\u094b\u091c\u093c\u093e"
    ],
    "name:ind_x_preferred":[
        "Santa Rosa"
    ],
    "name:tur_x_preferred":[
        "Santa Rosa"
    ],
    "name:urd_x_preferred":[
        "\u0633\u06cc\u0646\u0679\u0627 \u0631\u0648\u0633\u0627"
    ],
    "wof:name":"Santa Rosa",
    "wof:placetype":"locality"
},
  "geometry": {"coordinates":[-62.69498,-24.244],"type":"Point"}
}