{
  "type": "Feature",
  "properties": {
    "gn:admin1_code":"5.0",
    "gn:admin2_code":"14091.0",
    "gn:asciiname":"Las Ensenadas",
    "gn:country_code":"AR",
    "gn:dem":2153,
    "gn:feature_class":"P",
    "gn:feature_code":"PPL",
    "gn:name":"Las Ensenadas",
    "gn:population":0,
    "gn:timezone":"America/Argentina/Cordoba",
    "iso:country":"AR",
    "name:und_x_variant":[
        "Ensenadas",
        "Las Ensenadas"
    ],
    "wof:name":"Las Ensenadas",
    "wof:placetype":"locality"
},
  "geometry": {"coordinates":[-64.76156,-31.60256],"type":"Point"}
}