{
  "type": "Feature",
  "properties": {
    "gn:admin1_code":"8.0",
    "gn:admin2_code":"30063.0",
    "gn:asciiname":"Ibicuy",
    "gn:country_code":"AR",
    "gn:dem":6,
    "gn:feature_class":"P",
    "gn:feature_code":"PPL",
    "gn:name":"Ibicuy",
    "gn:population":0,
    "gn:timezone":"America/Argentina/Cordoba",
    "iso:country":"AR",
    "wof:name":"Ibicuy",
    "wof:placetype":"locality"
},
  "geometry": {"coordinates":[-59.15471,-33.74411],"type":"Point"}
}