{
  "type": "Feature",
  "properties": {
    "gn:admin1_code":"21.0",
    "gn:admin2_code":"82021.0",
    "gn:asciiname":"Pueblo Terragni",
    "gn:country_code":"AR",
    "gn:dem":106,
    "gn:feature_class":"P",
    "gn:feature_code":"PPL",
    "gn:name":"Pueblo Terragni",
    "gn:population":0,
    "gn:timezone":"America/Argentina/Cordoba",
    "iso:country":"AR",
    "wof:name":"Pueblo Terragni",
    "wof:placetype":"locality"
},
  "geometry": {"coordinates":[-61.73309,-31.15511],"type":"Point"}
}