{
  "type": "Feature",
  "properties": {
    "gn:admin1_code":"5.0",
    "gn:admin2_code":"14021.0",
    "gn:asciiname":"Tejeda",
    "gn:country_code":"AR",
    "gn:dem":362,
    "gn:feature_class":"P",
    "gn:feature_code":"PPL",
    "gn:name":"Tejeda",
    "gn:population":0,
    "gn:timezone":"America/Argentina/Cordoba",
    "iso:country":"AR",
    "wof:name":"Tejeda",
    "wof:placetype":"locality"
},
  "geometry": {"coordinates":[-63.98354000000001,-31.38801],"type":"Point"}
}