{
  "type": "Feature",
  "properties": {
    "gn:admin1_code":"5.0",
    "gn:admin2_code":"14021.0",
    "gn:asciiname":"Tejeda",
    "gn:country_code":"AR",
    "gn:dem":362,
    "gn:feature_class":"P",
    "gn:feature_code":"PPL",
    "gn:name":"Tejeda",
    "gn:population":0,
    "gn:timezone":"America/Argentina/Cordoba",
    "iso:country":"AR",
    "name:ara_x_preferred":[
        "\u062a\u064a\u062e\u064a\u062f\u0627"
    ],
    "name:azb_x_preferred":[
        "\u062a\u0647\u062f\u0627"
    ],
    "name:cat_x_preferred":[
        "Tejeda"
    ],
    "name:ceb_x_preferred":[
        "Tejeda"
    ],
    "name:deu_x_preferred":[
        "Tejeda"
    ],
    "name:eus_x_preferred":[
        "Tejeda"
    ],
    "name:fas_x_preferred":[
        "\u062a\u0647\u062f\u0627"
    ],
    "name:fra_x_preferred":[
        "Tejeda"
    ],
    "name:glg_x_preferred":[
        "Tejeda"
    ],
    "name:hun_x_preferred":[
        "Tejeda"
    ],
    "name:ita_x_preferred":[
        "Tejeda"
    ],
    "name:lat_x_preferred":[
        "Tejeda"
    ],
    "name:msa_x_preferred":[
        "Tejeda"
    ],
    "name:nld_x_preferred":[
        "Tejeda"
    ],
    "name:oci_x_preferred":[
        "Tejeda"
    ],
    "name:pol_x_preferred":[
        "Tejeda"
    ],
    "name:por_x_preferred":[
        "Tejeda"
    ],
    "name:rus_x_preferred":[
        "\u0422\u0435\u0445\u0435\u0434\u0430"
    ],
    "name:spa_x_preferred":[
        "Tejeda"
    ],
    "name:srd_x_preferred":[
        "Tejeda"
    ],
    "name:swe_x_preferred":[
        "Tejeda"
    ],
    "name:ukr_x_preferred":[
        "\u0422\u0435\u0445\u0435\u0434\u0430"
    ],
    "name:uzb_x_preferred":[
        "Tejeda"
    ],
    "name:war_x_preferred":[
        "Tejeda"
    ],
    "name:zho_x_preferred":[
        "\u7279\u8d6b\u8fbe"
    ],
    "wof:name":"Tejeda",
    "wof:placetype":"locality"
},
  "geometry": {"coordinates":[-63.98354000000001,-31.38801],"type":"Point"}
}