{
  "type": "Feature",
  "properties": {
    "gn:admin1_code":"02",
    "gn:admin2_code":"10021.0",
    "gn:asciiname":"Choya",
    "gn:country_code":"AR",
    "gn:dem":1295,
    "gn:feature_class":"P",
    "gn:feature_code":"PPL",
    "gn:name":"Choya",
    "gn:population":0,
    "gn:timezone":"America/Argentina/Catamarca",
    "iso:country":"AR",
    "wof:name":"Choya",
    "wof:placetype":"locality"
},
  "geometry": {"coordinates":[-66.38155999999999,-27.51872],"type":"Point"}
}