{
  "type": "Feature",
  "properties": {
    "gn:admin1_code":"2.0",
    "gn:admin2_code":"10042.0",
    "gn:asciiname":"San Pablo",
    "gn:country_code":"AR",
    "gn:dem":675,
    "gn:feature_class":"P",
    "gn:feature_code":"PPL",
    "gn:name":"San Pablo",
    "gn:population":0,
    "gn:timezone":"America/Argentina/Catamarca",
    "iso:country":"AR",
    "name:fas_x_preferred":[
        "\u0633\u0646 \u067e\u0627\u0628\u0644\u0648"
    ],
    "name:heb_x_preferred":[
        "\u05e1\u05df \u05e4\u05d1\u05dc\u05d5"
    ],
    "name:spa_x_preferred":[
        "San Pablo"
    ],
    "wof:name":"San Pablo",
    "wof:placetype":"locality"
},
  "geometry": {"coordinates":[-66.03564,-28.70064],"type":"Point"}
}