{
  "type": "Feature",
  "properties": {
    "gn:admin1_code":"2.0",
    "gn:admin2_code":"10084.0",
    "gn:asciiname":"Mischango",
    "gn:country_code":"AR",
    "gn:dem":1547,
    "gn:feature_class":"P",
    "gn:feature_code":"PPL",
    "gn:name":"Mischango",
    "gn:population":0,
    "gn:timezone":"America/Argentina/Catamarca",
    "iso:country":"AR",
    "wof:name":"Mischango",
    "wof:placetype":"locality"
},
  "geometry": {"coordinates":[-66.14031999999999,-28.25933],"type":"Point"}
}