{
  "type": "Feature",
  "properties": {
    "gn:admin1_code":"8.0",
    "gn:admin2_code":"30098.0",
    "gn:asciiname":"Pueblo Moscas",
    "gn:country_code":"AR",
    "gn:dem":46,
    "gn:feature_class":"P",
    "gn:feature_code":"PPL",
    "gn:name":"Pueblo Moscas",
    "gn:population":0,
    "gn:timezone":"America/Argentina/Cordoba",
    "iso:country":"AR",
    "name:por_x_preferred":[
        "Las Moscas"
    ],
    "name:spa_x_preferred":[
        "Las Moscas"
    ],
    "name:und_x_variant":[
        "Pueblo Moscas"
    ],
    "name:urd_x_preferred":[
        "\u0644\u0627\u0633 \u0645\u0648\u0633\u06a9\u0627\u0633"
    ],
    "wof:name":"Pueblo Moscas",
    "wof:placetype":"locality"
},
  "geometry": {"coordinates":[-58.95506999999999,-32.09169],"type":"Point"}
}