{
  "type": "Feature",
  "properties": {
    "gn:admin1_code":"1.0",
    "gn:admin2_code":"6049.0",
    "gn:asciiname":"Miramonte",
    "gn:country_code":"AR",
    "gn:dem":69,
    "gn:feature_class":"P",
    "gn:feature_code":"PPL",
    "gn:name":"Miramonte",
    "gn:population":0,
    "gn:timezone":"America/Argentina/Buenos_Aires",
    "iso:country":"AR",
    "name:deu_x_preferred":[
        "Miramonte"
    ],
    "wof:name":"Miramonte",
    "wof:placetype":"locality"
},
  "geometry": {"coordinates":[-59.43378000000001,-36.30483],"type":"Point"}
}