{
  "type": "Feature",
  "properties": {
    "iso:country":"AR",
    "name:cat_x_preferred":[
        "Tilcara"
    ],
    "name:ceb_x_preferred":[
        "Tilcara"
    ],
    "name:deu_x_preferred":[
        "Tilcara"
    ],
    "name:eng_x_preferred":[
        "Tilcara"
    ],
    "name:fas_x_preferred":[
        "\u062a\u06cc\u0644\u06a9\u0627\u0631\u0627"
    ],
    "name:fra_x_preferred":[
        "Tilcara"
    ],
    "name:ita_x_preferred":[
        "Tilcara"
    ],
    "name:jpn_x_preferred":[
        "\u30c6\u30a3\u30eb\u30ab\u30e9"
    ],
    "name:lit_x_preferred":[
        "Tilkara"
    ],
    "name:nld_x_preferred":[
        "Tilcara"
    ],
    "name:pol_x_preferred":[
        "Tilcara"
    ],
    "name:por_x_preferred":[
        "Tilcara"
    ],
    "name:spa_x_preferred":[
        "Tilcara"
    ],
    "name:swe_x_preferred":[
        "Tilcara"
    ],
    "name:tur_x_preferred":[
        "Tilcara"
    ],
    "name:ukr_x_preferred":[
        "\u0422\u0456\u043b\u044c\u043a\u0430\u0440\u0430"
    ],
    "name:zho_x_preferred":[
        "\u8482\u723e\u5361\u62c9"
    ],
    "qs:gn_country":"AR",
    "qs:gn_fcode":"PPL",
    "qs:gn_pop":5640,
    "qs:name":"Tilcara",
    "qs:name_adm0":"Argentina",
    "qs:name_adm1":"Jujuy",
    "qs:photos":1543,
    "qs:photos_1k":313,
    "qs:photos_9k":7,
    "qs:photos_9r":8,
    "qs:photos_all":1543,
    "qs:photos_sr":13,
    "qs:placetype":"Town",
    "qs:pop_sr":"5",
    "qs:woe_adm0":23424747,
    "wof:name":"Tilcara",
    "wof:placetype":"locality",
    "wof:population":5640
},
  "geometry": {"coordinates":[-65.3509,-23.57757],"type":"Point"}
}