{
  "type": "Feature",
  "properties": {
    "gn:admin1_code":"17",
    "gn:admin2_code":"66007.0",
    "gn:asciiname":"Ceibalito",
    "gn:cc2":"AR",
    "gn:country_code":"AR",
    "gn:dem":448,
    "gn:feature_class":"P",
    "gn:feature_code":"PPL",
    "gn:name":"Ceibalito",
    "gn:population":0,
    "gn:timezone":"America/Argentina/Salta",
    "iso:country":"AR",
    "name:ceb_x_preferred":[
        "Ceibalito"
    ],
    "name:spa_x_preferred":[
        "Ceibalito"
    ],
    "name:swe_x_preferred":[
        "Ceibalito"
    ],
    "name:und_x_variant":[
        "Sebalito",
        "Ceibalito"
    ],
    "wof:name":"Ceibalito",
    "wof:placetype":"locality"
},
  "geometry": {"coordinates":[-64.31667,-25.08333],"type":"Point"}
}