{
  "type": "Feature",
  "properties": {
    "gn:admin1_code":"12.0",
    "gn:admin2_code":"46084.0",
    "gn:asciiname":"Milagro",
    "gn:country_code":"AR",
    "gn:dem":377,
    "gn:feature_class":"P",
    "gn:feature_code":"PPLA2",
    "gn:name":"Milagro",
    "gn:population":0,
    "gn:timezone":"America/Argentina/La_Rioja",
    "iso:country":"AR",
    "name:ceb_x_preferred":[
        "Milagro"
    ],
    "name:pol_x_preferred":[
        "Milagro"
    ],
    "name:spa_x_preferred":[
        "Milagro"
    ],
    "name:und_x_variant":[
        "El Milagro"
    ],
    "wof:name":"Milagro",
    "wof:placetype":"locality"
},
  "geometry": {"coordinates":[-66.00098,-31.00326],"type":"Point"}
}