{
  "type": "Feature",
  "properties": {
    "gn:admin1_code":"5.0",
    "gn:admin2_code":"14140.0",
    "gn:asciiname":"Villa San Esteban",
    "gn:country_code":"AR",
    "gn:dem":145,
    "gn:feature_class":"P",
    "gn:feature_code":"PPL",
    "gn:name":"Villa San Esteban",
    "gn:population":0,
    "gn:timezone":"America/Argentina/Cordoba",
    "iso:country":"AR",
    "wof:name":"Villa San Esteban",
    "wof:placetype":"locality"
},
  "geometry": {"coordinates":[-62.89685,-31.63315],"type":"Point"}
}