{
  "type": "Feature",
  "properties": {
    "iso:country":"AR",
    "name:bel_x_preferred":[
        "\u041c\u043e\u0441\u0442 \u0406\u043d\u043a\u0430\u045e"
    ],
    "name:cat_x_preferred":[
        "Puente del Inca"
    ],
    "name:ceb_x_preferred":[
        "Puente del Inca"
    ],
    "name:deu_x_preferred":[
        "Puente del Inca"
    ],
    "name:dut_x_preferred":[
        "Puente del Inca"
    ],
    "name:eng_x_preferred":[
        "Puente del Inca"
    ],
    "name:fre_x_preferred":[
        "Puente del Inca"
    ],
    "name:ger_x_preferred":[
        "Puente del Inca"
    ],
    "name:oci_x_preferred":[
        "Puente del Inca"
    ],
    "name:por_x_preferred":[
        "Puente del Inca"
    ],
    "name:rus_x_preferred":[
        "\u041c\u043e\u0441\u0442 \u0418\u043d\u043a\u043e\u0432"
    ],
    "name:spa_x_preferred":[
        "Puente del Inca"
    ],
    "name:swe_x_preferred":[
        "Puente del Inca"
    ],
    "qs:gn_country":"AR",
    "qs:gn_fcode":"PPL",
    "qs:gn_pop":0,
    "qs:name":"Puente del Inca",
    "qs:name_adm0":"Argentina",
    "qs:name_adm1":"Mendoza",
    "qs:photos":480,
    "qs:photos_1k":97,
    "qs:photos_9k":2,
    "qs:photos_9r":5,
    "qs:photos_all":480,
    "qs:photos_sr":7,
    "qs:placetype":"Town",
    "qs:pop_sr":"4",
    "qs:woe_adm0":23424747,
    "wd:wordcount":389,
    "wof:name":"Puente del Inca",
    "wof:placetype":"locality"
},
  "geometry": {"coordinates":[-69.91309,-32.8239],"type":"Point"}
}