{
  "type": "Feature",
  "properties": {
    "gn:admin1_code":"19",
    "gn:asciiname":"Bajada Nueva",
    "gn:country_code":"AR",
    "gn:dem":363,
    "gn:feature_class":"P",
    "gn:feature_code":"PPL",
    "gn:name":"Bajada Nueva",
    "gn:population":0,
    "gn:timezone":"America/Argentina/Mendoza",
    "iso:country":"AR",
    "wof:name":"Bajada Nueva",
    "wof:placetype":"locality"
},
  "geometry": {"coordinates":[-66.51666999999999,-35.23333],"type":"Point"}
}