{
  "type": "Feature",
  "properties": {
    "iso:country":"AR",
    "name:ceb_x_preferred":[
        "Santo Tom\u00e9"
    ],
    "name:deu_x_preferred":[
        "Santo Tom\u00e9"
    ],
    "name:eng_x_preferred":[
        "Santo Tom\u00e9"
    ],
    "name:fra_x_preferred":[
        "Santo Tom\u00e9"
    ],
    "name:ita_x_preferred":[
        "Santo Tom\u00e9"
    ],
    "name:lit_x_preferred":[
        "Santo Tom\u0117"
    ],
    "name:nld_x_preferred":[
        "Santo Tom\u00e9"
    ],
    "name:por_x_preferred":[
        "Santo Tom\u00e9"
    ],
    "name:spa_x_preferred":[
        "Santo Tom\u00e9"
    ],
    "name:swe_x_preferred":[
        "Santo Tom\u00e9"
    ],
    "name:ukr_x_preferred":[
        "\u0421\u0430\u043d\u0442\u043e-\u0422\u043e\u043c\u0435"
    ],
    "name:zho_x_preferred":[
        "\u8056\u6258\u6258\u6885"
    ],
    "qs:gn_country":"AR",
    "qs:gn_fcode":"PPL",
    "qs:gn_pop":22634,
    "qs:name":"Santo Tom\u00e9",
    "qs:name_adm0":"Argentina",
    "qs:name_adm1":"Corrientes",
    "qs:photos":91,
    "qs:photos_1k":18,
    "qs:photos_9k":1,
    "qs:photos_9r":3,
    "qs:photos_all":91,
    "qs:photos_sr":3,
    "qs:placetype":"Town",
    "qs:pop_sr":"7",
    "qs:woe_adm0":23424747,
    "wd:wordcount":186,
    "wof:name":"Santo Tom\u00e9",
    "wof:placetype":"locality",
    "wof:population":22634
},
  "geometry": {"coordinates":[-56.04077,-28.54939],"type":"Point"}
}