{
  "type": "Feature",
  "properties": {
    "gn:admin1_code":"17.0",
    "gn:admin2_code":"66119.0",
    "gn:asciiname":"Seclantas Adentro",
    "gn:country_code":"AR",
    "gn:dem":2174,
    "gn:feature_class":"P",
    "gn:feature_code":"PPL",
    "gn:name":"Seclant\u00e1s Adentro",
    "gn:population":0,
    "gn:timezone":"America/Argentina/Salta",
    "iso:country":"AR",
    "wof:name":"Seclantas Adentro",
    "wof:placetype":"locality"
},
  "geometry": {"coordinates":[-66.26486,-25.29908],"type":"Point"}
}