{
  "type": "Feature",
  "properties": {
    "iso:country":"AR",
    "name:ceb_x_preferred":[
        "General O'Brien"
    ],
    "name:eng_x_preferred":[
        "O'Brien"
    ],
    "name:eng_x_variant":[
        "Eduardo O'Brien"
    ],
    "name:jpn_x_preferred":[
        "\u30aa\u30d6\u30e9\u30a4\u30a8\u30f3"
    ],
    "name:nld_x_preferred":[
        "O'Brien"
    ],
    "name:spa_x_preferred":[
        "General O'Brien"
    ],
    "name:spa_x_variant":[
        "Eduardo O'Brien"
    ],
    "name:swe_x_preferred":[
        "General O'Brien"
    ],
    "name:ukr_x_preferred":[
        "\u0415\u0434\u0443\u0430\u0440\u0434\u043e-\u041e'\u0411\u0440\u0430\u0454\u043d"
    ],
    "name:und_x_variant":[
        "O\u2019Brien"
    ],
    "qs:gn_country":"AR",
    "qs:gn_fcode":"PPL",
    "qs:gn_pop":0,
    "qs:name":"General O'Brien",
    "qs:name_adm0":"Argentina",
    "qs:name_adm1":"Buenos Aires",
    "qs:photos":0,
    "qs:photos_1k":0,
    "qs:photos_9k":1,
    "qs:photos_9r":1,
    "qs:photos_all":6,
    "qs:photos_sr":0,
    "qs:placetype":"Town",
    "qs:pop_sr":"6",
    "qs:woe_adm0":23424747,
    "wof:name":"General O'Brien",
    "wof:placetype":"locality"
},
  "geometry": {"coordinates":[-60.75461,-34.90314],"type":"Point"}
}