{
  "type": "Feature",
  "properties": {
    "gn:admin1_code":"9.0",
    "gn:admin2_code":"34007.0",
    "gn:asciiname":"Pozo del Mortero",
    "gn:country_code":"AR",
    "gn:dem":147,
    "gn:feature_class":"P",
    "gn:feature_code":"PPL",
    "gn:name":"Pozo del Mortero",
    "gn:population":0,
    "gn:timezone":"America/Argentina/Cordoba",
    "iso:country":"AR",
    "wof:name":"Pozo del Mortero",
    "wof:placetype":"locality"
},
  "geometry": {"coordinates":[-61.02973000000001,-24.40768],"type":"Point"}
}