{
  "type": "Feature",
  "properties": {
    "gn:admin1_code":"1.0",
    "gn:admin2_code":"6679.0",
    "gn:asciiname":"Sansinena",
    "gn:country_code":"AR",
    "gn:dem":114,
    "gn:feature_class":"P",
    "gn:feature_code":"PPL",
    "gn:name":"Sansinena",
    "gn:population":0,
    "gn:timezone":"America/Argentina/Buenos_Aires",
    "iso:country":"AR",
    "wof:name":"Sansinena",
    "wof:placetype":"locality"
},
  "geometry": {"coordinates":[-63.21381,-35.27653],"type":"Point"}
}