{
  "type": "Feature",
  "properties": {
    "gn:admin1_code":"17.0",
    "gn:admin2_code":"66126.0",
    "gn:asciiname":"Esteban de Urizar",
    "gn:country_code":"AR",
    "gn:dem":333,
    "gn:feature_class":"P",
    "gn:feature_code":"PPL",
    "gn:name":"Esteban de Urizar",
    "gn:population":0,
    "gn:timezone":"America/Argentina/Salta",
    "iso:country":"AR",
    "wof:name":"Esteban de Urizar",
    "wof:placetype":"locality"
},
  "geometry": {"coordinates":[-64.10824000000001,-23.56934],"type":"Point"}
}