{
  "type": "Feature",
  "properties": {
    "gn:admin1_code":"18.0",
    "gn:admin2_code":"70112.0",
    "gn:asciiname":"Matagusanos",
    "gn:country_code":"AR",
    "gn:dem":910,
    "gn:feature_class":"P",
    "gn:feature_code":"PPL",
    "gn:name":"Matagusanos",
    "gn:population":0,
    "gn:timezone":"America/Argentina/San_Juan",
    "iso:country":"AR",
    "wof:name":"Matagusanos",
    "wof:placetype":"locality"
},
  "geometry": {"coordinates":[-68.62944,-31.24639],"type":"Point"}
}