{
  "type": "Feature",
  "properties": {
    "gn:admin1_code":"22",
    "gn:admin2_code":"86147.0",
    "gn:asciiname":"El Charco",
    "gn:country_code":"AR",
    "gn:dem":297,
    "gn:feature_class":"P",
    "gn:feature_code":"PPL",
    "gn:name":"El Charco",
    "gn:population":0,
    "gn:timezone":"America/Argentina/Cordoba",
    "iso:country":"AR",
    "name:ceb_x_preferred":[
        "El Charco"
    ],
    "name:nld_x_preferred":[
        "El Charco"
    ],
    "name:spa_x_preferred":[
        "El Charco"
    ],
    "wof:name":"El Charco",
    "wof:placetype":"locality"
},
  "geometry": {"coordinates":[-64.70085,-27.22846],"type":"Point"}
}