{
  "type": "Feature",
  "properties": {
    "gn:admin1_code":"6.0",
    "gn:admin2_code":"18105.0",
    "gn:asciiname":"Naranjito",
    "gn:country_code":"AR",
    "gn:dem":63,
    "gn:feature_class":"P",
    "gn:feature_code":"PPL",
    "gn:name":"Naranjito",
    "gn:population":0,
    "gn:timezone":"America/Argentina/Cordoba",
    "iso:country":"AR",
    "name:bre_x_preferred":[
        "Naranjito"
    ],
    "name:ceb_x_preferred":[
        "Naranjito"
    ],
    "name:deu_x_preferred":[
        "Naranjito"
    ],
    "name:ita_x_preferred":[
        "Naranjito"
    ],
    "name:nld_x_preferred":[
        "Naranjito"
    ],
    "name:pol_x_preferred":[
        "Naranjito"
    ],
    "name:slv_x_preferred":[
        "Naranjito"
    ],
    "name:spa_x_preferred":[
        "Naranjito"
    ],
    "name:swe_x_preferred":[
        "Naranjito"
    ],
    "wof:name":"Naranjito",
    "wof:placetype":"locality"
},
  "geometry": {"coordinates":[-58.31593,-28.93446],"type":"Point"}
}