{
  "type": "Feature",
  "properties": {
    "gn:admin1_code":"12.0",
    "gn:admin2_code":"46084.0",
    "gn:asciiname":"Los Aguirres",
    "gn:country_code":"AR",
    "gn:dem":447,
    "gn:feature_class":"P",
    "gn:feature_code":"PPL",
    "gn:name":"Los Aguirres",
    "gn:population":0,
    "gn:timezone":"America/Argentina/La_Rioja",
    "iso:country":"AR",
    "name:und_x_variant":[
        "Aguirres",
        "Los Aguirres"
    ],
    "wof:name":"Los Aguirres",
    "wof:placetype":"locality"
},
  "geometry": {"coordinates":[-66.08918,-30.805],"type":"Point"}
}