{
  "type": "Feature",
  "properties": {
    "iso:country":"AR",
    "name:cat_x_preferred":[
        "Corralito"
    ],
    "name:deu_x_preferred":[
        "Corralito"
    ],
    "name:epo_x_preferred":[
        "Bebokorteto"
    ],
    "name:eus_x_preferred":[
        "Corralito"
    ],
    "name:fra_x_preferred":[
        "Corralito"
    ],
    "name:ita_x_preferred":[
        "Corralito"
    ],
    "name:por_x_preferred":[
        "Corralito"
    ],
    "name:rus_x_preferred":[
        "\u041a\u043e\u0440\u0440\u0430\u043b\u0438\u0442\u043e"
    ],
    "name:spa_x_preferred":[
        "Corralito"
    ],
    "qs:gn_country":"AR",
    "qs:gn_fcode":"PPL",
    "qs:gn_pop":0,
    "qs:name":"Corralito",
    "qs:name_adm0":"Argentina",
    "qs:name_adm1":"Salta",
    "qs:photos":88,
    "qs:photos_1k":18,
    "qs:photos_9k":1,
    "qs:photos_9r":3,
    "qs:photos_all":88,
    "qs:photos_sr":3,
    "qs:placetype":"Town",
    "qs:pop_sr":"0",
    "qs:woe_adm0":23424747,
    "wd:wordcount":1151,
    "wof:name":"Corralito",
    "wof:placetype":"locality"
},
  "geometry": {"coordinates":[-65.8493,-25.96684],"type":"Point"}
}