{
  "type": "Feature",
  "properties": {
    "iso:country":"AR",
    "name:ceb_x_preferred":[
        "Baradero"
    ],
    "name:dan_x_preferred":[
        "Baradero"
    ],
    "name:eng_x_preferred":[
        "Baradero"
    ],
    "name:fra_x_preferred":[
        "Baradero"
    ],
    "name:heb_x_preferred":[
        "\u05d1\u05d0\u05e8\u05d0\u05d3\u05e8\u05d5"
    ],
    "name:ita_x_preferred":[
        "Baradero"
    ],
    "name:jpn_x_preferred":[
        "\u30d0\u30e9\u30c7\u30ed"
    ],
    "name:nld_x_preferred":[
        "Baradero"
    ],
    "name:oci_x_preferred":[
        "Baradero"
    ],
    "name:pol_x_preferred":[
        "Baradero"
    ],
    "name:por_x_preferred":[
        "Baradero"
    ],
    "name:rus_x_preferred":[
        "\u0411\u0430\u0440\u0430\u0434\u0435\u0440\u043e"
    ],
    "name:spa_x_preferred":[
        "Baradero"
    ],
    "name:swe_x_preferred":[
        "Baradero"
    ],
    "name:ukr_x_preferred":[
        "\u0411\u0430\u0440\u0430\u0434\u0435\u0440\u043e"
    ],
    "name:zho_x_preferred":[
        "\u5df4\u62c9\u5fb7\u7f85"
    ],
    "qs:gn_country":"AR",
    "qs:gn_fcode":"PPL",
    "qs:gn_pop":0,
    "qs:name":"Baradero",
    "qs:name_adm0":"Argentina",
    "qs:name_adm1":"Buenos Aires",
    "qs:photos":330,
    "qs:photos_1k":67,
    "qs:photos_9k":1,
    "qs:photos_9r":5,
    "qs:photos_all":330,
    "qs:photos_sr":5,
    "qs:placetype":"Town",
    "qs:pop_sr":"5",
    "qs:woe_adm0":23424747,
    "wof:name":"Baradero",
    "wof:placetype":"locality"
},
  "geometry": {"coordinates":[-59.50807,-33.81105],"type":"Point"}
}