{
  "type": "Feature",
  "properties": {
    "gn:admin1_code":"13",
    "gn:admin2_code":"50077.0",
    "gn:asciiname":"Las Loicas",
    "gn:country_code":"AR",
    "gn:dem":1614,
    "gn:elevation":"1608.0",
    "gn:feature_class":"P",
    "gn:feature_code":"PPLF",
    "gn:name":"Las Loicas",
    "gn:population":85,
    "gn:timezone":"America/Argentina/Mendoza",
    "iso:country":"AR",
    "wof:name":"Las Loicas",
    "wof:placetype":"locality",
    "wof:population":85
},
  "geometry": {"coordinates":[-70.14015000000001,-35.79463],"type":"Point"}
}