{
  "type": "Feature",
  "properties": {
    "gn:admin1_code":"1.0",
    "gn:admin2_code":"6427.0",
    "gn:asciiname":"Villa Ansaldi",
    "gn:country_code":"AR",
    "gn:dem":26,
    "gn:feature_class":"P",
    "gn:feature_code":"PPL",
    "gn:name":"Villa Ansaldi",
    "gn:population":0,
    "gn:timezone":"America/Argentina/Buenos_Aires",
    "iso:country":"AR",
    "name:spa_x_preferred":[
        "Villa Ansaldi"
    ],
    "wof:name":"Villa Ansaldi",
    "wof:placetype":"locality"
},
  "geometry": {"coordinates":[-58.51445,-34.6796],"type":"Point"}
}