{
  "type": "Feature",
  "properties": {
    "gn:admin1_code":"5.0",
    "gn:admin2_code":"14175.0",
    "gn:asciiname":"Isla de San Antonio",
    "gn:country_code":"AR",
    "gn:dem":396,
    "gn:feature_class":"P",
    "gn:feature_code":"PPL",
    "gn:name":"Isla de San Antonio",
    "gn:population":0,
    "gn:timezone":"America/Argentina/Cordoba",
    "iso:country":"AR",
    "name:und_x_variant":[
        "La Isla de San Antonio",
        "Isla San Antonio",
        "Isla de San Antonio"
    ],
    "wof:name":"Isla de San Antonio",
    "wof:placetype":"locality"
},
  "geometry": {"coordinates":[-64.41722,-30.02949000000001],"type":"Point"}
}