{
  "type": "Feature",
  "properties": {
    "gn:admin1_code":"1.0",
    "gn:admin2_code":"6778.0",
    "gn:asciiname":"Domselaar",
    "gn:country_code":"AR",
    "gn:dem":23,
    "gn:feature_class":"P",
    "gn:feature_code":"PPL",
    "gn:name":"Domselaar",
    "gn:population":0,
    "gn:timezone":"America/Argentina/Buenos_Aires",
    "iso:country":"AR",
    "wof:name":"Domselaar",
    "wof:placetype":"locality"
},
  "geometry": {"coordinates":[-58.28554000000001,-35.07223],"type":"Point"}
}