{
  "type": "Feature",
  "properties": {
    "gn:admin1_code":"22",
    "gn:admin2_code":"86056.0",
    "gn:asciiname":"El Cabure",
    "gn:cc2":"AR",
    "gn:country_code":"AR",
    "gn:dem":191,
    "gn:feature_class":"P",
    "gn:feature_code":"PPL",
    "gn:name":"El Cabur\u00e9",
    "gn:population":0,
    "gn:timezone":"America/Argentina/Cordoba",
    "iso:country":"AR",
    "name:und_x_variant":[
        "Kil\u00f3metro 380",
        "El Cabur\u00e9"
    ],
    "wof:name":"El Cabure",
    "wof:placetype":"locality"
},
  "geometry": {"coordinates":[-62.36666999999999,-26.01667],"type":"Point"}
}