{
  "type": "Feature",
  "properties": {
    "gn:admin1_code":"21.0",
    "gn:admin2_code":"82112.0",
    "gn:asciiname":"La Blanca Central",
    "gn:country_code":"AR",
    "gn:dem":55,
    "gn:feature_class":"P",
    "gn:feature_code":"PPL",
    "gn:name":"La Blanca Central",
    "gn:population":0,
    "gn:timezone":"America/Argentina/Cordoba",
    "iso:country":"AR",
    "wof:name":"La Blanca Central",
    "wof:placetype":"locality"
},
  "geometry": {"coordinates":[-60.49022,-30.19256],"type":"Point"}
}