{
  "type": "Feature",
  "properties": {
    "gn:admin1_code":"5.0",
    "gn:admin2_code":"14168.0",
    "gn:asciiname":"Los Cometierra",
    "gn:country_code":"AR",
    "gn:dem":374,
    "gn:feature_class":"P",
    "gn:feature_code":"PPL",
    "gn:name":"Los Cometierra",
    "gn:population":0,
    "gn:timezone":"America/Argentina/Cordoba",
    "iso:country":"AR",
    "wof:name":"Los Cometierra",
    "wof:placetype":"locality"
},
  "geometry": {"coordinates":[-63.91983000000001,-30.8699],"type":"Point"}
}