{
  "type": "Feature",
  "properties": {
    "iso:country":"AR",
    "name:fra_x_preferred":[
        "Campana"
    ],
    "name:rus_x_preferred":[
        "\u041a\u0430\u043c\u043f\u0430\u043d\u0430"
    ],
    "ne:ADM0CAP":0.0,
    "ne:ADM0NAME":"Argentina",
    "ne:ADM0_A3":"ARG",
    "ne:ADM1NAME":"Ciudad de Buenos Aires",
    "ne:ADMIN1_COD":1,
    "ne:CAPALT":0,
    "ne:CHANGED":0,
    "ne:CHECKME":0,
    "ne:COMPARE":0,
    "ne:DIFFASCII":0,
    "ne:ELEVATION":0.0,
    "ne:FEATURECLA":"Populated place",
    "ne:FEATURE_CL":"P",
    "ne:FEATURE_CO":"PPL",
    "ne:GEONAMEID":3435810,
    "ne:GEONAMESNO":"GeoNames match with ascii name + lat + long whole numbers.",
    "ne:GN_ASCII":"Campana",
    "ne:GN_POP":81612,
    "ne:GTOPO30":3.0,
    "ne:ISO_A2":"AR",
    "ne:LABELRANK":3,
    "ne:LATITUDE":-34.159996,
    "ne:LONGITUDE":-58.959978,
    "ne:LS_MATCH":1,
    "ne:LS_NAME":"Campana",
    "ne:MAX_AREAKM":25.0,
    "ne:MAX_AREAMI":10.0,
    "ne:MAX_BBXMAX":-58.916667,
    "ne:MAX_BBXMIN":-58.983333,
    "ne:MAX_BBYMAX":-34.15,
    "ne:MAX_BBYMIN":-34.216667,
    "ne:MAX_NATSCA":10.0,
    "ne:MAX_PERKM":29.0,
    "ne:MAX_PERMI":18.0,
    "ne:MAX_POP10":72687,
    "ne:MAX_POP20":0,
    "ne:MAX_POP300":0,
    "ne:MAX_POP310":0,
    "ne:MAX_POP50":0,
    "ne:MEAN_BBXC":-58.952262,
    "ne:MEAN_BBYC":-34.179405,
    "ne:MEGACITY":0,
    "ne:MIN_AREAKM":25.0,
    "ne:MIN_AREAMI":10.0,
    "ne:MIN_BBXMAX":-58.916667,
    "ne:MIN_BBXMIN":-58.983333,
    "ne:MIN_BBYMAX":-34.15,
    "ne:MIN_BBYMIN":-34.216667,
    "ne:MIN_PERKM":29.0,
    "ne:MIN_PERMI":18.0,
    "ne:NAME":"Campana",
    "ne:NAMEASCII":"Campana",
    "ne:NAMEDIFF":0,
    "ne:NATSCALE":10,
    "ne:POP1950":0,
    "ne:POP1955":0,
    "ne:POP1960":0,
    "ne:POP1965":0,
    "ne:POP1970":0,
    "ne:POP1975":0,
    "ne:POP1980":0,
    "ne:POP1985":0,
    "ne:POP1990":0,
    "ne:POP1995":0,
    "ne:POP2000":0,
    "ne:POP2005":0,
    "ne:POP2010":0,
    "ne:POP2015":0,
    "ne:POP2020":0,
    "ne:POP2025":0,
    "ne:POP2050":0,
    "ne:POP_MAX":81612,
    "ne:POP_MIN":72687,
    "ne:POP_OTHER":231356,
    "ne:RANK_MAX":8,
    "ne:RANK_MIN":8,
    "ne:SCALERANK":8,
    "ne:SOV0NAME":"Argentina",
    "ne:SOV_A3":"ARG",
    "ne:TIMEZONE":"America/Argentina/Buenos_Aires",
    "ne:UN_FID":0,
    "ne:UN_LAT":0.0,
    "ne:UN_LONG":0.0,
    "ne:WORLDCITY":0,
    "qs:gn_country":"AR",
    "qs:gn_fcode":"PPL",
    "qs:gn_pop":81612,
    "qs:name":"Campana",
    "qs:name_adm0":"Argentina",
    "qs:name_adm1":"Buenos Aires",
    "qs:photos":576,
    "qs:photos_1k":117,
    "qs:photos_9k":3,
    "qs:photos_9r":5,
    "qs:photos_all":576,
    "qs:photos_sr":8,
    "qs:placetype":"Town",
    "qs:pop_sr":"8",
    "qs:woe_adm0":23424747,
    "wof:name":"Campana",
    "wof:placetype":"locality",
    "wof:population":81612
},
  "geometry": {"coordinates":[-58.95914,-34.16874],"type":"Point"}
}