{
  "type": "Feature",
  "properties": {
    "gn:admin1_code":"10.0",
    "gn:admin2_code":"38049.0",
    "gn:asciiname":"Lopiara",
    "gn:country_code":"AR",
    "gn:dem":3953,
    "gn:feature_class":"P",
    "gn:feature_code":"PPL",
    "gn:name":"Lopiara",
    "gn:population":0,
    "gn:timezone":"America/Argentina/Jujuy",
    "iso:country":"AR",
    "wof:name":"Lopiara",
    "wof:placetype":"locality"
},
  "geometry": {"coordinates":[-66.22071,-22.5844],"type":"Point"}
}