{
  "type": "Feature",
  "properties": {
    "gn:admin1_code":"22.0",
    "gn:admin2_code":"86014.0",
    "gn:asciiname":"Huachana",
    "gn:country_code":"AR",
    "gn:dem":215,
    "gn:feature_class":"P",
    "gn:feature_code":"PPL",
    "gn:name":"Huachana",
    "gn:population":0,
    "gn:timezone":"America/Argentina/Cordoba",
    "iso:country":"AR",
    "wof:name":"Huachana",
    "wof:placetype":"locality"
},
  "geometry": {"coordinates":[-63.4979,-26.4104],"type":"Point"}
}