{
  "type": "Feature",
  "properties": {
    "gn:admin1_code":"6.0",
    "gn:admin2_code":"18119.0",
    "gn:asciiname":"Alem Cue",
    "gn:country_code":"AR",
    "gn:dem":70,
    "gn:feature_class":"P",
    "gn:feature_code":"PPL",
    "gn:name":"Alem Cu\u00e9",
    "gn:population":0,
    "gn:timezone":"America/Argentina/Cordoba",
    "iso:country":"AR",
    "name:und_x_variant":[
        "Alen Cu\u00e9",
        "Alem Cu\u00e9"
    ],
    "wof:name":"Alem Cue",
    "wof:placetype":"locality"
},
  "geometry": {"coordinates":[-57.43696,-29.17479],"type":"Point"}
}