{
  "type": "Feature",
  "properties": {
    "iso:country":"AR",
    "name:deu_x_preferred":[
        "Theobald"
    ],
    "name:eng_x_preferred":[
        "Theobald"
    ],
    "name:epo_x_preferred":[
        "Teobaldo"
    ],
    "name:fra_x_preferred":[
        "Theobald"
    ],
    "name:hbs_x_preferred":[
        "Theobald"
    ],
    "name:hun_x_preferred":[
        "Teobald"
    ],
    "name:ita_x_preferred":[
        "Teobaldo"
    ],
    "name:jpn_x_preferred":[
        "\u30c6\u30aa\u30d0\u30eb\u30c9"
    ],
    "name:lat_x_preferred":[
        "Theobaldus"
    ],
    "name:nld_x_preferred":[
        "Theobald"
    ],
    "name:pol_x_preferred":[
        "Teobald"
    ],
    "name:por_x_preferred":[
        "Theobald"
    ],
    "name:spa_x_preferred":[
        "Theobald"
    ],
    "qs:gn_country":"AR",
    "qs:gn_fcode":"PPL",
    "qs:gn_pop":0,
    "qs:name":"Theobald",
    "qs:name_adm0":"Argentina",
    "qs:name_adm1":"Santa Fe",
    "qs:photos":0,
    "qs:photos_1k":0,
    "qs:photos_9k":1,
    "qs:photos_9r":1,
    "qs:photos_all":6,
    "qs:photos_sr":0,
    "qs:placetype":"Town",
    "qs:pop_sr":"0",
    "qs:woe_adm0":23424747,
    "wd:wordcount":494,
    "wof:name":"Theobald",
    "wof:placetype":"locality"
},
  "geometry": {"coordinates":[-60.31101,-33.31057],"type":"Point"}
}