{
  "type": "Feature",
  "properties": {
    "iso:country":"AR",
    "qs:gn_country":"AR",
    "qs:gn_fcode":"PPL",
    "qs:gn_pop":0,
    "qs:name":"F\u00e1brica Col\u00f3n",
    "qs:name_adm0":"Argentina",
    "qs:name_adm1":"Entre R\u00edos",
    "qs:photos":51,
    "qs:photos_1k":10,
    "qs:photos_9k":1,
    "qs:photos_9r":2,
    "qs:photos_all":51,
    "qs:photos_sr":2,
    "qs:placetype":"Town",
    "qs:pop_sr":"0",
    "qs:woe_adm0":23424747,
    "wof:name":"F\u00e1brica Col\u00f3n",
    "wof:placetype":"locality"
},
  "geometry": {"coordinates":[-58.18333,-32.15],"type":"Point"}
}