{
  "type": "Feature",
  "properties": {
    "gn:admin1_code":"10",
    "gn:admin2_code":"38070.0",
    "gn:asciiname":"El Fuerte",
    "gn:country_code":"AR",
    "gn:dem":1429,
    "gn:feature_class":"P",
    "gn:feature_code":"PPL",
    "gn:name":"El Fuerte",
    "gn:population":0,
    "gn:timezone":"America/Argentina/Jujuy",
    "iso:country":"AR",
    "name:bre_x_preferred":[
        "El Fuerte"
    ],
    "name:ceb_x_preferred":[
        "El Fuerte"
    ],
    "name:ita_x_preferred":[
        "El Fuerte"
    ],
    "name:nld_x_preferred":[
        "El Fuerte"
    ],
    "name:rus_x_preferred":[
        "\u042d\u043b\u044c-\u0424\u0443\u044d\u0440\u0442\u0435"
    ],
    "name:spa_x_preferred":[
        "El Fuerte"
    ],
    "name:srp_x_preferred":[
        "\u0415\u043b \u0424\u0443\u0435\u0440\u0442\u0435"
    ],
    "name:swe_x_preferred":[
        "El Fuerte"
    ],
    "name:vie_x_preferred":[
        "El Fuerte"
    ],
    "wof:name":"El Fuerte",
    "wof:placetype":"locality"
},
  "geometry": {"coordinates":[-64.40961999999999,-24.25983],"type":"Point"}
}