{
  "type": "Feature",
  "properties": {
    "gn:admin1_code":"10",
    "gn:admin2_code":"38070.0",
    "gn:asciiname":"El Fuerte",
    "gn:country_code":"AR",
    "gn:dem":1429,
    "gn:feature_class":"P",
    "gn:feature_code":"PPL",
    "gn:name":"El Fuerte",
    "gn:population":0,
    "gn:timezone":"America/Argentina/Jujuy",
    "iso:country":"AR",
    "wof:name":"El Fuerte",
    "wof:placetype":"locality"
},
  "geometry": {"coordinates":[-64.40961999999999,-24.25983],"type":"Point"}
}