{
  "type": "Feature",
  "properties": {
    "gn:admin1_code":"19.0",
    "gn:admin2_code":"74042.0",
    "gn:asciiname":"La Melina",
    "gn:country_code":"AR",
    "gn:dem":356,
    "gn:feature_class":"P",
    "gn:feature_code":"PPL",
    "gn:name":"La Melina",
    "gn:population":0,
    "gn:timezone":"America/Argentina/San_Luis",
    "iso:country":"AR",
    "wof:name":"La Melina",
    "wof:placetype":"locality"
},
  "geometry": {"coordinates":[-65.74928,-35.27009],"type":"Point"}
}