{
  "type": "Feature",
  "properties": {
    "gn:admin1_code":"05",
    "gn:admin2_code":"14021.0",
    "gn:asciiname":"Colonia Caroya",
    "gn:country_code":"AR",
    "gn:dem":498,
    "gn:feature_class":"P",
    "gn:feature_code":"PPL",
    "gn:name":"Colonia Caroya",
    "gn:population":0,
    "gn:timezone":"America/Argentina/Cordoba",
    "iso:country":"AR",
    "name:und_x_variant":[
        "Caroya",
        "Colonia Caroya"
    ],
    "wof:name":"Colonia Caroya",
    "wof:placetype":"locality"
},
  "geometry": {"coordinates":[-64.06519,-31.01978],"type":"Point"}
}