{
  "type": "Feature",
  "properties": {
    "gn:admin1_code":"12",
    "gn:admin2_code":"46014.0",
    "gn:asciiname":"Cebollar",
    "gn:country_code":"AR",
    "gn:dem":450,
    "gn:feature_class":"P",
    "gn:feature_code":"PPL",
    "gn:name":"Cebollar",
    "gn:population":0,
    "gn:timezone":"America/Argentina/La_Rioja",
    "iso:country":"AR",
    "wof:name":"Cebollar",
    "wof:placetype":"locality"
},
  "geometry": {"coordinates":[-66.56777,-29.08961],"type":"Point"}
}