{
  "type": "Feature",
  "properties": {
    "gn:admin1_code":"05",
    "gn:admin2_code":"14091.0",
    "gn:asciiname":"Cueva de los Indios",
    "gn:country_code":"AR",
    "gn:dem":1090,
    "gn:feature_class":"P",
    "gn:feature_code":"PPL",
    "gn:name":"Cueva de los Indios",
    "gn:population":0,
    "gn:timezone":"America/Argentina/Cordoba",
    "iso:country":"AR",
    "wof:name":"Cueva de los Indios",
    "wof:placetype":"locality"
},
  "geometry": {"coordinates":[-64.55,-31.15],"type":"Point"}
}