{
  "type": "Feature",
  "properties": {
    "gn:admin1_code":"1.0",
    "gn:admin2_code":"6392.0",
    "gn:asciiname":"Piedritas",
    "gn:country_code":"AR",
    "gn:dem":125,
    "gn:feature_class":"P",
    "gn:feature_code":"PPL",
    "gn:name":"Piedritas",
    "gn:population":0,
    "gn:timezone":"America/Argentina/Buenos_Aires",
    "iso:country":"AR",
    "name:und_x_variant":[
        "Las Piedritas",
        "Piedritas"
    ],
    "wof:name":"Piedritas",
    "wof:placetype":"locality"
},
  "geometry": {"coordinates":[-62.98365,-34.76832],"type":"Point"}
}