{
  "type": "Feature",
  "properties": {
    "gn:admin1_code":"09",
    "gn:admin2_code":"34063.0",
    "gn:asciiname":"El Desmonte",
    "gn:country_code":"AR",
    "gn:dem":230,
    "gn:feature_class":"P",
    "gn:feature_code":"PPL",
    "gn:name":"El Desmonte",
    "gn:population":0,
    "gn:timezone":"America/Argentina/Cordoba",
    "iso:country":"AR",
    "name:ceb_x_preferred":[
        "El Desmonte"
    ],
    "name:spa_x_preferred":[
        "El Desmonte"
    ],
    "wof:name":"El Desmonte",
    "wof:placetype":"locality"
},
  "geometry": {"coordinates":[-62.20404,-22.69373],"type":"Point"}
}