{
  "type": "Feature",
  "properties": {
    "gn:admin1_code":"21.0",
    "gn:admin2_code":"82063.0",
    "gn:asciiname":"Llambi Campbell",
    "gn:cc2":"AR",
    "gn:country_code":"AR",
    "gn:dem":46,
    "gn:feature_class":"P",
    "gn:feature_code":"PPL",
    "gn:name":"Llamb\u00ed Campbell",
    "gn:population":0,
    "gn:timezone":"America/Argentina/Cordoba",
    "iso:country":"AR",
    "name:und_x_variant":[
        "Campbell",
        "Llamb\u00ed Campell"
    ],
    "wof:name":"Llambi Campbell",
    "wof:placetype":"locality"
},
  "geometry": {"coordinates":[-60.75167,-31.18307],"type":"Point"}
}