{
  "type": "Feature",
  "properties": {
    "iso:country":"AR",
    "qs:gn_country":"AR",
    "qs:gn_fcode":"PPL",
    "qs:gn_pop":0,
    "qs:name":"Ba\u00f1ado Sur",
    "qs:name_adm0":"Argentina",
    "qs:name_adm1":"Corrientes",
    "qs:photos":1366,
    "qs:photos_1k":277,
    "qs:photos_9k":6,
    "qs:photos_9r":7,
    "qs:photos_all":1366,
    "qs:photos_sr":12,
    "qs:placetype":"Town",
    "qs:pop_sr":"0",
    "qs:woe_adm0":23424747,
    "wof:name":"Ba\u00f1ado Sur",
    "wof:placetype":"locality"
},
  "geometry": {"coordinates":[-58.85,-27.48333],"type":"Point"}
}