{
  "type": "Feature",
  "properties": {
    "gn:admin1_code":"1.0",
    "gn:admin2_code":"6833.0",
    "gn:asciiname":"Balneario Orense",
    "gn:country_code":"AR",
    "gn:dem":11,
    "gn:feature_class":"P",
    "gn:feature_code":"PPL",
    "gn:name":"Balneario Orense",
    "gn:population":0,
    "gn:timezone":"America/Argentina/Buenos_Aires",
    "iso:country":"AR",
    "wof:name":"Balneario Orense",
    "wof:placetype":"locality"
},
  "geometry": {"coordinates":[-59.73671,-38.80684],"type":"Point"}
}