{
  "type": "Feature",
  "properties": {
    "iso:country":"AR",
    "name:ceb_x_preferred":[
        "El Alc\u00e1zar"
    ],
    "name:eng_x_preferred":[
        "El Alc\u00e1zar"
    ],
    "name:jpn_x_preferred":[
        "\u30a8\u30eb\u30fb\u30a2\u30eb\u30ab\u30b5\u30eb"
    ],
    "name:nld_x_preferred":[
        "El Alc\u00e1zar"
    ],
    "name:por_x_preferred":[
        "El Alc\u00e1zar"
    ],
    "name:spa_x_preferred":[
        "El Alc\u00e1zar"
    ],
    "name:swe_x_preferred":[
        "El Alc\u00e1zar"
    ],
    "name:ukr_x_preferred":[
        "\u0415\u043b\u044c-\u0410\u043b\u044c\u043a\u0430\u0441\u0430\u0440"
    ],
    "qs:gn_country":"AR",
    "qs:gn_fcode":"PPL",
    "qs:gn_pop":5127,
    "qs:name":"El Alc\u00e1zar",
    "qs:name_adm0":"Argentina",
    "qs:name_adm1":"Misiones",
    "qs:photos":0,
    "qs:photos_1k":0,
    "qs:photos_9k":1,
    "qs:photos_9r":1,
    "qs:photos_all":1,
    "qs:photos_sr":0,
    "qs:placetype":"Town",
    "qs:pop_sr":"5",
    "qs:woe_adm0":23424747,
    "wd:wordcount":36,
    "wof:name":"El Alc\u00e1zar",
    "wof:placetype":"locality",
    "wof:population":5127
},
  "geometry": {"coordinates":[-54.81523,-26.71459],"type":"Point"}
}