{
  "type": "Feature",
  "properties": {
    "gn:admin1_code":"22.0",
    "gn:admin2_code":"86140.0",
    "gn:asciiname":"Las Islas",
    "gn:country_code":"AR",
    "gn:dem":83,
    "gn:feature_class":"P",
    "gn:feature_code":"PPL",
    "gn:name":"Las Islas",
    "gn:population":0,
    "gn:timezone":"America/Argentina/Cordoba",
    "iso:country":"AR",
    "wof:name":"Las Islas",
    "wof:placetype":"locality"
},
  "geometry": {"coordinates":[-63.11666999999999,-29.58333],"type":"Point"}
}