{
  "type": "Feature",
  "properties": {
    "gn:admin1_code":"17.0",
    "gn:admin2_code":"66126.0",
    "gn:asciiname":"Mision Zenta",
    "gn:country_code":"AR",
    "gn:dem":383,
    "gn:feature_class":"P",
    "gn:feature_code":"PPL",
    "gn:name":"Misi\u00f3n Zenta",
    "gn:population":0,
    "gn:timezone":"America/Argentina/Salta",
    "iso:country":"AR",
    "wof:name":"Mision Zenta",
    "wof:placetype":"locality"
},
  "geometry": {"coordinates":[-64.36667,-23.13333],"type":"Point"}
}