{
  "type": "Feature",
  "properties": {
    "gn:admin1_code":"21.0",
    "gn:admin2_code":"82119.0",
    "gn:asciiname":"Pujato",
    "gn:country_code":"AR",
    "gn:dem":74,
    "gn:feature_class":"P",
    "gn:feature_code":"PPL",
    "gn:name":"Pujato",
    "gn:population":0,
    "gn:timezone":"America/Argentina/Cordoba",
    "iso:country":"AR",
    "name:und_x_variant":[
        "Colonia Clodomira",
        "Colonia Clodo",
        "Pujato"
    ],
    "wof:name":"Pujato",
    "wof:placetype":"locality"
},
  "geometry": {"coordinates":[-61.04323,-33.01765],"type":"Point"}
}