{
  "type": "Feature",
  "properties": {
    "gn:admin1_code":"22",
    "gn:admin2_code":"86119.0",
    "gn:asciiname":"Amama",
    "gn:country_code":"AR",
    "gn:dem":163,
    "gn:feature_class":"P",
    "gn:feature_code":"PPL",
    "gn:name":"Amam\u00e1",
    "gn:population":0,
    "gn:timezone":"America/Argentina/Cordoba",
    "iso:country":"AR",
    "name:ceb_x_preferred":[
        "Amama"
    ],
    "name:deu_x_preferred":[
        "Amama"
    ],
    "name:eus_x_preferred":[
        "Amama"
    ],
    "name:swe_x_preferred":[
        "Amama"
    ],
    "wof:name":"Amama",
    "wof:placetype":"locality"
},
  "geometry": {"coordinates":[-63.03891,-27.20889],"type":"Point"}
}