{
  "type": "Feature",
  "properties": {
    "gn:admin1_code":"01",
    "gn:admin2_code":"6413.0",
    "gn:asciiname":"Agustina",
    "gn:country_code":"AR",
    "gn:dem":90,
    "gn:feature_class":"P",
    "gn:feature_code":"PPL",
    "gn:name":"Agustina",
    "gn:population":0,
    "gn:timezone":"America/Argentina/Buenos_Aires",
    "iso:country":"AR",
    "name:ceb_x_preferred":[
        "Agustina"
    ],
    "name:deu_x_preferred":[
        "Agustina"
    ],
    "name:spa_x_preferred":[
        "Agustina"
    ],
    "name:swe_x_preferred":[
        "Agustina"
    ],
    "wof:name":"Agustina",
    "wof:placetype":"locality"
},
  "geometry": {"coordinates":[-61.0664,-34.45962],"type":"Point"}
}