{
  "type": "Feature",
  "properties": {
    "iso:country":"AR",
    "name:ceb_x_preferred":[
        "Caseros"
    ],
    "name:eng_x_preferred":[
        "Caseros"
    ],
    "name:nld_x_preferred":[
        "Caseros"
    ],
    "name:por_x_preferred":[
        "Caseros"
    ],
    "name:spa_x_preferred":[
        "Caseros"
    ],
    "name:swe_x_preferred":[
        "Caseros"
    ],
    "name:und_x_variant":[
        "Colonia Caseros"
    ],
    "qs:gn_country":"AR",
    "qs:gn_fcode":"PPL",
    "qs:gn_pop":2109,
    "qs:name":"Caseros",
    "qs:name_adm0":"Argentina",
    "qs:name_adm1":"Entre R\u00edos",
    "qs:photos":0,
    "qs:photos_1k":0,
    "qs:photos_9k":1,
    "qs:photos_9r":2,
    "qs:photos_all":32,
    "qs:photos_sr":0,
    "qs:placetype":"Town",
    "qs:pop_sr":"7",
    "qs:woe_adm0":23424747,
    "wd:wordcount":37,
    "wof:name":"Caseros",
    "wof:placetype":"locality",
    "wof:population":2109
},
  "geometry": {"coordinates":[-58.47872,-32.46325],"type":"Point"}
}