{
  "type": "Feature",
  "properties": {
    "gn:country":"AR",
    "gn:fcode":"PPL",
    "gn:pop":1334,
    "iso:country":"AR",
    "name:eng_x_preferred":[
        "Coronel Baigorria"
    ],
    "name:spa_x_preferred":[
        "Coronel Baigorria"
    ],
    "name:swe_x_preferred":[
        "Coronel Baigorria"
    ],
    "qs:name":"Coronel Baigorria",
    "qs:photos_9r":0,
    "qs:photos_sr":0,
    "qs:pop_sr":"6",
    "wof:name":"Coronel Baigorria",
    "wof:placetype":"locality",
    "wof:population":1334
},
  "geometry": {"coordinates":[-64.36107,-32.8477],"type":"Point"}
}