{
  "type": "Feature",
  "properties": {
    "gn:admin1_code":"1.0",
    "gn:admin2_code":"6168.0",
    "gn:asciiname":"Centro Guerrero",
    "gn:country_code":"AR",
    "gn:dem":15,
    "gn:feature_class":"P",
    "gn:feature_code":"PPL",
    "gn:name":"Centro Guerrero",
    "gn:population":0,
    "gn:timezone":"America/Argentina/Buenos_Aires",
    "iso:country":"AR",
    "wof:name":"Centro Guerrero",
    "wof:placetype":"locality"
},
  "geometry": {"coordinates":[-57.82715,-36.05987],"type":"Point"}
}