{
  "type": "Feature",
  "properties": {
    "gn:admin1_code":"1.0",
    "gn:admin2_code":"6063.0",
    "gn:asciiname":"Napaleofu",
    "gn:country_code":"AR",
    "gn:dem":164,
    "gn:feature_class":"P",
    "gn:feature_code":"PPL",
    "gn:name":"Napaleof\u00fa",
    "gn:population":0,
    "gn:timezone":"America/Argentina/Buenos_Aires",
    "iso:country":"AR",
    "wof:name":"Napaleofu",
    "wof:placetype":"locality"
},
  "geometry": {"coordinates":[-58.74365,-37.62468],"type":"Point"}
}