{
  "type": "Feature",
  "properties": {
    "gn:admin1_code":"21",
    "gn:admin2_code":"82021.0",
    "gn:asciiname":"Coronel Fraga",
    "gn:country_code":"AR",
    "gn:dem":107,
    "gn:feature_class":"P",
    "gn:feature_code":"PPL",
    "gn:name":"Coronel Fraga",
    "gn:population":0,
    "gn:timezone":"America/Argentina/Cordoba",
    "iso:country":"AR",
    "name:und_x_variant":[
        "Fraga",
        "Coronel Fraga"
    ],
    "wof:name":"Coronel Fraga",
    "wof:placetype":"locality"
},
  "geometry": {"coordinates":[-61.91785,-31.17429000000001],"type":"Point"}
}