{
  "type": "Feature",
  "properties": {
    "gn:admin1_code":"10",
    "gn:admin2_code":"38049.0",
    "gn:asciiname":"Carahuasi",
    "gn:cc2":"AR",
    "gn:country_code":"AR",
    "gn:dem":3699,
    "gn:feature_class":"P",
    "gn:feature_code":"PPL",
    "gn:name":"Carahuasi",
    "gn:population":0,
    "gn:timezone":"America/Argentina/Jujuy",
    "iso:country":"AR",
    "name:und_x_variant":[
        "Curhuani",
        "Carahuasi"
    ],
    "wof:name":"Carahuasi",
    "wof:placetype":"locality"
},
  "geometry": {"coordinates":[-65.95,-22.48333],"type":"Point"}
}