{
  "type": "Feature",
  "properties": {
    "gn:admin1_code":"22.0",
    "gn:admin2_code":"86140.0",
    "gn:asciiname":"Puerta del Monte",
    "gn:country_code":"AR",
    "gn:dem":94,
    "gn:feature_class":"P",
    "gn:feature_code":"PPL",
    "gn:name":"Puerta del Monte",
    "gn:population":0,
    "gn:timezone":"America/Argentina/Cordoba",
    "iso:country":"AR",
    "wof:name":"Puerta del Monte",
    "wof:placetype":"locality"
},
  "geometry": {"coordinates":[-63.33312,-29.24572],"type":"Point"}
}