{
  "type": "Feature",
  "properties": {
    "gn:admin1_code":"4.0",
    "gn:admin2_code":"26021.0",
    "gn:asciiname":"El Tordillo",
    "gn:country_code":"AR",
    "gn:dem":586,
    "gn:feature_class":"P",
    "gn:feature_code":"PPL",
    "gn:name":"El Tordillo",
    "gn:population":0,
    "gn:timezone":"America/Argentina/Catamarca",
    "iso:country":"AR",
    "name:und_x_variant":[
        "Estancia El Tordillo",
        "El Tordillo"
    ],
    "wof:name":"El Tordillo",
    "wof:placetype":"locality"
},
  "geometry": {"coordinates":[-68.06953,-45.88917],"type":"Point"}
}