{
  "type": "Feature",
  "properties": {
    "gn:admin1_code":"2.0",
    "gn:admin2_code":"10014.0",
    "gn:asciiname":"Yerba Buena",
    "gn:country_code":"AR",
    "gn:dem":640,
    "gn:feature_class":"P",
    "gn:feature_code":"PPL",
    "gn:name":"Yerba Buena",
    "gn:population":0,
    "gn:timezone":"America/Argentina/Catamarca",
    "iso:country":"AR",
    "name:ceb_x_preferred":[
        "Yerba Buena"
    ],
    "name:deu_x_preferred":[
        "Yerba Buena"
    ],
    "name:fra_x_preferred":[
        "Yerba Buena"
    ],
    "name:ita_x_preferred":[
        "Yerba Buena"
    ],
    "name:mlg_x_preferred":[
        "Yerba Buena"
    ],
    "name:nld_x_preferred":[
        "Yerba Buena"
    ],
    "name:pol_x_preferred":[
        "Yerba Buena"
    ],
    "name:por_x_preferred":[
        "Yerba Buena"
    ],
    "name:rus_x_preferred":[
        "\u0419\u0435\u0440\u0431\u0430-\u0411\u0443\u044d\u043d\u0430"
    ],
    "name:spa_x_preferred":[
        "Yerba Buena"
    ],
    "name:swe_x_preferred":[
        "Yerba Buena"
    ],
    "name:tur_x_preferred":[
        "Yerba Buena"
    ],
    "wof:name":"Yerba Buena",
    "wof:placetype":"locality"
},
  "geometry": {"coordinates":[-65.46231999999999,-29.00592],"type":"Point"}
}