{
  "type": "Feature",
  "properties": {
    "gn:admin1_code":"2.0",
    "gn:admin2_code":"10014.0",
    "gn:asciiname":"Yerba Buena",
    "gn:country_code":"AR",
    "gn:dem":640,
    "gn:feature_class":"P",
    "gn:feature_code":"PPL",
    "gn:name":"Yerba Buena",
    "gn:population":0,
    "gn:timezone":"America/Argentina/Catamarca",
    "iso:country":"AR",
    "wof:name":"Yerba Buena",
    "wof:placetype":"locality"
},
  "geometry": {"coordinates":[-65.46231999999999,-29.00592],"type":"Point"}
}