{
  "type": "Feature",
  "properties": {
    "gn:admin1_code":"05",
    "gn:admin2_code":"14168.0",
    "gn:asciiname":"Alto Fresco",
    "gn:country_code":"AR",
    "gn:dem":978,
    "gn:feature_class":"P",
    "gn:feature_code":"PPL",
    "gn:name":"Alto Fresco",
    "gn:population":0,
    "gn:timezone":"America/Argentina/Cordoba",
    "iso:country":"AR",
    "wof:name":"Alto Fresco",
    "wof:placetype":"locality"
},
  "geometry": {"coordinates":[-64.30549999999999,-30.91632],"type":"Point"}
}