{
  "type": "Feature",
  "properties": {
    "gn:admin1_code":"20.0",
    "gn:admin2_code":"78014.0",
    "gn:asciiname":"Koluel Kayke",
    "gn:country_code":"AR",
    "gn:dem":307,
    "gn:feature_class":"P",
    "gn:feature_code":"PPL",
    "gn:name":"Koluel Kayke",
    "gn:population":0,
    "gn:timezone":"America/Argentina/Rio_Gallegos",
    "iso:country":"AR",
    "name:ceb_x_preferred":[
        "Koluel Kayke"
    ],
    "name:ita_x_preferred":[
        "Koluel Kayke"
    ],
    "name:spa_x_preferred":[
        "Koluel Kayke"
    ],
    "name:swe_x_preferred":[
        "Koluel Kayke"
    ],
    "name:und_x_variant":[
        "Kaluel Kaike",
        "Kohi el Kayke",
        "Koluel Kayke"
    ],
    "wof:name":"Koluel Kayke",
    "wof:placetype":"locality"
},
  "geometry": {"coordinates":[-68.22296,-46.71558],"type":"Point"}
}