{
  "type": "Feature",
  "properties": {
    "gn:admin1_code":"4.0",
    "gn:admin2_code":"26084.0",
    "gn:asciiname":"Estancia Valle Huemules",
    "gn:country_code":"AR",
    "gn:dem":547,
    "gn:feature_class":"P",
    "gn:feature_code":"PPL",
    "gn:name":"Estancia Valle Huemules",
    "gn:population":0,
    "gn:timezone":"America/Argentina/Catamarca",
    "iso:country":"AR",
    "name:und_x_variant":[
        "Casa Koslowsky",
        "Estancia Koslowsky",
        "Estancia Valle Huemules"
    ],
    "wof:name":"Estancia Valle Huemules",
    "wof:placetype":"locality"
},
  "geometry": {"coordinates":[-71.52025999999999,-45.95374],"type":"Point"}
}