{
  "type": "Feature",
  "properties": {
    "iso:country":"AR",
    "name:cat_x_preferred":[
        "Ballesteros"
    ],
    "name:ceb_x_preferred":[
        "Ballesteros"
    ],
    "name:deu_x_preferred":[
        "Ballesteros"
    ],
    "name:eng_x_preferred":[
        "Ballesteros"
    ],
    "name:fra_x_preferred":[
        "Ballesteros"
    ],
    "name:ita_x_preferred":[
        "Ballesteros"
    ],
    "name:nld_x_preferred":[
        "Ballesteros"
    ],
    "name:por_x_preferred":[
        "Ballesteros"
    ],
    "name:rus_x_preferred":[
        "\u0411\u0430\u043b\u044c\u0435\u0441\u0442\u0435\u0440\u043e\u0441"
    ],
    "name:spa_x_preferred":[
        "Ballesteros"
    ],
    "name:swe_x_preferred":[
        "Ballesteros"
    ],
    "name:ukr_x_preferred":[
        "\u0411\u0430\u043b\u044c\u0454\u0441\u0442\u0435\u0440\u043e\u0441"
    ],
    "name:war_x_preferred":[
        "Ballesteros"
    ],
    "qs:gn_country":"AR",
    "qs:gn_fcode":"PPL",
    "qs:gn_pop":0,
    "qs:name":"Ballesteros",
    "qs:name_adm0":"Argentina",
    "qs:name_adm1":"C\u00f3rdoba",
    "qs:photos":0,
    "qs:photos_1k":0,
    "qs:photos_9k":1,
    "qs:photos_9r":1,
    "qs:photos_all":15,
    "qs:photos_sr":0,
    "qs:placetype":"Town",
    "qs:pop_sr":"7",
    "qs:woe_adm0":23424747,
    "wd:wordcount":22,
    "wof:name":"Ballesteros",
    "wof:placetype":"locality"
},
  "geometry": {"coordinates":[-62.98302,-32.54534],"type":"Point"}
}