{
  "type": "Feature",
  "properties": {
    "gn:admin1_code":"2.0",
    "gn:admin2_code":"10084.0",
    "gn:asciiname":"Sijan",
    "gn:country_code":"AR",
    "gn:dem":953,
    "gn:feature_class":"P",
    "gn:feature_code":"PPL",
    "gn:name":"Sij\u00e1n",
    "gn:population":0,
    "gn:timezone":"America/Argentina/Catamarca",
    "iso:country":"AR",
    "name:ceb_x_preferred":[
        "Sij\u00e1n"
    ],
    "name:spa_x_preferred":[
        "Sij\u00e1n"
    ],
    "name:swe_x_preferred":[
        "Sij\u00e1n"
    ],
    "name:und_x_variant":[
        "Sij\u00e1n"
    ],
    "wof:name":"Sijan",
    "wof:placetype":"locality"
},
  "geometry": {"coordinates":[-66.22454,-28.26185],"type":"Point"}
}