{
  "type": "Feature",
  "properties": {
    "gn:admin1_code":"22.0",
    "gn:admin2_code":"86084.0",
    "gn:asciiname":"Guampacha",
    "gn:country_code":"AR",
    "gn:dem":467,
    "gn:feature_class":"P",
    "gn:feature_code":"PPL",
    "gn:name":"Guampacha",
    "gn:population":0,
    "gn:timezone":"America/Argentina/Cordoba",
    "iso:country":"AR",
    "wof:name":"Guampacha",
    "wof:placetype":"locality"
},
  "geometry": {"coordinates":[-64.79035,-28.01248],"type":"Point"}
}