{
  "type": "Feature",
  "properties": {
    "gn:admin1_code":"21.0",
    "gn:admin2_code":"82007.0",
    "gn:asciiname":"Iturraspe",
    "gn:country_code":"AR",
    "gn:dem":109,
    "gn:feature_class":"P",
    "gn:feature_code":"PPL",
    "gn:name":"Iturraspe",
    "gn:population":0,
    "gn:timezone":"America/Argentina/Cordoba",
    "iso:country":"AR",
    "wof:name":"Iturraspe",
    "wof:placetype":"locality"
},
  "geometry": {"coordinates":[-61.78729000000001,-32.42326],"type":"Point"}
}