{
  "type": "Feature",
  "properties": {
    "gn:admin1_code":"01",
    "gn:admin2_code":"6056.0",
    "gn:asciiname":"Cabildo",
    "gn:country_code":"AR",
    "gn:dem":158,
    "gn:feature_class":"P",
    "gn:feature_code":"PPL",
    "gn:name":"Cabildo",
    "gn:population":0,
    "gn:timezone":"America/Argentina/Buenos_Aires",
    "iso:country":"AR",
    "name:cat_x_preferred":[
        "Cabildo"
    ],
    "name:deu_x_preferred":[
        "Cabildo"
    ],
    "name:fra_x_preferred":[
        "Cabildo"
    ],
    "name:ita_x_preferred":[
        "Cabildo"
    ],
    "name:por_x_preferred":[
        "Cabildo"
    ],
    "name:rus_x_preferred":[
        "\u041a\u0430\u0431\u0438\u043b\u044c\u0434\u043e"
    ],
    "name:spa_x_preferred":[
        "Cabildo"
    ],
    "name:und_x_variant":[
        "Colonia Cabildo",
        "Cabildo"
    ],
    "wof:name":"Cabildo",
    "wof:placetype":"locality"
},
  "geometry": {"coordinates":[-61.89541,-38.48421],"type":"Point"}
}