{
  "type": "Feature",
  "properties": {
    "gn:admin1_code":"19.0",
    "gn:admin2_code":"74014.0",
    "gn:asciiname":"La Pampa Grande",
    "gn:country_code":"AR",
    "gn:dem":620,
    "gn:feature_class":"P",
    "gn:feature_code":"PPL",
    "gn:name":"La Pampa Grande",
    "gn:population":0,
    "gn:timezone":"America/Argentina/San_Luis",
    "iso:country":"AR",
    "wof:name":"La Pampa Grande",
    "wof:placetype":"locality"
},
  "geometry": {"coordinates":[-66.30678,-32.37323],"type":"Point"}
}