{
  "type": "Feature",
  "properties": {
    "gn:country":"AR",
    "gn:fcode":"PPL",
    "gn:pop":3046,
    "iso:country":"AR",
    "name:deu_x_preferred":[
        "Toledo"
    ],
    "name:eng_x_preferred":[
        "Toledo"
    ],
    "name:fra_x_preferred":[
        "Toledo"
    ],
    "name:nld_x_preferred":[
        "Toledo"
    ],
    "name:spa_x_preferred":[
        "Toledo"
    ],
    "name:ukr_x_preferred":[
        "\u0422\u043e\u043b\u0435\u0434\u043e"
    ],
    "qs:name":"Toledo",
    "qs:photos_9r":0,
    "qs:photos_sr":0,
    "qs:pop_sr":"4",
    "wd:wordcount":149,
    "wof:name":"Toledo",
    "wof:placetype":"locality",
    "wof:population":3046
},
  "geometry": {"coordinates":[-64.00946999999999,-31.55574],"type":"Point"}
}