{
  "type": "Feature",
  "properties": {
    "gn:country":"AR",
    "gn:fcode":"PPL",
    "gn:population":3046,
    "iso:country":"AR",
    "name:ara_x_preferred":[
        "\u062a\u0648\u0644\u064a\u062f\u0648"
    ],
    "name:bre_x_preferred":[
        "Toledo"
    ],
    "name:bul_x_preferred":[
        "\u0422\u043e\u043b\u0435\u0434\u043e"
    ],
    "name:cat_x_preferred":[
        "Toledo"
    ],
    "name:ceb_x_preferred":[
        "Toledo"
    ],
    "name:ces_x_preferred":[
        "Toledo"
    ],
    "name:dan_x_preferred":[
        "Toledo"
    ],
    "name:deu_x_preferred":[
        "Toledo"
    ],
    "name:eng_x_preferred":[
        "Toledo"
    ],
    "name:epo_x_preferred":[
        "Toledo"
    ],
    "name:est_x_preferred":[
        "Toledo"
    ],
    "name:fas_x_preferred":[
        "\u062a\u0648\u0644\u062f\u0648"
    ],
    "name:fin_x_preferred":[
        "Toledo"
    ],
    "name:fra_x_preferred":[
        "Toledo"
    ],
    "name:fry_x_preferred":[
        "Toledo"
    ],
    "name:glg_x_preferred":[
        "Toledo"
    ],
    "name:heb_x_preferred":[
        "\u05d8\u05d5\u05dc\u05d3\u05d5"
    ],
    "name:hrv_x_preferred":[
        "Toledo"
    ],
    "name:hun_x_preferred":[
        "Toledo"
    ],
    "name:ilo_x_preferred":[
        "Toledo"
    ],
    "name:ina_x_preferred":[
        "Toledo"
    ],
    "name:ind_x_preferred":[
        "Toledo"
    ],
    "name:ita_x_preferred":[
        "Toledo"
    ],
    "name:jpn_x_preferred":[
        "\u30c8\u30ec\u30c9"
    ],
    "name:kor_x_preferred":[
        "\ud1a8\ub808\ub3c4"
    ],
    "name:ltz_x_preferred":[
        "Toledo"
    ],
    "name:nds_x_preferred":[
        "Toledo"
    ],
    "name:nld_x_preferred":[
        "Toledo"
    ],
    "name:nor_x_preferred":[
        "Toledo"
    ],
    "name:pol_x_preferred":[
        "Toledo"
    ],
    "name:por_x_preferred":[
        "Toledo"
    ],
    "name:ron_x_preferred":[
        "Toledo"
    ],
    "name:rus_x_preferred":[
        "\u0422\u043e\u043b\u0435\u0434\u043e"
    ],
    "name:sco_x_preferred":[
        "Toledo"
    ],
    "name:slk_x_preferred":[
        "Toledo"
    ],
    "name:slv_x_preferred":[
        "Toledo"
    ],
    "name:spa_x_preferred":[
        "Toledo"
    ],
    "name:srp_x_preferred":[
        "\u0422\u043e\u043b\u0435\u0434\u043e"
    ],
    "name:swe_x_preferred":[
        "Toledo"
    ],
    "name:tgl_x_preferred":[
        "Toledo"
    ],
    "name:tur_x_preferred":[
        "Toledo"
    ],
    "name:ukr_x_preferred":[
        "\u0422\u043e\u043b\u0435\u0434\u043e"
    ],
    "name:vep_x_preferred":[
        "Toledo"
    ],
    "name:vie_x_preferred":[
        "Toledo"
    ],
    "name:vol_x_preferred":[
        "Toledo"
    ],
    "name:war_x_preferred":[
        "Toledo"
    ],
    "name:zho_x_preferred":[
        "\u6258\u840a\u591a"
    ],
    "qs:name":"Toledo",
    "qs:photos_9r":0,
    "qs:photos_sr":0,
    "qs:pop_sr":"4",
    "wd:wordcount":149,
    "wof:name":"Toledo",
    "wof:placetype":"locality",
    "wof:population":3046
},
  "geometry": {"coordinates":[-64.00946999999999,-31.55574],"type":"Point"}
}