{
  "type": "Feature",
  "properties": {
    "gn:admin1_code":"17",
    "gn:admin2_code":"66112.0",
    "gn:asciiname":"Conchas",
    "gn:country_code":"AR",
    "gn:dem":855,
    "gn:feature_class":"P",
    "gn:feature_code":"PPL",
    "gn:name":"Conchas",
    "gn:population":0,
    "gn:timezone":"America/Argentina/Salta",
    "iso:country":"AR",
    "wof:name":"Conchas",
    "wof:placetype":"locality"
},
  "geometry": {"coordinates":[-64.96410999999999,-25.47741],"type":"Point"}
}