{
  "type": "Feature",
  "properties": {
    "gn:admin1_code":"19.0",
    "gn:admin2_code":"74056.0",
    "gn:asciiname":"Suyuque Viejo",
    "gn:country_code":"AR",
    "gn:dem":1120,
    "gn:feature_class":"P",
    "gn:feature_code":"PPL",
    "gn:name":"Suyuque Viejo",
    "gn:population":0,
    "gn:timezone":"America/Argentina/San_Luis",
    "iso:country":"AR",
    "name:und_x_variant":[
        "Suyuque",
        "Suyuque Viejo"
    ],
    "wof:name":"Suyuque Viejo",
    "wof:placetype":"locality"
},
  "geometry": {"coordinates":[-66.26375999999999,-33.16104],"type":"Point"}
}