{
  "type": "Feature",
  "properties": {
    "gn:admin1_code":"22",
    "gn:admin2_code":"86035.0",
    "gn:asciiname":"El Aibe",
    "gn:country_code":"AR",
    "gn:dem":182,
    "gn:feature_class":"P",
    "gn:feature_code":"PPL",
    "gn:name":"El Aibe",
    "gn:population":0,
    "gn:timezone":"America/Argentina/Cordoba",
    "iso:country":"AR",
    "name:und_x_variant":[
        "Aive",
        "El Aibe"
    ],
    "wof:name":"El Aibe",
    "wof:placetype":"locality"
},
  "geometry": {"coordinates":[-64.25753,-27.5884],"type":"Point"}
}