{
  "type": "Feature",
  "properties": {
    "gn:admin1_code":"4.0",
    "gn:admin2_code":"26028.0",
    "gn:asciiname":"Malaspina",
    "gn:country_code":"AR",
    "gn:dem":512,
    "gn:feature_class":"P",
    "gn:feature_code":"PPL",
    "gn:name":"Malaspina",
    "gn:population":0,
    "gn:timezone":"America/Argentina/Catamarca",
    "iso:country":"AR",
    "name:ceb_x_preferred":[
        "Malaspina"
    ],
    "name:deu_x_preferred":[
        "Malaspina"
    ],
    "name:fra_x_preferred":[
        "Malaspina"
    ],
    "name:ita_x_preferred":[
        "Malaspina"
    ],
    "wof:name":"Malaspina",
    "wof:placetype":"locality"
},
  "geometry": {"coordinates":[-66.92433,-44.93903],"type":"Point"}
}