{
  "type": "Feature",
  "properties": {
    "iso:country":"AR",
    "qs:gn_pop":0,
    "qs:name":"Cumel\u00e9n",
    "qs:name_adm0":"Argentina",
    "qs:name_adm1":"Neuqu\u00e9n",
    "qs:photos":87,
    "qs:photos_1k":18,
    "qs:photos_9k":1,
    "qs:photos_9r":3,
    "qs:photos_all":87,
    "qs:photos_sr":3,
    "qs:placetype":"Town",
    "qs:pop_sr":"0",
    "qs:woe_adm0":23424747,
    "wof:name":"Cumel\u00e9n",
    "wof:placetype":"locality"
},
  "geometry": {"coordinates":[-71.59172,-40.803917],"type":"Point"}
}