{
  "type": "Feature",
  "properties": {
    "gn:admin1_code":"1.0",
    "gn:admin2_code":"6462.0",
    "gn:asciiname":"Vedia",
    "gn:country_code":"AR",
    "gn:dem":94,
    "gn:feature_class":"P",
    "gn:feature_code":"PPLA2",
    "gn:name":"Vedia",
    "gn:population":0,
    "gn:timezone":"America/Argentina/Buenos_Aires",
    "iso:country":"AR",
    "name:fas_x_preferred":[
        "\u0648\u062f\u06cc\u0627"
    ],
    "name:nld_x_preferred":[
        "Vedia"
    ],
    "name:spa_x_preferred":[
        "Vedia"
    ],
    "wof:name":"Vedia",
    "wof:placetype":"locality"
},
  "geometry": {"coordinates":[-61.54138,-34.49558],"type":"Point"}
}