{
  "type": "Feature",
  "properties": {
    "gn:admin1_code":"01",
    "gn:admin2_code":"6826.0",
    "gn:asciiname":"Colonia Martin Fierro",
    "gn:country_code":"AR",
    "gn:dem":94,
    "gn:feature_class":"P",
    "gn:feature_code":"PPL",
    "gn:name":"Colonia Mart\u00edn Fierro",
    "gn:population":0,
    "gn:timezone":"America/Argentina/Buenos_Aires",
    "iso:country":"AR",
    "wof:name":"Colonia Martin Fierro",
    "wof:placetype":"locality"
},
  "geometry": {"coordinates":[-62.80365,-35.74223],"type":"Point"}
}