{
  "type": "Feature",
  "properties": {
    "iso:country":"AR",
    "name:ceb_x_preferred":[
        "Plottier"
    ],
    "name:deu_x_preferred":[
        "Plottier"
    ],
    "name:eng_x_preferred":[
        "Plottier"
    ],
    "name:fas_x_preferred":[
        "\u067e\u0644\u0648\u062a\u06cc\u0647"
    ],
    "name:fra_x_preferred":[
        "Plottier"
    ],
    "name:hye_x_preferred":[
        "\u054a\u056c\u0578\u057f\u056b\u0565\u0580"
    ],
    "name:nld_x_preferred":[
        "Plottier"
    ],
    "name:oci_x_preferred":[
        "Plottier"
    ],
    "name:pol_x_preferred":[
        "Plottier"
    ],
    "name:por_x_preferred":[
        "Plottier"
    ],
    "name:ron_x_preferred":[
        "Plottier"
    ],
    "name:rus_x_preferred":[
        "\u041f\u043b\u043e\u0442\u0442\u044c\u0435\u0440"
    ],
    "name:spa_x_preferred":[
        "Plottier"
    ],
    "name:swe_x_preferred":[
        "Plottier"
    ],
    "name:ukr_x_preferred":[
        "\u041f\u043b\u043e\u0442\u0442'\u0454\u0440"
    ],
    "name:zho_x_preferred":[
        "\u666e\u6d1b\u8482\u57c3"
    ],
    "qs:gn_country":"AR",
    "qs:gn_fcode":"PPL",
    "qs:gn_pop":25186,
    "qs:name":"Plottier",
    "qs:name_adm0":"Argentina",
    "qs:name_adm1":"Neuqu\u00e9n",
    "qs:photos":378,
    "qs:photos_1k":77,
    "qs:photos_9k":2,
    "qs:photos_9r":5,
    "qs:photos_all":378,
    "qs:photos_sr":6,
    "qs:placetype":"Town",
    "qs:pop_sr":"7",
    "qs:woe_adm0":23424747,
    "wd:wordcount":243,
    "wof:name":"Plottier",
    "wof:placetype":"locality",
    "wof:population":25186
},
  "geometry": {"coordinates":[-68.23333,-38.96667],"type":"Point"}
}