{
  "type": "Feature",
  "properties": {
    "gn:admin1_code":"01",
    "gn:admin2_code":"6147.0",
    "gn:asciiname":"Centenario",
    "gn:country_code":"AR",
    "gn:dem":85,
    "gn:feature_class":"P",
    "gn:feature_code":"PPL",
    "gn:name":"Centenario",
    "gn:population":0,
    "gn:timezone":"America/Argentina/Buenos_Aires",
    "iso:country":"AR",
    "name:cat_x_preferred":[
        "Centenario"
    ],
    "name:glg_x_preferred":[
        "Centenario"
    ],
    "name:rus_x_preferred":[
        "\u0421\u0435\u043d\u0442\u0435\u043d\u0430\u0440\u0438\u043e"
    ],
    "name:spa_x_preferred":[
        "Centenario"
    ],
    "wof:name":"Centenario",
    "wof:placetype":"locality"
},
  "geometry": {"coordinates":[-61.43333000000001,-35.83333],"type":"Point"}
}