{
  "type": "Feature",
  "properties": {
    "gn:admin1_code":"01",
    "gn:admin2_code":"6147.0",
    "gn:asciiname":"Centenario",
    "gn:country_code":"AR",
    "gn:dem":85,
    "gn:feature_class":"P",
    "gn:feature_code":"PPL",
    "gn:name":"Centenario",
    "gn:population":0,
    "gn:timezone":"America/Argentina/Buenos_Aires",
    "iso:country":"AR",
    "wof:name":"Centenario",
    "wof:placetype":"locality"
},
  "geometry": {"coordinates":[-61.43333000000001,-35.83333],"type":"Point"}
}