{
  "type": "Feature",
  "properties": {
    "gn:admin1_code":"14.0",
    "gn:admin2_code":"54119.0",
    "gn:asciiname":"Barra Bonita",
    "gn:country_code":"AR",
    "gn:dem":117,
    "gn:feature_class":"P",
    "gn:feature_code":"PPL",
    "gn:name":"Barra Bonita",
    "gn:population":0,
    "gn:timezone":"America/Argentina/Cordoba",
    "iso:country":"AR",
    "name:ceb_x_preferred":[
        "Barra Bonita"
    ],
    "name:deu_x_preferred":[
        "Barra Bonita"
    ],
    "name:fra_x_preferred":[
        "Barra Bonita"
    ],
    "name:ita_x_preferred":[
        "Barra Bonita"
    ],
    "name:mlg_x_preferred":[
        "Barra Bonita"
    ],
    "name:nld_x_preferred":[
        "Barra Bonita"
    ],
    "name:nor_x_preferred":[
        "Barra Bonita"
    ],
    "name:por_x_preferred":[
        "Barra Bonita"
    ],
    "name:ron_x_preferred":[
        "Barra Bonita"
    ],
    "name:rus_x_preferred":[
        "\u0411\u0430\u0440\u0440\u0430-\u0411\u043e\u043d\u0438\u0442\u0430"
    ],
    "name:sco_x_preferred":[
        "Barra Bonita"
    ],
    "name:spa_x_preferred":[
        "Barra Bonita"
    ],
    "name:swe_x_preferred":[
        "Barra Bonita"
    ],
    "name:vol_x_preferred":[
        "Barra Bonita"
    ],
    "name:war_x_preferred":[
        "Barra Bonita"
    ],
    "wof:name":"Barra Bonita",
    "wof:placetype":"locality"
},
  "geometry": {"coordinates":[-54.84347,-27.59893],"type":"Point"}
}