{
  "type": "Feature",
  "properties": {
    "gn:admin1_code":"14.0",
    "gn:admin2_code":"54119.0",
    "gn:asciiname":"Barra Bonita",
    "gn:country_code":"AR",
    "gn:dem":117,
    "gn:feature_class":"P",
    "gn:feature_code":"PPL",
    "gn:name":"Barra Bonita",
    "gn:population":0,
    "gn:timezone":"America/Argentina/Cordoba",
    "iso:country":"AR",
    "wof:name":"Barra Bonita",
    "wof:placetype":"locality"
},
  "geometry": {"coordinates":[-54.84347,-27.59893],"type":"Point"}
}