{
  "type": "Feature",
  "properties": {
    "iso:country":"AR",
    "name:ceb_x_preferred":[
        "El Corcovado"
    ],
    "name:eng_x_preferred":[
        "Corcovado"
    ],
    "name:fra_x_preferred":[
        "Corcovado"
    ],
    "name:ita_x_preferred":[
        "Corcovado"
    ],
    "name:nld_x_preferred":[
        "Corcovado"
    ],
    "name:por_x_preferred":[
        "Corcovado"
    ],
    "name:spa_x_preferred":[
        "Corcovado"
    ],
    "name:swe_x_preferred":[
        "El Corcovado"
    ],
    "qs:gn_country":"AR",
    "qs:gn_fcode":"PPL",
    "qs:gn_pop":0,
    "qs:name":"Corcovado",
    "qs:name_adm0":"Argentina",
    "qs:name_adm1":"Chubut",
    "qs:photos":13,
    "qs:photos_1k":3,
    "qs:photos_9k":1,
    "qs:photos_9r":1,
    "qs:photos_all":13,
    "qs:photos_sr":1,
    "qs:placetype":"Town",
    "qs:pop_sr":"0",
    "qs:woe_adm0":23424747,
    "wd:wordcount":34,
    "wof:name":"Corcovado",
    "wof:placetype":"locality"
},
  "geometry": {"coordinates":[-71.59999999999999,-43.53333],"type":"Point"}
}