{
  "type": "Feature",
  "properties": {
    "gn:admin1_code":"5.0",
    "gn:admin2_code":"14049.0",
    "gn:asciiname":"Surisaltana",
    "gn:country_code":"AR",
    "gn:dem":920,
    "gn:feature_class":"P",
    "gn:feature_code":"PPL",
    "gn:name":"Surisaltana",
    "gn:population":0,
    "gn:timezone":"America/Argentina/Cordoba",
    "iso:country":"AR",
    "name:und_x_variant":[
        "Surisultana",
        "Surisaltana"
    ],
    "wof:name":"Surisaltana",
    "wof:placetype":"locality"
},
  "geometry": {"coordinates":[-64.46205,-30.51918],"type":"Point"}
}