{
  "type": "Feature",
  "properties": {
    "iso:country":"AR",
    "name:bar_x_preferred":[
        "San Carlos"
    ],
    "name:bre_x_preferred":[
        "San Carlos"
    ],
    "name:cat_x_preferred":[
        "San Carlos"
    ],
    "name:ceb_x_preferred":[
        "San Carlos"
    ],
    "name:deu_x_preferred":[
        "San Carlos"
    ],
    "name:eng_x_preferred":[
        "San Carlos Sud"
    ],
    "name:epo_x_preferred":[
        "San Carlos"
    ],
    "name:est_x_preferred":[
        "San Carlos"
    ],
    "name:fin_x_preferred":[
        "San Carlos"
    ],
    "name:fra_x_preferred":[
        "San Carlos"
    ],
    "name:heb_x_preferred":[
        "\u05e1\u05df \u05e7\u05e8\u05dc\u05d5\u05e1"
    ],
    "name:hun_x_preferred":[
        "San Carlos"
    ],
    "name:ilo_x_preferred":[
        "San Carlos"
    ],
    "name:ita_x_preferred":[
        "San Carlos"
    ],
    "name:jpn_x_preferred":[
        "\u30b5\u30f3\u30fb\u30ab\u30eb\u30ed\u30b9"
    ],
    "name:kat_x_preferred":[
        "\u10e1\u10d0\u10dc-\u10d9\u10d0\u10e0\u10da\u10dd\u10e1\u10d8"
    ],
    "name:kor_x_preferred":[
        "\uc0b0\uce74\ub97c\ub85c\uc2a4"
    ],
    "name:lit_x_preferred":[
        "San Karlosas"
    ],
    "name:nds_x_preferred":[
        "San Carlos"
    ],
    "name:nld_x_preferred":[
        "San Carlos Sud"
    ],
    "name:nld_x_variant":[
        "San Carlos"
    ],
    "name:pol_x_preferred":[
        "San Carlos"
    ],
    "name:por_x_preferred":[
        "San Carlos Sud"
    ],
    "name:por_x_variant":[
        "San Carlos"
    ],
    "name:rus_x_preferred":[
        "\u0421\u0430\u043d-\u041a\u0430\u0440\u043b\u043e\u0441"
    ],
    "name:sco_x_preferred":[
        "San Carlos"
    ],
    "name:slk_x_preferred":[
        "San Carlos"
    ],
    "name:spa_x_preferred":[
        "San Carlos Sud"
    ],
    "name:spa_x_variant":[
        "San Carlos"
    ],
    "name:srp_x_preferred":[
        "\u0421\u0430\u043d \u041a\u0430\u0440\u043b\u043e\u0441"
    ],
    "name:swe_x_preferred":[
        "San Carlos"
    ],
    "name:ukr_x_preferred":[
        "\u0421\u0430\u043d-\u041a\u0430\u0440\u043b\u043e\u0441-\u0421\u0443\u0434"
    ],
    "name:ukr_x_variant":[
        "\u0421\u0430\u043d-\u041a\u0430\u0440\u043b\u043e\u0441"
    ],
    "name:vol_x_preferred":[
        "San Carlos"
    ],
    "name:war_x_preferred":[
        "San Carlos"
    ],
    "name:zho_x_preferred":[
        "\u5723\u5361\u6d1b\u65af"
    ],
    "qs:gn_country":"AR",
    "qs:gn_fcode":"PPL",
    "qs:gn_pop":0,
    "qs:name":"San Carlos",
    "qs:name_adm0":"Argentina",
    "qs:name_adm1":"Santa Fe",
    "qs:photos":16,
    "qs:photos_1k":3,
    "qs:photos_9k":1,
    "qs:photos_9r":1,
    "qs:photos_all":16,
    "qs:photos_sr":1,
    "qs:placetype":"Town",
    "qs:pop_sr":"0",
    "qs:woe_adm0":23424747,
    "wof:name":"San Carlos",
    "wof:placetype":"locality"
},
  "geometry": {"coordinates":[-61.10119,-31.75692],"type":"Point"}
}