{
  "type": "Feature",
  "properties": {
    "iso:country":"AR",
    "name:eng_x_preferred":[
        "San Carlos Sud"
    ],
    "name:nld_x_preferred":[
        "San Carlos Sud"
    ],
    "name:por_x_preferred":[
        "San Carlos Sud"
    ],
    "name:spa_x_preferred":[
        "San Carlos Sud"
    ],
    "name:ukr_x_preferred":[
        "\u0421\u0430\u043d-\u041a\u0430\u0440\u043b\u043e\u0441-\u0421\u0443\u0434"
    ],
    "name:unk_x_variant":[
        "San Carlos Sud"
    ],
    "qs:gn_country":"AR",
    "qs:gn_fcode":"PPL",
    "qs:gn_pop":0,
    "qs:name":"San Carlos",
    "qs:name_adm0":"Argentina",
    "qs:name_adm1":"Santa Fe",
    "qs:photos":16,
    "qs:photos_1k":3,
    "qs:photos_9k":1,
    "qs:photos_9r":1,
    "qs:photos_all":16,
    "qs:photos_sr":1,
    "qs:placetype":"Town",
    "qs:pop_sr":"0",
    "qs:woe_adm0":23424747,
    "wof:name":"San Carlos",
    "wof:placetype":"locality"
},
  "geometry": {"coordinates":[-61.10119,-31.75692],"type":"Point"}
}