{
  "type": "Feature",
  "properties": {
    "gn:admin1_code":"22.0",
    "gn:admin2_code":"86070.0",
    "gn:asciiname":"Huritu Huasi",
    "gn:country_code":"AR",
    "gn:dem":145,
    "gn:feature_class":"P",
    "gn:feature_code":"PPL",
    "gn:name":"Hurit\u00fa Huasi",
    "gn:population":0,
    "gn:timezone":"America/Argentina/Cordoba",
    "iso:country":"AR",
    "wof:name":"Huritu Huasi",
    "wof:placetype":"locality"
},
  "geometry": {"coordinates":[-63.6061,-27.82628],"type":"Point"}
}