{
  "type": "Feature",
  "properties": {
    "gn:admin1_code":"01",
    "gn:admin2_code":"6182.0",
    "gn:asciiname":"Calderon",
    "gn:country_code":"AR",
    "gn:dem":82,
    "gn:feature_class":"P",
    "gn:feature_code":"PPL",
    "gn:name":"Calder\u00f3n",
    "gn:population":0,
    "gn:timezone":"America/Argentina/Buenos_Aires",
    "iso:country":"AR",
    "wof:name":"Calderon",
    "wof:placetype":"locality"
},
  "geometry": {"coordinates":[-62.05491,-38.72271],"type":"Point"}
}