{
  "type": "Feature",
  "properties": {
    "gn:admin1_code":"8.0",
    "gn:admin2_code":"30098.0",
    "gn:asciiname":"Puerto Campichuelo",
    "gn:country_code":"AR",
    "gn:dem":4,
    "gn:feature_class":"P",
    "gn:feature_code":"PPL",
    "gn:name":"Puerto Campichuelo",
    "gn:population":0,
    "gn:timezone":"America/Argentina/Cordoba",
    "iso:country":"AR",
    "wof:name":"Puerto Campichuelo",
    "wof:placetype":"locality"
},
  "geometry": {"coordinates":[-58.18526,-32.69194],"type":"Point"}
}