{
  "type": "Feature",
  "properties": {
    "iso:country":"AR",
    "name:ara_x_preferred":[
        "\u0628\u0631\u0627\u063a\u062f\u0648"
    ],
    "name:azb_x_preferred":[
        "\u0628\u0631\u0627\u0642\u0627\u062f\u0648"
    ],
    "name:deu_x_preferred":[
        "Bragado"
    ],
    "name:eng_x_preferred":[
        "Bragado"
    ],
    "name:fas_x_preferred":[
        "\u0628\u0631\u0627\u06af\u0627\u062f\u0648"
    ],
    "name:fra_x_preferred":[
        "Bragado"
    ],
    "name:ina_x_preferred":[
        "Bragado"
    ],
    "name:ita_x_preferred":[
        "Bragado"
    ],
    "name:nld_x_preferred":[
        "Bragado"
    ],
    "name:por_x_preferred":[
        "Bragado"
    ],
    "name:rus_x_preferred":[
        "\u0411\u0440\u0430\u0433\u0430\u0434\u043e"
    ],
    "name:sco_x_preferred":[
        "Bragado"
    ],
    "name:spa_x_preferred":[
        "Bragado"
    ],
    "name:ukr_x_preferred":[
        "\u0411\u0440\u0430\u0433\u0430\u0434\u043e"
    ],
    "name:zho_x_preferred":[
        "\u5e03\u62c9\u52a0\u591a"
    ],
    "qs:gn_country":"AR",
    "qs:gn_fcode":"PPL",
    "qs:gn_pop":0,
    "qs:name":"Bragado",
    "qs:name_adm0":"Argentina",
    "qs:name_adm1":"Buenos Aires",
    "qs:photos":244,
    "qs:photos_1k":49,
    "qs:photos_9k":1,
    "qs:photos_9r":4,
    "qs:photos_all":244,
    "qs:photos_sr":4,
    "qs:placetype":"Town",
    "qs:pop_sr":"7",
    "qs:woe_adm0":23424747,
    "wd:elevation":50.0,
    "wd:wordcount":258,
    "wof:name":"Bragado",
    "wof:placetype":"locality"
},
  "geometry": {"coordinates":[-60.48966,-35.11912],"type":"Point"}
}