{
  "type": "Feature",
  "properties": {
    "gn:admin1_code":"21",
    "gn:admin2_code":"82042.0",
    "gn:asciiname":"El Cantor",
    "gn:country_code":"AR",
    "gn:dem":116,
    "gn:feature_class":"P",
    "gn:feature_code":"PPL",
    "gn:name":"El Cantor",
    "gn:population":0,
    "gn:timezone":"America/Argentina/Cordoba",
    "iso:country":"AR",
    "wof:name":"El Cantor",
    "wof:placetype":"locality"
},
  "geometry": {"coordinates":[-62.15,-33.51667],"type":"Point"}
}