{
  "type": "Feature",
  "properties": {
    "gn:admin1_code":"8.0",
    "gn:admin2_code":"30098.0",
    "gn:asciiname":"Colonia El Sauce",
    "gn:country_code":"AR",
    "gn:dem":36,
    "gn:feature_class":"P",
    "gn:feature_code":"PPL",
    "gn:name":"Colonia El Sauce",
    "gn:population":0,
    "gn:timezone":"America/Argentina/Cordoba",
    "iso:country":"AR",
    "wof:name":"Colonia El Sauce",
    "wof:placetype":"locality"
},
  "geometry": {"coordinates":[-58.42663,-32.61536],"type":"Point"}
}