{
  "type": "Feature",
  "properties": {
    "gn:admin1_code":"01",
    "gn:admin2_code":"6553.0",
    "gn:asciiname":"Balneario Sauce Grande",
    "gn:country_code":"AR",
    "gn:dem":18,
    "gn:feature_class":"P",
    "gn:feature_code":"PPL",
    "gn:name":"Balneario Sauce Grande",
    "gn:population":0,
    "gn:timezone":"America/Argentina/Buenos_Aires",
    "iso:country":"AR",
    "wof:name":"Balneario Sauce Grande",
    "wof:placetype":"locality"
},
  "geometry": {"coordinates":[-61.20833,-38.99272],"type":"Point"}
}