{
  "type": "Feature",
  "properties": {
    "gn:admin1_code":"6.0",
    "gn:admin2_code":"18021.0",
    "gn:asciiname":"Laguna Brava",
    "gn:country_code":"AR",
    "gn:dem":66,
    "gn:feature_class":"P",
    "gn:feature_code":"PPL",
    "gn:name":"Laguna Brava",
    "gn:population":0,
    "gn:timezone":"America/Argentina/Cordoba",
    "iso:country":"AR",
    "name:ceb_x_preferred":[
        "Laguna Yolnajab"
    ],
    "name:lit_x_preferred":[
        "Jolnabachas"
    ],
    "name:mkd_x_preferred":[
        "\u041b\u0430\u0433\u0443\u043d\u0430 \u0411\u0440\u0430\u0432\u0430"
    ],
    "name:nld_x_preferred":[
        "Yolnabaj"
    ],
    "name:por_x_preferred":[
        "Lago Mirabel"
    ],
    "name:spa_x_preferred":[
        "Laguna Brava"
    ],
    "name:swe_x_preferred":[
        "Laguna Yolnajab"
    ],
    "wof:name":"Laguna Brava",
    "wof:placetype":"locality"
},
  "geometry": {"coordinates":[-58.71684000000001,-27.49567],"type":"Point"}
}