{
  "type": "Feature",
  "properties": {
    "gn:admin1_code":"18",
    "gn:admin2_code":"70021.0",
    "gn:asciiname":"Los Erizos",
    "gn:country_code":"AR",
    "gn:dem":3183,
    "gn:feature_class":"P",
    "gn:feature_code":"PPL",
    "gn:name":"Los Erizos",
    "gn:population":0,
    "gn:timezone":"America/Argentina/San_Juan",
    "iso:country":"AR",
    "wof:name":"Los Erizos",
    "wof:placetype":"locality"
},
  "geometry": {"coordinates":[-70.29805999999999,-31.69361],"type":"Point"}
}