{
  "type": "Feature",
  "properties": {
    "iso:country":"AR",
    "name:ceb_x_preferred":[
        "Matheu"
    ],
    "name:dut_x_preferred":[
        "Matheu"
    ],
    "name:eng_x_preferred":[
        "Matheu"
    ],
    "name:sco_x_preferred":[
        "Matheu"
    ],
    "name:spa_x_preferred":[
        "Matheu"
    ],
    "name:swe_x_preferred":[
        "Matheu"
    ],
    "name:unk_x_variant":[
        "Mathew"
    ],
    "qs:gn_country":"AR",
    "qs:gn_fcode":"PPL",
    "qs:gn_pop":0,
    "qs:name":"Matheu",
    "qs:name_adm0":"Argentina",
    "qs:name_adm1":"Buenos Aires",
    "qs:photos":285,
    "qs:photos_1k":58,
    "qs:photos_9k":1,
    "qs:photos_9r":4,
    "qs:photos_all":285,
    "qs:photos_sr":5,
    "qs:placetype":"Town",
    "qs:pop_sr":"0",
    "qs:woe_adm0":23424747,
    "wd:wordcount":14,
    "wof:name":"Matheu",
    "wof:placetype":"locality"
},
  "geometry": {"coordinates":[-58.83292,-34.38545],"type":"Point"}
}