{
  "type": "Feature",
  "properties": {
    "gn:admin1_code":"2.0",
    "gn:admin2_code":"10070.0",
    "gn:asciiname":"San Antonio",
    "gn:country_code":"AR",
    "gn:dem":273,
    "gn:feature_class":"P",
    "gn:feature_code":"PPL",
    "gn:name":"San Antonio",
    "gn:population":0,
    "gn:timezone":"America/Argentina/Catamarca",
    "iso:country":"AR",
    "name:heb_x_preferred":[
        "\u05e1\u05df \u05d0\u05e0\u05d8\u05d5\u05e0\u05d9\u05d5"
    ],
    "name:hun_x_preferred":[
        "San Antonio"
    ],
    "name:und_x_variant":[
        "San Antonio de la Paz",
        "San Antonio"
    ],
    "wof:name":"San Antonio",
    "wof:placetype":"locality"
},
  "geometry": {"coordinates":[-65.09744999999999,-28.93313],"type":"Point"}
}