{
  "type": "Feature",
  "properties": {
    "gn:country":"AR",
    "gn:fcode":"PPL",
    "gn:population":1481,
    "iso:country":"AR",
    "name:ceb_x_preferred":[
        "Alta Italia"
    ],
    "name:deu_x_preferred":[
        "Alta Italia"
    ],
    "name:eng_x_preferred":[
        "Alta Italia"
    ],
    "name:fas_x_preferred":[
        "\u0627\u0644\u062a\u0627 \u0627\u06cc\u062a\u0627\u0644\u06cc\u0627"
    ],
    "name:fra_x_preferred":[
        "Alta Italia"
    ],
    "name:nld_x_preferred":[
        "Alta Italia"
    ],
    "name:por_x_preferred":[
        "Alta Italia"
    ],
    "name:spa_x_preferred":[
        "Alta Italia"
    ],
    "name:swe_x_preferred":[
        "Alta Italia"
    ],
    "qs:name":"Alta Italia",
    "qs:photos_9r":0,
    "qs:photos_sr":0,
    "qs:pop_sr":"7",
    "wd:wordcount":43,
    "wof:name":"Alta Italia",
    "wof:placetype":"locality",
    "wof:population":1481
},
  "geometry": {"coordinates":[-64.11496,-35.3335],"type":"Point"}
}