{
  "type": "Feature",
  "properties": {
    "gn:admin1_code":"01",
    "gn:admin2_code":"6469.0",
    "gn:asciiname":"Bayauca",
    "gn:country_code":"AR",
    "gn:dem":84,
    "gn:feature_class":"P",
    "gn:feature_code":"PPL",
    "gn:name":"Bayauca",
    "gn:population":0,
    "gn:timezone":"America/Argentina/Buenos_Aires",
    "iso:country":"AR",
    "wof:name":"Bayauca",
    "wof:placetype":"locality"
},
  "geometry": {"coordinates":[-61.28751,-34.86807],"type":"Point"}
}