{
  "type": "Feature",
  "properties": {
    "gn:admin1_code":"1.0",
    "gn:admin2_code":"6399.0",
    "gn:asciiname":"Laguna Alsina",
    "gn:cc2":"AR",
    "gn:country_code":"AR",
    "gn:dem":118,
    "gn:feature_class":"P",
    "gn:feature_code":"PPL",
    "gn:name":"Laguna Alsina",
    "gn:population":0,
    "gn:timezone":"America/Argentina/Buenos_Aires",
    "iso:country":"AR",
    "name:und_x_variant":[
        "Bonifacio",
        "Laguna Alsina"
    ],
    "wof:name":"Laguna Alsina",
    "wof:placetype":"locality"
},
  "geometry": {"coordinates":[-62.21666999999999,-36.81667],"type":"Point"}
}