{
  "type": "Feature",
  "properties": {
    "gn:admin1_code":"22.0",
    "gn:admin2_code":"86098.0",
    "gn:asciiname":"Vilelas",
    "gn:country_code":"AR",
    "gn:dem":129,
    "gn:feature_class":"P",
    "gn:feature_code":"PPL",
    "gn:name":"Vilelas",
    "gn:population":0,
    "gn:timezone":"America/Argentina/Cordoba",
    "iso:country":"AR",
    "wof:name":"Vilelas",
    "wof:placetype":"locality"
},
  "geometry": {"coordinates":[-62.63333000000001,-27.95],"type":"Point"}
}