{
  "type": "Feature",
  "properties": {
    "gn:admin1_code":"24.0",
    "gn:admin2_code":"90014.0",
    "gn:asciiname":"Ingenio Cruz Alta",
    "gn:country_code":"AR",
    "gn:dem":424,
    "gn:feature_class":"P",
    "gn:feature_code":"PPL",
    "gn:name":"Ingenio Cruz Alta",
    "gn:population":0,
    "gn:timezone":"America/Argentina/Tucuman",
    "iso:country":"AR",
    "wof:name":"Ingenio Cruz Alta",
    "wof:placetype":"locality"
},
  "geometry": {"coordinates":[-65.10166,-26.88664],"type":"Point"}
}