{
  "type": "Feature",
  "properties": {
    "gn:admin1_code":"9.0",
    "gn:admin2_code":"34014.0",
    "gn:asciiname":"Tres Marias",
    "gn:country_code":"AR",
    "gn:dem":61,
    "gn:feature_class":"P",
    "gn:feature_code":"PPL",
    "gn:name":"Tres Mar\u00edas",
    "gn:population":0,
    "gn:timezone":"America/Argentina/Cordoba",
    "iso:country":"AR",
    "wof:name":"Tres Marias",
    "wof:placetype":"locality"
},
  "geometry": {"coordinates":[-58.20142,-26.32374],"type":"Point"}
}