{
  "type": "Feature",
  "properties": {
    "iso:country":"AR",
    "name:ceb_x_preferred":[
        "Colonia Carlos Pellegrini"
    ],
    "name:eng_x_preferred":[
        "Colonia Carlos Pellegrini"
    ],
    "name:nld_x_preferred":[
        "Colonia Carlos Pellegrini"
    ],
    "name:spa_x_preferred":[
        "Colonia Carlos Pellegrini"
    ],
    "name:swe_x_preferred":[
        "Colonia Carlos Pellegrini"
    ],
    "name:und_x_variant":[
        "Carlos Pellegrini"
    ],
    "qs:gn_country":"AR",
    "qs:gn_fcode":"PPL",
    "qs:gn_pop":880,
    "qs:name":"Colonia Carlos Pellegrini",
    "qs:name_adm0":"Argentina",
    "qs:name_adm1":"Corrientes",
    "qs:photos":996,
    "qs:photos_1k":202,
    "qs:photos_9k":4,
    "qs:photos_9r":6,
    "qs:photos_all":996,
    "qs:photos_sr":10,
    "qs:placetype":"Town",
    "qs:pop_sr":"2",
    "qs:woe_adm0":23424747,
    "wd:wordcount":161,
    "wof:name":"Colonia Carlos Pellegrini",
    "wof:placetype":"locality",
    "wof:population":880
},
  "geometry": {"coordinates":[-57.17434,-28.53556],"type":"Point"}
}