{
  "type": "Feature",
  "properties": {
    "gn:admin1_code":"16.0",
    "gn:asciiname":"Puerto Blest",
    "gn:country_code":"AR",
    "gn:dem":769,
    "gn:feature_class":"P",
    "gn:feature_code":"PPL",
    "gn:name":"Puerto Blest",
    "gn:population":0,
    "gn:timezone":"America/Argentina/Salta",
    "iso:country":"AR",
    "wof:name":"Puerto Blest",
    "wof:placetype":"locality"
},
  "geometry": {"coordinates":[-71.82066,-41.02477],"type":"Point"}
}