{
  "type": "Feature",
  "properties": {
    "gn:admin1_code":"2.0",
    "gn:admin2_code":"10042.0",
    "gn:asciiname":"Telaritos",
    "gn:country_code":"AR",
    "gn:dem":234,
    "gn:feature_class":"P",
    "gn:feature_code":"PPL",
    "gn:name":"Telaritos",
    "gn:population":0,
    "gn:timezone":"America/Argentina/Catamarca",
    "iso:country":"AR",
    "wof:name":"Telaritos",
    "wof:placetype":"locality"
},
  "geometry": {"coordinates":[-65.65884,-29.47093],"type":"Point"}
}