{
  "type": "Feature",
  "properties": {
    "gn:admin1_code":"18",
    "gn:admin2_code":"70070.0",
    "gn:asciiname":"Carpinteria",
    "gn:country_code":"AR",
    "gn:dem":607,
    "gn:feature_class":"P",
    "gn:feature_code":"PPL",
    "gn:name":"Carpinter\u00eda",
    "gn:population":0,
    "gn:timezone":"America/Argentina/San_Juan",
    "iso:country":"AR",
    "name:und_x_variant":[
        "La Carpinteria",
        "Carpinter\u00eda"
    ],
    "wof:name":"Carpinteria",
    "wof:placetype":"locality"
},
  "geometry": {"coordinates":[-68.56001999999999,-31.82341],"type":"Point"}
}