{
  "type": "Feature",
  "properties": {
    "gn:admin1_code":"18",
    "gn:admin2_code":"70056.0",
    "gn:asciiname":"Boca de la Quebrada",
    "gn:country_code":"AR",
    "gn:dem":1118,
    "gn:feature_class":"P",
    "gn:feature_code":"PPL",
    "gn:name":"Boca de la Quebrada",
    "gn:population":0,
    "gn:timezone":"America/Argentina/San_Juan",
    "iso:country":"AR",
    "wof:name":"Boca de la Quebrada",
    "wof:placetype":"locality"
},
  "geometry": {"coordinates":[-68.65998,-30.15201],"type":"Point"}
}