{
  "type": "Feature",
  "properties": {
    "iso:country":"AR",
    "name:unk_x_variant":[
        "Gobernador de la Vega"
    ],
    "qs:gn_country":"AR",
    "qs:gn_fcode":"PPL",
    "qs:gn_pop":0,
    "qs:name":"G\u00f3mez de la Vega",
    "qs:name_adm0":"Argentina",
    "qs:name_adm1":"Buenos Aires",
    "qs:photos":44,
    "qs:photos_1k":9,
    "qs:photos_9k":1,
    "qs:photos_9r":2,
    "qs:photos_all":44,
    "qs:photos_sr":2,
    "qs:placetype":"Town",
    "qs:pop_sr":"0",
    "qs:woe_adm0":23424747,
    "wof:name":"G\u00f3mez de la Vega",
    "wof:placetype":"locality"
},
  "geometry": {"coordinates":[-58.13597,-35.08903],"type":"Point"}
}