{
  "type": "Feature",
  "properties": {
    "gn:admin1_code":"08",
    "gn:asciiname":"R. Barbosa",
    "gn:country_code":"AR",
    "gn:dem":78,
    "gn:feature_class":"P",
    "gn:feature_code":"PPL",
    "gn:name":"R. Barbosa",
    "gn:population":0,
    "gn:timezone":"America/Argentina/Cordoba",
    "iso:country":"AR",
    "name:spa_x_preferred":[
        "R. Barbosa"
    ],
    "wof:name":"R. Barbosa",
    "wof:placetype":"locality"
},
  "geometry": {"coordinates":[-58.18937,-30.18128],"type":"Point"}
}