{
  "type": "Feature",
  "properties": {
    "gn:admin1_code":"5.0",
    "gn:admin2_code":"14028.0",
    "gn:asciiname":"Los Sauces",
    "gn:country_code":"AR",
    "gn:dem":573,
    "gn:feature_class":"P",
    "gn:feature_code":"PPL",
    "gn:name":"Los Sauces",
    "gn:population":0,
    "gn:timezone":"America/Argentina/Cordoba",
    "iso:country":"AR",
    "wof:name":"Los Sauces",
    "wof:placetype":"locality"
},
  "geometry": {"coordinates":[-64.68214,-30.73663],"type":"Point"}
}