{
  "type": "Feature",
  "properties": {
    "gn:admin1_code":"1.0",
    "gn:admin2_code":"6602.0",
    "gn:asciiname":"Juan A. Pradere",
    "gn:country_code":"AR",
    "gn:dem":22,
    "gn:feature_class":"P",
    "gn:feature_code":"PPL",
    "gn:name":"Juan A. Pradere",
    "gn:population":0,
    "gn:timezone":"America/Argentina/Buenos_Aires",
    "iso:country":"AR",
    "name:und_x_variant":[
        "J. Pradere",
        "Juan Pradere",
        "J.A. Pradere",
        "Juan A. Pradere"
    ],
    "wof:name":"Juan A. Pradere",
    "wof:placetype":"locality"
},
  "geometry": {"coordinates":[-62.65213000000001,-39.60032],"type":"Point"}
}