{
  "type": "Feature",
  "properties": {
    "gn:admin1_code":"05",
    "gn:admin2_code":"14105.0",
    "gn:asciiname":"Atahona",
    "gn:country_code":"AR",
    "gn:dem":225,
    "gn:feature_class":"P",
    "gn:feature_code":"PPL",
    "gn:name":"Atahona",
    "gn:population":0,
    "gn:timezone":"America/Argentina/Cordoba",
    "iso:country":"AR",
    "wof:name":"Atahona",
    "wof:placetype":"locality"
},
  "geometry": {"coordinates":[-63.70438000000001,-30.906],"type":"Point"}
}