{
  "type": "Feature",
  "properties": {
    "gn:admin1_code":"15",
    "gn:admin2_code":"58084.0",
    "gn:asciiname":"Banos de Copahue",
    "gn:country_code":"AR",
    "gn:dem":2001,
    "gn:feature_class":"P",
    "gn:feature_code":"PPL",
    "gn:name":"Ba\u00f1os de Copahue",
    "gn:population":0,
    "gn:timezone":"America/Argentina/Salta",
    "iso:country":"AR",
    "name:und_x_variant":[
        "Los Copahues",
        "Ba\u00f1os de Copahue"
    ],
    "wof:name":"Banos de Copahue",
    "wof:placetype":"locality"
},
  "geometry": {"coordinates":[-71.0886,-37.83745],"type":"Point"}
}