{
  "type": "Feature",
  "properties": {
    "iso:country":"AR",
    "name:deu_x_preferred":[
        "Viamonte"
    ],
    "name:spa_x_preferred":[
        "Viamonte"
    ],
    "name:unk_x_variant":[
        "General Viamonte"
    ],
    "qs:gn_country":"AR",
    "qs:gn_fcode":"PPL",
    "qs:gn_pop":1598,
    "qs:name":"Viamonte",
    "qs:name_adm0":"Argentina",
    "qs:name_adm1":"C\u00f3rdoba",
    "qs:photos":0,
    "qs:photos_1k":0,
    "qs:photos_9k":0,
    "qs:photos_9r":0,
    "qs:photos_all":0,
    "qs:photos_sr":0,
    "qs:placetype":"Town",
    "qs:pop_sr":"3",
    "qs:woe_adm0":23424747,
    "wd:wordcount":101,
    "wof:name":"Viamonte",
    "wof:placetype":"locality",
    "wof:population":1598
},
  "geometry": {"coordinates":[-63.09764,-33.74647],"type":"Point"}
}