{
  "type": "Feature",
  "properties": {
    "gn:admin1_code":"4.0",
    "gn:admin2_code":"26021.0",
    "gn:asciiname":"Manantial Rosales",
    "gn:country_code":"AR",
    "gn:dem":240,
    "gn:feature_class":"P",
    "gn:feature_code":"PPL",
    "gn:name":"Manantial Rosales",
    "gn:population":0,
    "gn:timezone":"America/Argentina/Catamarca",
    "iso:country":"AR",
    "wof:name":"Manantial Rosales",
    "wof:placetype":"locality"
},
  "geometry": {"coordinates":[-67.53333000000001,-45.83333],"type":"Point"}
}