{
  "type": "Feature",
  "properties": {
    "gn:admin1_code":"18",
    "gn:admin2_code":"70049.0",
    "gn:asciiname":"Chigua de Arriba",
    "gn:country_code":"AR",
    "gn:dem":1883,
    "gn:feature_class":"P",
    "gn:feature_code":"PPL",
    "gn:name":"Chigua de Arriba",
    "gn:population":0,
    "gn:timezone":"America/Argentina/San_Juan",
    "iso:country":"AR",
    "wof:name":"Chigua de Arriba",
    "wof:placetype":"locality"
},
  "geometry": {"coordinates":[-69.1534,-29.82278],"type":"Point"}
}