{
  "type": "Feature",
  "properties": {
    "gn:admin1_code":"21.0",
    "gn:admin2_code":"82126.0",
    "gn:asciiname":"San Martin de las Escobas",
    "gn:country_code":"AR",
    "gn:dem":75,
    "gn:feature_class":"P",
    "gn:feature_code":"PPL",
    "gn:name":"San Mart\u00edn de las Escobas",
    "gn:population":0,
    "gn:timezone":"America/Argentina/Cordoba",
    "iso:country":"AR",
    "name:und_x_variant":[
        "San Mart\u00edn",
        "San Mart\u00edn de las Escobas"
    ],
    "wof:name":"San Martin de las Escobas",
    "wof:placetype":"locality"
},
  "geometry": {"coordinates":[-61.56985,-31.8578],"type":"Point"}
}