{
  "type": "Feature",
  "properties": {
    "iso:country":"AR",
    "name:ast_x_preferred":[
        "Puerto Piray"
    ],
    "name:ceb_x_preferred":[
        "Puerto Piray"
    ],
    "name:eng_x_preferred":[
        "Puerto Piray"
    ],
    "name:fra_x_preferred":[
        "Puerto Piray"
    ],
    "name:nld_x_preferred":[
        "Puerto Piray"
    ],
    "name:pol_x_preferred":[
        "Puerto Piray"
    ],
    "name:por_x_preferred":[
        "Puerto Piray"
    ],
    "name:spa_x_preferred":[
        "Puerto Piray"
    ],
    "name:swe_x_preferred":[
        "Puerto Piray"
    ],
    "name:ukr_x_preferred":[
        "\u041f\u0443\u0435\u0440\u0442\u043e-\u041f\u0456\u0440\u0430\u0439"
    ],
    "qs:gn_country":"AR",
    "qs:gn_fcode":"PPL",
    "qs:gn_pop":8557,
    "qs:name":"Puerto Piray",
    "qs:name_adm0":"Argentina",
    "qs:name_adm1":"Misiones",
    "qs:photos":0,
    "qs:photos_1k":0,
    "qs:photos_9k":0,
    "qs:photos_9r":0,
    "qs:photos_all":0,
    "qs:photos_sr":0,
    "qs:placetype":"Town",
    "qs:pop_sr":"5",
    "qs:woe_adm0":23424747,
    "wd:wordcount":35,
    "wof:name":"Puerto Piray",
    "wof:placetype":"locality",
    "wof:population":8557
},
  "geometry": {"coordinates":[-54.71476,-26.46779],"type":"Point"}
}