{
  "type": "Feature",
  "properties": {
    "iso:country":"AR",
    "name:deu_x_preferred":[
        "San Luis del Palmar"
    ],
    "name:eng_x_preferred":[
        "San Luis del Palmar"
    ],
    "name:fra_x_preferred":[
        "San Luis del Palmar"
    ],
    "name:nld_x_preferred":[
        "San Luis del Palmar"
    ],
    "name:por_x_preferred":[
        "San Luis del Palmar"
    ],
    "name:spa_x_preferred":[
        "San Luis del Palmar"
    ],
    "name:swe_x_preferred":[
        "San Luis del Palmar"
    ],
    "name:ukr_x_preferred":[
        "\u0421\u0430\u043d-\u041b\u0443\u0457\u0441-\u0434\u0435-\u041f\u0430\u043b\u044c\u043c\u0430\u0440"
    ],
    "name:zho_x_preferred":[
        "\u8056\u8def\u6613\u65af\u5fb7\u723e\u5e15\u723e\u99ac"
    ],
    "qs:gn_country":"AR",
    "qs:gn_fcode":"PPL",
    "qs:gn_pop":15347,
    "qs:name":"San Luis del Palmar",
    "qs:name_adm0":"Argentina",
    "qs:name_adm1":"Corrientes",
    "qs:photos":0,
    "qs:photos_1k":0,
    "qs:photos_9k":1,
    "qs:photos_9r":1,
    "qs:photos_all":1,
    "qs:photos_sr":0,
    "qs:placetype":"Town",
    "qs:pop_sr":"7",
    "qs:woe_adm0":23424747,
    "wd:wordcount":65,
    "wof:name":"San Luis del Palmar",
    "wof:placetype":"locality",
    "wof:population":15347
},
  "geometry": {"coordinates":[-58.55454,-27.5079],"type":"Point"}
}