{
  "type": "Feature",
  "properties": {
    "gn:admin1_code":"19",
    "gn:admin2_code":"74014.0",
    "gn:asciiname":"Arbol Solo",
    "gn:country_code":"AR",
    "gn:dem":561,
    "gn:feature_class":"P",
    "gn:feature_code":"PPL",
    "gn:name":"\u00c1rbol Solo",
    "gn:population":0,
    "gn:timezone":"America/Argentina/San_Luis",
    "iso:country":"AR",
    "wof:name":"Arbol Solo",
    "wof:placetype":"locality"
},
  "geometry": {"coordinates":[-66.48671999999999,-32.50687],"type":"Point"}
}