{
  "type": "Feature",
  "properties": {
    "gn:admin1_code":"9.0",
    "gn:asciiname":"Puerto Galileo",
    "gn:country_code":"AR",
    "gn:dem":69,
    "gn:feature_class":"P",
    "gn:feature_code":"PPL",
    "gn:name":"Puerto Galileo",
    "gn:population":0,
    "gn:timezone":"America/Argentina/Cordoba",
    "iso:country":"AR",
    "wof:name":"Puerto Galileo",
    "wof:placetype":"locality"
},
  "geometry": {"coordinates":[-57.85,-25.08333],"type":"Point"}
}