{
  "type": "Feature",
  "properties": {
    "gn:admin1_code":"20.0",
    "gn:admin2_code":"78021.0",
    "gn:asciiname":"El Zurdo",
    "gn:country_code":"AR",
    "gn:dem":151,
    "gn:feature_class":"P",
    "gn:feature_code":"PPL",
    "gn:name":"El Zurdo",
    "gn:population":0,
    "gn:timezone":"America/Argentina/Rio_Gallegos",
    "iso:country":"AR",
    "wof:name":"El Zurdo",
    "wof:placetype":"locality"
},
  "geometry": {"coordinates":[-71.20763000000002,-51.9981],"type":"Point"}
}