{
  "type": "Feature",
  "properties": {
    "gn:admin1_code":"12.0",
    "gn:admin2_code":"46077.0",
    "gn:asciiname":"Ranchillos",
    "gn:country_code":"AR",
    "gn:dem":3696,
    "gn:feature_class":"P",
    "gn:feature_code":"PPL",
    "gn:name":"Ranchillos",
    "gn:population":0,
    "gn:timezone":"America/Argentina/La_Rioja",
    "iso:country":"AR",
    "name:und_x_variant":[
        "Ranchillo",
        "Ranchillos"
    ],
    "wof:name":"Ranchillos",
    "wof:placetype":"locality"
},
  "geometry": {"coordinates":[-69.17581,-28.595],"type":"Point"}
}