{
  "type": "Feature",
  "properties": {
    "gn:admin1_code":"3.0",
    "gn:admin2_code":"22063.0",
    "gn:asciiname":"Zaparinqui",
    "gn:country_code":"AR",
    "gn:dem":108,
    "gn:feature_class":"P",
    "gn:feature_code":"PPL",
    "gn:name":"Zaparinqui",
    "gn:population":0,
    "gn:timezone":"America/Argentina/Cordoba",
    "iso:country":"AR",
    "name:ceb_x_preferred":[
        "Zaparinqui"
    ],
    "name:spa_x_preferred":[
        "Zaparinqui"
    ],
    "name:swe_x_preferred":[
        "Zaparinqui"
    ],
    "wof:name":"Zaparinqui",
    "wof:placetype":"locality"
},
  "geometry": {"coordinates":[-60.56045,-26.06662],"type":"Point"}
}