{
  "type": "Feature",
  "properties": {
    "gn:admin1_code":"1.0",
    "gn:admin2_code":"6224.0",
    "gn:asciiname":"Henry Bell",
    "gn:country_code":"AR",
    "gn:dem":55,
    "gn:feature_class":"P",
    "gn:feature_code":"PPL",
    "gn:name":"Henry Bell",
    "gn:population":0,
    "gn:timezone":"America/Argentina/Buenos_Aires",
    "iso:country":"AR",
    "wof:name":"Henry Bell",
    "wof:placetype":"locality"
},
  "geometry": {"coordinates":[-59.95466999999999,-35.0477],"type":"Point"}
}