{
  "type": "Feature",
  "properties": {
    "gn:admin1_code":"22.0",
    "gn:admin2_code":"86014.0",
    "gn:asciiname":"Pozo Limpio",
    "gn:country_code":"AR",
    "gn:dem":194,
    "gn:feature_class":"P",
    "gn:feature_code":"PPL",
    "gn:name":"Pozo Limpio",
    "gn:population":0,
    "gn:timezone":"America/Argentina/Cordoba",
    "iso:country":"AR",
    "wof:name":"Pozo Limpio",
    "wof:placetype":"locality"
},
  "geometry": {"coordinates":[-63.56494,-26.81091],"type":"Point"}
}