{
  "type": "Feature",
  "properties": {
    "gn:admin1_code":"13.0",
    "gn:admin2_code":"50042.0",
    "gn:asciiname":"Maquinista Levet",
    "gn:country_code":"AR",
    "gn:dem":451,
    "gn:feature_class":"P",
    "gn:feature_code":"PPL",
    "gn:name":"Maquinista Levet",
    "gn:population":0,
    "gn:timezone":"America/Argentina/Mendoza",
    "iso:country":"AR",
    "name:und_x_variant":[
        "Sopanta",
        "Maquinista Levet"
    ],
    "wof:name":"Maquinista Levet",
    "wof:placetype":"locality"
},
  "geometry": {"coordinates":[-67.09903,-33.60117],"type":"Point"}
}