{
  "type": "Feature",
  "properties": {
    "iso:country":"AR",
    "name:ceb_x_preferred":[
        "Coronel Vidal"
    ],
    "name:dut_x_preferred":[
        "Coronel Vidal"
    ],
    "name:eng_x_preferred":[
        "Coronel Vidal"
    ],
    "name:nld_x_preferred":[
        "Coronel Vidal"
    ],
    "name:sco_x_preferred":[
        "Coronel Vidal"
    ],
    "name:spa_x_preferred":[
        "Coronel Vidal"
    ],
    "name:swe_x_preferred":[
        "Coronel Vidal"
    ],
    "name:ukr_x_preferred":[
        "\u041a\u043e\u0440\u043e\u043d\u0435\u043b\u044c-\u0412\u0456\u0434\u0430\u043b\u044c"
    ],
    "qs:gn_country":"AR",
    "qs:gn_fcode":"PPL",
    "qs:gn_pop":0,
    "qs:name":"Coronel Vidal",
    "qs:name_adm0":"Argentina",
    "qs:name_adm1":"Buenos Aires",
    "qs:photos":0,
    "qs:photos_1k":0,
    "qs:photos_9k":1,
    "qs:photos_9r":1,
    "qs:photos_all":9,
    "qs:photos_sr":0,
    "qs:placetype":"Town",
    "qs:pop_sr":"7",
    "qs:woe_adm0":23424747,
    "wd:wordcount":61,
    "wof:name":"Coronel Vidal",
    "wof:placetype":"locality"
},
  "geometry": {"coordinates":[-57.72865,-37.44604],"type":"Point"}
}