{
  "type": "Feature",
  "properties": {
    "gn:admin1_code":"1.0",
    "gn:admin2_code":"6196.0",
    "gn:asciiname":"Krabbe",
    "gn:country_code":"AR",
    "gn:dem":216,
    "gn:feature_class":"P",
    "gn:feature_code":"PPL",
    "gn:name":"Krabb\u00e9",
    "gn:population":0,
    "gn:timezone":"America/Argentina/Buenos_Aires",
    "iso:country":"AR",
    "wof:name":"Krabbe",
    "wof:placetype":"locality"
},
  "geometry": {"coordinates":[-61.14309,-37.78459],"type":"Point"}
}