{
  "type": "Feature",
  "properties": {
    "gn:admin1_code":"24.0",
    "gn:admin2_code":"90007.0",
    "gn:asciiname":"Gobernador Piedrabuena",
    "gn:country_code":"AR",
    "gn:dem":353,
    "gn:feature_class":"P",
    "gn:feature_code":"PPL",
    "gn:name":"Gobernador Piedrabuena",
    "gn:population":0,
    "gn:timezone":"America/Argentina/Tucuman",
    "iso:country":"AR",
    "wof:name":"Gobernador Piedrabuena",
    "wof:placetype":"locality"
},
  "geometry": {"coordinates":[-64.62498000000001,-26.73469],"type":"Point"}
}