{
  "type": "Feature",
  "properties": {
    "gn:admin1_code":"13",
    "gn:admin2_code":"50056.0",
    "gn:asciiname":"Costa de Araujo",
    "gn:country_code":"AR",
    "gn:dem":610,
    "gn:feature_class":"P",
    "gn:feature_code":"PPL",
    "gn:name":"Costa de Araujo",
    "gn:population":0,
    "gn:timezone":"America/Argentina/Mendoza",
    "iso:country":"AR",
    "name:und_x_variant":[
        "Costa del Araujo",
        "Costa de Araujo"
    ],
    "wof:name":"Costa de Araujo",
    "wof:placetype":"locality"
},
  "geometry": {"coordinates":[-68.3974,-32.75781],"type":"Point"}
}