{
  "type": "Feature",
  "properties": {
    "gn:admin1_code":"11",
    "gn:admin2_code":"42056.0",
    "gn:asciiname":"Ceballos",
    "gn:country_code":"AR",
    "gn:dem":139,
    "gn:feature_class":"P",
    "gn:feature_code":"PPL",
    "gn:name":"Ceballos",
    "gn:population":0,
    "gn:timezone":"America/Argentina/Salta",
    "iso:country":"AR",
    "name:und_x_variant":[
        "A. Ceballos",
        "Cevallos",
        "Ceballos"
    ],
    "wof:name":"Ceballos",
    "wof:placetype":"locality"
},
  "geometry": {"coordinates":[-63.77713000000001,-35.29008],"type":"Point"}
}