{
  "type": "Feature",
  "properties": {
    "gn:admin1_code":"20.0",
    "gn:admin2_code":"78049.0",
    "gn:asciiname":"Lago Cardiel",
    "gn:cc2":"AR",
    "gn:country_code":"AR",
    "gn:dem":486,
    "gn:feature_class":"P",
    "gn:feature_code":"PPL",
    "gn:name":"Lago Cardiel",
    "gn:population":0,
    "gn:timezone":"America/Argentina/Rio_Gallegos",
    "iso:country":"AR",
    "name:ara_x_preferred":[
        "\u0628\u062d\u064a\u0631\u0629 \u0643\u0627\u0631\u062f\u064a\u0644"
    ],
    "name:ben_x_preferred":[
        "\u09b2\u09be\u0997\u09cb"
    ],
    "name:deu_x_preferred":[
        "Cardiel-See"
    ],
    "name:ell_x_preferred":[
        "\u039b\u03ac\u03b3\u03ba\u03bf \u039a\u03b1\u03c1\u03bd\u03c4\u03b9\u03ad\u03bb"
    ],
    "name:fas_x_preferred":[
        "\u0644\u0627\u06af\u0648 \u06a9\u0627\u0631\u062f\u06cc\u0644"
    ],
    "name:hin_x_preferred":[
        "\u0932\u093e\u0917\u094b \u0915\u093e\u0930\u094d\u0921\u093f\u090f\u0932"
    ],
    "name:hun_x_preferred":[
        "Lago Cardiel"
    ],
    "name:ind_x_preferred":[
        "Danau Cardiel"
    ],
    "name:jpn_x_preferred":[
        "\u30ab\u30eb\u30c7\u30a3\u30a8\u30eb\u6e56"
    ],
    "name:kor_x_preferred":[
        "\ub77c\uace0 \uce74\ub514\uc5d8"
    ],
    "name:por_x_preferred":[
        "Lago Cardiel"
    ],
    "name:tur_x_preferred":[
        "Lago Cardiel"
    ],
    "name:ukr_x_preferred":[
        "\u041a\u0430\u0440\u0434\u0456\u0454\u043b\u044c"
    ],
    "name:und_x_variant":[
        "Felt\u00f3n",
        "Lago Cardiel"
    ],
    "name:urd_x_preferred":[
        "\u0644\u0627\u06af\u0648 \u06a9\u0627\u0631\u0688\u06cc\u0641"
    ],
    "name:vie_x_preferred":[
        "H\u1ed3 Cardiel"
    ],
    "name:zho_cn_x_preferred":[
        "\u5361\u8fea\u5c14\u6e56"
    ],
    "name:zho_tw_x_preferred":[
        "\u5361\u8fea\u723e\u6e56"
    ],
    "wof:name":"Lago Cardiel",
    "wof:placetype":"locality"
},
  "geometry": {"coordinates":[-71.40000000000001,-48.96667],"type":"Point"}
}