{
  "type": "Feature",
  "properties": {
    "gn:admin1_code":"20.0",
    "gn:admin2_code":"78049.0",
    "gn:asciiname":"Lago Cardiel",
    "gn:cc2":"AR",
    "gn:country_code":"AR",
    "gn:dem":486,
    "gn:feature_class":"P",
    "gn:feature_code":"PPL",
    "gn:name":"Lago Cardiel",
    "gn:population":0,
    "gn:timezone":"America/Argentina/Rio_Gallegos",
    "iso:country":"AR",
    "name:und_x_variant":[
        "Felt\u00f3n",
        "Lago Cardiel"
    ],
    "wof:name":"Lago Cardiel",
    "wof:placetype":"locality"
},
  "geometry": {"coordinates":[-71.40000000000001,-48.96667],"type":"Point"}
}