{
  "type": "Feature",
  "properties": {
    "gn:admin1_code":"24.0",
    "gn:admin2_code":"90035.0",
    "gn:asciiname":"Sol de Mayo",
    "gn:country_code":"AR",
    "gn:dem":283,
    "gn:feature_class":"P",
    "gn:feature_code":"PPL",
    "gn:name":"Sol de Mayo",
    "gn:population":0,
    "gn:timezone":"America/Argentina/Tucuman",
    "iso:country":"AR",
    "wof:name":"Sol de Mayo",
    "wof:placetype":"locality"
},
  "geometry": {"coordinates":[-65.13333,-27.58333],"type":"Point"}
}