{
  "type": "Feature",
  "properties": {
    "gn:admin1_code":"21",
    "gn:admin2_code":"82035.0",
    "gn:asciiname":"Colonia Mascias",
    "gn:country_code":"AR",
    "gn:dem":25,
    "gn:feature_class":"P",
    "gn:feature_code":"PPL",
    "gn:name":"Colonia Masc\u00edas",
    "gn:population":0,
    "gn:timezone":"America/Argentina/Cordoba",
    "iso:country":"AR",
    "wof:name":"Colonia Mascias",
    "wof:placetype":"locality"
},
  "geometry": {"coordinates":[-60.00846,-30.81299000000001],"type":"Point"}
}