{
  "type": "Feature",
  "properties": {
    "gn:admin1_code":"19",
    "gn:admin2_code":"74007.0",
    "gn:asciiname":"Chipiscu",
    "gn:cc2":"AR",
    "gn:country_code":"AR",
    "gn:dem":626,
    "gn:feature_class":"P",
    "gn:feature_code":"PPL",
    "gn:name":"Chipisc\u00fa",
    "gn:population":0,
    "gn:timezone":"America/Argentina/San_Luis",
    "iso:country":"AR",
    "name:und_x_variant":[
        "Chipisca",
        "Chipisc\u00fa"
    ],
    "wof:name":"Chipiscu",
    "wof:placetype":"locality"
},
  "geometry": {"coordinates":[-67.03333000000001,-32.18333],"type":"Point"}
}