{
  "type": "Feature",
  "properties": {
    "gn:admin1_code":"4.0",
    "gn:admin2_code":"26056.0",
    "gn:asciiname":"Jaramillo",
    "gn:country_code":"AR",
    "gn:dem":922,
    "gn:feature_class":"P",
    "gn:feature_code":"PPL",
    "gn:name":"Jaramillo",
    "gn:population":0,
    "gn:timezone":"America/Argentina/Catamarca",
    "iso:country":"AR",
    "name:spa_x_preferred":[
        "Jaramillo"
    ],
    "wof:name":"Jaramillo",
    "wof:placetype":"locality"
},
  "geometry": {"coordinates":[-71.24132,-43.84343],"type":"Point"}
}