{
  "type": "Feature",
  "properties": {
    "iso:country":"AR",
    "name:dut_x_preferred":[
        "Alejo Ledesma"
    ],
    "name:eng_x_preferred":[
        "Alejo Ledesma"
    ],
    "name:por_x_preferred":[
        "Alejo Ledesma"
    ],
    "name:spa_x_preferred":[
        "Alejo Ledesma"
    ],
    "name:swe_x_preferred":[
        "Alejo Ledesma"
    ],
    "name:ukr_x_preferred":[
        "\u0410\u043b\u0435\u0445\u043e-\u041b\u0435\u0434\u0435\u0441\u043c\u0430"
    ],
    "name:unk_x_variant":[
        "Ledesma"
    ],
    "qs:gn_country":"AR",
    "qs:gn_fcode":"PPL",
    "qs:gn_pop":3310,
    "qs:name":"Alejo Ledesma",
    "qs:name_adm0":"Argentina",
    "qs:name_adm1":"C\u00f3rdoba",
    "qs:photos":0,
    "qs:photos_1k":0,
    "qs:photos_9k":2,
    "qs:photos_9r":5,
    "qs:photos_all":398,
    "qs:photos_sr":0,
    "qs:placetype":"Town",
    "qs:pop_sr":"7",
    "qs:woe_adm0":23424747,
    "wof:name":"Alejo Ledesma",
    "wof:placetype":"locality",
    "wof:population":3310
},
  "geometry": {"coordinates":[-62.62304,-33.60643],"type":"Point"}
}