{
  "type": "Feature",
  "properties": {
    "gn:admin1_code":"12",
    "gn:admin2_code":"46028.0",
    "gn:asciiname":"Banda Florida",
    "gn:country_code":"AR",
    "gn:dem":1156,
    "gn:feature_class":"P",
    "gn:feature_code":"PPL",
    "gn:name":"Banda Florida",
    "gn:population":0,
    "gn:timezone":"America/Argentina/La_Rioja",
    "iso:country":"AR",
    "name:ceb_x_preferred":[
        "Banda Florida"
    ],
    "name:spa_x_preferred":[
        "Banda Florida"
    ],
    "wof:name":"Banda Florida",
    "wof:placetype":"locality"
},
  "geometry": {"coordinates":[-68.24611999999999,-29.30278],"type":"Point"}
}