{
  "type": "Feature",
  "properties": {
    "gn:admin1_code":"17.0",
    "gn:admin2_code":"66161.0",
    "gn:asciiname":"Salto",
    "gn:country_code":"AR",
    "gn:dem":2476,
    "gn:feature_class":"P",
    "gn:feature_code":"PPL",
    "gn:name":"Salto",
    "gn:population":0,
    "gn:timezone":"America/Argentina/Salta",
    "iso:country":"AR",
    "wof:name":"Salto",
    "wof:placetype":"locality"
},
  "geometry": {"coordinates":[-64.88333,-22.13333],"type":"Point"}
}