{
  "type": "Feature",
  "properties": {
    "gn:admin1_code":"6.0",
    "gn:admin2_code":"18105.0",
    "gn:asciiname":"Ita Cora",
    "gn:country_code":"AR",
    "gn:dem":75,
    "gn:feature_class":"P",
    "gn:feature_code":"PPL",
    "gn:name":"It\u00e1 Cor\u00e1",
    "gn:population":0,
    "gn:timezone":"America/Argentina/Cordoba",
    "iso:country":"AR",
    "wof:name":"Ita Cora",
    "wof:placetype":"locality"
},
  "geometry": {"coordinates":[-58.15351,-28.90862000000001],"type":"Point"}
}