{
  "type": "Feature",
  "properties": {
    "gn:admin1_code":"05",
    "gn:admin2_code":"14175.0",
    "gn:asciiname":"Churqui Canada",
    "gn:country_code":"AR",
    "gn:dem":451,
    "gn:feature_class":"P",
    "gn:feature_code":"PPL",
    "gn:name":"Churqui Ca\u00f1ada",
    "gn:population":0,
    "gn:timezone":"America/Argentina/Cordoba",
    "iso:country":"AR",
    "name:und_x_variant":[
        "Churqui",
        "Churqui Ca\u00f1ada"
    ],
    "wof:name":"Churqui Canada",
    "wof:placetype":"locality"
},
  "geometry": {"coordinates":[-63.86372,-30.17526],"type":"Point"}
}