{
  "type": "Feature",
  "properties": {
    "gn:admin1_code":"02",
    "gn:admin2_code":"10035.0",
    "gn:asciiname":"Condorhuasi",
    "gn:country_code":"AR",
    "gn:dem":2005,
    "gn:feature_class":"P",
    "gn:feature_code":"PPL",
    "gn:name":"C\u00f3ndorhuasi",
    "gn:population":0,
    "gn:timezone":"America/Argentina/Catamarca",
    "iso:country":"AR",
    "wof:name":"Condorhuasi",
    "wof:placetype":"locality"
},
  "geometry": {"coordinates":[-67.10120999999999,-27.49422],"type":"Point"}
}