{
  "type": "Feature",
  "properties": {
    "iso:country":"AR",
    "name:ast_x_preferred":[
        "Bajo Caracoles"
    ],
    "name:eng_x_preferred":[
        "Bajo Caracoles"
    ],
    "name:fra_x_preferred":[
        "Bajo Caracoles"
    ],
    "name:nld_x_preferred":[
        "Bajo Caracoles"
    ],
    "name:spa_x_preferred":[
        "Bajo Caracoles"
    ],
    "name:und_x_variant":[
        "Casa Folch"
    ],
    "qs:gn_country":"AR",
    "qs:gn_fcode":"PPL",
    "qs:gn_pop":0,
    "qs:name":"Bajo de Los Caracoles",
    "qs:name_adm0":"Argentina",
    "qs:name_adm1":"Santa Cruz",
    "qs:photos":13,
    "qs:photos_1k":3,
    "qs:photos_9k":1,
    "qs:photos_9r":1,
    "qs:photos_all":13,
    "qs:photos_sr":1,
    "qs:placetype":"Town",
    "qs:pop_sr":"4",
    "qs:woe_adm0":23424747,
    "wd:wordcount":89,
    "wof:name":"Bajo de Los Caracoles",
    "wof:placetype":"locality"
},
  "geometry": {"coordinates":[-70.92716,-47.44521],"type":"Point"}
}