{
  "type": "Feature",
  "properties": {
    "gn:admin1_code":"12.0",
    "gn:admin2_code":"46084.0",
    "gn:asciiname":"Los Alanices",
    "gn:country_code":"AR",
    "gn:dem":364,
    "gn:feature_class":"P",
    "gn:feature_code":"PPL",
    "gn:name":"Los Alanices",
    "gn:population":0,
    "gn:timezone":"America/Argentina/La_Rioja",
    "iso:country":"AR",
    "name:und_x_variant":[
        "Alanices",
        "Los Alanices"
    ],
    "wof:name":"Los Alanices",
    "wof:placetype":"locality"
},
  "geometry": {"coordinates":[-65.98689,-30.79747],"type":"Point"}
}