{
  "type": "Feature",
  "properties": {
    "gn:admin1_code":"24",
    "gn:admin2_code":"90021.0",
    "gn:asciiname":"Alto Verde",
    "gn:country_code":"AR",
    "gn:dem":379,
    "gn:feature_class":"P",
    "gn:feature_code":"PPL",
    "gn:name":"Alto Verde",
    "gn:population":0,
    "gn:timezone":"America/Argentina/Tucuman",
    "iso:country":"AR",
    "wof:name":"Alto Verde",
    "wof:placetype":"locality"
},
  "geometry": {"coordinates":[-65.60865,-27.37805],"type":"Point"}
}