{
  "type": "Feature",
  "properties": {
    "iso:country":"AR",
    "name:ceb_x_preferred":[
        "Juan Bautista Alberdi"
    ],
    "name:deu_x_preferred":[
        "Juan Bautista Alberdi"
    ],
    "name:eng_x_preferred":[
        "Juan Bautista Alberdi"
    ],
    "name:fra_x_preferred":[
        "Juan Bautista Alberdi"
    ],
    "name:ita_x_preferred":[
        "Juan Bautista Alberdi"
    ],
    "name:jpn_x_preferred":[
        "\u30d5\u30a2\u30f3\u30fb\u30d0\u30a6\u30c6\u30a3\u30b9\u30bf\u30fb\u30a2\u30eb\u30d9\u30eb\u30c7\u30a3"
    ],
    "name:nld_x_preferred":[
        "Juan Bautista Alberdi"
    ],
    "name:por_x_preferred":[
        "Juan Bautista Alberdi"
    ],
    "name:spa_x_preferred":[
        "Juan Bautista Alberdi"
    ],
    "name:swe_x_preferred":[
        "Juan Bautista Alberdi"
    ],
    "name:ukr_x_preferred":[
        "\u0425\u0443\u0430\u043d-\u0411\u0430\u0443\u0442\u0456\u0441\u0442\u0430-\u0410\u043b\u044c\u0431\u0435\u0440\u0434\u0456"
    ],
    "name:zho_x_preferred":[
        "\u80e1\u5b89\u5305\u8482\u65af\u5854\u963f\u723e\u97cb\u8fea"
    ],
    "qs:gn_country":"AR",
    "qs:gn_fcode":"PPL",
    "qs:gn_pop":0,
    "qs:name":"Juan Bautista Alberdi",
    "qs:name_adm0":"Argentina",
    "qs:name_adm1":"Tucum\u00e1n",
    "qs:photos":0,
    "qs:photos_1k":0,
    "qs:photos_9k":1,
    "qs:photos_9r":1,
    "qs:photos_all":7,
    "qs:photos_sr":0,
    "qs:placetype":"Town",
    "qs:pop_sr":"0",
    "qs:woe_adm0":23424747,
    "wd:wordcount":32,
    "wof:name":"Juan Bautista Alberdi",
    "wof:placetype":"locality"
},
  "geometry": {"coordinates":[-65.61978999999999,-27.58589],"type":"Point"}
}