{
  "type": "Feature",
  "properties": {
    "gn:admin1_code":"11",
    "gn:admin2_code":"42112.0",
    "gn:asciiname":"Casa de Piedra",
    "gn:country_code":"AR",
    "gn:dem":292,
    "gn:elevation":"283.0",
    "gn:feature_class":"P",
    "gn:feature_code":"PPL",
    "gn:name":"Casa de Piedra",
    "gn:population":0,
    "gn:timezone":"America/Argentina/Salta",
    "iso:country":"AR",
    "wof:name":"Casa de Piedra",
    "wof:placetype":"locality"
},
  "geometry": {"coordinates":[-67.15075,-38.1542],"type":"Point"}
}