{
  "type": "Feature",
  "properties": {
    "gn:admin1_code":"10.0",
    "gn:admin2_code":"38070.0",
    "gn:asciiname":"El Piquete",
    "gn:country_code":"AR",
    "gn:dem":490,
    "gn:feature_class":"P",
    "gn:feature_code":"PPL",
    "gn:name":"El Piquete",
    "gn:population":0,
    "gn:timezone":"America/Argentina/Jujuy",
    "iso:country":"AR",
    "wof:name":"El Piquete",
    "wof:placetype":"locality"
},
  "geometry": {"coordinates":[-64.65000000000001,-24.21667],"type":"Point"}
}