{
  "type": "Feature",
  "properties": {
    "iso:country":"AR",
    "name:eng_x_preferred":[
        "El Hoyo"
    ],
    "name:fra_x_preferred":[
        "El Hoyo"
    ],
    "name:ita_x_preferred":[
        "El Hoyo"
    ],
    "name:nld_x_preferred":[
        "El Hoyo"
    ],
    "name:spa_x_preferred":[
        "El Hoyo"
    ],
    "name:swe_x_preferred":[
        "Hoyo de Epuy\u00e9n"
    ],
    "qs:gn_country":"AR",
    "qs:gn_fcode":"PPL",
    "qs:gn_pop":2498,
    "qs:name":"Hoyo de Epuy\u00e9n",
    "qs:name_adm0":"Argentina",
    "qs:name_adm1":"Chubut",
    "qs:photos":17,
    "qs:photos_1k":3,
    "qs:photos_9k":1,
    "qs:photos_9r":1,
    "qs:photos_all":17,
    "qs:photos_sr":1,
    "qs:placetype":"Town",
    "qs:pop_sr":"4",
    "qs:woe_adm0":23424747,
    "wof:name":"Hoyo de Epuy\u00e9n",
    "wof:placetype":"locality",
    "wof:population":2498
},
  "geometry": {"coordinates":[-71.50811,-42.07189],"type":"Point"}
}