{
  "type": "Feature",
  "properties": {
    "iso:country":"AR",
    "name:bel_x_preferred":[
        "\u041a\u0430\u0440\u043a\u0430\u0440\u0430\u043d\u044c\u044f"
    ],
    "name:ceb_x_preferred":[
        "Carcara\u00f1\u00e1"
    ],
    "name:dan_x_preferred":[
        "Carcara\u00f1\u00e1"
    ],
    "name:eng_x_preferred":[
        "Carcara\u00f1\u00e1"
    ],
    "name:fra_x_preferred":[
        "Carcara\u00f1\u00e1"
    ],
    "name:heb_x_preferred":[
        "\u05e7\u05e8\u05e7\u05e8\u05e0\u05d9\u05d9\u05d4"
    ],
    "name:ita_x_preferred":[
        "Carcara\u00f1\u00e1"
    ],
    "name:jpn_x_preferred":[
        "\u30ab\u30eb\u30ab\u30e9\u30cb\u30e3\u30fc"
    ],
    "name:nld_x_preferred":[
        "Carcara\u00f1\u00e1"
    ],
    "name:rus_x_preferred":[
        "\u041a\u0430\u0440\u043a\u0430\u0440\u0430\u043d\u044c\u044f"
    ],
    "name:spa_x_preferred":[
        "Carcara\u00f1\u00e1"
    ],
    "name:swe_x_preferred":[
        "Carcara\u00f1\u00e1"
    ],
    "name:ukr_x_preferred":[
        "\u041a\u0430\u0440\u043a\u0430\u0440\u0430\u043d\u044c\u044f"
    ],
    "name:zho_x_preferred":[
        "\u5361\u5361\u862d\u62ff"
    ],
    "qs:gn_country":"AR",
    "qs:gn_fcode":"PPL",
    "qs:gn_pop":15619,
    "qs:name":"Carcara\u00f1\u00e1",
    "qs:name_adm0":"Argentina",
    "qs:name_adm1":"Santa Fe",
    "qs:photos":163,
    "qs:photos_1k":33,
    "qs:photos_9k":1,
    "qs:photos_9r":4,
    "qs:photos_all":163,
    "qs:photos_sr":4,
    "qs:placetype":"Town",
    "qs:pop_sr":"7",
    "qs:woe_adm0":23424747,
    "wd:wordcount":132,
    "wof:name":"Carcara\u00f1\u00e1",
    "wof:placetype":"locality",
    "wof:population":15619
},
  "geometry": {"coordinates":[-61.15331,-32.85679],"type":"Point"}
}