{
  "type": "Feature",
  "properties": {
    "gn:admin1_code":"18.0",
    "gn:admin2_code":"70021.0",
    "gn:asciiname":"Puchuzun",
    "gn:country_code":"AR",
    "gn:dem":1478,
    "gn:feature_class":"P",
    "gn:feature_code":"PPL",
    "gn:name":"Puchuz\u00fan",
    "gn:population":0,
    "gn:timezone":"America/Argentina/San_Juan",
    "iso:country":"AR",
    "wof:name":"Puchuzun",
    "wof:placetype":"locality"
},
  "geometry": {"coordinates":[-69.47187,-31.13237],"type":"Point"}
}