{
  "type": "Feature",
  "properties": {
    "iso:country":"AR",
    "name:ceb_x_preferred":[
        "General Alvear"
    ],
    "name:dut_x_preferred":[
        "General Alvear"
    ],
    "name:eng_x_preferred":[
        "General Alvear"
    ],
    "name:por_x_preferred":[
        "General Alvear"
    ],
    "name:spa_x_preferred":[
        "General Alvear"
    ],
    "name:swe_x_preferred":[
        "General Alvear"
    ],
    "name:ukr_x_preferred":[
        "\u0425\u0435\u043d\u0435\u0440\u0430\u043b\u044c-\u0410\u043b\u044c\u0432\u0435\u0430\u0440"
    ],
    "qs:gn_country":"AR",
    "qs:gn_fcode":"PPL",
    "qs:gn_pop":1431,
    "qs:name":"General Alvear",
    "qs:name_adm0":"Argentina",
    "qs:name_adm1":"Misiones",
    "qs:photos":0,
    "qs:photos_1k":0,
    "qs:photos_9k":1,
    "qs:photos_9r":1,
    "qs:photos_all":1,
    "qs:photos_sr":0,
    "qs:placetype":"Town",
    "qs:pop_sr":"3",
    "qs:woe_adm0":23424747,
    "wd:wordcount":38,
    "wof:name":"General Alvear",
    "wof:placetype":"locality",
    "wof:population":1431
},
  "geometry": {"coordinates":[-55.16667,-27.43333],"type":"Point"}
}