{
  "type": "Feature",
  "properties": {
    "gn:admin1_code":"10",
    "gn:admin2_code":"38077.0",
    "gn:asciiname":"Cieneguillas",
    "gn:cc2":"AR",
    "gn:country_code":"AR",
    "gn:dem":3677,
    "gn:feature_class":"P",
    "gn:feature_code":"PPL",
    "gn:name":"Cieneguillas",
    "gn:population":0,
    "gn:timezone":"America/Argentina/Jujuy",
    "iso:country":"AR",
    "name:und_x_variant":[
        "Cieneguilla",
        "Cienaguillas",
        "Cieneguillas"
    ],
    "wof:name":"Cieneguillas",
    "wof:placetype":"locality"
},
  "geometry": {"coordinates":[-65.88333,-22.08333],"type":"Point"}
}