{
  "type": "Feature",
  "properties": {
    "gn:admin1_code":"08",
    "gn:admin2_code":"30028.0",
    "gn:asciiname":"J. Miguez",
    "gn:country_code":"AR",
    "gn:dem":75,
    "gn:feature_class":"P",
    "gn:feature_code":"PPL",
    "gn:name":"J. M\u00edguez",
    "gn:population":0,
    "gn:timezone":"America/Argentina/Cordoba",
    "iso:country":"AR",
    "name:spa_x_preferred":[
        "J. M\u00edguez"
    ],
    "wof:name":"J. Miguez",
    "wof:placetype":"locality"
},
  "geometry": {"coordinates":[-58.49707,-30.61873],"type":"Point"}
}