{
  "type": "Feature",
  "properties": {
    "gn:admin1_code":"9.0",
    "gn:admin2_code":"34042.0",
    "gn:asciiname":"Tres Lagunas",
    "gn:country_code":"AR",
    "gn:dem":83,
    "gn:feature_class":"P",
    "gn:feature_code":"PPL",
    "gn:name":"Tres Lagunas",
    "gn:population":0,
    "gn:timezone":"America/Argentina/Cordoba",
    "iso:country":"AR",
    "wof:name":"Tres Lagunas",
    "wof:placetype":"locality"
},
  "geometry": {"coordinates":[-58.45172,-25.25129],"type":"Point"}
}