{
  "type": "Feature",
  "properties": {
    "gn:admin1_code":"16.0",
    "gn:admin2_code":"62021.0",
    "gn:asciiname":"Rio Villegas",
    "gn:country_code":"AR",
    "gn:dem":529,
    "gn:feature_class":"P",
    "gn:feature_code":"PPL",
    "gn:name":"R\u00edo Villegas",
    "gn:population":0,
    "gn:timezone":"America/Argentina/Salta",
    "iso:country":"AR",
    "wof:name":"Rio Villegas",
    "wof:placetype":"locality"
},
  "geometry": {"coordinates":[-71.50126,-41.57821],"type":"Point"}
}