{
  "type": "Feature",
  "properties": {
    "gn:admin1_code":"9.0",
    "gn:admin2_code":"34063.0",
    "gn:asciiname":"Pozo de los Chanchos",
    "gn:cc2":"AR",
    "gn:country_code":"AR",
    "gn:dem":205,
    "gn:feature_class":"P",
    "gn:feature_code":"PPL",
    "gn:name":"Pozo de los Chanchos",
    "gn:population":0,
    "gn:timezone":"America/Argentina/Cordoba",
    "iso:country":"AR",
    "name:und_x_variant":[
        "Paloma",
        "La Paloma",
        "Puesto Pozo de los Chanchos",
        "Pozo de los Chanchos"
    ],
    "wof:name":"Pozo de los Chanchos",
    "wof:placetype":"locality"
},
  "geometry": {"coordinates":[-62.08333,-23.26667],"type":"Point"}
}