{
  "type": "Feature",
  "properties": {
    "iso:country":"AR",
    "name:ceb_x_preferred":[
        "Cavanagh"
    ],
    "name:eng_x_preferred":[
        "Cavanagh"
    ],
    "name:por_x_preferred":[
        "Cavanagh"
    ],
    "name:spa_x_preferred":[
        "Cavanagh"
    ],
    "name:swe_x_preferred":[
        "Cavanagh"
    ],
    "qs:gn_country":"AR",
    "qs:gn_fcode":"PPL",
    "qs:gn_pop":1150,
    "qs:name":"Cavanagh",
    "qs:name_adm0":"Argentina",
    "qs:name_adm1":"C\u00f3rdoba",
    "qs:photos":0,
    "qs:photos_1k":0,
    "qs:photos_9k":0,
    "qs:photos_9r":0,
    "qs:photos_all":0,
    "qs:photos_sr":0,
    "qs:placetype":"Town",
    "qs:pop_sr":"3",
    "qs:woe_adm0":23424747,
    "wd:wordcount":1249,
    "wof:name":"Cavanagh",
    "wof:placetype":"locality",
    "wof:population":1150
},
  "geometry": {"coordinates":[-62.33888,-33.47606],"type":"Point"}
}