{
  "type": "Feature",
  "properties": {
    "gn:admin1_code":"21.0",
    "gn:admin2_code":"82133.0",
    "gn:asciiname":"Espin",
    "gn:country_code":"AR",
    "gn:dem":61,
    "gn:feature_class":"P",
    "gn:feature_code":"PPL",
    "gn:name":"Esp\u00edn",
    "gn:population":0,
    "gn:timezone":"America/Argentina/Cordoba",
    "iso:country":"AR",
    "name:deu_x_preferred":[
        "Espin"
    ],
    "name:ita_x_preferred":[
        "Espin"
    ],
    "wof:name":"Espin",
    "wof:placetype":"locality"
},
  "geometry": {"coordinates":[-60.2205,-29.55132],"type":"Point"}
}