{
  "type": "Feature",
  "properties": {
    "gn:admin1_code":"23.0",
    "gn:admin2_code":"94007.0",
    "gn:asciiname":"Jose Menendez",
    "gn:country_code":"AR",
    "gn:dem":19,
    "gn:feature_class":"P",
    "gn:feature_code":"PPL",
    "gn:name":"Jos\u00e9 Men\u00e9ndez",
    "gn:population":0,
    "gn:timezone":"America/Argentina/Ushuaia",
    "iso:country":"AR",
    "name:und_x_variant":[
        "Estancia J. Men\u00e9ndez",
        "Candelaria",
        "Jos\u00e9 Men\u00e9ndez"
    ],
    "wof:name":"Jose Menendez",
    "wof:placetype":"locality"
},
  "geometry": {"coordinates":[-67.78319999999999,-53.85763000000001],"type":"Point"}
}