{
  "type": "Feature",
  "properties": {
    "gn:admin1_code":"02",
    "gn:admin2_code":"10042.0",
    "gn:asciiname":"Canada Larga",
    "gn:country_code":"AR",
    "gn:dem":465,
    "gn:feature_class":"P",
    "gn:feature_code":"PPL",
    "gn:name":"Ca\u00f1ada Larga",
    "gn:population":0,
    "gn:timezone":"America/Argentina/Catamarca",
    "iso:country":"AR",
    "wof:name":"Canada Larga",
    "wof:placetype":"locality"
},
  "geometry": {"coordinates":[-65.63333,-29.06667],"type":"Point"}
}