{
  "type": "Feature",
  "properties": {
    "gn:admin1_code":"3.0",
    "gn:admin2_code":"22154.0",
    "gn:asciiname":"Paso de Oso",
    "gn:country_code":"AR",
    "gn:dem":86,
    "gn:feature_class":"P",
    "gn:feature_code":"PPL",
    "gn:name":"Paso de Oso",
    "gn:population":0,
    "gn:timezone":"America/Argentina/Cordoba",
    "iso:country":"AR",
    "name:und_x_variant":[
        "Fort\u00edn Paso del Oso",
        "Paso del Oso",
        "Paso de Oso"
    ],
    "wof:name":"Paso de Oso",
    "wof:placetype":"locality"
},
  "geometry": {"coordinates":[-59.84428000000001,-26.69882],"type":"Point"}
}