{
  "type": "Feature",
  "properties": {
    "gn:country":"AR",
    "gn:fcode":"PPL",
    "gn:population":2138,
    "iso:country":"AR",
    "name:ceb_x_preferred":[
        "Alpachiri"
    ],
    "name:deu_x_preferred":[
        "Alpachiri"
    ],
    "name:eng_x_preferred":[
        "Alpachiri"
    ],
    "name:fas_x_preferred":[
        "\u0627\u0644\u067e\u0627\u0686\u06cc\u0631\u06cc"
    ],
    "name:fra_x_preferred":[
        "Alpachiri"
    ],
    "name:nld_x_preferred":[
        "Alpachiri"
    ],
    "name:por_x_preferred":[
        "Alpachiri"
    ],
    "name:spa_x_preferred":[
        "Alpachiri"
    ],
    "name:swe_x_preferred":[
        "Alpachiri"
    ],
    "qs:name":"Alpachiri",
    "qs:photos_9r":0,
    "qs:photos_sr":0,
    "qs:pop_sr":"4",
    "wd:wordcount":73,
    "wof:name":"Alpachiri",
    "wof:placetype":"locality",
    "wof:population":2138
},
  "geometry": {"coordinates":[-63.77445,-37.37704],"type":"Point"}
}