{
  "type": "Feature",
  "properties": {
    "gn:admin1_code":"13.0",
    "gn:admin2_code":"50077.0",
    "gn:asciiname":"Los Ramblones",
    "gn:country_code":"AR",
    "gn:dem":2051,
    "gn:feature_class":"P",
    "gn:feature_code":"PPL",
    "gn:name":"Los Ramblones",
    "gn:population":0,
    "gn:timezone":"America/Argentina/Mendoza",
    "iso:country":"AR",
    "wof:name":"Los Ramblones",
    "wof:placetype":"locality"
},
  "geometry": {"coordinates":[-69.38333,-36.01667],"type":"Point"}
}