{
  "type": "Feature",
  "properties": {
    "iso:country":"AR",
    "name:eng_x_preferred":[
        "Marull"
    ],
    "name:nld_x_preferred":[
        "Marull"
    ],
    "name:por_x_preferred":[
        "Marull"
    ],
    "name:spa_x_preferred":[
        "Marull"
    ],
    "name:swe_x_preferred":[
        "Marull"
    ],
    "name:unk_x_variant":[
        "Kil\u00f3metro 267"
    ],
    "qs:gn_country":"AR",
    "qs:gn_fcode":"PPL",
    "qs:gn_pop":1765,
    "qs:name":"Marull",
    "qs:name_adm0":"Argentina",
    "qs:name_adm1":"C\u00f3rdoba",
    "qs:photos":0,
    "qs:photos_1k":0,
    "qs:photos_9k":0,
    "qs:photos_9r":0,
    "qs:photos_all":0,
    "qs:photos_sr":0,
    "qs:placetype":"Town",
    "qs:pop_sr":"3",
    "qs:woe_adm0":23424747,
    "wof:name":"Marull",
    "wof:placetype":"locality",
    "wof:population":1765
},
  "geometry": {"coordinates":[-62.82576,-30.99471],"type":"Point"}
}