{
  "type": "Feature",
  "properties": {
    "gn:admin1_code":"05",
    "gn:admin2_code":"14168.0",
    "gn:asciiname":"Agua de las Piedras",
    "gn:country_code":"AR",
    "gn:dem":759,
    "gn:feature_class":"P",
    "gn:feature_code":"PPL",
    "gn:name":"Agua de las Piedras",
    "gn:population":0,
    "gn:timezone":"America/Argentina/Cordoba",
    "iso:country":"AR",
    "wof:name":"Agua de las Piedras",
    "wof:placetype":"locality"
},
  "geometry": {"coordinates":[-64.20721,-30.80905],"type":"Point"}
}