{
  "type": "Feature",
  "properties": {
    "iso:country":"AR",
    "name:ceb_x_preferred":[
        "Iruya"
    ],
    "name:deu_x_preferred":[
        "Iruya"
    ],
    "name:eng_x_preferred":[
        "Iruya"
    ],
    "name:fra_x_preferred":[
        "Iruya"
    ],
    "name:nld_x_preferred":[
        "Iruya"
    ],
    "name:por_x_preferred":[
        "Iruya"
    ],
    "name:spa_x_preferred":[
        "Iruya"
    ],
    "name:zho_x_preferred":[
        "\u4f0a\u9b6f\u4e9e"
    ],
    "qs:gn_country":"AR",
    "qs:gn_fcode":"PPL",
    "qs:gn_pop":0,
    "qs:name":"Iruya",
    "qs:name_adm0":"Argentina",
    "qs:name_adm1":"Salta",
    "qs:photos":478,
    "qs:photos_1k":97,
    "qs:photos_9k":2,
    "qs:photos_9r":5,
    "qs:photos_all":478,
    "qs:photos_sr":7,
    "qs:placetype":"Town",
    "qs:pop_sr":"0",
    "qs:woe_adm0":23424747,
    "wof:name":"Iruya",
    "wof:placetype":"locality"
},
  "geometry": {"coordinates":[-65.23333,-22.76667],"type":"Point"}
}