{
  "type": "Feature",
  "properties": {
    "gn:admin1_code":"18.0",
    "gn:admin2_code":"70056.0",
    "gn:asciiname":"Villa Mercedes",
    "gn:country_code":"AR",
    "gn:dem":1148,
    "gn:feature_class":"P",
    "gn:feature_code":"PPL",
    "gn:name":"Villa Mercedes",
    "gn:population":0,
    "gn:timezone":"America/Argentina/San_Juan",
    "iso:country":"AR",
    "wof:name":"Villa Mercedes",
    "wof:placetype":"locality"
},
  "geometry": {"coordinates":[-68.70419,-30.1081],"type":"Point"}
}