{
  "type": "Feature",
  "properties": {
    "gn:admin1_code":"05",
    "gn:admin2_code":"14126.0",
    "gn:asciiname":"El Banado",
    "gn:country_code":"AR",
    "gn:dem":1063,
    "gn:feature_class":"P",
    "gn:feature_code":"PPL",
    "gn:name":"El Ba\u00f1ado",
    "gn:population":0,
    "gn:timezone":"America/Argentina/Cordoba",
    "iso:country":"AR",
    "wof:name":"El Banado",
    "wof:placetype":"locality"
},
  "geometry": {"coordinates":[-65.10908000000001,-31.48905],"type":"Point"}
}