{
  "type": "Feature",
  "properties": {
    "iso:country":"AR",
    "name:und_x_variant":[
        "A. Etcheverry"
    ],
    "qs:gn_country":"AR",
    "qs:gn_fcode":"PPL",
    "qs:gn_pop":0,
    "qs:name":"\u00c1ngel Etcheverry",
    "qs:name_adm0":"Argentina",
    "qs:name_adm1":"Buenos Aires",
    "qs:photos":0,
    "qs:photos_1k":0,
    "qs:photos_9k":0,
    "qs:photos_9r":0,
    "qs:photos_all":0,
    "qs:photos_sr":0,
    "qs:placetype":"Town",
    "qs:pop_sr":"0",
    "qs:woe_adm0":23424747,
    "wof:name":"\u00c1ngel Etcheverry",
    "wof:placetype":"locality"
},
  "geometry": {"coordinates":[-58.06997,-35.02812],"type":"Point"}
}