{
  "type": "Feature",
  "properties": {
    "iso:country":"AR",
    "name:eng_x_preferred":[
        "Barreal"
    ],
    "name:nld_x_preferred":[
        "Barreal"
    ],
    "name:spa_x_preferred":[
        "Barreal"
    ],
    "name:ukr_x_preferred":[
        "\u0411\u0430\u0440\u0440\u0435\u0430\u043b\u044c"
    ],
    "name:und_x_variant":[
        "Barriales"
    ],
    "name:zho_x_preferred":[
        "\u5df4\u96f7\u963f\u723e"
    ],
    "qs:gn_country":"AR",
    "qs:gn_fcode":"PPL",
    "qs:gn_pop":0,
    "qs:name":"Barreal",
    "qs:name_adm0":"Argentina",
    "qs:name_adm1":"San Juan",
    "qs:photos":119,
    "qs:photos_1k":24,
    "qs:photos_9k":1,
    "qs:photos_9r":3,
    "qs:photos_all":119,
    "qs:photos_sr":3,
    "qs:placetype":"Town",
    "qs:pop_sr":"0",
    "qs:woe_adm0":23424747,
    "wof:name":"Barreal",
    "wof:placetype":"locality"
},
  "geometry": {"coordinates":[-69.46617999999999,-31.62304],"type":"Point"}
}