{
  "type": "Feature",
  "properties": {
    "iso:country":"AR",
    "name:ceb_x_preferred":[
        "Capilla del Monte"
    ],
    "name:deu_x_preferred":[
        "Capilla del Monte"
    ],
    "name:eng_x_preferred":[
        "Capilla del Monte"
    ],
    "name:fra_x_preferred":[
        "Capilla del Monte"
    ],
    "name:ita_x_preferred":[
        "Capilla del Monte"
    ],
    "name:jpn_x_preferred":[
        "\u30ab\u30d4\u30fc\u30b8\u30e3\u30c7\u30eb\u30e2\u30f3\u30c6"
    ],
    "name:lit_x_preferred":[
        "Kapilja del Mont\u0117"
    ],
    "name:nld_x_preferred":[
        "Capilla del Monte"
    ],
    "name:por_x_preferred":[
        "Capilla del Monte"
    ],
    "name:spa_x_preferred":[
        "Capilla del Monte"
    ],
    "name:swe_x_preferred":[
        "Capilla del Monte"
    ],
    "name:ukr_x_preferred":[
        "\u041a\u0430\u043f\u0456\u043b\u044c\u044f-\u0434\u0435\u043b\u044c-\u041c\u043e\u043d\u0442\u0435"
    ],
    "name:zho_x_preferred":[
        "\u5361\u76ae\u4e9e\u5fb7\u723e\u8499\u7279"
    ],
    "qs:gn_country":"AR",
    "qs:gn_fcode":"PPL",
    "qs:gn_pop":9085,
    "qs:name":"Capilla del Monte",
    "qs:name_adm0":"Argentina",
    "qs:name_adm1":"C\u00f3rdoba",
    "qs:photos":786,
    "qs:photos_1k":159,
    "qs:photos_9k":3,
    "qs:photos_9r":6,
    "qs:photos_all":786,
    "qs:photos_sr":9,
    "qs:placetype":"Town",
    "qs:pop_sr":"7",
    "qs:woe_adm0":23424747,
    "wd:wordcount":171,
    "wof:name":"Capilla del Monte",
    "wof:placetype":"locality",
    "wof:population":9085
},
  "geometry": {"coordinates":[-64.52515,-30.86088],"type":"Point"}
}