{
  "type": "Feature",
  "properties": {
    "iso:country":"AR",
    "name:eng_x_preferred":[
        "Tancacha"
    ],
    "name:nld_x_preferred":[
        "Tancacha"
    ],
    "name:por_x_preferred":[
        "Tancacha"
    ],
    "name:spa_x_preferred":[
        "Tancacha"
    ],
    "name:ukr_x_preferred":[
        "\u0422\u0430\u043d\u043a\u0430\u0447\u0430"
    ],
    "qs:gn_country":"AR",
    "qs:gn_fcode":"PPL",
    "qs:gn_pop":5184,
    "qs:name":"Tancacha",
    "qs:name_adm0":"Argentina",
    "qs:name_adm1":"C\u00f3rdoba",
    "qs:photos":0,
    "qs:photos_1k":0,
    "qs:photos_9k":1,
    "qs:photos_9r":1,
    "qs:photos_all":1,
    "qs:photos_sr":0,
    "qs:placetype":"Town",
    "qs:pop_sr":"5",
    "qs:woe_adm0":23424747,
    "wof:name":"Tancacha",
    "wof:placetype":"locality",
    "wof:population":5184
},
  "geometry": {"coordinates":[-63.9807,-32.24309],"type":"Point"}
}