{
  "type": "Feature",
  "properties": {
    "iso:country":"AR",
    "qs:gn_country":"AR",
    "qs:gn_fcode":"PPL",
    "qs:gn_pop":0,
    "qs:name":"Puerto Canoas",
    "qs:name_adm0":"Argentina",
    "qs:name_adm1":"Misiones",
    "qs:photos":3954,
    "qs:photos_1k":801,
    "qs:photos_9k":18,
    "qs:photos_9r":12,
    "qs:photos_all":3954,
    "qs:photos_sr":22,
    "qs:placetype":"Town",
    "qs:pop_sr":"0",
    "qs:woe_adm0":23424747,
    "wof:name":"Puerto Canoas",
    "wof:placetype":"locality"
},
  "geometry": {"coordinates":[-54.42805,-25.70392],"type":"Point"}
}