{
  "type": "Feature",
  "properties": {
    "gn:admin1_code":"14.0",
    "gn:admin2_code":"54077.0",
    "gn:asciiname":"Puerto Oro Verde",
    "gn:country_code":"AR",
    "gn:dem":140,
    "gn:feature_class":"P",
    "gn:feature_code":"PPL",
    "gn:name":"Puerto Oro Verde",
    "gn:population":0,
    "gn:timezone":"America/Argentina/Cordoba",
    "iso:country":"AR",
    "wof:name":"Puerto Oro Verde",
    "wof:placetype":"locality"
},
  "geometry": {"coordinates":[-55.12748000000001,-26.86052],"type":"Point"}
}