{
  "type": "Feature",
  "properties": {
    "gn:admin1_code":"05",
    "gn:admin2_code":"14056.0",
    "gn:asciiname":"Bengolea",
    "gn:country_code":"AR",
    "gn:dem":232,
    "gn:feature_class":"P",
    "gn:feature_code":"PPL",
    "gn:name":"Bengolea",
    "gn:population":0,
    "gn:timezone":"America/Argentina/Cordoba",
    "iso:country":"AR",
    "wof:name":"Bengolea",
    "wof:placetype":"locality"
},
  "geometry": {"coordinates":[-63.6726,-33.02518],"type":"Point"}
}