{
  "type": "Feature",
  "properties": {
    "iso:country":"AR",
    "name:ceb_x_preferred":[
        "Roque P\u00e9rez"
    ],
    "name:dan_x_preferred":[
        "Roque P\u00e9rez"
    ],
    "name:eng_x_preferred":[
        "Roque P\u00e9rez"
    ],
    "name:fra_x_preferred":[
        "Roque P\u00e9rez"
    ],
    "name:ita_x_preferred":[
        "Roque P\u00e9rez"
    ],
    "name:ltz_x_preferred":[
        "Roque P\u00e9rez"
    ],
    "name:nld_x_preferred":[
        "Roque P\u00e9rez"
    ],
    "name:rus_x_preferred":[
        "\u0420\u043e\u043a\u0435-\u041f\u0435\u0440\u0435\u0441"
    ],
    "name:spa_x_preferred":[
        "Roque P\u00e9rez"
    ],
    "name:swe_x_preferred":[
        "Roque P\u00e9rez"
    ],
    "name:ukr_x_preferred":[
        "\u0420\u043e\u043a\u0435-\u041f\u0435\u0440\u0435\u0441"
    ],
    "name:und_x_variant":[
        "R. P\u00e9rez"
    ],
    "qs:gn_country":"AR",
    "qs:gn_fcode":"PPL",
    "qs:gn_pop":0,
    "qs:name":"Roque P\u00e9rez",
    "qs:name_adm0":"Argentina",
    "qs:name_adm1":"Buenos Aires",
    "qs:photos":0,
    "qs:photos_1k":0,
    "qs:photos_9k":0,
    "qs:photos_9r":0,
    "qs:photos_all":0,
    "qs:photos_sr":0,
    "qs:placetype":"Town",
    "qs:pop_sr":"7",
    "qs:woe_adm0":23424747,
    "wd:elevation":26.0,
    "wd:wordcount":41,
    "wof:name":"Roque P\u00e9rez",
    "wof:placetype":"locality"
},
  "geometry": {"coordinates":[-59.33271,-35.39794],"type":"Point"}
}