{
  "type": "Feature",
  "properties": {
    "iso:country":"AR",
    "qs:gn_country":"AR",
    "qs:gn_fcode":"PPL",
    "qs:gn_pop":0,
    "qs:name":"Villa Independencia",
    "qs:name_adm0":"Argentina",
    "qs:name_adm1":"C\u00f3rdoba",
    "qs:photos":100,
    "qs:photos_1k":20,
    "qs:photos_9k":1,
    "qs:photos_9r":3,
    "qs:photos_all":100,
    "qs:photos_sr":3,
    "qs:placetype":"Town",
    "qs:pop_sr":"0",
    "qs:woe_adm0":23424747,
    "wd:wordcount":50,
    "wof:name":"Villa Independencia",
    "wof:placetype":"locality"
},
  "geometry": {"coordinates":[-64.51322,-31.45594],"type":"Point"}
}