{
  "type": "Feature",
  "properties": {
    "gn:admin1_code":"21.0",
    "gn:admin2_code":"82126.0",
    "gn:asciiname":"Maria Susana",
    "gn:country_code":"AR",
    "gn:dem":112,
    "gn:feature_class":"P",
    "gn:feature_code":"PPL",
    "gn:name":"Mar\u00eda Susana",
    "gn:population":0,
    "gn:timezone":"America/Argentina/Cordoba",
    "iso:country":"AR",
    "wof:name":"Maria Susana",
    "wof:placetype":"locality"
},
  "geometry": {"coordinates":[-61.90292,-32.26561],"type":"Point"}
}