{
  "type": "Feature",
  "properties": {
    "gn:admin1_code":"24.0",
    "gn:admin2_code":"90056.0",
    "gn:asciiname":"Lunarejos",
    "gn:country_code":"AR",
    "gn:dem":299,
    "gn:feature_class":"P",
    "gn:feature_code":"PPL",
    "gn:name":"Lunarejos",
    "gn:population":0,
    "gn:timezone":"America/Argentina/Tucuman",
    "iso:country":"AR",
    "wof:name":"Lunarejos",
    "wof:placetype":"locality"
},
  "geometry": {"coordinates":[-65.20014,-27.34347],"type":"Point"}
}