{
  "type": "Feature",
  "properties": {
    "gn:admin1_code":"5.0",
    "gn:admin2_code":"14077.0",
    "gn:asciiname":"Toros Muertos",
    "gn:country_code":"AR",
    "gn:dem":902,
    "gn:feature_class":"P",
    "gn:feature_code":"PPL",
    "gn:name":"Toros Muertos",
    "gn:population":0,
    "gn:timezone":"America/Argentina/Cordoba",
    "iso:country":"AR",
    "wof:name":"Toros Muertos",
    "wof:placetype":"locality"
},
  "geometry": {"coordinates":[-65.12181,-31.26992000000001],"type":"Point"}
}