{
  "type": "Feature",
  "properties": {
    "gn:admin1_code":"8.0",
    "gn:admin2_code":"30084.0",
    "gn:asciiname":"El Pingo",
    "gn:country_code":"AR",
    "gn:dem":96,
    "gn:feature_class":"P",
    "gn:feature_code":"PPL",
    "gn:name":"El Pingo",
    "gn:population":0,
    "gn:timezone":"America/Argentina/Cordoba",
    "iso:country":"AR",
    "name:por_x_preferred":[
        "El Pingo"
    ],
    "name:spa_x_preferred":[
        "El Pingo"
    ],
    "wof:name":"El Pingo",
    "wof:placetype":"locality"
},
  "geometry": {"coordinates":[-59.8916,-31.58286],"type":"Point"}
}