{
  "type": "Feature",
  "properties": {
    "gn:admin1_code":"5.0",
    "gn:admin2_code":"14133.0",
    "gn:asciiname":"Los Molles",
    "gn:country_code":"AR",
    "gn:dem":870,
    "gn:feature_class":"P",
    "gn:feature_code":"PPL",
    "gn:name":"Los Molles",
    "gn:population":0,
    "gn:timezone":"America/Argentina/Cordoba",
    "iso:country":"AR",
    "wof:name":"Los Molles",
    "wof:placetype":"locality"
},
  "geometry": {"coordinates":[-65.02506,-31.96415],"type":"Point"}
}