{
  "type": "Feature",
  "properties": {
    "gn:admin1_code":"5.0",
    "gn:admin2_code":"14133.0",
    "gn:asciiname":"Quebracho Ladeado",
    "gn:country_code":"AR",
    "gn:dem":813,
    "gn:feature_class":"P",
    "gn:feature_code":"PPL",
    "gn:name":"Quebracho Ladeado",
    "gn:population":0,
    "gn:timezone":"America/Argentina/Cordoba",
    "iso:country":"AR",
    "wof:name":"Quebracho Ladeado",
    "wof:placetype":"locality"
},
  "geometry": {"coordinates":[-65.03270999999999,-32.25878],"type":"Point"}
}