{
  "type": "Feature",
  "properties": {
    "gn:admin1_code":"1.0",
    "gn:admin2_code":"6742.0",
    "gn:asciiname":"Defferrari",
    "gn:country_code":"AR",
    "gn:dem":105,
    "gn:feature_class":"P",
    "gn:feature_code":"PPL",
    "gn:name":"Defferrari",
    "gn:population":0,
    "gn:timezone":"America/Argentina/Buenos_Aires",
    "iso:country":"AR",
    "wof:name":"Defferrari",
    "wof:placetype":"locality"
},
  "geometry": {"coordinates":[-59.38703,-38.30148],"type":"Point"}
}