{
  "type": "Feature",
  "properties": {
    "gn:admin1_code":"20.0",
    "gn:admin2_code":"78049.0",
    "gn:asciiname":"La Herreria",
    "gn:country_code":"AR",
    "gn:dem":394,
    "gn:feature_class":"P",
    "gn:feature_code":"PPL",
    "gn:name":"La Herrer\u00eda",
    "gn:population":0,
    "gn:timezone":"America/Argentina/Rio_Gallegos",
    "iso:country":"AR",
    "wof:name":"La Herreria",
    "wof:placetype":"locality"
},
  "geometry": {"coordinates":[-70.55,-48.56667],"type":"Point"}
}