{
  "type": "Feature",
  "properties": {
    "gn:admin1_code":"5.0",
    "gn:admin2_code":"14161.0",
    "gn:asciiname":"Las Isletillas",
    "gn:country_code":"AR",
    "gn:dem":337,
    "gn:feature_class":"P",
    "gn:feature_code":"PPL",
    "gn:name":"Las Isletillas",
    "gn:population":0,
    "gn:timezone":"America/Argentina/Cordoba",
    "iso:country":"AR",
    "wof:name":"Las Isletillas",
    "wof:placetype":"locality"
},
  "geometry": {"coordinates":[-63.92875,-32.51001],"type":"Point"}
}