{
  "type": "Feature",
  "properties": {
    "gn:country":"AR",
    "gn:fcode":"PPL",
    "gn:pop":4290,
    "iso:country":"AR",
    "qs:name":"San Antonio",
    "qs:photos_9r":0,
    "qs:photos_sr":0,
    "qs:pop_sr":"4",
    "wof:name":"San Antonio",
    "wof:placetype":"locality",
    "wof:population":4290
},
  "geometry": {"coordinates":[-65.71218,-28.00927],"type":"Point"}
}