{
  "type": "Feature",
  "properties": {
    "gn:admin1_code":"01",
    "gn:admin2_code":"6840.0",
    "gn:asciiname":"Podesta",
    "gn:country_code":"AR",
    "gn:dem":24,
    "gn:feature_class":"P",
    "gn:feature_code":"PPL",
    "gn:name":"Podesta",
    "gn:population":0,
    "gn:timezone":"America/Argentina/Buenos_Aires",
    "iso:country":"AR",
    "name:spa_x_preferred":[
        "Podesta"
    ],
    "wof:name":"Podesta",
    "wof:placetype":"locality"
},
  "geometry": {"coordinates":[-58.60215,-34.58475],"type":"Point"}
}