{
  "type": "Feature",
  "properties": {
    "iso:country":"AR",
    "qs:gn_pop":0,
    "qs:name":"Ea. Los Tajamares",
    "qs:name_adm0":"Argentina",
    "qs:name_adm1":"Chubut",
    "qs:photos":29,
    "qs:photos_1k":6,
    "qs:photos_9k":1,
    "qs:photos_9r":2,
    "qs:photos_all":29,
    "qs:photos_sr":2,
    "qs:placetype":"Town",
    "qs:pop_sr":"0",
    "qs:woe_adm0":23424747,
    "wof:name":"Ea. Los Tajamares",
    "wof:placetype":"locality"
},
  "geometry": {"coordinates":[-66.47552399999999,-43.699713],"type":"Point"}
}