{
  "type": "Feature",
  "properties": {
    "gn:admin1_code":"5.0",
    "gn:admin2_code":"14147.0",
    "gn:asciiname":"Villa Serranita",
    "gn:country_code":"AR",
    "gn:dem":547,
    "gn:feature_class":"P",
    "gn:feature_code":"PPL",
    "gn:name":"Villa Serranita",
    "gn:population":0,
    "gn:timezone":"America/Argentina/Cordoba",
    "iso:country":"AR",
    "wof:name":"Villa Serranita",
    "wof:placetype":"locality"
},
  "geometry": {"coordinates":[-64.45548000000001,-31.73599],"type":"Point"}
}