{
  "type": "Feature",
  "properties": {
    "gn:admin1_code":"16",
    "gn:admin2_code":"62014.0",
    "gn:asciiname":"Colonia Josefa",
    "gn:country_code":"AR",
    "gn:dem":106,
    "gn:feature_class":"P",
    "gn:feature_code":"PPL",
    "gn:name":"Colonia Josefa",
    "gn:population":0,
    "gn:timezone":"America/Argentina/Salta",
    "iso:country":"AR",
    "wof:name":"Colonia Josefa",
    "wof:placetype":"locality"
},
  "geometry": {"coordinates":[-65.41667,-39.73333],"type":"Point"}
}