{
  "type": "Feature",
  "properties": {
    "gn:admin1_code":"17",
    "gn:admin2_code":"66161.0",
    "gn:asciiname":"Chorro",
    "gn:country_code":"AR",
    "gn:dem":3113,
    "gn:feature_class":"P",
    "gn:feature_code":"PPL",
    "gn:name":"Chorro",
    "gn:population":0,
    "gn:timezone":"America/Argentina/Salta",
    "iso:country":"AR",
    "name:bre_x_preferred":[
        "Chorro"
    ],
    "name:spa_x_preferred":[
        "Chorro"
    ],
    "wof:name":"Chorro",
    "wof:placetype":"locality"
},
  "geometry": {"coordinates":[-64.93333,-22.28333],"type":"Point"}
}