{
  "type": "Feature",
  "properties": {
    "gn:admin1_code":"01",
    "gn:admin2_code":"6189.0",
    "gn:asciiname":"Centro Urquiza",
    "gn:country_code":"AR",
    "gn:dem":221,
    "gn:feature_class":"P",
    "gn:feature_code":"PPL",
    "gn:name":"Centro Urquiza",
    "gn:population":0,
    "gn:timezone":"America/Argentina/Buenos_Aires",
    "iso:country":"AR",
    "wof:name":"Centro Urquiza",
    "wof:placetype":"locality"
},
  "geometry": {"coordinates":[-61.37622,-38.47838],"type":"Point"}
}