{
  "type": "Feature",
  "properties": {
    "iso:country":"AR",
    "name:ara_x_preferred":[
        "\u0643\u0648\u0633\u062a\u0627 \u062f\u064a\u0644 \u0625\u0633\u062a\u064a"
    ],
    "name:eng_x_preferred":[
        "Costa del Este"
    ],
    "name:nld_x_preferred":[
        "Costa del Este"
    ],
    "name:spa_x_preferred":[
        "Costa del Este"
    ],
    "qs:gn_country":"AR",
    "qs:gn_fcode":"PPL",
    "qs:gn_pop":0,
    "qs:name":"Costa Del Este",
    "qs:name_adm0":"Argentina",
    "qs:name_adm1":"Buenos Aires",
    "qs:photos":0,
    "qs:photos_1k":0,
    "qs:photos_9k":1,
    "qs:photos_9r":1,
    "qs:photos_all":2,
    "qs:photos_sr":0,
    "qs:placetype":"Town",
    "qs:pop_sr":"0",
    "qs:woe_adm0":23424747,
    "wd:wordcount":66,
    "wof:name":"Costa Del Este",
    "wof:placetype":"locality"
},
  "geometry": {"coordinates":[-56.69327,-36.61122],"type":"Point"}
}