{
  "type": "Feature",
  "properties": {
    "iso:country":"AR",
    "name:ara_x_preferred":[
        "\u0628\u0644\u062f\u064a\u0629 \u0623\u0644\u062a\u0648 \u0631\u064a\u0648 \u0633\u0646\u062c\u0648\u0631"
    ],
    "name:ceb_x_preferred":[
        "Alto R\u00edo Senguer"
    ],
    "name:deu_x_preferred":[
        "Alto R\u00edo Senguer"
    ],
    "name:eng_x_preferred":[
        "Alto R\u00edo Senguer"
    ],
    "name:fas_x_preferred":[
        "\u0622\u0644\u062a\u0648 \u0631\u06cc\u0648 \u0633\u06af\u0648\u06cc\u0631"
    ],
    "name:fas_x_variant":[
        "\u0627\u0644\u062a\u0648 \u0631\u06cc\u0648 \u0633\u06af\u0648\u06cc\u0631"
    ],
    "name:fra_x_preferred":[
        "Alto R\u00edo Senguer"
    ],
    "name:ita_x_preferred":[
        "Alto R\u00edo Senguer"
    ],
    "name:jpn_x_preferred":[
        "\u30a2\u30eb\u30c8\u30fb\u30ea\u30aa\u30fb\u30bb\u30f3\u30b2\u30eb"
    ],
    "name:lit_x_preferred":[
        "Alto Rio Sengeras"
    ],
    "name:nld_x_preferred":[
        "Alto R\u00edo Senguer"
    ],
    "name:por_x_preferred":[
        "Alto R\u00edo Senguer"
    ],
    "name:slk_x_preferred":[
        "Alto R\u00edo Senguer"
    ],
    "name:spa_x_preferred":[
        "Alto R\u00edo Senguer"
    ],
    "name:swe_x_preferred":[
        "Alto R\u00edo Senguer"
    ],
    "name:unk_x_variant":[
        "Brazo Norte"
    ],
    "name:zho_x_preferred":[
        "\u4e0a\u91cc\u5967\u68ee\u683c\u723e"
    ],
    "qs:gn_country":"AR",
    "qs:gn_fcode":"PPL",
    "qs:gn_pop":1700,
    "qs:name":"Alto R\u00edo Senguerr",
    "qs:name_adm0":"Argentina",
    "qs:name_adm1":"Chubut",
    "qs:photos":0,
    "qs:photos_1k":0,
    "qs:photos_9k":1,
    "qs:photos_9r":3,
    "qs:photos_all":85,
    "qs:photos_sr":0,
    "qs:placetype":"Town",
    "qs:pop_sr":"3",
    "qs:woe_adm0":23424747,
    "wd:wordcount":49,
    "wof:name":"Alto R\u00edo Senguerr",
    "wof:placetype":"locality",
    "wof:population":1700
},
  "geometry": {"coordinates":[-70.81982000000001,-45.04105],"type":"Point"}
}