{
  "type": "Feature",
  "properties": {
    "gn:admin1_code":"14.0",
    "gn:admin2_code":"54098.0",
    "gn:asciiname":"Corpus",
    "gn:country_code":"AR",
    "gn:dem":162,
    "gn:feature_class":"P",
    "gn:feature_code":"PPL",
    "gn:name":"Corpus",
    "gn:population":0,
    "gn:timezone":"America/Argentina/Cordoba",
    "iso:country":"AR",
    "name:bul_x_preferred":[
        "\u041a\u043e\u0440\u043f\u0443\u0441"
    ],
    "name:ceb_x_preferred":[
        "Corpus"
    ],
    "name:ces_x_preferred":[
        "Jazykov\u00fd korpus"
    ],
    "name:deu_x_preferred":[
        "Textkorpus"
    ],
    "name:deu_x_variant":[
        "Corpus"
    ],
    "name:ell_x_preferred":[
        "\u03a3\u03ce\u03bc\u03b1 \u03ba\u03b5\u03b9\u03bc\u03ad\u03bd\u03c9\u03bd"
    ],
    "name:eng_x_preferred":[
        "Text corpus"
    ],
    "name:epo_x_preferred":[
        "Korpuso"
    ],
    "name:eus_x_preferred":[
        "Testu corpus"
    ],
    "name:fra_x_preferred":[
        "Corpus"
    ],
    "name:ita_x_preferred":[
        "Corpus"
    ],
    "name:jpn_x_preferred":[
        "\u30b3\u30fc\u30d1\u30b9"
    ],
    "name:msa_x_preferred":[
        "Korpus"
    ],
    "name:nld_x_preferred":[
        "Corpus"
    ],
    "name:por_x_preferred":[
        "Corpus"
    ],
    "name:slk_x_preferred":[
        "Korpus"
    ],
    "name:spa_x_preferred":[
        "Corpus"
    ],
    "name:spa_x_variant":[
        "Corpus Christi"
    ],
    "name:swe_x_preferred":[
        "Corpus"
    ],
    "name:tha_x_preferred":[
        "\u0e04\u0e25\u0e31\u0e07\u0e02\u0e49\u0e2d\u0e04\u0e27\u0e32\u0e21"
    ],
    "name:zho_x_preferred":[
        "\u8bed\u6599\u5e93"
    ],
    "wof:name":"Corpus",
    "wof:placetype":"locality"
},
  "geometry": {"coordinates":[-55.51028,-27.12806],"type":"Point"}
}