{
  "type": "Feature",
  "properties": {
    "gn:admin1_code":"1.0",
    "gn:admin2_code":"6189.0",
    "gn:asciiname":"Jose A. Guisasola",
    "gn:country_code":"AR",
    "gn:dem":120,
    "gn:feature_class":"P",
    "gn:feature_code":"PPL",
    "gn:name":"Jos\u00e9 A. Guisasola",
    "gn:population":0,
    "gn:timezone":"America/Argentina/Buenos_Aires",
    "iso:country":"AR",
    "name:und_x_variant":[
        "Perdido",
        "J.A. Guisasola",
        "Jos\u00e9 A. Guisasola"
    ],
    "wof:name":"Jose A. Guisasola",
    "wof:placetype":"locality"
},
  "geometry": {"coordinates":[-61.08789,-38.67578],"type":"Point"}
}