{
  "type": "Feature",
  "properties": {
    "gn:admin1_code":"23.0",
    "gn:admin2_code":"94007.0",
    "gn:asciiname":"Mision Salesiana de Santo Domingo",
    "gn:country_code":"AR",
    "gn:dem":7,
    "gn:feature_class":"P",
    "gn:feature_code":"PPL",
    "gn:name":"Misi\u00f3n Salesiana de Santo Domingo",
    "gn:population":0,
    "gn:timezone":"America/Argentina/Ushuaia",
    "iso:country":"AR",
    "wof:name":"Mision Salesiana de Santo Domingo",
    "wof:placetype":"locality"
},
  "geometry": {"coordinates":[-67.79911,-53.72317],"type":"Point"}
}