{
  "type": "Feature",
  "properties": {
    "gn:gn_country":"AR",
    "gn:gn_fcode":"PPL",
    "gn:gn_pop":0,
    "iso:country":"AR",
    "name:bul_x_preferred":[
        "\u041b\u0438\u043d\u0447"
    ],
    "name:ceb_x_preferred":[
        "Lynch"
    ],
    "name:ces_x_preferred":[
        "Lynch"
    ],
    "name:deu_x_preferred":[
        "Lynch"
    ],
    "name:est_x_preferred":[
        "Lynch"
    ],
    "name:fin_x_preferred":[
        "Lynch"
    ],
    "name:fra_x_preferred":[
        "Lynch"
    ],
    "name:heb_x_preferred":[
        "\u05dc\u05d9\u05e0\u05e5'"
    ],
    "name:ita_x_preferred":[
        "Lynch"
    ],
    "name:jpn_x_preferred":[
        "\u30ea\u30f3\u30c1"
    ],
    "name:kor_x_preferred":[
        "\ub9b0\uce58"
    ],
    "name:lav_x_preferred":[
        "Lynch"
    ],
    "name:lit_x_preferred":[
        "Lynch"
    ],
    "name:nld_x_preferred":[
        "Lynch"
    ],
    "name:pol_x_preferred":[
        "Lynch"
    ],
    "name:por_x_preferred":[
        "Lynch"
    ],
    "name:rus_x_preferred":[
        "\u041b\u0438\u043d\u0447"
    ],
    "name:spa_x_preferred":[
        "Lynch"
    ],
    "name:srp_x_preferred":[
        "\u041b\u0438\u043d\u0447"
    ],
    "name:swe_x_preferred":[
        "Lynch"
    ],
    "name:tgl_x_preferred":[
        "Lynch"
    ],
    "name:ukr_x_preferred":[
        "\u041b\u0456\u043d\u0447"
    ],
    "name:vol_x_preferred":[
        "Lynch"
    ],
    "qs_pg:aaroncc":"AR",
    "qs_pg:gn_country":"AR",
    "qs_pg:gn_fcode":"PPL",
    "qs_pg:gn_pop":0,
    "qs_pg:name":"Lynch",
    "qs_pg:name_adm0":"Argentina",
    "qs_pg:name_adm1":"Ciudad de Buenos Aires",
    "qs_pg:photos":128,
    "qs_pg:photos_1k":26,
    "qs_pg:photos_9k":1,
    "qs_pg:photos_9r":3,
    "qs_pg:photos_all":128,
    "qs_pg:photos_sr":3,
    "qs_pg:pop_sr":0,
    "qs_pg:qs_pg_placetype":"neighbourhood",
    "qs_pg:qs_pg_placetype_gp":"Suburb",
    "qs_pg:woe_adm0":23424747,
    "woe:adm0_id":23424747,
    "woe:name_adm0":"Argentina",
    "woe:name_adm1":"Ciudad de Buenos Aires",
    "woe:placetype":"Suburb",
    "wof:name":"Lynch",
    "wof:placetype":"neighbourhood"
},
  "geometry": {"coordinates":[-58.52493,-34.59256],"type":"Point"}
}