{
  "type": "Feature",
  "properties": {
    "gn:admin1_code":"22.0",
    "gn:admin2_code":"86049.0",
    "gn:asciiname":"Tipiro",
    "gn:country_code":"AR",
    "gn:dem":218,
    "gn:feature_class":"P",
    "gn:feature_code":"PPL",
    "gn:name":"Tipiro",
    "gn:population":0,
    "gn:timezone":"America/Argentina/Cordoba",
    "iso:country":"AR",
    "wof:name":"Tipiro",
    "wof:placetype":"locality"
},
  "geometry": {"coordinates":[-64.43482,-27.63446],"type":"Point"}
}