{
  "type": "Feature",
  "properties": {
    "gn:admin1_code":"01",
    "gn:admin2_code":"6770.0",
    "gn:asciiname":"Colonia Velaz",
    "gn:country_code":"AR",
    "gn:dem":49,
    "gn:feature_class":"P",
    "gn:feature_code":"PPL",
    "gn:name":"Colonia V\u00e9laz",
    "gn:population":0,
    "gn:timezone":"America/Argentina/Buenos_Aires",
    "iso:country":"AR",
    "wof:name":"Colonia Velaz",
    "wof:placetype":"locality"
},
  "geometry": {"coordinates":[-60.02506,-33.81176],"type":"Point"}
}