{
  "type": "Feature",
  "properties": {
    "gn:admin1_code":"22.0",
    "gn:admin2_code":"86119.0",
    "gn:asciiname":"Otumpa",
    "gn:country_code":"AR",
    "gn:dem":156,
    "gn:feature_class":"P",
    "gn:feature_code":"PPL",
    "gn:name":"Otumpa",
    "gn:population":0,
    "gn:timezone":"America/Argentina/Cordoba",
    "iso:country":"AR",
    "wof:name":"Otumpa",
    "wof:placetype":"locality"
},
  "geometry": {"coordinates":[-62.21666999999999,-27.31667],"type":"Point"}
}