{
  "type": "Feature",
  "properties": {
    "gn:admin1_code":"08",
    "gn:admin2_code":"30056.0",
    "gn:asciiname":"Pueblo General Belgrano",
    "gn:country_code":"AR",
    "gn:dem":12,
    "gn:feature_class":"P",
    "gn:feature_code":"PPL",
    "gn:name":"Pueblo General Belgrano",
    "gn:population":0,
    "gn:timezone":"America/Argentina/Cordoba",
    "iso:country":"AR",
    "wof:name":"Pueblo General Belgrano",
    "wof:placetype":"locality"
},
  "geometry": {"coordinates":[-58.51416,-33.01028],"type":"Point"}
}