{
  "type": "Feature",
  "properties": {
    "iso:country":"AR",
    "name:ast_x_preferred":[
        "Federal"
    ],
    "name:ceb_x_preferred":[
        "Federal"
    ],
    "name:eng_x_preferred":[
        "Federal"
    ],
    "name:fra_x_preferred":[
        "Federal"
    ],
    "name:nld_x_preferred":[
        "Federal"
    ],
    "name:pol_x_preferred":[
        "Federal"
    ],
    "name:por_x_preferred":[
        "Federal"
    ],
    "name:rus_x_preferred":[
        "\u0424\u0435\u0434\u0435\u0440\u0430\u043b\u044c"
    ],
    "name:spa_x_preferred":[
        "Federal"
    ],
    "name:swe_x_preferred":[
        "Federal"
    ],
    "name:tur_x_preferred":[
        "Federal"
    ],
    "name:ukr_x_preferred":[
        "\u0424\u0435\u0434\u0435\u0440\u0430\u043b\u044c"
    ],
    "name:und_x_variant":[
        "Villa Federal"
    ],
    "name:zho_x_preferred":[
        "\u8cbb\u5fb7\u62c9\u723e"
    ],
    "qs:gn_country":"AR",
    "qs:gn_fcode":"PPL",
    "qs:gn_pop":16333,
    "qs:name":"Federal",
    "qs:name_adm0":"Argentina",
    "qs:name_adm1":"Entre R\u00edos",
    "qs:photos":5,
    "qs:photos_1k":1,
    "qs:photos_9k":1,
    "qs:photos_9r":1,
    "qs:photos_all":5,
    "qs:photos_sr":1,
    "qs:placetype":"Town",
    "qs:pop_sr":"7",
    "qs:woe_adm0":23424747,
    "wd:wordcount":134,
    "wof:name":"Federal",
    "wof:placetype":"locality",
    "wof:population":16333
},
  "geometry": {"coordinates":[-58.78326,-30.95465],"type":"Point"}
}