{
  "type": "Feature",
  "properties": {
    "gn:admin1_code":"05",
    "gn:admin2_code":"14028.0",
    "gn:asciiname":"Banado de Soto",
    "gn:country_code":"AR",
    "gn:dem":498,
    "gn:feature_class":"P",
    "gn:feature_code":"PPL",
    "gn:name":"Ba\u00f1ado de Soto",
    "gn:population":0,
    "gn:timezone":"America/Argentina/Cordoba",
    "iso:country":"AR",
    "wof:name":"Banado de Soto",
    "wof:placetype":"locality"
},
  "geometry": {"coordinates":[-65.05476999999999,-30.79258],"type":"Point"}
}