{
  "type": "Feature",
  "properties": {
    "gn:admin1_code":"17.0",
    "gn:admin2_code":"66133.0",
    "gn:asciiname":"El Pertigo",
    "gn:country_code":"AR",
    "gn:dem":219,
    "gn:feature_class":"P",
    "gn:feature_code":"PPL",
    "gn:name":"El P\u00e9rtigo",
    "gn:population":0,
    "gn:timezone":"America/Argentina/Salta",
    "iso:country":"AR",
    "wof:name":"El Pertigo",
    "wof:placetype":"locality"
},
  "geometry": {"coordinates":[-62.85,-23.65],"type":"Point"}
}