{
  "type": "Feature",
  "properties": {
    "gn:admin1_code":"01",
    "gn:admin2_code":"6277.0",
    "gn:asciiname":"Blaquier",
    "gn:country_code":"AR",
    "gn:dem":112,
    "gn:feature_class":"P",
    "gn:feature_code":"PPL",
    "gn:name":"Blaquier",
    "gn:population":0,
    "gn:timezone":"America/Argentina/Buenos_Aires",
    "iso:country":"AR",
    "wof:name":"Blaquier",
    "wof:placetype":"locality"
},
  "geometry": {"coordinates":[-62.47686,-34.63645],"type":"Point"}
}