{
  "type": "Feature",
  "properties": {
    "gn:admin1_code":"24.0",
    "gn:admin2_code":"90035.0",
    "gn:asciiname":"Toro Muerto",
    "gn:country_code":"AR",
    "gn:dem":313,
    "gn:feature_class":"P",
    "gn:feature_code":"PPL",
    "gn:name":"Toro Muerto",
    "gn:population":0,
    "gn:timezone":"America/Argentina/Tucuman",
    "iso:country":"AR",
    "wof:name":"Toro Muerto",
    "wof:placetype":"locality"
},
  "geometry": {"coordinates":[-65.36541,-27.56182],"type":"Point"}
}