{
  "type": "Feature",
  "properties": {
    "gn:admin1_code":"24.0",
    "gn:admin2_code":"90035.0",
    "gn:asciiname":"Toro Muerto",
    "gn:country_code":"AR",
    "gn:dem":313,
    "gn:feature_class":"P",
    "gn:feature_code":"PPL",
    "gn:name":"Toro Muerto",
    "gn:population":0,
    "gn:timezone":"America/Argentina/Tucuman",
    "iso:country":"AR",
    "name:bel_x_preferred":[
        "\u0422\u043e\u0440\u0430-\u041c\u0443\u044d\u0440\u0442\u0430"
    ],
    "name:ces_x_preferred":[
        "Toro Muerto"
    ],
    "name:ita_x_preferred":[
        "Toro Muerto"
    ],
    "name:kat_x_preferred":[
        "\u10e2\u10dd\u10e0\u10dd-\u10db\u10e3\u10d4\u10e0\u10e2\u10dd"
    ],
    "name:lit_x_preferred":[
        "Toro Muerto petroglifai"
    ],
    "name:mkd_x_preferred":[
        "\u0422\u043e\u0440\u043e \u041c\u0443\u0435\u0440\u0442\u043e"
    ],
    "name:que_x_preferred":[
        "Hatun Qillqapampa"
    ],
    "name:rus_x_preferred":[
        "\u0422\u043e\u0440\u043e-\u041c\u0443\u044d\u0440\u0442\u043e"
    ],
    "wof:name":"Toro Muerto",
    "wof:placetype":"locality"
},
  "geometry": {"coordinates":[-65.36541,-27.56182],"type":"Point"}
}