{
  "type": "Feature",
  "properties": {
    "iso:country":"AR",
    "qs:gn_country":"AR",
    "qs:gn_fcode":"PPL",
    "qs:gn_pop":3350,
    "qs:name":"San Alonso",
    "qs:name_adm0":"Argentina",
    "qs:name_adm1":"Corrientes",
    "qs:photos":0,
    "qs:photos_1k":0,
    "qs:photos_9k":0,
    "qs:photos_9r":0,
    "qs:photos_all":0,
    "qs:photos_sr":0,
    "qs:placetype":"Town",
    "qs:pop_sr":"4",
    "qs:woe_adm0":23424747,
    "wof:name":"San Alonso",
    "wof:placetype":"locality",
    "wof:population":3350
},
  "geometry": {"coordinates":[-55.8973,-27.74586],"type":"Point"}
}