{
  "type": "Feature",
  "properties": {
    "gn:admin1_code":"05",
    "gn:admin2_code":"14126.0",
    "gn:asciiname":"Cienaga de Allende",
    "gn:country_code":"AR",
    "gn:dem":1005,
    "gn:feature_class":"P",
    "gn:feature_code":"PPL",
    "gn:name":"Ci\u00e9naga de Allende",
    "gn:population":0,
    "gn:timezone":"America/Argentina/Cordoba",
    "iso:country":"AR",
    "wof:name":"Cienaga de Allende",
    "wof:placetype":"locality"
},
  "geometry": {"coordinates":[-65.11288,-31.74179],"type":"Point"}
}