{
  "type": "Feature",
  "properties": {
    "gn:admin1_code":"08",
    "gn:admin2_code":"30028.0",
    "gn:asciiname":"F. Leonardeli",
    "gn:country_code":"AR",
    "gn:dem":48,
    "gn:feature_class":"P",
    "gn:feature_code":"PPL",
    "gn:name":"F. Leonardeli",
    "gn:population":0,
    "gn:timezone":"America/Argentina/Cordoba",
    "iso:country":"AR",
    "name:spa_x_preferred":[
        "F. Leonardeli"
    ],
    "wof:name":"F. Leonardeli",
    "wof:placetype":"locality"
},
  "geometry": {"coordinates":[-58.01645,-30.65268],"type":"Point"}
}