{
  "type": "Feature",
  "properties": {
    "gn:admin1_code":"21.0",
    "gn:admin2_code":"82056.0",
    "gn:asciiname":"San Estanislao",
    "gn:country_code":"AR",
    "gn:dem":116,
    "gn:feature_class":"P",
    "gn:feature_code":"PPL",
    "gn:name":"San Estanislao",
    "gn:population":0,
    "gn:timezone":"America/Argentina/Cordoba",
    "iso:country":"AR",
    "wof:name":"San Estanislao",
    "wof:placetype":"locality"
},
  "geometry": {"coordinates":[-61.51536,-32.90774],"type":"Point"}
}