{
  "type": "Feature",
  "properties": {
    "gn:admin1_code":"21.0",
    "gn:admin2_code":"82056.0",
    "gn:asciiname":"San Estanislao",
    "gn:country_code":"AR",
    "gn:dem":116,
    "gn:feature_class":"P",
    "gn:feature_code":"PPL",
    "gn:name":"San Estanislao",
    "gn:population":0,
    "gn:timezone":"America/Argentina/Cordoba",
    "iso:country":"AR",
    "name:deu_x_preferred":[
        "San Estanislao"
    ],
    "name:eus_x_preferred":[
        "San Estanislao"
    ],
    "name:fas_x_preferred":[
        "\u0633\u0646 \u0627\u0633\u062a\u0627\u0646\u06cc\u0633\u0644\u0627\u0648"
    ],
    "name:grn_x_preferred":[
        "Santani"
    ],
    "name:ita_x_preferred":[
        "San Estanislao"
    ],
    "name:kat_x_preferred":[
        "\u10e1\u10d0\u10dc-\u10d4\u10e1\u10e2\u10d0\u10dc\u10d8\u10e1\u10da\u10d0\u10dd"
    ],
    "name:lit_x_preferred":[
        "San Estanislao"
    ],
    "name:pol_x_preferred":[
        "San Estanislao"
    ],
    "name:por_x_preferred":[
        "San Estanislao"
    ],
    "name:ron_x_preferred":[
        "San Estanislao"
    ],
    "name:spa_x_preferred":[
        "San Estanislao"
    ],
    "name:zho_x_preferred":[
        "\u8056\u57c3\u65af\u5854\u5c3c\u65af\u52de"
    ],
    "wof:name":"San Estanislao",
    "wof:placetype":"locality"
},
  "geometry": {"coordinates":[-61.51536,-32.90774],"type":"Point"}
}