{
  "type": "Feature",
  "properties": {
    "iso:country":"AR",
    "name:ceb_x_preferred":[
        "El Salto"
    ],
    "name:deu_x_preferred":[
        "El Salto"
    ],
    "name:epo_x_preferred":[
        "El Salto"
    ],
    "name:ita_x_preferred":[
        "El Salto"
    ],
    "name:spa_x_preferred":[
        "El Salto"
    ],
    "name:srp_x_preferred":[
        "\u0415\u043b \u0421\u0430\u043b\u0442\u043e"
    ],
    "name:swe_x_preferred":[
        "El Salto"
    ],
    "name:vie_x_preferred":[
        "El Salto"
    ],
    "qs:gn_pop":0,
    "qs:name":"El Salto",
    "qs:name_adm0":"Argentina",
    "qs:name_adm1":"Mendoza",
    "qs:photos":41,
    "qs:photos_1k":8,
    "qs:photos_9k":1,
    "qs:photos_9r":2,
    "qs:photos_all":41,
    "qs:photos_sr":2,
    "qs:placetype":"Town",
    "qs:pop_sr":"0",
    "qs:woe_adm0":23424747,
    "wof:name":"El Salto",
    "wof:placetype":"locality"
},
  "geometry": {"coordinates":[-69.351,-32.960966],"type":"Point"}
}