{
  "type": "Feature",
  "properties": {
    "gn:admin1_code":"5.0",
    "gn:admin2_code":"14112.0",
    "gn:asciiname":"Puesto de Castro",
    "gn:country_code":"AR",
    "gn:dem":101,
    "gn:feature_class":"P",
    "gn:feature_code":"PPL",
    "gn:name":"Puesto de Castro",
    "gn:population":0,
    "gn:timezone":"America/Argentina/Cordoba",
    "iso:country":"AR",
    "wof:name":"Puesto de Castro",
    "wof:placetype":"locality"
},
  "geometry": {"coordinates":[-63.42533,-30.26952],"type":"Point"}
}