{
  "type": "Feature",
  "properties": {
    "gn:admin1_code":"21",
    "gn:admin2_code":"82035.0",
    "gn:asciiname":"Colonia Campo del Medio",
    "gn:country_code":"AR",
    "gn:dem":24,
    "gn:feature_class":"P",
    "gn:feature_code":"PPL",
    "gn:name":"Colonia Campo del Medio",
    "gn:population":0,
    "gn:timezone":"America/Argentina/Cordoba",
    "iso:country":"AR",
    "wof:name":"Colonia Campo del Medio",
    "wof:placetype":"locality"
},
  "geometry": {"coordinates":[-60.13193,-31.14165],"type":"Point"}
}