{
  "type": "Feature",
  "properties": {
    "gn:admin1_code":"13.0",
    "gn:admin2_code":"50105.0",
    "gn:asciiname":"El Nihuil",
    "gn:cc2":"AR",
    "gn:country_code":"AR",
    "gn:dem":1326,
    "gn:feature_class":"P",
    "gn:feature_code":"PPL",
    "gn:name":"El Nihuil",
    "gn:population":0,
    "gn:timezone":"America/Argentina/Mendoza",
    "iso:country":"AR",
    "name:und_x_variant":[
        "Fort\u00edn Nihuil",
        "Niguil",
        "Nihuil",
        "El Nihuil"
    ],
    "wof:name":"El Nihuil",
    "wof:placetype":"locality"
},
  "geometry": {"coordinates":[-68.66667,-35.03333],"type":"Point"}
}