{
  "type": "Feature",
  "properties": {
    "gn:admin1_code":"5.0",
    "gn:admin2_code":"14098.0",
    "gn:asciiname":"El Tambo",
    "gn:country_code":"AR",
    "gn:dem":608,
    "gn:feature_class":"P",
    "gn:feature_code":"PPL",
    "gn:name":"El Tambo",
    "gn:population":0,
    "gn:timezone":"America/Argentina/Cordoba",
    "iso:country":"AR",
    "name:ceb_x_preferred":[
        "El Tambo"
    ],
    "name:fas_x_preferred":[
        "\u0627\u0644 \u062a\u0627\u0645\u0628\u0648"
    ],
    "name:fra_x_preferred":[
        "El Tambo"
    ],
    "name:ita_x_preferred":[
        "El Tambo"
    ],
    "name:nld_x_preferred":[
        "El Tambo"
    ],
    "name:swe_x_preferred":[
        "El Tambo"
    ],
    "wof:name":"El Tambo",
    "wof:placetype":"locality"
},
  "geometry": {"coordinates":[-64.53333000000001,-32.93333],"type":"Point"}
}