{
  "type": "Feature",
  "properties": {
    "iso:country":"AR",
    "qs:gn_country":"AR",
    "qs:gn_fcode":"PPL",
    "qs:gn_pop":0,
    "qs:name":"Villa Arcadia",
    "qs:name_adm0":"Argentina",
    "qs:name_adm1":"Buenos Aires",
    "qs:photos":0,
    "qs:photos_1k":0,
    "qs:photos_9k":1,
    "qs:photos_9r":1,
    "qs:photos_all":2,
    "qs:photos_sr":0,
    "qs:placetype":"Town",
    "qs:pop_sr":"0",
    "qs:woe_adm0":23424747,
    "wof:name":"Villa Arcadia",
    "wof:placetype":"locality"
},
  "geometry": {"coordinates":[-61.96667,-38.88333],"type":"Point"}
}