{
  "type": "Feature",
  "properties": {
    "iso:country":"AR",
    "name:cat_x_preferred":[
        "O'Higgins"
    ],
    "name:ces_x_preferred":[
        "O'Higgins"
    ],
    "name:deu_x_preferred":[
        "O\u2019Higgins"
    ],
    "name:fin_x_preferred":[
        "O\u2019Higgins"
    ],
    "name:fra_x_preferred":[
        "O'Higgins"
    ],
    "name:heb_x_preferred":[
        "\u05d0\u05d5'\u05d4\u05d9\u05d2\u05d9\u05e0\u05e1"
    ],
    "name:ita_x_preferred":[
        "O'Higgins"
    ],
    "name:nld_x_preferred":[
        "O'Higgins"
    ],
    "name:pol_x_preferred":[
        "O\u2019Higgins"
    ],
    "name:por_x_preferred":[
        "O'Higgins"
    ],
    "name:rus_x_preferred":[
        "\u041e\u2019\u0425\u0438\u0433\u0433\u0438\u043d\u0441"
    ],
    "name:spa_x_preferred":[
        "O'Higgins"
    ],
    "name:swe_x_preferred":[
        "O'Higgins"
    ],
    "name:tur_x_preferred":[
        "O'Higgins"
    ],
    "qs:gn_country":"AR",
    "qs:gn_fcode":"PPL",
    "qs:gn_pop":0,
    "qs:name":"O'Higgins",
    "qs:name_adm0":"Argentina",
    "qs:name_adm1":"Buenos Aires",
    "qs:photos":0,
    "qs:photos_1k":0,
    "qs:photos_9k":1,
    "qs:photos_9r":1,
    "qs:photos_all":19,
    "qs:photos_sr":0,
    "qs:placetype":"Town",
    "qs:pop_sr":"0",
    "qs:woe_adm0":23424747,
    "wd:wordcount":120,
    "wof:name":"O'Higgins",
    "wof:placetype":"locality"
},
  "geometry": {"coordinates":[-60.6995,-34.58468],"type":"Point"}
}