{
  "type": "Feature",
  "properties": {
    "gn:admin1_code":"01",
    "gn:admin2_code":"6007.0",
    "gn:asciiname":"Colonia San Miguel Arcangel",
    "gn:country_code":"AR",
    "gn:dem":181,
    "gn:feature_class":"P",
    "gn:feature_code":"PPL",
    "gn:name":"Colonia San Miguel Arc\u00e1ngel",
    "gn:population":0,
    "gn:timezone":"America/Argentina/Buenos_Aires",
    "iso:country":"AR",
    "name:und_x_variant":[
        "San Miguel Arc\u00e1ngel",
        "Colonia San Miguel Arc\u00e1ngel"
    ],
    "wof:name":"Colonia San Miguel Arcangel",
    "wof:placetype":"locality"
},
  "geometry": {"coordinates":[-63.11816,-37.44906],"type":"Point"}
}