{
  "type": "Feature",
  "properties": {
    "gn:admin1_code":"5.0",
    "gn:admin2_code":"14105.0",
    "gn:asciiname":"Rangel",
    "gn:country_code":"AR",
    "gn:dem":276,
    "gn:feature_class":"P",
    "gn:feature_code":"PPL",
    "gn:name":"Rangel",
    "gn:population":0,
    "gn:timezone":"America/Argentina/Cordoba",
    "iso:country":"AR",
    "name:rus_x_preferred":[
        "\u0420\u0430\u043d\u0445\u0435\u043b\u044c"
    ],
    "wof:name":"Rangel",
    "wof:placetype":"locality"
},
  "geometry": {"coordinates":[-63.77887,-31.12171],"type":"Point"}
}