{
  "type": "Feature",
  "properties": {
    "iso:country":"AR",
    "name:ceb_x_preferred":[
        "Ranchos"
    ],
    "name:spa_x_preferred":[
        "Ranchos"
    ],
    "name:swe_x_preferred":[
        "Ranchos"
    ],
    "name:unk_x_variant":[
        "General Paz"
    ],
    "qs:gn_country":"AR",
    "qs:gn_fcode":"PPL",
    "qs:gn_pop":0,
    "qs:name":"Ranchos",
    "qs:name_adm0":"Argentina",
    "qs:name_adm1":"Buenos Aires",
    "qs:photos":37,
    "qs:photos_1k":7,
    "qs:photos_9k":1,
    "qs:photos_9r":2,
    "qs:photos_all":37,
    "qs:photos_sr":2,
    "qs:placetype":"Town",
    "qs:pop_sr":"0",
    "qs:woe_adm0":23424747,
    "wd:wordcount":104,
    "wof:name":"Ranchos",
    "wof:placetype":"locality"
},
  "geometry": {"coordinates":[-58.31733,-35.51619],"type":"Point"}
}