{
  "type": "Feature",
  "properties": {
    "gn:admin1_code":"5.0",
    "gn:admin2_code":"14084.0",
    "gn:asciiname":"Vivero",
    "gn:country_code":"AR",
    "gn:dem":127,
    "gn:feature_class":"P",
    "gn:feature_code":"PPL",
    "gn:name":"Vivero",
    "gn:population":0,
    "gn:timezone":"America/Argentina/Cordoba",
    "iso:country":"AR",
    "wof:name":"Vivero",
    "wof:placetype":"locality"
},
  "geometry": {"coordinates":[-62.83333,-34.23333],"type":"Point"}
}