{
  "type": "Feature",
  "properties": {
    "gn:admin1_code":"12",
    "gn:admin2_code":"46070.0",
    "gn:asciiname":"Atiles",
    "gn:country_code":"AR",
    "gn:dem":750,
    "gn:feature_class":"P",
    "gn:feature_code":"PPL",
    "gn:name":"Atiles",
    "gn:population":0,
    "gn:timezone":"America/Argentina/La_Rioja",
    "iso:country":"AR",
    "wof:name":"Atiles",
    "wof:placetype":"locality"
},
  "geometry": {"coordinates":[-66.66988000000001,-30.76243],"type":"Point"}
}