{
  "type": "Feature",
  "properties": {
    "gn:admin1_code":"1.0",
    "gn:admin2_code":"6588.0",
    "gn:asciiname":"Mulcahy",
    "gn:country_code":"AR",
    "gn:dem":75,
    "gn:feature_class":"P",
    "gn:feature_code":"PPL",
    "gn:name":"Mulcahy",
    "gn:population":0,
    "gn:timezone":"America/Argentina/Buenos_Aires",
    "iso:country":"AR",
    "wof:name":"Mulcahy",
    "wof:placetype":"locality"
},
  "geometry": {"coordinates":[-60.70951,-35.49449],"type":"Point"}
}