{
  "type": "Feature",
  "properties": {
    "gn:admin1_code":"02",
    "gn:admin2_code":"10084.0",
    "gn:asciiname":"Colpes",
    "gn:country_code":"AR",
    "gn:dem":911,
    "gn:feature_class":"P",
    "gn:feature_code":"PPL",
    "gn:name":"Colpes",
    "gn:population":0,
    "gn:timezone":"America/Argentina/Catamarca",
    "iso:country":"AR",
    "name:und_x_variant":[
        "Golpes",
        "Colpes"
    ],
    "wof:name":"Colpes",
    "wof:placetype":"locality"
},
  "geometry": {"coordinates":[-66.19564,-28.05848],"type":"Point"}
}