{
  "type": "Feature",
  "properties": {
    "iso:country":"AR",
    "name:ceb_x_preferred":[
        "Santo Pip\u00f3"
    ],
    "name:deu_x_preferred":[
        "Santo Pip\u00f3"
    ],
    "name:eng_x_preferred":[
        "Santo Pip\u00f3"
    ],
    "name:fra_x_preferred":[
        "Santo Pip\u00f3"
    ],
    "name:nld_x_preferred":[
        "Santo Pip\u00f3"
    ],
    "name:por_x_preferred":[
        "Santo Pip\u00f3"
    ],
    "name:spa_x_preferred":[
        "Santo Pip\u00f3"
    ],
    "name:swe_x_preferred":[
        "Santo Pip\u00f3"
    ],
    "name:ukr_x_preferred":[
        "\u0421\u0430\u043d\u0442\u043e-\u041f\u0456\u043f\u043e"
    ],
    "name:unk_x_variant":[
        "Colonia Santo Pip\u00f3"
    ],
    "qs:gn_country":"AR",
    "qs:gn_fcode":"PPL",
    "qs:gn_pop":5447,
    "qs:name":"Santo Pip\u00f3",
    "qs:name_adm0":"Argentina",
    "qs:name_adm1":"Misiones",
    "qs:photos":0,
    "qs:photos_1k":0,
    "qs:photos_9k":1,
    "qs:photos_9r":1,
    "qs:photos_all":4,
    "qs:photos_sr":0,
    "qs:placetype":"Town",
    "qs:pop_sr":"5",
    "qs:woe_adm0":23424747,
    "wd:wordcount":35,
    "wof:name":"Santo Pip\u00f3",
    "wof:placetype":"locality",
    "wof:population":5447
},
  "geometry": {"coordinates":[-55.40867,-27.14132],"type":"Point"}
}