{
  "type": "Feature",
  "properties": {
    "gn:admin1_code":"1.0",
    "gn:admin2_code":"6224.0",
    "gn:asciiname":"La Rica",
    "gn:country_code":"AR",
    "gn:dem":55,
    "gn:feature_class":"P",
    "gn:feature_code":"PPL",
    "gn:name":"La Rica",
    "gn:population":0,
    "gn:timezone":"America/Argentina/Buenos_Aires",
    "iso:country":"AR",
    "name:spa_x_preferred":[
        "La Rica"
    ],
    "wof:name":"La Rica",
    "wof:placetype":"locality"
},
  "geometry": {"coordinates":[-59.8621,-34.97265],"type":"Point"}
}