{
  "type": "Feature",
  "properties": {
    "gn:admin1_code":"2.0",
    "gn:asciiname":"La Tusca",
    "gn:country_code":"AR",
    "gn:dem":763,
    "gn:feature_class":"P",
    "gn:feature_code":"PPL",
    "gn:name":"La Tusca",
    "gn:population":0,
    "gn:timezone":"America/Argentina/Catamarca",
    "iso:country":"AR",
    "wof:name":"La Tusca",
    "wof:placetype":"locality"
},
  "geometry": {"coordinates":[-66.66284,-28.30911],"type":"Point"}
}