{
  "type": "Feature",
  "properties": {
    "iso:country":"AR",
    "qs:gn_pop":0,
    "qs:name":"9 de Julio",
    "qs:name_adm0":"Argentina",
    "qs:name_adm1":"Buenos Aires",
    "qs:photos":44,
    "qs:photos_1k":9,
    "qs:photos_9k":1,
    "qs:photos_9r":2,
    "qs:photos_all":44,
    "qs:photos_sr":2,
    "qs:placetype":"Town",
    "qs:pop_sr":"0",
    "qs:woe_adm0":23424747,
    "wof:name":"9 de Julio",
    "wof:placetype":"locality"
},
  "geometry": {"coordinates":[-60.8822735,-35.449501],"type":"Point"}
}