{
  "type": "Feature",
  "properties": {
    "iso:country":"AR",
    "name:ara_x_preferred":[
        "\u0627\u0644\u0641\u064a\u0631\u060c \u0643\u0648\u0631\u064a\u064a\u0646\u062a\u0633"
    ],
    "name:ben_x_preferred":[
        "\u0986\u09b2\u09ad\u09bf\u09af\u09bc\u09be\u09b0"
    ],
    "name:cat_x_preferred":[
        "Alvear"
    ],
    "name:chi_x_preferred":[
        "\u963f\u723e\u97cb\u4e9e\u723e"
    ],
    "name:dan_x_preferred":[
        "Alvear"
    ],
    "name:dut_x_preferred":[
        "Alvear"
    ],
    "name:eng_x_preferred":[
        "Alvear"
    ],
    "name:fas_x_preferred":[
        "\u0627\u0644\u0648\u06cc\u06cc\u0631\u060c \u06a9\u0648\u0631\u06cc\u0646\u062a\u0633"
    ],
    "name:fin_x_preferred":[
        "Alvear"
    ],
    "name:fra_x_preferred":[
        "Alvear"
    ],
    "name:fre_x_preferred":[
        "Alvear"
    ],
    "name:gre_x_preferred":[
        "\u0391\u03bb\u03b2\u03b9\u03ac\u03c1"
    ],
    "name:guj_x_preferred":[
        "\u0a85\u0ab2\u0ab5\u0ac0\u0a85\u0ab0"
    ],
    "name:hin_x_preferred":[
        "\u0905\u0935\u0940\u092f\u0930"
    ],
    "name:ind_x_preferred":[
        "Alvear"
    ],
    "name:ita_x_preferred":[
        "Alvear"
    ],
    "name:jpn_x_preferred":[
        "\u30a2\u30eb\u30d9\u30a2\u30eb"
    ],
    "name:kan_x_preferred":[
        "\u0c85\u0cb2\u0ccd\u0cb5\u0cc6\u0cb0\u0ccd"
    ],
    "name:kor_x_preferred":[
        "\uc54c\ubca0\uc544\ub974"
    ],
    "name:lav_x_preferred":[
        "Alve\u0101ra"
    ],
    "name:lit_x_preferred":[
        "Alvearas"
    ],
    "name:mar_x_preferred":[
        "\u0906\u0932\u0935\u0947\u0905\u0930"
    ],
    "name:may_x_preferred":[
        "Alvear"
    ],
    "name:nld_x_preferred":[
        "Alvear"
    ],
    "name:nob_x_preferred":[
        "Alvear"
    ],
    "name:per_x_preferred":[
        "\u0627\u0644\u0648\u06cc\u06cc\u0631\u060c \u06a9\u0648\u0631\u06cc\u0646\u062a\u0633"
    ],
    "name:pol_x_preferred":[
        "Alvear"
    ],
    "name:por_x_preferred":[
        "Alvear"
    ],
    "name:rus_x_preferred":[
        "\u0410\u043b\u044c\u0432\u0435\u0430\u0440"
    ],
    "name:sin_x_preferred":[
        "\u0d87\u0dbd\u0dca\u0dc0\u0dd2\u0dba\u0dbb"
    ],
    "name:spa_x_preferred":[
        "Alvear"
    ],
    "name:swe_x_preferred":[
        "Alvear"
    ],
    "name:tam_x_preferred":[
        "\u0b85\u0bb3\u0bcd\u0bb5\u0bc7\u0bb0\u0bcd"
    ],
    "name:tel_x_preferred":[
        "\u0c05\u0c32\u0c35\u0c40\u0c30\u0c4d"
    ],
    "name:tha_x_preferred":[
        "\u0e2d\u0e31\u0e25\u0e40\u0e27\u0e35\u0e22\u0e23\u0e4c"
    ],
    "name:tur_x_preferred":[
        "Alvear"
    ],
    "name:ukr_x_preferred":[
        "\u0410\u043b\u044c\u0432\u0435\u0430\u0440"
    ],
    "name:urd_x_preferred":[
        "\u0627\u0644\u0648\u06cc\u0627\u0631"
    ],
    "name:vie_x_preferred":[
        "Alvear"
    ],
    "name:zho_x_preferred":[
        "\u963f\u723e\u97cb\u4e9e\u723e"
    ],
    "qs:gn_country":"AR",
    "qs:gn_fcode":"PPL",
    "qs:gn_pop":7917,
    "qs:name":"Alvear",
    "qs:name_adm0":"Argentina",
    "qs:name_adm1":"Corrientes",
    "qs:photos":66,
    "qs:photos_1k":13,
    "qs:photos_9k":1,
    "qs:photos_9r":2,
    "qs:photos_all":66,
    "qs:photos_sr":2,
    "qs:placetype":"Town",
    "qs:pop_sr":"5",
    "qs:woe_adm0":23424747,
    "wd:wordcount":340,
    "wof:name":"Alvear",
    "wof:placetype":"locality",
    "wof:population":7917
},
  "geometry": {"coordinates":[-56.55043,-29.09683],"type":"Point"}
}