{
  "type": "Feature",
  "properties": {
    "gn:admin1_code":"21.0",
    "gn:admin2_code":"82028.0",
    "gn:asciiname":"Francisco Paz",
    "gn:country_code":"AR",
    "gn:dem":77,
    "gn:feature_class":"P",
    "gn:feature_code":"PPL",
    "gn:name":"Francisco Paz",
    "gn:population":0,
    "gn:timezone":"America/Argentina/Cordoba",
    "iso:country":"AR",
    "name:und_x_variant":[
        "Franco Paz",
        "F. Paz",
        "Francisco Paz"
    ],
    "wof:name":"Francisco Paz",
    "wof:placetype":"locality"
},
  "geometry": {"coordinates":[-60.86814,-33.41546],"type":"Point"}
}