{
  "type": "Feature",
  "properties": {
    "gn:admin1_code":"13.0",
    "gn:admin2_code":"50063.0",
    "gn:asciiname":"La Carrodilla",
    "gn:country_code":"AR",
    "gn:dem":865,
    "gn:feature_class":"P",
    "gn:feature_code":"PPL",
    "gn:name":"La Carrodilla",
    "gn:population":0,
    "gn:timezone":"America/Argentina/Mendoza",
    "iso:country":"AR",
    "name:und_x_variant":[
        "Carrodilla",
        "La Carrodilla"
    ],
    "wof:name":"La Carrodilla",
    "wof:placetype":"locality"
},
  "geometry": {"coordinates":[-68.84705,-32.96115],"type":"Point"}
}