{
  "type": "Feature",
  "properties": {
    "iso:country":"AR",
    "name:ara_x_preferred":[
        "\u0631\u064a\u0648 \u063a\u0631\u0627\u0646\u062f\u064a\u060c \u062a\u064a\u064a\u0631\u0627 \u062f\u064a\u0644 \u0641\u0648\u064a\u063a\u0648"
    ],
    "name:ara_x_variant":[
        "\u0631\u064a\u0648 \u063a\u0631\u0627\u0646\u062f\u064a"
    ],
    "name:azb_x_preferred":[
        "\u0631\u06cc\u0648 \u0642\u0631\u0627\u0646\u062f\u0647"
    ],
    "name:cat_x_preferred":[
        "R\u00edo Grande"
    ],
    "name:ceb_x_preferred":[
        "R\u00edo Grande"
    ],
    "name:ces_x_preferred":[
        "R\u00edo Grande"
    ],
    "name:deu_x_preferred":[
        "R\u00edo Grande"
    ],
    "name:eng_x_preferred":[
        "R\u00edo Grande"
    ],
    "name:epo_x_preferred":[
        "R\u00edo Grande"
    ],
    "name:fas_x_preferred":[
        "\u0631\u06cc\u0648 \u06af\u0631\u0627\u0646\u062f\u0647\u060c \u062a\u06cc\u0631\u0627 \u062f\u0644 \u0641\u0648\u0626\u06af\u0648"
    ],
    "name:fas_x_variant":[
        "\u0631\u06cc\u0648 \u06af\u0631\u0627\u0646\u062f\u0647"
    ],
    "name:fra_x_preferred":[
        "R\u00edo Grande"
    ],
    "name:fry_x_preferred":[
        "R\u00edo Grande"
    ],
    "name:heb_x_preferred":[
        "\u05e8\u05d9\u05d5 \u05d2\u05e8\u05d0\u05e0\u05d3\u05d4"
    ],
    "name:hun_x_preferred":[
        "R\u00edo Grande"
    ],
    "name:ita_x_preferred":[
        "R\u00edo Grande"
    ],
    "name:jpn_x_preferred":[
        "\u30ea\u30aa\u30fb\u30b0\u30e9\u30f3\u30c7"
    ],
    "name:kor_x_preferred":[
        "\ub9ac\uc624\uadf8\ub780\ub370"
    ],
    "name:lit_x_preferred":[
        "Rio Grand\u0117"
    ],
    "name:nld_x_preferred":[
        "R\u00edo Grande"
    ],
    "name:nno_x_preferred":[
        "Rio Grande p\u00e5 Eldlandet"
    ],
    "name:nob_x_preferred":[
        "Rio Grande"
    ],
    "name:nor_x_preferred":[
        "Rio Grande"
    ],
    "name:pol_x_preferred":[
        "R\u00edo Grande"
    ],
    "name:por_x_preferred":[
        "Rio Grande"
    ],
    "name:rus_x_preferred":[
        "\u0420\u0438\u043e-\u0413\u0440\u0430\u043d\u0434\u0435"
    ],
    "name:slk_x_preferred":[
        "R\u00edo Grande"
    ],
    "name:slv_x_preferred":[
        "R\u00edo Grande"
    ],
    "name:spa_x_preferred":[
        "R\u00edo Grande"
    ],
    "name:swe_x_preferred":[
        "R\u00edo Grande"
    ],
    "name:ukr_x_preferred":[
        "\u0420\u0456\u043e-\u0413\u0440\u0430\u043d\u0434\u0435"
    ],
    "name:zho_x_preferred":[
        "\u91cc\u5967\u683c\u862d\u5fb7"
    ],
    "qs:gn_country":"AR",
    "qs:gn_fcode":"PPL",
    "qs:gn_pop":0,
    "qs:name":"R\u00edo Grande",
    "qs:name_adm0":"Argentina",
    "qs:name_adm1":"Tierra del Fuego Antartida e Islas Del Atlantico Sur",
    "qs:photos":337,
    "qs:photos_1k":68,
    "qs:photos_9k":1,
    "qs:photos_9r":5,
    "qs:photos_all":337,
    "qs:photos_sr":5,
    "qs:placetype":"Town",
    "qs:pop_sr":"7",
    "qs:woe_adm0":23424747,
    "wd:wordcount":690,
    "wof:name":"R\u00edo Grande",
    "wof:placetype":"locality"
},
  "geometry": {"coordinates":[-67.70946000000001,-53.78769],"type":"Point"}
}