{
  "type": "Feature",
  "properties": {
    "iso:country":"AR",
    "name:ara_x_preferred":[
        "\u0645\u064a\u0631\u0644\u0648\u060c \u0628\u0648\u064a\u0646\u0633 \u0622\u064a\u0631\u0633"
    ],
    "name:ceb_x_preferred":[
        "Merlo"
    ],
    "name:deu_x_preferred":[
        "Merlo"
    ],
    "name:eng_x_preferred":[
        "Merlo"
    ],
    "name:epo_x_preferred":[
        "Merlo"
    ],
    "name:fas_x_preferred":[
        "\u0645\u0631\u0644\u0648"
    ],
    "name:fra_x_preferred":[
        "Merlo"
    ],
    "name:hye_x_preferred":[
        "\u0544\u0565\u0580\u056c\u0578"
    ],
    "name:ita_x_preferred":[
        "Merlo"
    ],
    "name:jpn_x_preferred":[
        "\u30e1\u30eb\u30ed"
    ],
    "name:kor_x_preferred":[
        "\uba54\ub97c\ub85c"
    ],
    "name:nld_x_preferred":[
        "Merlo"
    ],
    "name:pol_x_preferred":[
        "Merlo"
    ],
    "name:por_x_preferred":[
        "Merlo"
    ],
    "name:rus_x_preferred":[
        "\u041c\u0435\u0440\u043b\u043e"
    ],
    "name:spa_x_preferred":[
        "Merlo"
    ],
    "name:srp_x_preferred":[
        "\u041c\u0435\u0440\u043b\u043e"
    ],
    "name:swe_x_preferred":[
        "Merlo"
    ],
    "name:ukr_x_preferred":[
        "\u041c\u0435\u0440\u043b\u043e"
    ],
    "name:vie_x_preferred":[
        "Merlo"
    ],
    "name:zho_x_preferred":[
        "\u6885\u6d1b"
    ],
    "qs:gn_country":"AR",
    "qs:gn_fcode":"PPL",
    "qs:gn_pop":0,
    "qs:name":"Merlo",
    "qs:name_adm0":"Argentina",
    "qs:name_adm1":"Buenos Aires",
    "qs:photos":227,
    "qs:photos_1k":46,
    "qs:photos_9k":1,
    "qs:photos_9r":4,
    "qs:photos_all":227,
    "qs:photos_sr":4,
    "qs:placetype":"Town",
    "qs:pop_sr":"0",
    "qs:woe_adm0":23424747,
    "wd:elevation":16.0,
    "wd:wordcount":1205,
    "wof:name":"Merlo",
    "wof:placetype":"locality"
},
  "geometry": {"coordinates":[-58.72225,-34.66854],"type":"Point"}
}