{
  "type": "Feature",
  "properties": {
    "gn:admin1_code":"24.0",
    "gn:admin2_code":"90112.0",
    "gn:asciiname":"Tapia",
    "gn:country_code":"AR",
    "gn:dem":693,
    "gn:feature_class":"P",
    "gn:feature_code":"PPL",
    "gn:name":"Tapia",
    "gn:population":0,
    "gn:timezone":"America/Argentina/Tucuman",
    "iso:country":"AR",
    "wof:name":"Tapia",
    "wof:placetype":"locality"
},
  "geometry": {"coordinates":[-65.27864,-26.59308],"type":"Point"}
}