{
  "type": "Feature",
  "properties": {
    "gn:admin1_code":"24.0",
    "gn:admin2_code":"90112.0",
    "gn:asciiname":"Tapia",
    "gn:country_code":"AR",
    "gn:dem":693,
    "gn:feature_class":"P",
    "gn:feature_code":"PPL",
    "gn:name":"Tapia",
    "gn:population":0,
    "gn:timezone":"America/Argentina/Tucuman",
    "iso:country":"AR",
    "name:ast_x_preferred":[
        "Tapia"
    ],
    "name:cat_x_preferred":[
        "Tapia"
    ],
    "name:ceb_x_preferred":[
        "Tapia"
    ],
    "name:ces_x_preferred":[
        "Tapia"
    ],
    "name:deu_x_preferred":[
        "Tapia"
    ],
    "name:eus_x_preferred":[
        "Tapia"
    ],
    "name:fin_x_preferred":[
        "Tapia"
    ],
    "name:fra_x_preferred":[
        "Tapia"
    ],
    "name:hun_x_preferred":[
        "Tapia"
    ],
    "name:ita_x_preferred":[
        "Tapia"
    ],
    "name:rus_x_preferred":[
        "\u0422\u0430\u043f\u0438\u044f"
    ],
    "name:spa_x_preferred":[
        "Tapia"
    ],
    "name:swe_x_preferred":[
        "Tapia"
    ],
    "name:ukr_x_preferred":[
        "\u0422\u0430\u043f\u0456\u044f"
    ],
    "wof:name":"Tapia",
    "wof:placetype":"locality"
},
  "geometry": {"coordinates":[-65.27864,-26.59308],"type":"Point"}
}