{
  "type": "Feature",
  "properties": {
    "gn:admin1_code":"22.0",
    "gn:admin2_code":"86084.0",
    "gn:asciiname":"Puerta Grande",
    "gn:country_code":"AR",
    "gn:dem":428,
    "gn:feature_class":"P",
    "gn:feature_code":"PPL",
    "gn:name":"Puerta Grande",
    "gn:population":0,
    "gn:timezone":"America/Argentina/Cordoba",
    "iso:country":"AR",
    "wof:name":"Puerta Grande",
    "wof:placetype":"locality"
},
  "geometry": {"coordinates":[-65.08333,-28.11667000000001],"type":"Point"}
}