{
  "type": "Feature",
  "properties": {
    "gn:country":"AR",
    "gn:fcode":"PPLA2",
    "gn:pop":0,
    "iso:country":"AR",
    "name:ara_x_preferred":[
        "\u0641\u0644\u0648\u0631\u0646\u062a\u064a\u0646\u0648 \u0623\u0645\u0641\u064a\u0646\u0648"
    ],
    "name:cat_x_preferred":[
        "Florentino Ameghino"
    ],
    "name:ceb_x_preferred":[
        "Florentino Ameghino"
    ],
    "name:ces_x_preferred":[
        "Florentino Ameghino"
    ],
    "name:deu_x_preferred":[
        "Florentino Ameghino"
    ],
    "name:eng_x_preferred":[
        "Florentino Ameghino"
    ],
    "name:epo_x_preferred":[
        "Florentino Ameghino"
    ],
    "name:fin_x_preferred":[
        "Florentino Ameghino"
    ],
    "name:fra_x_preferred":[
        "Florentino Ameghino"
    ],
    "name:glg_x_preferred":[
        "Florentino Ameghino"
    ],
    "name:hun_x_preferred":[
        "Florentino Ameghino"
    ],
    "name:ita_x_preferred":[
        "Florentino Ameghino"
    ],
    "name:jpn_x_preferred":[
        "\u30d5\u30ed\u30ec\u30f3\u30c6\u30a3\u30fc\u30ce\u30fb\u30a2\u30e1\u30ae\u30ce"
    ],
    "name:lat_x_preferred":[
        "Florentinus Ameghino"
    ],
    "name:mlg_x_preferred":[
        "Florentino Ameghino"
    ],
    "name:nld_x_preferred":[
        "Florentino Ameghino"
    ],
    "name:nor_x_preferred":[
        "Florentino Ameghino"
    ],
    "name:oci_x_preferred":[
        "Florentino Ameghino"
    ],
    "name:pol_x_preferred":[
        "Florentino Ameghino"
    ],
    "name:por_x_preferred":[
        "Florentino Ameghino"
    ],
    "name:rus_x_preferred":[
        "\u0410\u043c\u0435\u0433\u0438\u043d\u043e"
    ],
    "name:spa_x_preferred":[
        "Florentino Ameghino"
    ],
    "name:swe_x_preferred":[
        "Florentino Ameghino"
    ],
    "name:ukr_x_preferred":[
        "\u0424\u043b\u043e\u0440\u0435\u043d\u0442\u0456\u043d\u043e-\u0410\u043c\u0435\u0433\u0456\u043d\u043e"
    ],
    "name:ukr_x_variant":[
        "\u0424\u043b\u043e\u0440\u0435\u043d\u0442\u0438\u043d\u043e \u0410\u043c\u0435\u0433\u0456\u043d\u043e"
    ],
    "name:zho_x_preferred":[
        "\u4f5b\u7f85\u502b\u5929\u5974\u00b7\u963f\u7c73\u5e0c\u8afe"
    ],
    "qs:name":"Florentino Ameghino",
    "qs:photos_9r":0,
    "qs:photos_sr":0,
    "qs:pop_sr":"7",
    "wd:wordcount":977,
    "wof:name":"Florentino Ameghino",
    "wof:placetype":"locality",
    "wof:population":0
},
  "geometry": {"coordinates":[-62.46701,-34.84405],"type":"Point"}
}