{
  "type": "Feature",
  "properties": {
    "gn:country":"AR",
    "gn:fcode":"PPLA2",
    "gn:pop":0,
    "iso:country":"AR",
    "name:eng_x_preferred":[
        "Florentino Ameghino"
    ],
    "name:nld_x_preferred":[
        "Florentino Ameghino"
    ],
    "name:spa_x_preferred":[
        "Florentino Ameghino"
    ],
    "name:ukr_x_preferred":[
        "\u0424\u043b\u043e\u0440\u0435\u043d\u0442\u0456\u043d\u043e-\u0410\u043c\u0435\u0433\u0456\u043d\u043e"
    ],
    "qs:name":"Florentino Ameghino",
    "qs:photos_9r":0,
    "qs:photos_sr":0,
    "qs:pop_sr":"7",
    "wd:wordcount":977,
    "wof:name":"Florentino Ameghino",
    "wof:placetype":"locality",
    "wof:population":0
},
  "geometry": {"coordinates":[-62.46701,-34.84405],"type":"Point"}
}