{
  "type": "Feature",
  "properties": {
    "gn:admin1_code":"17.0",
    "gn:admin2_code":"66112.0",
    "gn:asciiname":"San Jose de la Horqueta",
    "gn:country_code":"AR",
    "gn:dem":354,
    "gn:feature_class":"P",
    "gn:feature_code":"PPL",
    "gn:name":"San Jos\u00e9 de la Horqueta",
    "gn:population":0,
    "gn:timezone":"America/Argentina/Salta",
    "iso:country":"AR",
    "wof:name":"San Jose de la Horqueta",
    "wof:placetype":"locality"
},
  "geometry": {"coordinates":[-64.09999999999999,-25.28333],"type":"Point"}
}