{
  "type": "Feature",
  "properties": {
    "gn:admin1_code":"08",
    "gn:admin2_code":"30084.0",
    "gn:asciiname":"Aldea El Chaleco",
    "gn:country_code":"AR",
    "gn:dem":99,
    "gn:feature_class":"P",
    "gn:feature_code":"PPL",
    "gn:name":"Aldea El Chaleco",
    "gn:population":0,
    "gn:timezone":"America/Argentina/Cordoba",
    "iso:country":"AR",
    "name:und_x_variant":[
        "Chaleco",
        "Aldea Chaleco",
        "Aldea El Chaleco"
    ],
    "wof:name":"Aldea El Chaleco",
    "wof:placetype":"locality"
},
  "geometry": {"coordinates":[-60.35819,-31.99755],"type":"Point"}
}