{
  "type": "Feature",
  "properties": {
    "iso:country":"AR",
    "name:bel_x_preferred":[
        "\u0422\u0430\u043f\u0456\u044f\u043b\u0435\u0441"
    ],
    "name:ceb_x_preferred":[
        "Tapiales"
    ],
    "name:dan_x_preferred":[
        "Tapiales"
    ],
    "name:deu_x_preferred":[
        "Tapiales"
    ],
    "name:eng_x_preferred":[
        "Tapiales"
    ],
    "name:est_x_preferred":[
        "Tapiales"
    ],
    "name:fra_x_preferred":[
        "Tapiales"
    ],
    "name:ita_x_preferred":[
        "Tapiales"
    ],
    "name:jpn_x_preferred":[
        "\u30bf\u30d4\u30a2\u30ec\u30b9"
    ],
    "name:nld_x_preferred":[
        "Tapiales"
    ],
    "name:nob_x_preferred":[
        "Tapiales"
    ],
    "name:por_x_preferred":[
        "Tapiales"
    ],
    "name:rus_x_preferred":[
        "\u0422\u0430\u043f\u044c\u044f\u043b\u0435\u0441"
    ],
    "name:sco_x_preferred":[
        "Tapiales"
    ],
    "name:spa_x_preferred":[
        "Tapiales"
    ],
    "name:swe_x_preferred":[
        "Tapiales"
    ],
    "qs:gn_pop":0,
    "qs:name":"Tapiales",
    "qs:name_adm0":"Argentina",
    "qs:name_adm1":"Buenos Aires",
    "qs:photos":30,
    "qs:photos_1k":6,
    "qs:photos_9k":1,
    "qs:photos_9r":2,
    "qs:photos_all":30,
    "qs:photos_sr":2,
    "qs:placetype":"Town",
    "qs:pop_sr":"0",
    "qs:woe_adm0":23424747,
    "wd:wordcount":268,
    "wof:name":"Tapiales",
    "wof:placetype":"locality"
},
  "geometry": {"coordinates":[-58.512321,-34.70301],"type":"Point"}
}