{
  "type": "Feature",
  "properties": {
    "iso:country":"AR",
    "name:eng_x_preferred":[
        "Santa Mar\u00eda de Punilla"
    ],
    "name:ita_x_preferred":[
        "Santa Mar\u00eda de Punilla"
    ],
    "name:nld_x_preferred":[
        "Santa Mar\u00eda de Punilla"
    ],
    "name:rus_x_preferred":[
        "\u0421\u0430\u043d\u0442\u0430-\u041c\u0430\u0440\u0438\u044f-\u0434\u0435-\u041f\u0443\u043d\u0438\u043b\u044c\u044f"
    ],
    "name:spa_x_preferred":[
        "Santa Mar\u00eda de Punilla"
    ],
    "name:ukr_x_preferred":[
        "\u0421\u0430\u043d\u0442\u0430-\u041c\u0430\u0440\u0456\u044f-\u0434\u0435-\u041f\u0443\u043d\u0456\u043b\u044c\u044f"
    ],
    "name:unk_x_variant":[
        "Santa Mar\u00eda de Punilla"
    ],
    "qs:gn_country":"AR",
    "qs:gn_fcode":"PPL",
    "qs:gn_pop":0,
    "qs:name":"Santa Mar\u00eda",
    "qs:name_adm0":"Argentina",
    "qs:name_adm1":"C\u00f3rdoba",
    "qs:photos":119,
    "qs:photos_1k":24,
    "qs:photos_9k":1,
    "qs:photos_9r":3,
    "qs:photos_all":119,
    "qs:photos_sr":3,
    "qs:placetype":"Town",
    "qs:pop_sr":"0",
    "qs:woe_adm0":23424747,
    "wof:name":"Santa Mar\u00eda",
    "wof:placetype":"locality"
},
  "geometry": {"coordinates":[-64.46666999999999,-31.26667],"type":"Point"}
}