{
  "type": "Feature",
  "properties": {
    "gn:admin1_code":"01",
    "gn:admin2_code":"6539.0",
    "gn:asciiname":"Ciudad Parque General San Martin",
    "gn:country_code":"AR",
    "gn:dem":28,
    "gn:feature_class":"P",
    "gn:feature_code":"PPL",
    "gn:name":"Ciudad Parque General San Mart\u00edn",
    "gn:population":0,
    "gn:timezone":"America/Argentina/Buenos_Aires",
    "iso:country":"AR",
    "name:spa_x_preferred":[
        "Ciudad Parque General San Mart\u00edn"
    ],
    "wof:name":"Ciudad Parque General San Martin",
    "wof:placetype":"locality"
},
  "geometry": {"coordinates":[-58.75813,-34.68943],"type":"Point"}
}