{
  "type": "Feature",
  "properties": {
    "gn:admin1_code":"17.0",
    "gn:admin2_code":"66035.0",
    "gn:asciiname":"La Merced",
    "gn:country_code":"AR",
    "gn:dem":1239,
    "gn:feature_class":"P",
    "gn:feature_code":"PPL",
    "gn:name":"La Merced",
    "gn:population":0,
    "gn:timezone":"America/Argentina/Salta",
    "iso:country":"AR",
    "name:ita_x_preferred":[
        "La Merced"
    ],
    "name:por_x_preferred":[
        "La Merced"
    ],
    "name:spa_x_preferred":[
        "La Merced"
    ],
    "name:urd_x_preferred":[
        "\u0644\u0627 \u0645\u0631\u0633\u06cc\u0688"
    ],
    "wof:name":"La Merced",
    "wof:placetype":"locality"
},
  "geometry": {"coordinates":[-65.48865000000001,-24.96877000000001],"type":"Point"}
}