{
  "type": "Feature",
  "properties": {
    "iso:country":"AR",
    "name:ara_x_preferred":[
        "\u06f2\u06f5 \u0645\u0627\u064a\u0648"
    ],
    "name:ben_x_preferred":[
        "25 \u09a6\u09c7 \u09ae\u09be\u09df\u09cb"
    ],
    "name:deu_x_preferred":[
        "25 de Mayo"
    ],
    "name:ell_x_preferred":[
        "25 \u03bd\u03c4\u03b5 \u039c\u03ac\u03b9\u03bf"
    ],
    "name:heb_x_preferred":[
        "25 \u05d3\u05d4 \u05de\u05d0\u05d9\u05d5"
    ],
    "name:hin_x_preferred":[
        "25 \u0921\u0947 \u092e\u093e\u092f\u094b"
    ],
    "name:hun_x_preferred":[
        "25 de Mayo"
    ],
    "name:ind_x_preferred":[
        "25 de Mayo"
    ],
    "name:ita_x_preferred":[
        "25 de Mayo"
    ],
    "name:kor_x_preferred":[
        "25 \ub370 \ub9c8\uc694"
    ],
    "name:rus_x_preferred":[
        "\u0412\u0435\u0439\u043d\u0442\u0438\u0441\u0438\u043d\u043a\u043e-\u0434\u0435-\u041c\u0430\u0439\u043e"
    ],
    "name:urd_x_preferred":[
        "25 \u0688\u06cc \u0645\u0627\u06cc\u0648"
    ],
    "name:vie_x_preferred":[
        "25 de Mayo"
    ],
    "ne:ADM0CAP":0.0,
    "ne:ADM0NAME":"Argentina",
    "ne:ADM0_A3":"ARG",
    "ne:ADM1NAME":"RRo Negro",
    "ne:ADMIN1_COD":0,
    "ne:CAPALT":0,
    "ne:CHANGED":4,
    "ne:CHECKME":2,
    "ne:COMPARE":1,
    "ne:DIFFASCII":0,
    "ne:DIFFNOTE":"Name changed.",
    "ne:ELEVATION":0.0,
    "ne:FEATURECLA":"Populated place",
    "ne:GEONAMEID":-1,
    "ne:GEONAMESNO":"No GeoNames match due to small population, not in GeoNames, or poor NEV placement.",
    "ne:GN_POP":0,
    "ne:GTOPO30":0.0,
    "ne:ISO_A2":"AR",
    "ne:LABELRANK":3,
    "ne:LATITUDE":-37.800033,
    "ne:LONGITUDE":-67.683295,
    "ne:LS_MATCH":0,
    "ne:LS_NAME":"25 de Mayo",
    "ne:MAX_AREAKM":0.0,
    "ne:MAX_AREAMI":0.0,
    "ne:MAX_BBXMAX":0.0,
    "ne:MAX_BBXMIN":0.0,
    "ne:MAX_BBYMAX":0.0,
    "ne:MAX_BBYMIN":0.0,
    "ne:MAX_NATSCA":0.0,
    "ne:MAX_PERKM":0.0,
    "ne:MAX_PERMI":0.0,
    "ne:MAX_POP10":0,
    "ne:MAX_POP20":0,
    "ne:MAX_POP300":0,
    "ne:MAX_POP310":0,
    "ne:MAX_POP50":0,
    "ne:MEAN_BBXC":0.0,
    "ne:MEAN_BBYC":0.0,
    "ne:MEGACITY":0,
    "ne:MIN_AREAKM":0.0,
    "ne:MIN_AREAMI":0.0,
    "ne:MIN_BBXMAX":0.0,
    "ne:MIN_BBXMIN":0.0,
    "ne:MIN_BBYMAX":0.0,
    "ne:MIN_BBYMIN":0.0,
    "ne:MIN_PERKM":0.0,
    "ne:MIN_PERMI":0.0,
    "ne:NAME":"25 de Mayo",
    "ne:NAMEALT":"Veinticinco de Mayo",
    "ne:NAMEASCII":"25 de Mayo",
    "ne:NAMEDIFF":1,
    "ne:NATSCALE":10,
    "ne:POP1950":0,
    "ne:POP1955":0,
    "ne:POP1960":0,
    "ne:POP1965":0,
    "ne:POP1970":0,
    "ne:POP1975":0,
    "ne:POP1980":0,
    "ne:POP1985":0,
    "ne:POP1990":0,
    "ne:POP1995":0,
    "ne:POP2000":0,
    "ne:POP2005":0,
    "ne:POP2010":0,
    "ne:POP2015":0,
    "ne:POP2020":0,
    "ne:POP2025":0,
    "ne:POP2050":0,
    "ne:POP_MAX":17430,
    "ne:POP_MIN":17430,
    "ne:POP_OTHER":0,
    "ne:RANK_MAX":6,
    "ne:RANK_MIN":6,
    "ne:SCALERANK":8,
    "ne:SOV0NAME":"Argentina",
    "ne:SOV_A3":"ARG",
    "ne:UN_FID":0,
    "ne:UN_LAT":0.0,
    "ne:UN_LONG":0.0,
    "ne:WORLDCITY":0,
    "ne:min_zoom":7.0,
    "wof:name":"25 de Mayo",
    "wof:placetype":"locality"
},
  "geometry": {"coordinates":[-67.683295,-37.800033],"type":"Point"}
}