{
  "type": "Feature",
  "properties": {
    "gn:admin1_code":"08",
    "gn:admin2_code":"30084.0",
    "gn:asciiname":"Aldea Repollo",
    "gn:country_code":"AR",
    "gn:dem":106,
    "gn:feature_class":"P",
    "gn:feature_code":"PPL",
    "gn:name":"Aldea Repollo",
    "gn:population":0,
    "gn:timezone":"America/Argentina/Cordoba",
    "iso:country":"AR",
    "wof:name":"Aldea Repollo",
    "wof:placetype":"locality"
},
  "geometry": {"coordinates":[-60.36733,-32.01653],"type":"Point"}
}