{
  "type": "Feature",
  "properties": {
    "gn:admin1_code":"22.0",
    "gn:admin2_code":"86077.0",
    "gn:asciiname":"Tomas Young",
    "gn:country_code":"AR",
    "gn:dem":96,
    "gn:feature_class":"P",
    "gn:feature_code":"PPL",
    "gn:name":"Tom\u00e1s Young",
    "gn:population":0,
    "gn:timezone":"America/Argentina/Cordoba",
    "iso:country":"AR",
    "name:ara_x_preferred":[
        "\u062a\u0648\u0645\u0627\u0633 \u064a\u0648\u0646\u063a"
    ],
    "name:deu_x_preferred":[
        "Tomas Young"
    ],
    "name:und_x_variant":[
        "Kil\u00f3metro 433",
        "Tom\u00e1s Young"
    ],
    "wof:name":"Tomas Young",
    "wof:placetype":"locality"
},
  "geometry": {"coordinates":[-62.18232,-28.60102],"type":"Point"}
}