{
  "type": "Feature",
  "properties": {
    "gn:admin1_code":"21.0",
    "gn:admin2_code":"82021.0",
    "gn:asciiname":"Fassi",
    "gn:country_code":"AR",
    "gn:dem":102,
    "gn:feature_class":"P",
    "gn:feature_code":"PPL",
    "gn:name":"Fassi",
    "gn:population":0,
    "gn:timezone":"America/Argentina/Cordoba",
    "iso:country":"AR",
    "wof:name":"Fassi",
    "wof:placetype":"locality"
},
  "geometry": {"coordinates":[-61.61666999999999,-31.13333],"type":"Point"}
}