{
  "type": "Feature",
  "properties": {
    "iso:country":"AR",
    "name:deu_x_preferred":[
        "Pellegrini"
    ],
    "name:fra_x_preferred":[
        "Pellegrini"
    ],
    "name:heb_x_preferred":[
        "\u05e4\u05dc\u05d2\u05e8\u05d9\u05e0\u05d9"
    ],
    "name:ita_x_preferred":[
        "Pellegrini"
    ],
    "name:jpn_x_preferred":[
        "\u30da\u30ec\u30b0\u30ea\u30fc\u30cb"
    ],
    "name:nld_x_preferred":[
        "Pellegrini"
    ],
    "name:por_x_preferred":[
        "Pellegrini"
    ],
    "name:rus_x_preferred":[
        "\u041f\u0435\u043b\u043b\u0435\u0433\u0440\u0438\u043d\u0438"
    ],
    "name:slk_x_preferred":[
        "Pellegrini"
    ],
    "name:spa_x_preferred":[
        "Pellegrini"
    ],
    "name:unk_x_variant":[
        "Carlos Pellegrini"
    ],
    "qs:gn_country":"AR",
    "qs:gn_fcode":"PPL",
    "qs:gn_pop":0,
    "qs:name":"Pellegrini",
    "qs:name_adm0":"Argentina",
    "qs:name_adm1":"Buenos Aires",
    "qs:photos":0,
    "qs:photos_1k":0,
    "qs:photos_9k":1,
    "qs:photos_9r":2,
    "qs:photos_all":31,
    "qs:photos_sr":0,
    "qs:placetype":"Town",
    "qs:pop_sr":"0",
    "qs:woe_adm0":23424747,
    "wd:wordcount":151,
    "wof:name":"Pellegrini",
    "wof:placetype":"locality"
},
  "geometry": {"coordinates":[-63.1655,-36.26584],"type":"Point"}
}