{
  "type": "Feature",
  "properties": {
    "iso:country":"AR",
    "name:spa_x_preferred":[
        "Jos\u00e9 Rivera Indarte"
    ],
    "name:unk_x_variant":[
        "R. Indarte"
    ],
    "qs:gn_country":"AR",
    "qs:gn_fcode":"PPL",
    "qs:gn_pop":0,
    "qs:name":"Rivera Indarte",
    "qs:name_adm0":"Argentina",
    "qs:name_adm1":"C\u00f3rdoba",
    "qs:photos":190,
    "qs:photos_1k":39,
    "qs:photos_9k":1,
    "qs:photos_9r":4,
    "qs:photos_all":190,
    "qs:photos_sr":4,
    "qs:placetype":"Town",
    "qs:pop_sr":"0",
    "qs:woe_adm0":23424747,
    "wd:wordcount":470,
    "wof:name":"Rivera Indarte",
    "wof:placetype":"locality"
},
  "geometry": {"coordinates":[-64.29770000000001,-31.32383],"type":"Point"}
}