{
  "type": "Feature",
  "properties": {
    "iso:country":"AR",
    "name:arz_x_preferred":[
        "\u0686\u0648\u0633 \u0631\u064a\u06a4\u064a\u0631\u0627 \u0627\u064a\u0646\u062f\u0627\u0631\u062a"
    ],
    "name:ast_x_preferred":[
        "Jos\u00e9 Rivera Indarte"
    ],
    "name:cat_x_preferred":[
        "Jos\u00e9 Rivera Indarte"
    ],
    "name:dan_x_preferred":[
        "Jos\u00e9 Rivera Indarte"
    ],
    "name:deu_x_preferred":[
        "Jos\u00e9 Rivera Indarte"
    ],
    "name:eng_x_preferred":[
        "Jos\u00e9 Rivera Indarte"
    ],
    "name:fra_x_preferred":[
        "Jos\u00e9 Rivera Indarte"
    ],
    "name:gle_x_preferred":[
        "Jos\u00e9 Rivera Indarte"
    ],
    "name:nld_x_preferred":[
        "Jos\u00e9 Rivera Indarte"
    ],
    "name:nno_x_preferred":[
        "Jos\u00e9 Rivera Indarte"
    ],
    "name:nob_x_preferred":[
        "Jos\u00e9 Rivera Indarte"
    ],
    "name:slv_x_preferred":[
        "Jos\u00e9 Rivera Indarte"
    ],
    "name:spa_x_preferred":[
        "Jos\u00e9 Rivera Indarte"
    ],
    "name:sqi_x_preferred":[
        "Jos\u00e9 Rivera Indarte"
    ],
    "name:swe_x_preferred":[
        "Jos\u00e9 Rivera Indarte"
    ],
    "name:und_x_variant":[
        "R. Indarte"
    ],
    "qs:gn_country":"AR",
    "qs:gn_fcode":"PPL",
    "qs:gn_pop":0,
    "qs:name":"Rivera Indarte",
    "qs:name_adm0":"Argentina",
    "qs:name_adm1":"C\u00f3rdoba",
    "qs:photos":190,
    "qs:photos_1k":39,
    "qs:photos_9k":1,
    "qs:photos_9r":4,
    "qs:photos_all":190,
    "qs:photos_sr":4,
    "qs:placetype":"Town",
    "qs:pop_sr":"0",
    "qs:woe_adm0":23424747,
    "wd:wordcount":470,
    "wof:name":"Rivera Indarte",
    "wof:placetype":"locality"
},
  "geometry": {"coordinates":[-64.29770000000001,-31.32383],"type":"Point"}
}