{
  "type": "Feature",
  "properties": {
    "gn:admin1_code":"22.0",
    "gn:admin2_code":"86056.0",
    "gn:asciiname":"Manga Bajada",
    "gn:country_code":"AR",
    "gn:dem":253,
    "gn:feature_class":"P",
    "gn:feature_code":"PPL",
    "gn:name":"Manga Bajada",
    "gn:population":0,
    "gn:timezone":"America/Argentina/Cordoba",
    "iso:country":"AR",
    "wof:name":"Manga Bajada",
    "wof:placetype":"locality"
},
  "geometry": {"coordinates":[-63.71666999999999,-26.03333],"type":"Point"}
}