{
  "type": "Feature",
  "properties": {
    "gn:admin1_code":"5.0",
    "gn:admin2_code":"14168.0",
    "gn:asciiname":"Los Chanares",
    "gn:country_code":"AR",
    "gn:dem":728,
    "gn:feature_class":"P",
    "gn:feature_code":"PPL",
    "gn:name":"Los Cha\u00f1ares",
    "gn:population":0,
    "gn:timezone":"America/Argentina/Cordoba",
    "iso:country":"AR",
    "wof:name":"Los Chanares",
    "wof:placetype":"locality"
},
  "geometry": {"coordinates":[-64.18054000000001,-30.49376],"type":"Point"}
}