{
  "type": "Feature",
  "properties": {
    "gn:admin1_code":"12.0",
    "gn:admin2_code":"46021.0",
    "gn:asciiname":"Pinchas",
    "gn:country_code":"AR",
    "gn:dem":1379,
    "gn:feature_class":"P",
    "gn:feature_code":"PPL",
    "gn:name":"Pinchas",
    "gn:population":0,
    "gn:timezone":"America/Argentina/La_Rioja",
    "iso:country":"AR",
    "wof:name":"Pinchas",
    "wof:placetype":"locality"
},
  "geometry": {"coordinates":[-66.95963,-28.93035],"type":"Point"}
}