{
  "type": "Feature",
  "properties": {
    "gn:admin1_code":"18.0",
    "gn:admin2_code":"70070.0",
    "gn:asciiname":"Sanchez de Loria",
    "gn:country_code":"AR",
    "gn:dem":618,
    "gn:feature_class":"P",
    "gn:feature_code":"PPL",
    "gn:name":"S\u00e1nchez de Loria",
    "gn:population":0,
    "gn:timezone":"America/Argentina/San_Juan",
    "iso:country":"AR",
    "wof:name":"Sanchez de Loria",
    "wof:placetype":"locality"
},
  "geometry": {"coordinates":[-68.53333000000001,-31.61667000000001],"type":"Point"}
}