{
  "type": "Feature",
  "properties": {
    "gn:admin1_code":"20.0",
    "gn:admin2_code":"78049.0",
    "gn:asciiname":"Tamel Aike",
    "gn:country_code":"AR",
    "gn:dem":548,
    "gn:feature_class":"P",
    "gn:feature_code":"PPL",
    "gn:name":"Tamel Aike",
    "gn:population":0,
    "gn:timezone":"America/Argentina/Rio_Gallegos",
    "iso:country":"AR",
    "name:und_x_variant":[
        "Tamel Aiken",
        "Tamel Aike"
    ],
    "wof:name":"Tamel Aike",
    "wof:placetype":"locality"
},
  "geometry": {"coordinates":[-70.97214,-48.30204000000001],"type":"Point"}
}