{
  "type": "Feature",
  "properties": {
    "iso:country":"AR",
    "name:ceb_x_preferred":[
        "Volc\u00e1n"
    ],
    "name:eng_x_preferred":[
        "Volc\u00e1n"
    ],
    "name:ita_x_preferred":[
        "Volc\u00e1n"
    ],
    "name:nld_x_preferred":[
        "Volc\u00e1n"
    ],
    "name:spa_x_preferred":[
        "Volc\u00e1n"
    ],
    "name:swe_x_preferred":[
        "Volc\u00e1n"
    ],
    "qs:gn_country":"AR",
    "qs:gn_fcode":"PPL",
    "qs:gn_pop":0,
    "qs:name":"Volc\u00e1n",
    "qs:name_adm0":"Argentina",
    "qs:name_adm1":"Jujuy",
    "qs:photos":98,
    "qs:photos_1k":20,
    "qs:photos_9k":1,
    "qs:photos_9r":3,
    "qs:photos_all":98,
    "qs:photos_sr":3,
    "qs:placetype":"Town",
    "qs:pop_sr":"0",
    "qs:woe_adm0":23424747,
    "wd:wordcount":33,
    "wof:name":"Volc\u00e1n",
    "wof:placetype":"locality"
},
  "geometry": {"coordinates":[-65.46623,-23.91709],"type":"Point"}
}