{
  "type": "Feature",
  "properties": {
    "gn:admin1_code":"5.0",
    "gn:admin2_code":"14063.0",
    "gn:asciiname":"Saladillo",
    "gn:country_code":"AR",
    "gn:dem":99,
    "gn:feature_class":"P",
    "gn:feature_code":"PPL",
    "gn:name":"Saladillo",
    "gn:population":0,
    "gn:timezone":"America/Argentina/Cordoba",
    "iso:country":"AR",
    "wof:name":"Saladillo",
    "wof:placetype":"locality"
},
  "geometry": {"coordinates":[-62.34477,-32.93438],"type":"Point"}
}