{
  "type": "Feature",
  "properties": {
    "gn:admin1_code":"5.0",
    "gn:admin2_code":"14175.0",
    "gn:asciiname":"Las Arrias",
    "gn:country_code":"AR",
    "gn:dem":189,
    "gn:feature_class":"P",
    "gn:feature_code":"PPL",
    "gn:name":"Las Arrias",
    "gn:population":0,
    "gn:timezone":"America/Argentina/Cordoba",
    "iso:country":"AR",
    "wof:name":"Las Arrias",
    "wof:placetype":"locality"
},
  "geometry": {"coordinates":[-63.59748,-30.3807],"type":"Point"}
}