{
  "type": "Feature",
  "properties": {
    "gn:admin1_code":"19.0",
    "gn:admin2_code":"74056.0",
    "gn:asciiname":"La Sena",
    "gn:country_code":"AR",
    "gn:dem":620,
    "gn:feature_class":"P",
    "gn:feature_code":"PPL",
    "gn:name":"La Se\u00f1a",
    "gn:population":0,
    "gn:timezone":"America/Argentina/San_Luis",
    "iso:country":"AR",
    "wof:name":"La Sena",
    "wof:placetype":"locality"
},
  "geometry": {"coordinates":[-66.31667,-33.86667],"type":"Point"}
}