{
  "type": "Feature",
  "properties": {
    "gn:admin1_code":"18.0",
    "gn:admin2_code":"70056.0",
    "gn:asciiname":"Niquivil",
    "gn:cc2":"AR",
    "gn:country_code":"AR",
    "gn:dem":1023,
    "gn:feature_class":"P",
    "gn:feature_code":"PPL",
    "gn:name":"Niquivil",
    "gn:population":0,
    "gn:timezone":"America/Argentina/San_Juan",
    "iso:country":"AR",
    "name:und_x_variant":[
        "Eva Per\u00f3n",
        "Niquivil"
    ],
    "wof:name":"Niquivil",
    "wof:placetype":"locality"
},
  "geometry": {"coordinates":[-68.68889,-30.40917],"type":"Point"}
}