{
  "type": "Feature",
  "properties": {
    "gn:admin1_code":"1.0",
    "gn:admin2_code":"6119.0",
    "gn:asciiname":"Gobernador Obligado",
    "gn:country_code":"AR",
    "gn:dem":28,
    "gn:feature_class":"P",
    "gn:feature_code":"PPL",
    "gn:name":"Gobernador Obligado",
    "gn:population":0,
    "gn:timezone":"America/Argentina/Buenos_Aires",
    "iso:country":"AR",
    "name:und_x_variant":[
        "Gobernador Ubligado",
        "Gobernador Obligado"
    ],
    "wof:name":"Gobernador Obligado",
    "wof:placetype":"locality"
},
  "geometry": {"coordinates":[-58.19866999999999,-35.16276],"type":"Point"}
}