{
  "type": "Feature",
  "properties": {
    "gn:admin1_code":"05",
    "gn:admin2_code":"14091.0",
    "gn:asciiname":"Villa Santa Cruz Del Lago",
    "gn:country_code":"AR",
    "gn:dem":784,
    "gn:feature_class":"P",
    "gn:feature_code":"PPL",
    "gn:name":"Villa Santa Cruz Del Lago",
    "gn:population":0,
    "gn:timezone":"America/Argentina/Cordoba",
    "iso:country":"AR",
    "wof:name":"Villa Santa Cruz Del Lago",
    "wof:placetype":"locality"
},
  "geometry": {"coordinates":[-64.52601,-31.36155],"type":"Point"}
}