{
  "type": "Feature",
  "properties": {
    "gn:admin1_code":"2.0",
    "gn:admin2_code":"10021.0",
    "gn:asciiname":"Villa Vil",
    "gn:country_code":"AR",
    "gn:dem":1293,
    "gn:feature_class":"P",
    "gn:feature_code":"PPL",
    "gn:name":"Villa Vil",
    "gn:population":0,
    "gn:timezone":"America/Argentina/Catamarca",
    "iso:country":"AR",
    "wof:name":"Villa Vil",
    "wof:placetype":"locality"
},
  "geometry": {"coordinates":[-66.25044,-27.5768],"type":"Point"}
}