{
  "type": "Feature",
  "properties": {
    "iso:country":"AR",
    "name:eng_x_preferred":[
        "San Antonio de Arredondo"
    ],
    "name:nld_x_preferred":[
        "San Antonio de Arredondo"
    ],
    "name:por_x_preferred":[
        "San Antonio de Arredondo"
    ],
    "name:spa_x_preferred":[
        "San Antonio de Arredondo"
    ],
    "name:ukr_x_preferred":[
        "\u0421\u0430\u043d-\u0410\u043d\u0442\u043e\u043d\u0456\u043e-\u0434\u0435-\u0410\u0440\u0440\u0435\u0434\u043e\u043d\u0434\u043e"
    ],
    "name:und_x_variant":[
        "San Antonio"
    ],
    "qs:gn_country":"AR",
    "qs:gn_fcode":"PPL",
    "qs:gn_pop":0,
    "qs:name":"San Antonio de Arredondo",
    "qs:name_adm0":"Argentina",
    "qs:name_adm1":"C\u00f3rdoba",
    "qs:photos":183,
    "qs:photos_1k":37,
    "qs:photos_9k":1,
    "qs:photos_9r":4,
    "qs:photos_all":183,
    "qs:photos_sr":4,
    "qs:placetype":"Town",
    "qs:pop_sr":"0",
    "qs:woe_adm0":23424747,
    "wof:name":"San Antonio de Arredondo",
    "wof:placetype":"locality"
},
  "geometry": {"coordinates":[-64.53042000000001,-31.47949],"type":"Point"}
}