{
  "type": "Feature",
  "properties": {
    "iso:country":"AR",
    "name:ara_x_preferred":[
        "\u0645\u0648\u0631\u064a\u0646\u0648"
    ],
    "name:bul_x_preferred":[
        "\u041c\u043e\u0440\u0435\u043d\u043e"
    ],
    "name:cat_x_preferred":[
        "Moreno"
    ],
    "name:ceb_x_preferred":[
        "Moreno"
    ],
    "name:ces_x_preferred":[
        "Moreno"
    ],
    "name:deu_x_preferred":[
        "Moreno"
    ],
    "name:fin_x_preferred":[
        "Moreno"
    ],
    "name:fra_x_preferred":[
        "Moreno"
    ],
    "name:heb_x_preferred":[
        "\u05de\u05d5\u05e8\u05e0\u05d5"
    ],
    "name:ita_x_preferred":[
        "Moreno"
    ],
    "name:jpn_x_preferred":[
        "\u30e2\u30ec\u30ce"
    ],
    "name:kor_x_preferred":[
        "\ubaa8\ub808\ub178"
    ],
    "name:lav_x_preferred":[
        "Moreno"
    ],
    "name:lit_x_preferred":[
        "Morenas"
    ],
    "name:nld_x_preferred":[
        "Moreno"
    ],
    "name:pol_x_preferred":[
        "Moreno"
    ],
    "name:por_x_preferred":[
        "Moreno"
    ],
    "name:rus_x_preferred":[
        "\u041c\u043e\u0440\u0435\u043d\u043e"
    ],
    "name:sco_x_preferred":[
        "Moreno"
    ],
    "name:slk_x_preferred":[
        "Moreno"
    ],
    "name:spa_x_preferred":[
        "Moreno"
    ],
    "name:srp_x_preferred":[
        "\u041c\u043e\u0440\u0435\u043d\u043e"
    ],
    "name:swe_x_preferred":[
        "Moreno"
    ],
    "name:ukr_x_preferred":[
        "\u041c\u043e\u0440\u0435\u043d\u043e"
    ],
    "qs:gn_adm0_cc":"AR",
    "qs:gn_local":3838583,
    "qs:local_max":4639,
    "qs:local_sum":17736,
    "qs:localhoods":14,
    "qs:name":"Moreno",
    "qs:name_adm0":"Argentina",
    "qs:name_adm1":"Santa Fe",
    "qs:name_adm2":"Rosario",
    "qs:name_local":"Rosario",
    "qs:photo_max":480,
    "qs:photo_sum":605,
    "qs:placetype":"Suburb",
    "qs:quad_count":9,
    "qs:woe_adm0":23424747,
    "qs:woe_adm1":2344695,
    "qs:woe_adm2":20070927,
    "qs:woe_lau":0,
    "qs:woe_local":466862,
    "qs:woe_ver":"7.10.0",
    "wof:lang":[
        "spa"
    ],
    "wof:name":"Moreno",
    "wof:placetype":"neighbourhood"
},
  "geometry": {"coordinates":[-60.670961,-32.930057],"type":"Point"}
}