{
  "type": "Feature",
  "properties": {
    "iso:country":"AR",
    "name:spa_x_preferred":[
        "Moreno"
    ],
    "name:unk_x_variant":[
        "Moreno"
    ],
    "qs:gn_adm0_cc":"AR",
    "qs:gn_local":3838583,
    "qs:local_max":4639,
    "qs:local_sum":17736,
    "qs:localhoods":14,
    "qs:name":"Moreno",
    "qs:name_adm0":"Argentina",
    "qs:name_adm1":"Santa Fe",
    "qs:name_adm2":"Rosario",
    "qs:name_local":"Rosario",
    "qs:photo_max":480,
    "qs:photo_sum":605,
    "qs:placetype":"Suburb",
    "qs:quad_count":9,
    "qs:woe_adm0":23424747,
    "qs:woe_adm1":2344695,
    "qs:woe_adm2":20070927,
    "qs:woe_lau":0,
    "qs:woe_local":466862,
    "qs:woe_ver":"7.10.0",
    "wof:lang":[
        "spa"
    ],
    "wof:name":"Moreno",
    "wof:placetype":"neighbourhood"
},
  "geometry": {"coordinates":[-60.670961,-32.930057],"type":"Point"}
}