{
  "type": "Feature",
  "properties": {
    "iso:country":"AR",
    "name:bul_x_preferred":[
        "\u0421\u0435\u0440\u043e \u0415\u043b \u041a\u043e\u043d\u0434\u043e\u0440"
    ],
    "name:ces_x_preferred":[
        "Cerro el C\u00f3ndor"
    ],
    "name:deu_x_preferred":[
        "El C\u00f3ndor"
    ],
    "name:fra_x_preferred":[
        "El C\u00f3ndor"
    ],
    "name:ita_x_preferred":[
        "Monte Cerro El C\u00f3ndor"
    ],
    "name:kat_x_preferred":[
        "\u10e1\u10d4\u10e0\u10dd-\u10d4\u10da-\u10d9\u10dd\u10dc\u10d3\u10dd\u10e0\u10d8"
    ],
    "name:msa_x_preferred":[
        "Gunung Cerro El C\u00f3ndor"
    ],
    "name:rus_x_preferred":[
        "\u0421\u0435\u0440\u0440\u043e-\u042d\u043b\u044c-\u041a\u043e\u043d\u0434\u043e\u0440"
    ],
    "name:slk_x_preferred":[
        "Cerro el C\u00f3ndor"
    ],
    "name:ukr_x_preferred":[
        "\u0421\u0435\u0440\u0440\u043e-\u0415\u043b\u044c-\u041a\u043e\u043d\u0434\u043e\u0440"
    ],
    "qs:gn_pop":0,
    "qs:name":"El C\u00f3ndor",
    "qs:name_adm0":"Argentina",
    "qs:name_adm1":"C\u00f3rdoba",
    "qs:photos":133,
    "qs:photos_1k":27,
    "qs:photos_9k":1,
    "qs:photos_9r":3,
    "qs:photos_all":133,
    "qs:photos_sr":3,
    "qs:placetype":"Town",
    "qs:pop_sr":"0",
    "qs:woe_adm0":23424747,
    "wd:wordcount":145,
    "wof:name":"El C\u00f3ndor",
    "wof:placetype":"locality"
},
  "geometry": {"coordinates":[-64.67943099999999,-31.636867],"type":"Point"}
}