{
  "type": "Feature",
  "properties": {
    "iso:country":"AR",
    "name:ceb_x_preferred":[
        "Chamical"
    ],
    "name:fra_x_preferred":[
        "Chamical"
    ],
    "name:ita_x_preferred":[
        "Chamical"
    ],
    "name:por_x_preferred":[
        "Chamical"
    ],
    "name:spa_x_preferred":[
        "Chamical"
    ],
    "name:swe_x_preferred":[
        "Chamical"
    ],
    "name:unk_x_variant":[
        "Gobernador Gordillo"
    ],
    "name:zho_x_preferred":[
        "\u67e5\u99ac\u5361\u723e"
    ],
    "ne:ADM0CAP":0.0,
    "ne:ADM0NAME":"Argentina",
    "ne:ADM0_A3":"ARG",
    "ne:ADM1NAME":"La Rioja",
    "ne:ADMIN1_COD":0,
    "ne:CAPALT":0,
    "ne:CHANGED":0,
    "ne:CHECKME":0,
    "ne:COMPARE":0,
    "ne:DIFFASCII":0,
    "ne:ELEVATION":0.0,
    "ne:FEATURECLA":"Populated place",
    "ne:GEONAMEID":-1,
    "ne:GEONAMESNO":"No GeoNames match due to small population, not in GeoNames, or poor NEV placement.",
    "ne:GN_POP":0,
    "ne:GTOPO30":0.0,
    "ne:ISO_A2":"AR",
    "ne:LABELRANK":3,
    "ne:LATITUDE":-30.349583,
    "ne:LONGITUDE":-66.31666,
    "ne:LS_MATCH":1,
    "ne:LS_NAME":"Chamical",
    "ne:MAX_AREAKM":10.0,
    "ne:MAX_AREAMI":4.0,
    "ne:MAX_BBXMAX":-66.291667,
    "ne:MAX_BBXMIN":-66.325,
    "ne:MAX_BBYMAX":-30.333333,
    "ne:MAX_BBYMIN":-30.383333,
    "ne:MAX_NATSCA":20.0,
    "ne:MAX_PERKM":17.0,
    "ne:MAX_PERMI":11.0,
    "ne:MAX_POP10":8989,
    "ne:MAX_POP20":8989,
    "ne:MAX_POP300":0,
    "ne:MAX_POP310":0,
    "ne:MAX_POP50":0,
    "ne:MEAN_BBXC":-66.310577,
    "ne:MEAN_BBYC":-30.357372,
    "ne:MEGACITY":0,
    "ne:MIN_AREAKM":10.0,
    "ne:MIN_AREAMI":4.0,
    "ne:MIN_BBXMAX":-66.291667,
    "ne:MIN_BBXMIN":-66.325,
    "ne:MIN_BBYMAX":-30.333333,
    "ne:MIN_BBYMIN":-30.383333,
    "ne:MIN_PERKM":17.0,
    "ne:MIN_PERMI":11.0,
    "ne:NAME":"Chamical",
    "ne:NAMEASCII":"Chamical",
    "ne:NAMEDIFF":0,
    "ne:NATSCALE":20,
    "ne:POP1950":0,
    "ne:POP1955":0,
    "ne:POP1960":0,
    "ne:POP1965":0,
    "ne:POP1970":0,
    "ne:POP1975":0,
    "ne:POP1980":0,
    "ne:POP1985":0,
    "ne:POP1990":0,
    "ne:POP1995":0,
    "ne:POP2000":0,
    "ne:POP2005":0,
    "ne:POP2010":0,
    "ne:POP2015":0,
    "ne:POP2020":0,
    "ne:POP2025":0,
    "ne:POP2050":0,
    "ne:POP_MAX":8989,
    "ne:POP_MIN":8989,
    "ne:POP_OTHER":8385,
    "ne:RANK_MAX":5,
    "ne:RANK_MIN":5,
    "ne:SCALERANK":7,
    "ne:SOV0NAME":"Argentina",
    "ne:SOV_A3":"ARG",
    "ne:UN_FID":0,
    "ne:UN_LAT":0.0,
    "ne:UN_LONG":0.0,
    "ne:WORLDCITY":0,
    "qs:gn_country":"AR",
    "qs:gn_fcode":"PPL",
    "qs:gn_pop":13383,
    "qs:name":"Chamical",
    "qs:name_adm0":"Argentina",
    "qs:name_adm1":"La Rioja",
    "qs:photos":0,
    "qs:photos_1k":0,
    "qs:photos_9k":1,
    "qs:photos_9r":1,
    "qs:photos_all":1,
    "qs:photos_sr":0,
    "qs:placetype":"Town",
    "qs:pop_sr":"6",
    "qs:woe_adm0":23424747,
    "wd:wordcount":661,
    "wof:name":"Chamical",
    "wof:placetype":"locality",
    "wof:population":13383
},
  "geometry": {"coordinates":[-66.31399,-30.36002],"type":"Point"}
}