{
  "type": "Feature",
  "properties": {
    "gn:admin1_code":"21",
    "gn:admin2_code":"82091.0",
    "gn:asciiname":"Colonia Rosa",
    "gn:country_code":"AR",
    "gn:dem":96,
    "gn:feature_class":"P",
    "gn:feature_code":"PPL",
    "gn:name":"Colonia Rosa",
    "gn:population":0,
    "gn:timezone":"America/Argentina/Cordoba",
    "iso:country":"AR",
    "wof:name":"Colonia Rosa",
    "wof:placetype":"locality"
},
  "geometry": {"coordinates":[-61.98351,-30.29986],"type":"Point"}
}