{
  "type": "Feature",
  "properties": {
    "iso:country":"AR",
    "name:unk_x_variant":[
        "Palomar"
    ],
    "qs:gn_country":"AR",
    "qs:gn_fcode":"PPL",
    "qs:gn_pop":0,
    "qs:name":"El Palomar",
    "qs:name_adm0":"Argentina",
    "qs:name_adm1":"Santiago del Estero",
    "qs:photos":0,
    "qs:photos_1k":0,
    "qs:photos_9k":0,
    "qs:photos_9r":0,
    "qs:photos_all":0,
    "qs:photos_sr":0,
    "qs:placetype":"Town",
    "qs:pop_sr":"0",
    "qs:woe_adm0":23424747,
    "wd:wordcount":191,
    "wof:name":"El Palomar",
    "wof:placetype":"locality"
},
  "geometry": {"coordinates":[-64.59688,-26.88315],"type":"Point"}
}