{
  "type": "Feature",
  "properties": {
    "iso:country":"AR",
    "name:spa_x_preferred":[
        "Bosques"
    ],
    "qs:gn_country":"AR",
    "qs:gn_fcode":"PPL",
    "qs:gn_pop":0,
    "qs:name":"Bosques",
    "qs:name_adm0":"Argentina",
    "qs:name_adm1":"Buenos Aires",
    "qs:photos":23,
    "qs:photos_1k":5,
    "qs:photos_9k":1,
    "qs:photos_9r":1,
    "qs:photos_all":23,
    "qs:photos_sr":1,
    "qs:placetype":"Town",
    "qs:pop_sr":"0",
    "qs:woe_adm0":23424747,
    "wof:name":"Bosques",
    "wof:placetype":"locality"
},
  "geometry": {"coordinates":[-58.23443,-34.81927],"type":"Point"}
}