{
  "type": "Feature",
  "properties": {
    "gn:admin1_code":"08",
    "gn:admin2_code":"30084.0",
    "gn:asciiname":"Antonio Tomas",
    "gn:country_code":"AR",
    "gn:dem":59,
    "gn:feature_class":"P",
    "gn:feature_code":"PPL",
    "gn:name":"Antonio Tom\u00e1s",
    "gn:population":0,
    "gn:timezone":"America/Argentina/Cordoba",
    "iso:country":"AR",
    "name:und_x_variant":[
        "Santo Tom\u00e1s",
        "Antonio Tom\u00e1s"
    ],
    "wof:name":"Antonio Tomas",
    "wof:placetype":"locality"
},
  "geometry": {"coordinates":[-60.04774000000001,-31.42378],"type":"Point"}
}