{
  "type": "Feature",
  "properties": {
    "gn:admin1_code":"21.0",
    "gn:admin2_code":"82105.0",
    "gn:asciiname":"San Eugenio",
    "gn:country_code":"AR",
    "gn:dem":37,
    "gn:feature_class":"P",
    "gn:feature_code":"PPL",
    "gn:name":"San Eugenio",
    "gn:population":0,
    "gn:timezone":"America/Argentina/Cordoba",
    "iso:country":"AR",
    "wof:name":"San Eugenio",
    "wof:placetype":"locality"
},
  "geometry": {"coordinates":[-61.11395,-32.07418],"type":"Point"}
}