{
  "type": "Feature",
  "properties": {
    "iso:country":"AR",
    "name:ceb_x_preferred":[
        "Jard\u00edn Am\u00e9rica"
    ],
    "name:eng_x_preferred":[
        "Jard\u00edn Am\u00e9rica"
    ],
    "name:fra_x_preferred":[
        "Jard\u00edn Am\u00e9rica"
    ],
    "name:lit_x_preferred":[
        "Chardin Amerika"
    ],
    "name:nld_x_preferred":[
        "Jard\u00edn Am\u00e9rica"
    ],
    "name:por_x_preferred":[
        "Jard\u00edn Am\u00e9rica"
    ],
    "name:spa_x_preferred":[
        "Jard\u00edn Am\u00e9rica"
    ],
    "name:swe_x_preferred":[
        "Jard\u00edn Am\u00e9rica"
    ],
    "name:ukr_x_preferred":[
        "\u0425\u0430\u0440\u0434\u0456\u043d-\u0410\u043c\u0435\u0440\u0438\u043a\u0430"
    ],
    "name:urd_x_preferred":[
        "\u062c\u0631\u062f\u06cc\u0646 \u0627\u0645\u06cc\u0631\u06a9\u0627"
    ],
    "qs:gn_country":"AR",
    "qs:gn_fcode":"PPL",
    "qs:gn_pop":24905,
    "qs:name":"Jard\u00edn Am\u00e9rica",
    "qs:name_adm0":"Argentina",
    "qs:name_adm1":"Misiones",
    "qs:photos":0,
    "qs:photos_1k":0,
    "qs:photos_9k":1,
    "qs:photos_9r":1,
    "qs:photos_all":3,
    "qs:photos_sr":0,
    "qs:placetype":"Town",
    "qs:pop_sr":"7",
    "qs:woe_adm0":23424747,
    "wd:wordcount":300,
    "wof:name":"Jard\u00edn Am\u00e9rica",
    "wof:placetype":"locality",
    "wof:population":24905
},
  "geometry": {"coordinates":[-55.22698,-27.04346],"type":"Point"}
}