{
  "type": "Feature",
  "properties": {
    "gn:country":"AR",
    "gn:fcode":"PPL",
    "gn:pop":7398,
    "iso:country":"AR",
    "name:eng_x_preferred":[
        "Concepci\u00f3n de la Sierra"
    ],
    "name:fra_x_preferred":[
        "Concepci\u00f3n de la Sierra"
    ],
    "name:ita_x_preferred":[
        "Concepci\u00f3n de la Sierra"
    ],
    "name:nld_x_preferred":[
        "Concepci\u00f3n de la Sierra"
    ],
    "name:pol_x_preferred":[
        "Concepci\u00f3n de la Sierra"
    ],
    "name:por_x_preferred":[
        "Concepci\u00f3n de la Sierra"
    ],
    "name:spa_x_preferred":[
        "Concepci\u00f3n de la Sierra"
    ],
    "name:swe_x_preferred":[
        "Concepci\u00f3n de la Sierra"
    ],
    "name:ukr_x_preferred":[
        "\u041a\u043e\u043d\u0441\u0435\u043f\u0441\u044c\u0439\u043e\u043d-\u0434\u0435-\u043b\u0430-\u0421\u044c\u0454\u0440\u0440\u0430"
    ],
    "name:zho_x_preferred":[
        "\u5b54\u585e\u666e\u897f\u7fc1\u5fb7\u62c9\u8b1d\u62c9"
    ],
    "qs:name":"Concepci\u00f3n de la Sierra",
    "qs:photos_9r":0,
    "qs:photos_sr":0,
    "qs:pop_sr":"5",
    "wd:wordcount":67,
    "wof:name":"Concepci\u00f3n de la Sierra",
    "wof:placetype":"locality",
    "wof:population":7398
},
  "geometry": {"coordinates":[-55.52031,-27.98311],"type":"Point"}
}