{
  "type": "Feature",
  "properties": {
    "gn:admin1_code":"22",
    "gn:admin2_code":"86147.0",
    "gn:asciiname":"Amicha",
    "gn:country_code":"AR",
    "gn:dem":319,
    "gn:feature_class":"P",
    "gn:feature_code":"PPL",
    "gn:name":"Amicha",
    "gn:population":0,
    "gn:timezone":"America/Argentina/Cordoba",
    "iso:country":"AR",
    "wof:name":"Amicha",
    "wof:placetype":"locality"
},
  "geometry": {"coordinates":[-64.85904000000001,-27.64175],"type":"Point"}
}