{
  "type": "Feature",
  "properties": {
    "gn:admin1_code":"11.0",
    "gn:admin2_code":"42056.0",
    "gn:asciiname":"Vertiz",
    "gn:country_code":"AR",
    "gn:dem":144,
    "gn:feature_class":"P",
    "gn:feature_code":"PPL",
    "gn:name":"V\u00e9rtiz",
    "gn:population":0,
    "gn:timezone":"America/Argentina/Salta",
    "iso:country":"AR",
    "name:ceb_x_preferred":[
        "V\u00e9rtiz"
    ],
    "name:por_x_preferred":[
        "V\u00e9rtiz"
    ],
    "name:spa_x_preferred":[
        "V\u00e9rtiz"
    ],
    "name:swe_x_preferred":[
        "V\u00e9rtiz"
    ],
    "name:und_x_variant":[
        "V\u00e9rtiz"
    ],
    "wof:name":"Vertiz",
    "wof:placetype":"locality"
},
  "geometry": {"coordinates":[-63.90879,-35.42625],"type":"Point"}
}