{
  "type": "Feature",
  "properties": {
    "gn:admin1_code":"8.0",
    "gn:admin2_code":"30056.0",
    "gn:asciiname":"Enrique Carbo",
    "gn:country_code":"AR",
    "gn:dem":17,
    "gn:feature_class":"P",
    "gn:feature_code":"PPL",
    "gn:name":"Enrique Carb\u00f3",
    "gn:population":0,
    "gn:timezone":"America/Argentina/Cordoba",
    "iso:country":"AR",
    "name:por_x_preferred":[
        "Enrique Carb\u00f3"
    ],
    "name:spa_x_preferred":[
        "Enrique Carb\u00f3"
    ],
    "name:und_x_variant":[
        "Carb\u00f3 Estaci\u00f3n",
        "E. Carb\u00f3",
        "Carbo",
        "Enrique Carb\u00f3"
    ],
    "wof:name":"Enrique Carbo",
    "wof:placetype":"locality"
},
  "geometry": {"coordinates":[-59.20934000000001,-33.14823],"type":"Point"}
}