{
  "type": "Feature",
  "properties": {
    "gn:admin1_code":"22.0",
    "gn:admin2_code":"86070.0",
    "gn:asciiname":"La Canada",
    "gn:country_code":"AR",
    "gn:dem":156,
    "gn:feature_class":"P",
    "gn:feature_code":"PPLA2",
    "gn:name":"La Ca\u00f1ada",
    "gn:population":0,
    "gn:timezone":"America/Argentina/Cordoba",
    "iso:country":"AR",
    "name:ceb_x_preferred":[
        "La Ca\u00f1ada"
    ],
    "name:deu_x_preferred":[
        "La Ca\u00f1ada"
    ],
    "name:fra_x_preferred":[
        "La Ca\u00f1ada"
    ],
    "name:ita_x_preferred":[
        "La Ca\u00f1ada"
    ],
    "name:nld_x_preferred":[
        "La Ca\u00f1ada"
    ],
    "name:spa_x_preferred":[
        "La Ca\u00f1ada"
    ],
    "name:swe_x_preferred":[
        "La Ca\u00f1ada"
    ],
    "name:urd_x_preferred":[
        "\u0644\u0627 \u06a9\u0627\u0646\u0627\u0688\u0627"
    ],
    "name:zho_x_preferred":[
        "\u62c9\u5361\u5c3c\u4e9e\u9054"
    ],
    "wof:name":"La Canada",
    "wof:placetype":"locality"
},
  "geometry": {"coordinates":[-63.77366,-27.70826],"type":"Point"}
}