{
  "type": "Feature",
  "properties": {
    "gn:admin1_code":"22.0",
    "gn:admin2_code":"86070.0",
    "gn:asciiname":"La Canada",
    "gn:country_code":"AR",
    "gn:dem":156,
    "gn:feature_class":"P",
    "gn:feature_code":"PPLA2",
    "gn:name":"La Ca\u00f1ada",
    "gn:population":0,
    "gn:timezone":"America/Argentina/Cordoba",
    "iso:country":"AR",
    "name:und_x_variant":[
        "La Ca\u00f1ada"
    ],
    "wof:name":"La Canada",
    "wof:placetype":"locality"
},
  "geometry": {"coordinates":[-63.77366,-27.70826],"type":"Point"}
}