{
  "type": "Feature",
  "properties": {
    "gn:admin1_code":"19.0",
    "gn:admin2_code":"74049.0",
    "gn:asciiname":"Los Molles",
    "gn:country_code":"AR",
    "gn:dem":842,
    "gn:feature_class":"P",
    "gn:feature_code":"PPL",
    "gn:name":"Los Molles",
    "gn:population":0,
    "gn:timezone":"America/Argentina/San_Luis",
    "iso:country":"AR",
    "wof:name":"Los Molles",
    "wof:placetype":"locality"
},
  "geometry": {"coordinates":[-65.00985,-32.43832],"type":"Point"}
}