{
  "type": "Feature",
  "properties": {
    "gn:admin1_code":"11.0",
    "gn:admin2_code":"42154.0",
    "gn:asciiname":"Quehue",
    "gn:country_code":"AR",
    "gn:dem":262,
    "gn:feature_class":"P",
    "gn:feature_code":"PPL",
    "gn:name":"Quehu\u00e9",
    "gn:population":0,
    "gn:timezone":"America/Argentina/Salta",
    "iso:country":"AR",
    "name:ceb_x_preferred":[
        "Quehu\u00e9"
    ],
    "name:por_x_preferred":[
        "Quehue"
    ],
    "name:spa_x_preferred":[
        "Quehu\u00e9"
    ],
    "name:swe_x_preferred":[
        "Quehu\u00e9"
    ],
    "name:und_x_variant":[
        "Quehu\u00e9"
    ],
    "wof:name":"Quehue",
    "wof:placetype":"locality"
},
  "geometry": {"coordinates":[-64.51368000000001,-37.12222],"type":"Point"}
}