{
  "type": "Feature",
  "properties": {
    "gn:admin1_code":"13.0",
    "gn:admin2_code":"50084.0",
    "gn:asciiname":"El Mirador",
    "gn:country_code":"AR",
    "gn:dem":651,
    "gn:feature_class":"P",
    "gn:feature_code":"PPL",
    "gn:name":"El Mirador",
    "gn:population":0,
    "gn:timezone":"America/Argentina/Mendoza",
    "iso:country":"AR",
    "wof:name":"El Mirador",
    "wof:placetype":"locality"
},
  "geometry": {"coordinates":[-68.346,-33.34332],"type":"Point"}
}