{
  "type": "Feature",
  "properties": {
    "gn:admin1_code":"19",
    "gn:admin2_code":"74042.0",
    "gn:asciiname":"Casimiro Gomez",
    "gn:country_code":"AR",
    "gn:dem":268,
    "gn:feature_class":"P",
    "gn:feature_code":"PPL",
    "gn:name":"Casimiro G\u00f3mez",
    "gn:population":0,
    "gn:timezone":"America/Argentina/San_Luis",
    "iso:country":"AR",
    "wof:name":"Casimiro Gomez",
    "wof:placetype":"locality"
},
  "geometry": {"coordinates":[-65.11981999999999,-35.08831],"type":"Point"}
}