{
  "type": "Feature",
  "properties": {
    "gn:admin1_code":"20.0",
    "gn:admin2_code":"78042.0",
    "gn:asciiname":"Lai Aike",
    "gn:country_code":"AR",
    "gn:dem":285,
    "gn:feature_class":"P",
    "gn:feature_code":"PPL",
    "gn:name":"Lai Aike",
    "gn:population":0,
    "gn:timezone":"America/Argentina/Rio_Gallegos",
    "iso:country":"AR",
    "name:und_x_variant":[
        "Estancia Laiaike",
        "Lai Aike"
    ],
    "wof:name":"Lai Aike",
    "wof:placetype":"locality"
},
  "geometry": {"coordinates":[-68.74009000000001,-49.38193],"type":"Point"}
}