{
  "type": "Feature",
  "properties": {
    "gn:country":"AR",
    "gn:fcode":"PPL",
    "gn:population":1687,
    "iso:country":"AR",
    "name:als_x_preferred":[
        "Santa Maria"
    ],
    "name:bre_x_preferred":[
        "Santa Maria"
    ],
    "name:bul_x_preferred":[
        "\u0421\u0430\u043d\u0442\u0430 \u041c\u0430\u0440\u0438\u044f"
    ],
    "name:cat_x_preferred":[
        "Santa Mar\u00eda"
    ],
    "name:cat_x_variant":[
        "Santa Maria"
    ],
    "name:ceb_x_preferred":[
        "Santa Mar\u00eda"
    ],
    "name:ceb_x_variant":[
        "Santa Maria"
    ],
    "name:ces_x_preferred":[
        "Santa Maria"
    ],
    "name:deu_x_preferred":[
        "Santa Maria"
    ],
    "name:eng_x_preferred":[
        "Santa Mar\u00eda"
    ],
    "name:epo_x_preferred":[
        "Santa Maria"
    ],
    "name:est_x_preferred":[
        "Santa Maria"
    ],
    "name:eus_x_preferred":[
        "Santa Maria"
    ],
    "name:fas_x_preferred":[
        "\u0633\u0627\u0646\u062a\u0627 \u0645\u0627\u0631\u06cc\u0627"
    ],
    "name:fin_x_preferred":[
        "Santa Maria"
    ],
    "name:fra_x_preferred":[
        "Santa Mar\u00eda"
    ],
    "name:fra_x_variant":[
        "Santa Maria"
    ],
    "name:heb_x_preferred":[
        "\u05e1\u05e0\u05d8\u05d4 \u05de\u05e8\u05d9\u05d4"
    ],
    "name:hun_x_preferred":[
        "Santa Maria"
    ],
    "name:ilo_x_preferred":[
        "Santa Maria"
    ],
    "name:ind_x_preferred":[
        "Santa Maria"
    ],
    "name:ita_x_preferred":[
        "Santa Maria"
    ],
    "name:jpn_x_preferred":[
        "\u30b5\u30f3\u30bf\u30de\u30ea\u30a2"
    ],
    "name:kat_x_preferred":[
        "\u10e1\u10d0\u10dc\u10e2\u10d0-\u10db\u10d0\u10e0\u10d8\u10d0"
    ],
    "name:kor_x_preferred":[
        "\uc0b0\ud0c0\ub9c8\ub9ac\uc544"
    ],
    "name:lit_x_preferred":[
        "Santa Marija"
    ],
    "name:nld_x_preferred":[
        "Santa Mar\u00eda"
    ],
    "name:nld_x_variant":[
        "Santa Maria"
    ],
    "name:nor_x_preferred":[
        "Santa Maria"
    ],
    "name:pol_x_preferred":[
        "Santa Maria"
    ],
    "name:por_x_preferred":[
        "Santa Mar\u00eda"
    ],
    "name:por_x_variant":[
        "Santa Maria"
    ],
    "name:ron_x_preferred":[
        "Santa Maria"
    ],
    "name:rus_x_preferred":[
        "\u0421\u0430\u043d\u0442\u0430-\u041c\u0430\u0440\u0438\u044f"
    ],
    "name:sco_x_preferred":[
        "Santa Maria"
    ],
    "name:slk_x_preferred":[
        "Santa Mar\u00eda"
    ],
    "name:spa_x_preferred":[
        "Santa Mar\u00eda"
    ],
    "name:srp_x_preferred":[
        "\u0421\u0430\u043d\u0442\u0430 \u041c\u0430\u0440\u0438\u0458\u0430"
    ],
    "name:swe_x_preferred":[
        "Santa Mar\u00eda"
    ],
    "name:swe_x_variant":[
        "Santa Maria"
    ],
    "name:tgl_x_preferred":[
        "Santa Maria"
    ],
    "name:tur_x_preferred":[
        "Santa Maria"
    ],
    "name:ukr_x_preferred":[
        "\u0421\u0430\u043d\u0442\u0430-\u041c\u0430\u0440\u0456\u044f"
    ],
    "name:und_x_variant":[
        "Hubbart"
    ],
    "name:vol_x_preferred":[
        "Santa Maria"
    ],
    "name:war_x_preferred":[
        "Santa Maria"
    ],
    "name:zho_x_preferred":[
        "\u8056\u99ac\u5229\u4e9e"
    ],
    "qs:name":"Santa Mar\u00eda",
    "qs:photos_9r":0,
    "qs:photos_sr":0,
    "qs:pop_sr":"3",
    "wd:wordcount":1180,
    "wof:name":"Santa Mar\u00eda",
    "wof:placetype":"locality",
    "wof:population":1687
},
  "geometry": {"coordinates":[-55.38541,-27.90356],"type":"Point"}
}