{
  "type": "Feature",
  "properties": {
    "gn:country":"AR",
    "gn:fcode":"PPL",
    "gn:pop":1687,
    "iso:country":"AR",
    "name:cat_x_preferred":[
        "Santa Mar\u00eda"
    ],
    "name:eng_x_preferred":[
        "Santa Mar\u00eda"
    ],
    "name:fra_x_preferred":[
        "Santa Mar\u00eda"
    ],
    "name:nld_x_preferred":[
        "Santa Mar\u00eda"
    ],
    "name:por_x_preferred":[
        "Santa Mar\u00eda"
    ],
    "name:spa_x_preferred":[
        "Santa Mar\u00eda"
    ],
    "name:swe_x_preferred":[
        "Santa Mar\u00eda"
    ],
    "name:unk_x_variant":[
        "Hubbart"
    ],
    "qs:name":"Santa Mar\u00eda",
    "qs:photos_9r":0,
    "qs:photos_sr":0,
    "qs:pop_sr":"3",
    "wd:wordcount":1180,
    "wof:name":"Santa Mar\u00eda",
    "wof:placetype":"locality",
    "wof:population":1687
},
  "geometry": {"coordinates":[-55.38541,-27.90356],"type":"Point"}
}