{
  "type": "Feature",
  "properties": {
    "gn:admin1_code":"10.0",
    "gn:admin2_code":"38084.0",
    "gn:asciiname":"Sijes",
    "gn:country_code":"AR",
    "gn:dem":4211,
    "gn:feature_class":"P",
    "gn:feature_code":"PPL",
    "gn:name":"Sijes",
    "gn:population":0,
    "gn:timezone":"America/Argentina/Jujuy",
    "iso:country":"AR",
    "wof:name":"Sijes",
    "wof:placetype":"locality"
},
  "geometry": {"coordinates":[-66.55155999999999,-23.97492],"type":"Point"}
}