{
  "type": "Feature",
  "properties": {
    "gn:admin1_code":"22.0",
    "gn:admin2_code":"86140.0",
    "gn:asciiname":"Pozo del Chanar",
    "gn:country_code":"AR",
    "gn:dem":92,
    "gn:feature_class":"P",
    "gn:feature_code":"PPL",
    "gn:name":"Pozo del Cha\u00f1ar",
    "gn:population":0,
    "gn:timezone":"America/Argentina/Cordoba",
    "iso:country":"AR",
    "wof:name":"Pozo del Chanar",
    "wof:placetype":"locality"
},
  "geometry": {"coordinates":[-63.28011,-29.42371],"type":"Point"}
}