{
  "type": "Feature",
  "properties": {
    "iso:country":"AR",
    "name:ceb_x_preferred":[
        "Fitz Roy"
    ],
    "name:eng_x_preferred":[
        "Fitz Roy"
    ],
    "name:nld_x_preferred":[
        "Fitz Roy"
    ],
    "name:spa_x_preferred":[
        "Fitz Roy"
    ],
    "name:swe_x_preferred":[
        "Fitz Roy"
    ],
    "qs:gn_country":"AR",
    "qs:gn_fcode":"PPL",
    "qs:gn_pop":0,
    "qs:name":"Fitz Roy",
    "qs:name_adm0":"Argentina",
    "qs:name_adm1":"Santa Cruz",
    "qs:photos":0,
    "qs:photos_1k":0,
    "qs:photos_9k":1,
    "qs:photos_9r":1,
    "qs:photos_all":1,
    "qs:photos_sr":0,
    "qs:placetype":"Town",
    "qs:pop_sr":"5",
    "qs:woe_adm0":23424747,
    "wd:wordcount":49,
    "wof:name":"Fitz Roy",
    "wof:placetype":"locality"
},
  "geometry": {"coordinates":[-67.24815,-47.0256],"type":"Point"}
}