{
  "type": "Feature",
  "properties": {
    "gn:admin1_code":"6.0",
    "gn:admin2_code":"18091.0",
    "gn:asciiname":"Puente Batel",
    "gn:country_code":"AR",
    "gn:dem":63,
    "gn:feature_class":"P",
    "gn:feature_code":"PPL",
    "gn:name":"Puente Batel",
    "gn:population":0,
    "gn:timezone":"America/Argentina/Cordoba",
    "iso:country":"AR",
    "name:und_x_variant":[
        "Batel",
        "Puente Batel"
    ],
    "wof:name":"Puente Batel",
    "wof:placetype":"locality"
},
  "geometry": {"coordinates":[-58.76859,-28.97715],"type":"Point"}
}