{
  "type": "Feature",
  "properties": {
    "iso:country":"AR",
    "qs:gn_country":"AR",
    "qs:gn_fcode":"PPL",
    "qs:gn_pop":0,
    "qs:name":"Cruz de Piedra",
    "qs:name_adm0":"Argentina",
    "qs:name_adm1":"Mendoza",
    "qs:photos":30,
    "qs:photos_1k":6,
    "qs:photos_9k":1,
    "qs:photos_9r":2,
    "qs:photos_all":30,
    "qs:photos_sr":2,
    "qs:placetype":"Town",
    "qs:pop_sr":"0",
    "qs:woe_adm0":23424747,
    "wof:name":"Cruz de Piedra",
    "wof:placetype":"locality"
},
  "geometry": {"coordinates":[-68.79861,-33.03194],"type":"Point"}
}