{
  "type": "Feature",
  "properties": {
    "gn:admin1_code":"1.0",
    "gn:admin2_code":"6042.0",
    "gn:asciiname":"Solanet",
    "gn:country_code":"AR",
    "gn:dem":55,
    "gn:feature_class":"P",
    "gn:feature_code":"PPL",
    "gn:name":"Solanet",
    "gn:population":0,
    "gn:timezone":"America/Argentina/Buenos_Aires",
    "iso:country":"AR",
    "wof:name":"Solanet",
    "wof:placetype":"locality"
},
  "geometry": {"coordinates":[-58.50972,-36.84286],"type":"Point"}
}