{
  "type": "Feature",
  "properties": {
    "gn:admin1_code":"01",
    "gn:admin2_code":"6189.0",
    "gn:asciiname":"Calvo",
    "gn:country_code":"AR",
    "gn:dem":87,
    "gn:feature_class":"P",
    "gn:feature_code":"PPL",
    "gn:name":"Calvo",
    "gn:population":0,
    "gn:timezone":"America/Argentina/Buenos_Aires",
    "iso:country":"AR",
    "name:und_x_variant":[
        "Calva",
        "Calvo"
    ],
    "wof:name":"Calvo",
    "wof:placetype":"locality"
},
  "geometry": {"coordinates":[-61.41132,-38.76522],"type":"Point"}
}