{
  "type": "Feature",
  "properties": {
    "gn:admin1_code":"5.0",
    "gn:admin2_code":"14098.0",
    "gn:asciiname":"Tres Pozos",
    "gn:country_code":"AR",
    "gn:dem":429,
    "gn:feature_class":"P",
    "gn:feature_code":"PPL",
    "gn:name":"Tres Pozos",
    "gn:population":0,
    "gn:timezone":"America/Argentina/Cordoba",
    "iso:country":"AR",
    "name:spa_x_preferred":[
        "Tres Pozos"
    ],
    "wof:name":"Tres Pozos",
    "wof:placetype":"locality"
},
  "geometry": {"coordinates":[-64.10551,-32.40786],"type":"Point"}
}