{
  "type": "Feature",
  "properties": {
    "gn:admin1_code":"10.0",
    "gn:admin2_code":"38014.0",
    "gn:asciiname":"Pampa Blanca",
    "gn:country_code":"AR",
    "gn:dem":766,
    "gn:feature_class":"P",
    "gn:feature_code":"PPL",
    "gn:name":"Pampa Blanca",
    "gn:population":0,
    "gn:timezone":"America/Argentina/Jujuy",
    "iso:country":"AR",
    "name:ceb_x_preferred":[
        "Pampa Blanca"
    ],
    "name:ita_x_preferred":[
        "Pampa Blanca"
    ],
    "name:spa_x_preferred":[
        "Pampa Blanca"
    ],
    "name:swe_x_preferred":[
        "Pampa Blanca"
    ],
    "wof:name":"Pampa Blanca",
    "wof:placetype":"locality"
},
  "geometry": {"coordinates":[-65.07545999999999,-24.53082],"type":"Point"}
}