{
  "type": "Feature",
  "properties": {
    "gn:admin1_code":"1.0",
    "gn:admin2_code":"6070.0",
    "gn:asciiname":"Ireneo Portela",
    "gn:country_code":"AR",
    "gn:dem":28,
    "gn:feature_class":"P",
    "gn:feature_code":"PPL",
    "gn:name":"Ireneo Portela",
    "gn:population":0,
    "gn:timezone":"America/Argentina/Buenos_Aires",
    "iso:country":"AR",
    "name:und_x_variant":[
        "I. Portela",
        "Ireneo Portela"
    ],
    "wof:name":"Ireneo Portela",
    "wof:placetype":"locality"
},
  "geometry": {"coordinates":[-59.67065,-33.97969000000001],"type":"Point"}
}