{
  "type": "Feature",
  "properties": {
    "gn:admin1_code":"24.0",
    "gn:admin2_code":"90007.0",
    "gn:asciiname":"La Ramada",
    "gn:country_code":"AR",
    "gn:dem":566,
    "gn:feature_class":"P",
    "gn:feature_code":"PPL",
    "gn:name":"La Ramada",
    "gn:population":0,
    "gn:timezone":"America/Argentina/Tucuman",
    "iso:country":"AR",
    "wof:name":"La Ramada",
    "wof:placetype":"locality"
},
  "geometry": {"coordinates":[-64.94861,-26.68645],"type":"Point"}
}