{
  "type": "Feature",
  "properties": {
    "gn:admin1_code":"15",
    "gn:admin2_code":"58091.0",
    "gn:asciiname":"Rincon de Los Sauces",
    "gn:country_code":"AR",
    "gn:dem":608,
    "gn:feature_class":"P",
    "gn:feature_code":"PPLA2",
    "gn:name":"Rinc\u00f3n de Los Sauces",
    "gn:population":0,
    "gn:timezone":"America/Argentina/Salta",
    "iso:country":"AR",
    "wof:name":"Rincon de Los Sauces",
    "wof:placetype":"locality"
},
  "geometry": {"coordinates":[-68.92874,-37.39844],"type":"Point"}
}