{
  "type": "Feature",
  "properties": {
    "gn:admin1_code":"10",
    "gn:admin2_code":"38112.0",
    "gn:asciiname":"Cienaguilla",
    "gn:country_code":"AR",
    "gn:dem":3853,
    "gn:feature_class":"P",
    "gn:feature_code":"PPL",
    "gn:name":"Cienaguilla",
    "gn:population":0,
    "gn:timezone":"America/Argentina/Jujuy",
    "iso:country":"AR",
    "wof:name":"Cienaguilla",
    "wof:placetype":"locality"
},
  "geometry": {"coordinates":[-65.40000000000001,-22.46667],"type":"Point"}
}