{
  "type": "Feature",
  "properties": {
    "iso:country":"AR",
    "name:pol_x_preferred":[
        "Guaymall\u00e9n Mendoza"
    ],
    "name:spa_x_preferred":[
        "Club Deportivo y Social Guaymall\u00e9n"
    ],
    "qs:gn_country":"AR",
    "qs:gn_fcode":"PPL",
    "qs:gn_pop":0,
    "qs:name":"Rodeo de la Cruz",
    "qs:name_adm0":"Argentina",
    "qs:name_adm1":"Mendoza",
    "qs:photos":0,
    "qs:photos_1k":0,
    "qs:photos_9k":1,
    "qs:photos_9r":1,
    "qs:photos_all":11,
    "qs:photos_sr":0,
    "qs:placetype":"Town",
    "qs:pop_sr":"0",
    "qs:woe_adm0":23424747,
    "wof:name":"Rodeo de la Cruz",
    "wof:placetype":"locality"
},
  "geometry": {"coordinates":[-68.73935,-32.92277],"type":"Point"}
}