{
  "type": "Feature",
  "properties": {
    "gn:admin1_code":"22.0",
    "gn:admin2_code":"86070.0",
    "gn:asciiname":"Tusca Pozo",
    "gn:country_code":"AR",
    "gn:dem":146,
    "gn:feature_class":"P",
    "gn:feature_code":"PPL",
    "gn:name":"Tusca Pozo",
    "gn:population":0,
    "gn:timezone":"America/Argentina/Cordoba",
    "iso:country":"AR",
    "wof:name":"Tusca Pozo",
    "wof:placetype":"locality"
},
  "geometry": {"coordinates":[-63.46375,-27.60947],"type":"Point"}
}