{
  "type": "Feature",
  "properties": {
    "iso:country":"AR",
    "name:ceb_x_preferred":[
        "Pozo del Molle"
    ],
    "name:eng_x_preferred":[
        "Pozo del Molle"
    ],
    "name:ita_x_preferred":[
        "Pozo del Molle"
    ],
    "name:nld_x_preferred":[
        "Pozo del Molle"
    ],
    "name:por_x_preferred":[
        "Pozo del Molle"
    ],
    "name:spa_x_preferred":[
        "Pozo del Molle"
    ],
    "name:swe_x_preferred":[
        "Pozo del Molle"
    ],
    "name:ukr_x_preferred":[
        "\u041f\u043e\u0441\u043e-\u0434\u0435\u043b\u044c-\u041c\u043e\u043b\u044c\u0454"
    ],
    "qs:gn_country":"AR",
    "qs:gn_fcode":"PPL",
    "qs:gn_pop":5429,
    "qs:name":"Pozo del Molle",
    "qs:name_adm0":"Argentina",
    "qs:name_adm1":"C\u00f3rdoba",
    "qs:photos":0,
    "qs:photos_1k":0,
    "qs:photos_9k":1,
    "qs:photos_9r":1,
    "qs:photos_all":6,
    "qs:photos_sr":0,
    "qs:placetype":"Town",
    "qs:pop_sr":"6",
    "qs:woe_adm0":23424747,
    "wof:name":"Pozo del Molle",
    "wof:placetype":"locality",
    "wof:population":5429
},
  "geometry": {"coordinates":[-62.91984,-32.0186],"type":"Point"}
}