{
  "type": "Feature",
  "properties": {
    "gn:admin1_code":"18.0",
    "gn:admin2_code":"70021.0",
    "gn:asciiname":"Tamberias",
    "gn:country_code":"AR",
    "gn:dem":1473,
    "gn:feature_class":"P",
    "gn:feature_code":"PPLA2",
    "gn:name":"Tamber\u00edas",
    "gn:population":0,
    "gn:timezone":"America/Argentina/San_Juan",
    "iso:country":"AR",
    "name:und_x_variant":[
        "Tamber\u00eda",
        "Tamber\u00edas"
    ],
    "wof:name":"Tamberias",
    "wof:placetype":"locality"
},
  "geometry": {"coordinates":[-69.4255,-31.46646],"type":"Point"}
}