{
  "type": "Feature",
  "properties": {
    "gn:admin1_code":"12.0",
    "gn:admin2_code":"46007.0",
    "gn:asciiname":"Estacion Mazan",
    "gn:country_code":"AR",
    "gn:dem":667,
    "gn:feature_class":"P",
    "gn:feature_code":"PPL",
    "gn:name":"Estaci\u00f3n Maz\u00e1n",
    "gn:population":0,
    "gn:timezone":"America/Argentina/La_Rioja",
    "iso:country":"AR",
    "name:ceb_x_preferred":[
        "Estaci\u00f3n Maz\u00e1n"
    ],
    "name:spa_x_preferred":[
        "Estaci\u00f3n Maz\u00e1n"
    ],
    "name:swe_x_preferred":[
        "Estaci\u00f3n Maz\u00e1n"
    ],
    "wof:name":"Estacion Mazan",
    "wof:placetype":"locality"
},
  "geometry": {"coordinates":[-66.49099,-28.67631],"type":"Point"}
}