{
  "type": "Feature",
  "properties": {
    "gn:admin1_code":"15",
    "gn:admin2_code":"58091.0",
    "gn:asciiname":"Cortaderas",
    "gn:country_code":"AR",
    "gn:dem":779,
    "gn:feature_class":"P",
    "gn:feature_code":"PPL",
    "gn:name":"Cortaderas",
    "gn:population":0,
    "gn:timezone":"America/Argentina/Salta",
    "iso:country":"AR",
    "wof:name":"Cortaderas",
    "wof:placetype":"locality"
},
  "geometry": {"coordinates":[-69.58333,-37.66667],"type":"Point"}
}