{
  "type": "Feature",
  "properties": {
    "gn:admin1_code":"13.0",
    "gn:admin2_code":"50049.0",
    "gn:asciiname":"Minas Salagasta",
    "gn:cc2":"AR",
    "gn:country_code":"AR",
    "gn:dem":985,
    "gn:feature_class":"P",
    "gn:feature_code":"PPL",
    "gn:name":"Minas Salagasta",
    "gn:population":0,
    "gn:timezone":"America/Argentina/Mendoza",
    "iso:country":"AR",
    "name:und_x_variant":[
        "Salagasta",
        "Minas Salagasta"
    ],
    "wof:name":"Minas Salagasta",
    "wof:placetype":"locality"
},
  "geometry": {"coordinates":[-68.83333,-32.58333],"type":"Point"}
}