{
  "type": "Feature",
  "properties": {
    "gn:country":"AR",
    "gn:fcode":"PPL",
    "gn:pop":15537,
    "iso:country":"AR",
    "name:ces_x_preferred":[
        "El Bols\u00f3n"
    ],
    "name:deu_x_preferred":[
        "El Bols\u00f3n"
    ],
    "name:eng_x_preferred":[
        "El Bols\u00f3n"
    ],
    "name:fra_x_preferred":[
        "El Bols\u00f3n"
    ],
    "name:heb_x_preferred":[
        "\u05d0\u05dc \u05d1\u05d5\u05dc\u05e1\u05d5\u05df"
    ],
    "name:ita_x_preferred":[
        "El Bols\u00f3n"
    ],
    "name:jpn_x_preferred":[
        "\u30a8\u30eb\u30fb\u30dc\u30eb\u30bd\u30f3"
    ],
    "name:lit_x_preferred":[
        "El Bolsonas"
    ],
    "name:nld_x_preferred":[
        "El Bols\u00f3n"
    ],
    "name:por_x_preferred":[
        "El Bols\u00f3n"
    ],
    "name:slk_x_preferred":[
        "El Bols\u00f3n"
    ],
    "name:spa_x_preferred":[
        "El Bols\u00f3n"
    ],
    "name:swe_x_preferred":[
        "El Bols\u00f3n"
    ],
    "name:ukr_x_preferred":[
        "\u0415\u043b\u044c-\u0411\u043e\u043b\u044c\u0441\u043e\u043d"
    ],
    "name:zho_x_preferred":[
        "\u57c3\u723e\u535a\u723e\u677e"
    ],
    "qs:name":"El Bols\u00f3n",
    "qs:photos_9r":0,
    "qs:photos_sr":0,
    "qs:pop_sr":"6",
    "wd:wordcount":28,
    "wof:name":"El Bols\u00f3n",
    "wof:placetype":"locality",
    "wof:population":15537
},
  "geometry": {"coordinates":[-71.51667,-41.96667],"type":"Point"}
}