{
  "type": "Feature",
  "properties": {
    "gn:admin1_code":"16",
    "gn:admin2_code":"62084.0",
    "gn:asciiname":"Aguada Cecilio",
    "gn:country_code":"AR",
    "gn:dem":225,
    "gn:feature_class":"P",
    "gn:feature_code":"PPL",
    "gn:name":"Aguada Cecilio",
    "gn:population":0,
    "gn:timezone":"America/Argentina/Salta",
    "iso:country":"AR",
    "wof:name":"Aguada Cecilio",
    "wof:placetype":"locality"
},
  "geometry": {"coordinates":[-65.80082,-40.85669],"type":"Point"}
}