{
  "type": "Feature",
  "properties": {
    "gn:admin1_code":"16",
    "gn:admin2_code":"62084.0",
    "gn:asciiname":"Aguada Cecilio",
    "gn:country_code":"AR",
    "gn:dem":225,
    "gn:feature_class":"P",
    "gn:feature_code":"PPL",
    "gn:name":"Aguada Cecilio",
    "gn:population":0,
    "gn:timezone":"America/Argentina/Salta",
    "iso:country":"AR",
    "name:ceb_x_preferred":[
        "Aguada Cecilio"
    ],
    "name:fas_x_preferred":[
        "\u0627\u06af\u0648\u0627\u062f\u0627 \u0633\u0633\u06cc\u0644\u06cc\u0648"
    ],
    "name:spa_x_preferred":[
        "Aguada Cecilio"
    ],
    "name:urd_x_preferred":[
        "\u0627\u06af\u0648\u0627\u062f\u0627 \u0633\u06cc\u0633\u06cc\u0644\u06cc\u0648"
    ],
    "wof:name":"Aguada Cecilio",
    "wof:placetype":"locality"
},
  "geometry": {"coordinates":[-65.80082,-40.85669],"type":"Point"}
}