{
  "type": "Feature",
  "properties": {
    "gn:admin1_code":"02",
    "gn:admin2_code":"10098.0",
    "gn:asciiname":"Alijilan",
    "gn:country_code":"AR",
    "gn:dem":570,
    "gn:feature_class":"P",
    "gn:feature_code":"PPL",
    "gn:name":"Alijil\u00e1n",
    "gn:population":0,
    "gn:timezone":"America/Argentina/Catamarca",
    "iso:country":"AR",
    "name:und_x_variant":[
        "Alijil\u00e1n"
    ],
    "wof:name":"Alijilan",
    "wof:placetype":"locality"
},
  "geometry": {"coordinates":[-65.49379999999999,-28.17971],"type":"Point"}
}