{
  "type": "Feature",
  "properties": {
    "gn:admin1_code":"11.0",
    "gn:admin2_code":"42084.0",
    "gn:asciiname":"Lihuel-Calel",
    "gn:country_code":"AR",
    "gn:dem":394,
    "gn:feature_class":"P",
    "gn:feature_code":"PPL",
    "gn:name":"Lihuel-Calel",
    "gn:population":0,
    "gn:timezone":"America/Argentina/Salta",
    "iso:country":"AR",
    "wof:name":"Lihuel-Calel",
    "wof:placetype":"locality"
},
  "geometry": {"coordinates":[-65.58465,-38.01418],"type":"Point"}
}