{
  "type": "Feature",
  "properties": {
    "gn:admin1_code":"22.0",
    "gn:admin2_code":"86028.0",
    "gn:asciiname":"Punta Corral",
    "gn:country_code":"AR",
    "gn:dem":115,
    "gn:feature_class":"P",
    "gn:feature_code":"PPL",
    "gn:name":"Punta Corral",
    "gn:population":0,
    "gn:timezone":"America/Argentina/Cordoba",
    "iso:country":"AR",
    "wof:name":"Punta Corral",
    "wof:placetype":"locality"
},
  "geometry": {"coordinates":[-63.52245,-28.52424],"type":"Point"}
}