{
  "type": "Feature",
  "properties": {
    "gn:admin1_code":"22.0",
    "gn:admin2_code":"86063.0",
    "gn:asciiname":"El Retiro",
    "gn:country_code":"AR",
    "gn:dem":448,
    "gn:feature_class":"P",
    "gn:feature_code":"PPL",
    "gn:name":"El Retiro",
    "gn:population":0,
    "gn:timezone":"America/Argentina/Cordoba",
    "iso:country":"AR",
    "wof:name":"El Retiro",
    "wof:placetype":"locality"
},
  "geometry": {"coordinates":[-64.88333,-28.38333],"type":"Point"}
}