{
  "type": "Feature",
  "properties": {
    "gn:admin1_code":"10.0",
    "gn:admin2_code":"38007.0",
    "gn:asciiname":"Tabladitas",
    "gn:country_code":"AR",
    "gn:dem":3889,
    "gn:feature_class":"P",
    "gn:feature_code":"PPL",
    "gn:name":"Tabladitas",
    "gn:population":0,
    "gn:timezone":"America/Argentina/Jujuy",
    "iso:country":"AR",
    "wof:name":"Tabladitas",
    "wof:placetype":"locality"
},
  "geometry": {"coordinates":[-65.59687,-22.74609],"type":"Point"}
}