{
  "type": "Feature",
  "properties": {
    "iso:country":"AR",
    "name:ceb_x_preferred":[
        "Villa R\u00edo Hondo"
    ],
    "name:eng_x_preferred":[
        "Villa R\u00edo Hondo"
    ],
    "name:fra_x_preferred":[
        "Villa R\u00edo Hondo"
    ],
    "name:fra_x_variant":[
        "villa R\u00edo Hondo"
    ],
    "name:nld_x_preferred":[
        "Villa R\u00edo Hondo"
    ],
    "name:spa_x_preferred":[
        "Villa R\u00edo Hondo"
    ],
    "name:swe_x_preferred":[
        "Villa R\u00edo Hondo"
    ],
    "name:unk_x_variant":[
        "Villa R\u00edo Hondo"
    ],
    "qs:gn_country":"AR",
    "qs:gn_fcode":"PPL",
    "qs:gn_pop":0,
    "qs:name":"R\u00edo Hondo",
    "qs:name_adm0":"Argentina",
    "qs:name_adm1":"Santiago del Estero",
    "qs:photos":15,
    "qs:photos_1k":3,
    "qs:photos_9k":1,
    "qs:photos_9r":1,
    "qs:photos_all":15,
    "qs:photos_sr":1,
    "qs:placetype":"Town",
    "qs:pop_sr":"0",
    "qs:woe_adm0":23424747,
    "wd:wordcount":35,
    "wof:name":"R\u00edo Hondo",
    "wof:placetype":"locality"
},
  "geometry": {"coordinates":[-64.91502,-27.59341],"type":"Point"}
}