{
  "type": "Feature",
  "properties": {
    "gn:admin1_code":"5.0",
    "gn:admin2_code":"14035.0",
    "gn:asciiname":"Nicolas Bruzone",
    "gn:country_code":"AR",
    "gn:dem":203,
    "gn:feature_class":"P",
    "gn:feature_code":"PPL",
    "gn:name":"Nicol\u00e1s Bruzone",
    "gn:population":0,
    "gn:timezone":"America/Argentina/Cordoba",
    "iso:country":"AR",
    "name:und_x_variant":[
        "N. Bruzone",
        "Nicol\u00e1s Bruzone"
    ],
    "wof:name":"Nicolas Bruzone",
    "wof:placetype":"locality"
},
  "geometry": {"coordinates":[-64.33960999999999,-34.43815],"type":"Point"}
}