{
  "type": "Feature",
  "properties": {
    "gn:admin1_code":"8.0",
    "gn:admin2_code":"30113.0",
    "gn:asciiname":"Jubileo",
    "gn:country_code":"AR",
    "gn:dem":74,
    "gn:feature_class":"P",
    "gn:feature_code":"PPL",
    "gn:name":"Jubileo",
    "gn:population":0,
    "gn:timezone":"America/Argentina/Cordoba",
    "iso:country":"AR",
    "name:por_x_preferred":[
        "Jubileo"
    ],
    "name:spa_x_preferred":[
        "Jubileo"
    ],
    "wof:name":"Jubileo",
    "wof:placetype":"locality"
},
  "geometry": {"coordinates":[-58.63385,-31.73358],"type":"Point"}
}