{
  "type": "Feature",
  "properties": {
    "gn:admin1_code":"17.0",
    "gn:admin2_code":"66133.0",
    "gn:asciiname":"La Entrada",
    "gn:country_code":"AR",
    "gn:dem":215,
    "gn:feature_class":"P",
    "gn:feature_code":"PPL",
    "gn:name":"La Entrada",
    "gn:population":0,
    "gn:timezone":"America/Argentina/Salta",
    "iso:country":"AR",
    "wof:name":"La Entrada",
    "wof:placetype":"locality"
},
  "geometry": {"coordinates":[-62.78333000000001,-23.71667],"type":"Point"}
}