{
  "type": "Feature",
  "properties": {
    "gn:gn_country":"AR",
    "gn:gn_fcode":"PPLX",
    "gn:gn_pop":0,
    "iso:country":"AR",
    "qs_pg:aaroncc":"AR",
    "qs_pg:gn_country":"AR",
    "qs_pg:gn_fcode":"PPLX",
    "qs_pg:gn_pop":0,
    "qs_pg:name":"Presidente Rivadavia",
    "qs_pg:name_adm0":"Argentina",
    "qs_pg:name_adm1":"Ciudad de Buenos Aires",
    "qs_pg:photos":513,
    "qs_pg:photos_1k":104,
    "qs_pg:photos_9k":2,
    "qs_pg:photos_9r":5,
    "qs_pg:photos_all":513,
    "qs_pg:photos_sr":7,
    "qs_pg:pop_sr":0,
    "qs_pg:qs_pg_placetype":"neighbourhood",
    "qs_pg:qs_pg_placetype_gp":"Suburb",
    "qs_pg:woe_adm0":23424747,
    "woe:adm0_id":23424747,
    "woe:name_adm0":"Argentina",
    "woe:name_adm1":"Ciudad de Buenos Aires",
    "woe:placetype":"Suburb",
    "wof:name":"Presidente Rivadavia",
    "wof:placetype":"neighbourhood"
},
  "geometry": {"coordinates":[-58.43333,-34.65],"type":"Point"}
}