{
  "type": "Feature",
  "properties": {
    "iso:country":"AR",
    "qs:gn_country":"AR",
    "qs:gn_fcode":"PPL",
    "qs:gn_pop":0,
    "qs:name":"Puerto Manzano",
    "qs:name_adm0":"Argentina",
    "qs:name_adm1":"Neuqu\u00e9n",
    "qs:photos":28,
    "qs:photos_1k":6,
    "qs:photos_9k":1,
    "qs:photos_9r":2,
    "qs:photos_all":28,
    "qs:photos_sr":2,
    "qs:placetype":"Town",
    "qs:pop_sr":"0",
    "qs:woe_adm0":23424747,
    "wof:name":"Puerto Manzano",
    "wof:placetype":"locality"
},
  "geometry": {"coordinates":[-71.60575,-40.80064],"type":"Point"}
}