{
  "type": "Feature",
  "properties": {
    "gn:admin1_code":"20.0",
    "gn:admin2_code":"78021.0",
    "gn:asciiname":"Gaypon",
    "gn:country_code":"AR",
    "gn:dem":137,
    "gn:feature_class":"P",
    "gn:feature_code":"PPL",
    "gn:name":"Gayp\u00f3n",
    "gn:population":0,
    "gn:timezone":"America/Argentina/Rio_Gallegos",
    "iso:country":"AR",
    "wof:name":"Gaypon",
    "wof:placetype":"locality"
},
  "geometry": {"coordinates":[-71.46666999999999,-51.96667],"type":"Point"}
}