{
  "type": "Feature",
  "properties": {
    "gn:admin1_code":"2.0",
    "gn:admin2_code":"10021.0",
    "gn:asciiname":"Rodeo Grande",
    "gn:country_code":"AR",
    "gn:dem":2171,
    "gn:feature_class":"P",
    "gn:feature_code":"PPL",
    "gn:name":"Rodeo Grande",
    "gn:population":0,
    "gn:timezone":"America/Argentina/Catamarca",
    "iso:country":"AR",
    "wof:name":"Rodeo Grande",
    "wof:placetype":"locality"
},
  "geometry": {"coordinates":[-66.43826,-27.4526],"type":"Point"}
}