{
  "type": "Feature",
  "properties": {
    "gn:admin1_code":"24.0",
    "gn:admin2_code":"90014.0",
    "gn:asciiname":"Ranchillos",
    "gn:country_code":"AR",
    "gn:dem":393,
    "gn:feature_class":"P",
    "gn:feature_code":"PPL",
    "gn:name":"Ranchillos",
    "gn:population":0,
    "gn:timezone":"America/Argentina/Tucuman",
    "iso:country":"AR",
    "wof:name":"Ranchillos",
    "wof:placetype":"locality"
},
  "geometry": {"coordinates":[-65.04553,-26.95424],"type":"Point"}
}