{
  "type": "Feature",
  "properties": {
    "iso:country":"AR",
    "name:dut_x_preferred":[
        "Aldea Valle Mar\u00eda"
    ],
    "name:eng_x_preferred":[
        "Aldea Valle Mar\u00eda"
    ],
    "name:fas_x_preferred":[
        "\u0627\u0644\u062f\u06cc\u0627 \u0648\u0627\u0644 \u0645\u0627\u0631\u06cc\u0627"
    ],
    "name:per_x_preferred":[
        "\u0627\u0644\u062f\u06cc\u0627 \u0648\u0627\u0644 \u0645\u0627\u0631\u06cc\u0627"
    ],
    "name:por_x_preferred":[
        "Aldea Valle Mar\u00eda"
    ],
    "name:spa_x_preferred":[
        "Aldea Valle Mar\u00eda"
    ],
    "name:ukr_x_preferred":[
        "\u0410\u043b\u044c\u0434\u0435\u0430-\u0412\u0430\u043b\u044c\u0454-\u041c\u0430\u0440\u0456\u044f"
    ],
    "qs:gn_country":"AR",
    "qs:gn_fcode":"PPL",
    "qs:gn_pop":0,
    "qs:name":"Valle Mar\u00eda",
    "qs:name_adm0":"Argentina",
    "qs:name_adm1":"Entre R\u00edos",
    "qs:photos":18,
    "qs:photos_1k":4,
    "qs:photos_9k":1,
    "qs:photos_9r":1,
    "qs:photos_all":18,
    "qs:photos_sr":1,
    "qs:placetype":"Town",
    "qs:pop_sr":"0",
    "qs:woe_adm0":23424747,
    "wd:wordcount":39,
    "wof:name":"Valle Mar\u00eda",
    "wof:placetype":"locality"
},
  "geometry": {"coordinates":[-60.588,-31.9909],"type":"Point"}
}