{
  "type": "Feature",
  "properties": {
    "gn:admin1_code":"20",
    "gn:admin2_code":"78042.0",
    "gn:asciiname":"Canadon Once de Septiembre",
    "gn:country_code":"AR",
    "gn:dem":110,
    "gn:feature_class":"P",
    "gn:feature_code":"PPL",
    "gn:name":"Ca\u00f1ad\u00f3n Once de Septiembre",
    "gn:population":0,
    "gn:timezone":"America/Argentina/Rio_Gallegos",
    "iso:country":"AR",
    "name:und_x_variant":[
        "Estancia Ca\u00f1ad\u00f3n II de Setiembre",
        "Ca\u00f1ad\u00f3n 11 de Septiembre",
        "Ca\u00f1ad\u00f3n Once de Setiembre",
        "Ca\u00f1ad\u00f3n Once de Septiembre"
    ],
    "wof:name":"Canadon Once de Septiembre",
    "wof:placetype":"locality"
},
  "geometry": {"coordinates":[-67.37778,-48.65004],"type":"Point"}
}