{
  "type": "Feature",
  "properties": {
    "gn:admin1_code":"16",
    "gn:admin2_code":"62063.0",
    "gn:asciiname":"Colonia Julia y Echarren",
    "gn:country_code":"AR",
    "gn:dem":78,
    "gn:feature_class":"P",
    "gn:feature_code":"PPL",
    "gn:name":"Colonia Julia y Echarren",
    "gn:population":0,
    "gn:timezone":"America/Argentina/Salta",
    "iso:country":"AR",
    "name:ceb_x_preferred":[
        "Colonia Julia y Echarren"
    ],
    "name:spa_x_preferred":[
        "Colonia Juli\u00e1 y Echarren"
    ],
    "name:swe_x_preferred":[
        "Colonia Julia y Echarren"
    ],
    "name:und_x_variant":[
        "Colonia J. y Echarren"
    ],
    "wof:name":"Colonia Julia y Echarren",
    "wof:placetype":"locality"
},
  "geometry": {"coordinates":[-64.02729000000001,-39.03504],"type":"Point"}
}