{
  "type": "Feature",
  "properties": {
    "gn:admin1_code":"05",
    "gn:asciiname":"Colonia Mackinlay",
    "gn:country_code":"AR",
    "gn:dem":96,
    "gn:feature_class":"P",
    "gn:feature_code":"PPL",
    "gn:name":"Colonia Mackinlay",
    "gn:population":0,
    "gn:timezone":"America/Argentina/Cordoba",
    "iso:country":"AR",
    "wof:name":"Colonia Mackinlay",
    "wof:placetype":"locality"
},
  "geometry": {"coordinates":[-62.11666999999999,-30.36667000000001],"type":"Point"}
}