{
  "type": "Feature",
  "properties": {
    "gn:admin1_code":"22.0",
    "gn:admin2_code":"86098.0",
    "gn:asciiname":"Tiun Punco",
    "gn:country_code":"AR",
    "gn:dem":130,
    "gn:feature_class":"P",
    "gn:feature_code":"PPL",
    "gn:name":"Tiun Punco",
    "gn:population":0,
    "gn:timezone":"America/Argentina/Cordoba",
    "iso:country":"AR",
    "name:und_x_variant":[
        "Tiun Puncc",
        "Tiun Punco"
    ],
    "wof:name":"Tiun Punco",
    "wof:placetype":"locality"
},
  "geometry": {"coordinates":[-63.32119,-28.04154],"type":"Point"}
}