{
  "type": "Feature",
  "properties": {
    "iso:country":"AR",
    "name:ceb_x_preferred":[
        "Garup\u00e1"
    ],
    "name:dut_x_preferred":[
        "Garup\u00e1"
    ],
    "name:eng_x_preferred":[
        "Garup\u00e1"
    ],
    "name:fre_x_preferred":[
        "Garup\u00e1"
    ],
    "name:ger_x_preferred":[
        "Garup\u00e1"
    ],
    "name:ita_x_preferred":[
        "Garup\u00e1"
    ],
    "name:por_x_preferred":[
        "Garup\u00e1"
    ],
    "name:spa_x_preferred":[
        "Garup\u00e1"
    ],
    "name:swe_x_preferred":[
        "Garup\u00e1"
    ],
    "qs:gn_country":"AR",
    "qs:gn_fcode":"PPL",
    "qs:gn_pop":28814,
    "qs:name":"Garup\u00e1",
    "qs:name_adm0":"Argentina",
    "qs:name_adm1":"Misiones",
    "qs:photos":10,
    "qs:photos_1k":2,
    "qs:photos_9k":1,
    "qs:photos_9r":1,
    "qs:photos_all":10,
    "qs:photos_sr":1,
    "qs:placetype":"Town",
    "qs:pop_sr":"7",
    "qs:woe_adm0":23424747,
    "wd:wordcount":57,
    "wof:name":"Garup\u00e1",
    "wof:placetype":"locality",
    "wof:population":28814
},
  "geometry": {"coordinates":[-55.82921,-27.48171],"type":"Point"}
}