{
  "type": "Feature",
  "properties": {
    "gn:admin1_code":"5.0",
    "gn:admin2_code":"14049.0",
    "gn:asciiname":"El Quebracho",
    "gn:country_code":"AR",
    "gn:dem":422,
    "gn:feature_class":"P",
    "gn:feature_code":"PPL",
    "gn:name":"El Quebracho",
    "gn:population":0,
    "gn:timezone":"America/Argentina/Cordoba",
    "iso:country":"AR",
    "wof:name":"El Quebracho",
    "wof:placetype":"locality"
},
  "geometry": {"coordinates":[-64.64966,-30.38706],"type":"Point"}
}