{
  "type": "Feature",
  "properties": {
    "gn:gn_country":"AR",
    "gn:gn_fcode":"PPL",
    "gn:gn_pop":5685,
    "gn:population":5685,
    "iso:country":"AR",
    "name:ceb_x_preferred":[
        "Perugorr\u00eda"
    ],
    "name:eng_x_preferred":[
        "Perugorr\u00eda"
    ],
    "name:fra_x_preferred":[
        "Perugorr\u00eda"
    ],
    "name:nld_x_preferred":[
        "Perugorr\u00eda"
    ],
    "name:spa_x_preferred":[
        "Perugorr\u00eda"
    ],
    "name:swe_x_preferred":[
        "Perugorr\u00eda"
    ],
    "name:ukr_x_preferred":[
        "\u041f\u0435\u0440\u0443\u0433\u043e\u0440\u0440\u0456\u044f"
    ],
    "name:unk_x_variant":[
        "Perrugorr\u00eda"
    ],
    "qs_pg:aaroncc":"AR",
    "qs_pg:gn_country":"AR",
    "qs_pg:gn_fcode":"PPL",
    "qs_pg:gn_pop":5685,
    "qs_pg:name":"Perugorr\u00eda",
    "qs_pg:photos_9r":0,
    "qs_pg:photos_sr":0,
    "qs_pg:pop_sr":6,
    "qs_pg:qs_pg_placetype":"locality",
    "wof:name":"Perugorr\u00eda",
    "wof:placetype":"locality",
    "wof:population":5685
},
  "geometry": {"coordinates":[-58.61059,-29.34132],"type":"Point"}
}