{
  "type": "Feature",
  "properties": {
    "gn:admin1_code":"17.0",
    "gn:admin2_code":"66007.0",
    "gn:asciiname":"General Pizarro",
    "gn:country_code":"AR",
    "gn:dem":369,
    "gn:feature_class":"P",
    "gn:feature_code":"PPL",
    "gn:name":"General Pizarro",
    "gn:population":0,
    "gn:timezone":"America/Argentina/Salta",
    "iso:country":"AR",
    "name:ceb_x_preferred":[
        "General Pizarro"
    ],
    "name:por_x_preferred":[
        "General Pizarro"
    ],
    "name:spa_x_preferred":[
        "General Pizarro"
    ],
    "name:swe_x_preferred":[
        "General Pizarro"
    ],
    "wof:name":"General Pizarro",
    "wof:placetype":"locality"
},
  "geometry": {"coordinates":[-63.99384000000001,-24.22813],"type":"Point"}
}