{
  "type": "Feature",
  "properties": {
    "iso:country":"AR",
    "name:cat_x_preferred":[
        "Alberti"
    ],
    "name:dut_x_preferred":[
        "Alberti"
    ],
    "name:eng_x_preferred":[
        "Alberti"
    ],
    "name:fre_x_preferred":[
        "Alberti"
    ],
    "name:ita_x_preferred":[
        "Alberti"
    ],
    "name:per_x_preferred":[
        "\u0627\u0644\u0628\u0631\u062a\u06cc\u060c \u0628\u0648\u06cc\u0646\u0633 \u0627\u06cc\u0631\u0633"
    ],
    "name:pol_x_preferred":[
        "Alberti"
    ],
    "name:por_x_preferred":[
        "Alberti"
    ],
    "name:spa_x_preferred":[
        "Alberti"
    ],
    "name:ukr_x_preferred":[
        "\u0410\u043b\u044c\u0431\u0435\u0440\u0442\u0456"
    ],
    "qs:gn_country":"AR",
    "qs:gn_fcode":"PPL",
    "qs:gn_pop":0,
    "qs:name":"Alberti",
    "qs:name_adm0":"Argentina",
    "qs:name_adm1":"Buenos Aires",
    "qs:photos":0,
    "qs:photos_1k":0,
    "qs:photos_9k":1,
    "qs:photos_9r":2,
    "qs:photos_all":54,
    "qs:photos_sr":0,
    "qs:placetype":"Town",
    "qs:pop_sr":"7",
    "qs:woe_adm0":23424747,
    "wof:name":"Alberti",
    "wof:placetype":"locality"
},
  "geometry": {"coordinates":[-60.27587,-35.02692],"type":"Point"}
}