{
  "type": "Feature",
  "properties": {
    "iso:country":"AR",
    "name:bul_x_preferred":[
        "\u0410\u043b\u0431\u0435\u0440\u0442\u0438"
    ],
    "name:cat_x_preferred":[
        "Alberti"
    ],
    "name:ceb_x_preferred":[
        "Alberti"
    ],
    "name:ces_x_preferred":[
        "Alberti"
    ],
    "name:deu_x_preferred":[
        "Alberti"
    ],
    "name:eng_x_preferred":[
        "Alberti"
    ],
    "name:fas_x_preferred":[
        "\u0627\u0644\u0628\u0631\u062a\u06cc\u060c \u0628\u0648\u06cc\u0646\u0633 \u0627\u06cc\u0631\u0633"
    ],
    "name:fas_x_variant":[
        "\u0627\u0644\u0628\u0631\u062a\u06cc"
    ],
    "name:fin_x_preferred":[
        "Alberti"
    ],
    "name:fra_x_preferred":[
        "Alberti"
    ],
    "name:heb_x_preferred":[
        "\u05d0\u05dc\u05d1\u05e8\u05d8\u05d9"
    ],
    "name:hun_x_preferred":[
        "Alberti"
    ],
    "name:ita_x_preferred":[
        "Alberti"
    ],
    "name:kor_x_preferred":[
        "\uc54c\ubca0\ub974\ud2f0"
    ],
    "name:nds_x_preferred":[
        "Alberti"
    ],
    "name:nld_x_preferred":[
        "Alberti"
    ],
    "name:pol_x_preferred":[
        "Alberti"
    ],
    "name:por_x_preferred":[
        "Alberti"
    ],
    "name:rus_x_preferred":[
        "\u0410\u043b\u044c\u0431\u0435\u0440\u0442\u0438"
    ],
    "name:slv_x_preferred":[
        "Alberti"
    ],
    "name:spa_x_preferred":[
        "Alberti"
    ],
    "name:srp_x_preferred":[
        "Alberti"
    ],
    "name:swe_x_preferred":[
        "Alberti"
    ],
    "name:ukr_x_preferred":[
        "\u0410\u043b\u044c\u0431\u0435\u0440\u0442\u0456"
    ],
    "name:vie_x_preferred":[
        "Alberti"
    ],
    "name:zho_x_preferred":[
        "\u963f\u5c14\u8d1d\u8482"
    ],
    "qs:gn_country":"AR",
    "qs:gn_fcode":"PPL",
    "qs:gn_pop":0,
    "qs:name":"Alberti",
    "qs:name_adm0":"Argentina",
    "qs:name_adm1":"Buenos Aires",
    "qs:photos":0,
    "qs:photos_1k":0,
    "qs:photos_9k":1,
    "qs:photos_9r":2,
    "qs:photos_all":54,
    "qs:photos_sr":0,
    "qs:placetype":"Town",
    "qs:pop_sr":"7",
    "qs:woe_adm0":23424747,
    "wof:name":"Alberti",
    "wof:placetype":"locality"
},
  "geometry": {"coordinates":[-60.27587,-35.02692],"type":"Point"}
}