{
  "type": "Feature",
  "properties": {
    "gn:admin1_code":"11",
    "gn:admin2_code":"42112.0",
    "gn:asciiname":"Colonia Chica",
    "gn:country_code":"AR",
    "gn:dem":309,
    "gn:feature_class":"P",
    "gn:feature_code":"PPL",
    "gn:name":"Colonia Chica",
    "gn:population":0,
    "gn:timezone":"America/Argentina/Salta",
    "iso:country":"AR",
    "wof:name":"Colonia Chica",
    "wof:placetype":"locality"
},
  "geometry": {"coordinates":[-67.82539,-37.95795],"type":"Point"}
}