{
  "type": "Feature",
  "properties": {
    "gn:admin1_code":"18.0",
    "gn:admin2_code":"70056.0",
    "gn:asciiname":"Huerta de Huachi",
    "gn:country_code":"AR",
    "gn:dem":1501,
    "gn:feature_class":"P",
    "gn:feature_code":"PPL",
    "gn:name":"Huerta de Huachi",
    "gn:population":0,
    "gn:timezone":"America/Argentina/San_Juan",
    "iso:country":"AR",
    "name:und_x_variant":[
        "Huerta de Guachi",
        "Huerta de Huachi"
    ],
    "wof:name":"Huerta de Huachi",
    "wof:placetype":"locality"
},
  "geometry": {"coordinates":[-68.75201,-30.01394],"type":"Point"}
}