{
  "type": "Feature",
  "properties": {
    "gn:admin1_code":"4.0",
    "gn:admin2_code":"26014.0",
    "gn:asciiname":"El Mayoco",
    "gn:country_code":"AR",
    "gn:dem":839,
    "gn:feature_class":"P",
    "gn:feature_code":"PPL",
    "gn:name":"El Mayoco",
    "gn:population":0,
    "gn:timezone":"America/Argentina/Catamarca",
    "iso:country":"AR",
    "wof:name":"El Mayoco",
    "wof:placetype":"locality"
},
  "geometry": {"coordinates":[-70.96684999999999,-42.73353],"type":"Point"}
}