{
  "type": "Feature",
  "properties": {
    "gn:admin1_code":"1.0",
    "gn:admin2_code":"6476.0",
    "gn:asciiname":"Las Nutrias",
    "gn:country_code":"AR",
    "gn:dem":90,
    "gn:feature_class":"P",
    "gn:feature_code":"PPL",
    "gn:name":"Las Nutrias",
    "gn:population":0,
    "gn:timezone":"America/Argentina/Buenos_Aires",
    "iso:country":"AR",
    "wof:name":"Las Nutrias",
    "wof:placetype":"locality"
},
  "geometry": {"coordinates":[-58.4591,-38.07973],"type":"Point"}
}