{
  "type": "Feature",
  "properties": {
    "gn:admin1_code":"1.0",
    "gn:admin2_code":"6413.0",
    "gn:asciiname":"Fortin Tiburcio",
    "gn:country_code":"AR",
    "gn:dem":92,
    "gn:feature_class":"P",
    "gn:feature_code":"PPL",
    "gn:name":"Fort\u00edn Tiburcio",
    "gn:population":0,
    "gn:timezone":"America/Argentina/Buenos_Aires",
    "iso:country":"AR",
    "wof:name":"Fortin Tiburcio",
    "wof:placetype":"locality"
},
  "geometry": {"coordinates":[-61.12901,-34.34547],"type":"Point"}
}