{
  "type": "Feature",
  "properties": {
    "iso:country":"AR",
    "name:spa_x_preferred":[
        "Los Conquistadores"
    ],
    "qs:gn_country":"AR",
    "qs:gn_fcode":"PPL",
    "qs:gn_pop":1214,
    "qs:name":"Los Conquistadores",
    "qs:name_adm0":"Argentina",
    "qs:name_adm1":"Entre R\u00edos",
    "qs:photos":0,
    "qs:photos_1k":0,
    "qs:photos_9k":0,
    "qs:photos_9r":0,
    "qs:photos_all":0,
    "qs:photos_sr":0,
    "qs:placetype":"Town",
    "qs:pop_sr":"7",
    "qs:woe_adm0":23424747,
    "wd:wordcount":1232,
    "wof:name":"Los Conquistadores",
    "wof:placetype":"locality",
    "wof:population":1214
},
  "geometry": {"coordinates":[-58.46773,-30.5908],"type":"Point"}
}