{
  "type": "Feature",
  "properties": {
    "gn:admin1_code":"1.0",
    "gn:admin2_code":"6638.0",
    "gn:asciiname":"Manzone",
    "gn:country_code":"AR",
    "gn:dem":27,
    "gn:feature_class":"P",
    "gn:feature_code":"PPL",
    "gn:name":"Manzone",
    "gn:population":0,
    "gn:timezone":"America/Argentina/Buenos_Aires",
    "iso:country":"AR",
    "name:spa_x_preferred":[
        "Manzone"
    ],
    "wof:name":"Manzone",
    "wof:placetype":"locality"
},
  "geometry": {"coordinates":[-58.87001,-34.49179],"type":"Point"}
}