{
  "type": "Feature",
  "properties": {
    "gn:admin1_code":"3.0",
    "gn:admin2_code":"22039.0",
    "gn:asciiname":"Zuberbuehler",
    "gn:country_code":"AR",
    "gn:dem":80,
    "gn:feature_class":"P",
    "gn:feature_code":"PPL",
    "gn:name":"Zuberb\u00fchler",
    "gn:population":0,
    "gn:timezone":"America/Argentina/Cordoba",
    "iso:country":"AR",
    "name:spa_x_preferred":[
        "Zuberb\u00fchler"
    ],
    "name:und_x_variant":[
        "Zuberb\u00fchler"
    ],
    "wof:name":"Zuberbuehler",
    "wof:placetype":"locality"
},
  "geometry": {"coordinates":[-61.36538,-27.71558],"type":"Point"}
}