{
  "type": "Feature",
  "properties": {
    "gn:admin1_code":"2.0",
    "gn:admin2_code":"10056.0",
    "gn:asciiname":"Rio de Avila",
    "gn:country_code":"AR",
    "gn:dem":977,
    "gn:feature_class":"P",
    "gn:feature_code":"PPL",
    "gn:name":"R\u00edo de \u00c1vila",
    "gn:population":0,
    "gn:timezone":"America/Argentina/Catamarca",
    "iso:country":"AR",
    "wof:name":"Rio de Avila",
    "wof:placetype":"locality"
},
  "geometry": {"coordinates":[-65.41667,-28.45],"type":"Point"}
}