{
  "type": "Feature",
  "properties": {
    "gn:admin1_code":"9.0",
    "gn:admin2_code":"34007.0",
    "gn:asciiname":"Mision Pilaga",
    "gn:country_code":"AR",
    "gn:dem":171,
    "gn:feature_class":"P",
    "gn:feature_code":"PPL",
    "gn:name":"Misi\u00f3n Pilag\u00e1",
    "gn:population":0,
    "gn:timezone":"America/Argentina/Cordoba",
    "iso:country":"AR",
    "wof:name":"Mision Pilaga",
    "wof:placetype":"locality"
},
  "geometry": {"coordinates":[-61.18333000000001,-23.58333],"type":"Point"}
}