{
  "type": "Feature",
  "properties": {
    "gn:admin1_code":"21",
    "gn:admin2_code":"82042.0",
    "gn:asciiname":"Coronel Rosetti",
    "gn:cc2":"AR",
    "gn:country_code":"AR",
    "gn:dem":114,
    "gn:feature_class":"P",
    "gn:feature_code":"PPL",
    "gn:name":"Coronel Rosetti",
    "gn:population":0,
    "gn:timezone":"America/Argentina/Cordoba",
    "iso:country":"AR",
    "name:und_x_variant":[
        "Rosetti",
        "Coronel Roseti",
        "Coronel Rosetti"
    ],
    "wof:name":"Coronel Rosetti",
    "wof:placetype":"locality"
},
  "geometry": {"coordinates":[-62.56667,-34.28333],"type":"Point"}
}