{
  "type": "Feature",
  "properties": {
    "gn:admin1_code":"22.0",
    "gn:admin2_code":"86098.0",
    "gn:asciiname":"Pozo del Toba",
    "gn:country_code":"AR",
    "gn:dem":104,
    "gn:feature_class":"P",
    "gn:feature_code":"PPL",
    "gn:name":"Pozo del Toba",
    "gn:population":0,
    "gn:timezone":"America/Argentina/Cordoba",
    "iso:country":"AR",
    "name:und_x_variant":[
        "Pozo Tobas",
        "Pozo del Tobas",
        "Pozo del Toba"
    ],
    "wof:name":"Pozo del Toba",
    "wof:placetype":"locality"
},
  "geometry": {"coordinates":[-61.97756999999999,-27.94935],"type":"Point"}
}