{
  "type": "Feature",
  "properties": {
    "gn:admin1_code":"22",
    "gn:admin2_code":"86056.0",
    "gn:asciiname":"Desvio Kilometro 1342",
    "gn:country_code":"AR",
    "gn:dem":168,
    "gn:feature_class":"P",
    "gn:feature_code":"PPL",
    "gn:name":"Desv\u00edo Kil\u00f3metro 1342",
    "gn:population":0,
    "gn:timezone":"America/Argentina/Cordoba",
    "iso:country":"AR",
    "wof:name":"Desvio Kilometro 1342",
    "wof:placetype":"locality"
},
  "geometry": {"coordinates":[-61.96666999999999,-26.18333],"type":"Point"}
}