{
  "type": "Feature",
  "properties": {
    "gn:country":"AR",
    "gn:fcode":"PPL",
    "gn:population":10959,
    "iso:country":"AR",
    "name:ceb_x_preferred":[
        "Quimil\u00ed"
    ],
    "name:deu_x_preferred":[
        "Quimil\u00ed"
    ],
    "name:eng_x_preferred":[
        "Quimil\u00ed"
    ],
    "name:fra_x_preferred":[
        "Quimil\u00ed"
    ],
    "name:ita_x_preferred":[
        "Quimil\u00ed"
    ],
    "name:mlg_x_preferred":[
        "Quimil\u00ed"
    ],
    "name:nld_x_preferred":[
        "Quimil\u00ed"
    ],
    "name:pol_x_preferred":[
        "Quimil\u00ed"
    ],
    "name:spa_x_preferred":[
        "Quimil\u00ed"
    ],
    "name:swe_x_preferred":[
        "Quimil\u00ed"
    ],
    "name:ukr_x_preferred":[
        "\u041a\u0456\u043b\u0456\u043c\u0456\u043b\u0456"
    ],
    "name:zho_x_preferred":[
        "\u57fa\u7c73\u5229"
    ],
    "qs:name":"Quimil\u00ed",
    "qs:photos_9r":0,
    "qs:photos_sr":0,
    "qs:pop_sr":"7",
    "wd:wordcount":64,
    "wof:name":"Quimil\u00ed",
    "wof:placetype":"locality",
    "wof:population":10959
},
  "geometry": {"coordinates":[-62.41667,-27.63333],"type":"Point"}
}