{
  "type": "Feature",
  "properties": {
    "gn:admin1_code":"05",
    "gn:admin2_code":"14119.0",
    "gn:asciiname":"Colonia Videla",
    "gn:country_code":"AR",
    "gn:dem":250,
    "gn:feature_class":"P",
    "gn:feature_code":"PPL",
    "gn:name":"Colonia Videla",
    "gn:population":0,
    "gn:timezone":"America/Argentina/Cordoba",
    "iso:country":"AR",
    "wof:name":"Colonia Videla",
    "wof:placetype":"locality"
},
  "geometry": {"coordinates":[-63.50377,-31.91638],"type":"Point"}
}