{
  "type": "Feature",
  "properties": {
    "iso:country":"AR",
    "name:ceb_x_preferred":[
        "San Francisco del Monte de Oro"
    ],
    "name:chi_x_preferred":[
        "\u8056\u5f17\u6717\u897f\u65af\u79d1\u5fb7\u723e\u8499\u7279\u8499\u5967\u7f85"
    ],
    "name:deu_x_preferred":[
        "San Francisco del Monte de Oro"
    ],
    "name:dut_x_preferred":[
        "San Francisco del Monte de Oro"
    ],
    "name:eng_x_preferred":[
        "San Francisco del Monte de Oro"
    ],
    "name:fra_x_preferred":[
        "San Francisco del Monte de Oro"
    ],
    "name:fre_x_preferred":[
        "San Francisco del Monte de Oro"
    ],
    "name:ger_x_preferred":[
        "San Francisco del Monte de Oro"
    ],
    "name:nld_x_preferred":[
        "San Francisco del Monte de Oro"
    ],
    "name:por_x_preferred":[
        "San Francisco del Monte de Oro"
    ],
    "name:spa_x_preferred":[
        "San Francisco del Monte de Oro"
    ],
    "name:swe_x_preferred":[
        "San Francisco del Monte de Oro"
    ],
    "name:ukr_x_preferred":[
        "\u0421\u0430\u043d-\u0424\u0440\u0430\u043d\u0441\u0456\u0441\u043a\u043e-\u0434\u0435\u043b\u044c-\u041c\u043e\u043d\u0442\u0435-\u0434\u0435-\u041e\u0440\u043e"
    ],
    "name:unk_x_variant":[
        "San Francisco"
    ],
    "name:zho_x_preferred":[
        "\u8056\u5f17\u6717\u897f\u65af\u79d1\u5fb7\u723e\u8499\u7279\u8499\u5967\u7f85"
    ],
    "qs:gn_country":"AR",
    "qs:gn_fcode":"PPL",
    "qs:gn_pop":3295,
    "qs:name":"San Francisco del Monte De Oro",
    "qs:name_adm0":"Argentina",
    "qs:name_adm1":"San Luis",
    "qs:photos":12,
    "qs:photos_1k":2,
    "qs:photos_9k":1,
    "qs:photos_9r":1,
    "qs:photos_all":12,
    "qs:photos_sr":1,
    "qs:placetype":"Town",
    "qs:pop_sr":"7",
    "qs:woe_adm0":23424747,
    "wd:wordcount":39,
    "wof:name":"San Francisco del Monte De Oro",
    "wof:placetype":"locality",
    "wof:population":3295
},
  "geometry": {"coordinates":[-66.12539,-32.59825],"type":"Point"}
}