{
  "type": "Feature",
  "properties": {
    "gn:admin1_code":"12.0",
    "gn:admin2_code":"46014.0",
    "gn:asciiname":"Las Mesillas",
    "gn:country_code":"AR",
    "gn:dem":438,
    "gn:feature_class":"P",
    "gn:feature_code":"PPL",
    "gn:name":"Las Mesillas",
    "gn:population":0,
    "gn:timezone":"America/Argentina/La_Rioja",
    "iso:country":"AR",
    "wof:name":"Las Mesillas",
    "wof:placetype":"locality"
},
  "geometry": {"coordinates":[-66.71666999999999,-29.25],"type":"Point"}
}