{
  "type": "Feature",
  "properties": {
    "iso:country":"AR",
    "name:dut_x_preferred":[
        "San Antonio"
    ],
    "name:eng_x_preferred":[
        "San Antonio"
    ],
    "name:por_x_preferred":[
        "San Antonio"
    ],
    "name:spa_x_preferred":[
        "San Antonio"
    ],
    "name:swe_x_preferred":[
        "San Antonio"
    ],
    "name:ukr_x_preferred":[
        "\u0421\u0430\u043d-\u0410\u043d\u0442\u043e\u043d\u0456\u043e"
    ],
    "qs:gn_country":"AR",
    "qs:gn_fcode":"PPL",
    "qs:gn_pop":0,
    "qs:name":"San Antonio",
    "qs:name_adm0":"Argentina",
    "qs:name_adm1":"Misiones",
    "qs:photos":0,
    "qs:photos_1k":0,
    "qs:photos_9k":1,
    "qs:photos_9r":1,
    "qs:photos_all":1,
    "qs:photos_sr":0,
    "qs:placetype":"Town",
    "qs:pop_sr":"0",
    "qs:woe_adm0":23424747,
    "wof:name":"San Antonio",
    "wof:placetype":"locality"
},
  "geometry": {"coordinates":[-53.73333,-26.05],"type":"Point"}
}