{
  "type": "Feature",
  "properties": {
    "gn:admin1_code":"17.0",
    "gn:admin2_code":"66070.0",
    "gn:asciiname":"San Pedro",
    "gn:country_code":"AR",
    "gn:dem":3416,
    "gn:feature_class":"P",
    "gn:feature_code":"PPL",
    "gn:name":"San Pedro",
    "gn:population":0,
    "gn:timezone":"America/Argentina/Salta",
    "iso:country":"AR",
    "wof:name":"San Pedro",
    "wof:placetype":"locality"
},
  "geometry": {"coordinates":[-65.11667,-22.61667000000001],"type":"Point"}
}