{
  "type": "Feature",
  "properties": {
    "gn:admin1_code":"1.0",
    "gn:admin2_code":"6875.0",
    "gn:asciiname":"Nicolas Levalle",
    "gn:country_code":"AR",
    "gn:dem":41,
    "gn:feature_class":"P",
    "gn:feature_code":"PPL",
    "gn:name":"Nicol\u00e1s Levalle",
    "gn:population":0,
    "gn:timezone":"America/Argentina/Buenos_Aires",
    "iso:country":"AR",
    "wof:name":"Nicolas Levalle",
    "wof:placetype":"locality"
},
  "geometry": {"coordinates":[-62.87748000000001,-38.85099],"type":"Point"}
}