{
  "type": "Feature",
  "properties": {
    "gn:admin1_code":"5.0",
    "gn:admin2_code":"14028.0",
    "gn:asciiname":"Pichanas",
    "gn:country_code":"AR",
    "gn:dem":434,
    "gn:feature_class":"P",
    "gn:feature_code":"PPL",
    "gn:name":"Pichanas",
    "gn:population":0,
    "gn:timezone":"America/Argentina/Cordoba",
    "iso:country":"AR",
    "wof:name":"Pichanas",
    "wof:placetype":"locality"
},
  "geometry": {"coordinates":[-65.16163,-30.8124],"type":"Point"}
}