{
  "type": "Feature",
  "properties": {
    "gn:admin1_code":"10",
    "gn:admin2_code":"38007.0",
    "gn:asciiname":"Agua Chica",
    "gn:country_code":"AR",
    "gn:dem":3616,
    "gn:feature_class":"P",
    "gn:feature_code":"PPL",
    "gn:name":"Agua Chica",
    "gn:population":0,
    "gn:timezone":"America/Argentina/Jujuy",
    "iso:country":"AR",
    "wof:name":"Agua Chica",
    "wof:placetype":"locality"
},
  "geometry": {"coordinates":[-65.74006,-22.93579],"type":"Point"}
}