{
  "type": "Feature",
  "properties": {
    "gn:admin1_code":"5.0",
    "gn:admin2_code":"14175.0",
    "gn:asciiname":"El Mistolar",
    "gn:country_code":"AR",
    "gn:dem":69,
    "gn:feature_class":"P",
    "gn:feature_code":"PPL",
    "gn:name":"El Mistolar",
    "gn:population":0,
    "gn:timezone":"America/Argentina/Cordoba",
    "iso:country":"AR",
    "wof:name":"El Mistolar",
    "wof:placetype":"locality"
},
  "geometry": {"coordinates":[-62.86666999999999,-30.58333],"type":"Point"}
}