{
  "type": "Feature",
  "properties": {
    "gn:admin1_code":"13",
    "gn:admin2_code":"50077.0",
    "gn:asciiname":"Aguada del Toro",
    "gn:country_code":"AR",
    "gn:dem":1004,
    "gn:feature_class":"P",
    "gn:feature_code":"PPL",
    "gn:name":"Aguada del Toro",
    "gn:population":0,
    "gn:timezone":"America/Argentina/Mendoza",
    "iso:country":"AR",
    "wof:name":"Aguada del Toro",
    "wof:placetype":"locality"
},
  "geometry": {"coordinates":[-68.54961,-36.64242],"type":"Point"}
}