{
  "type": "Feature",
  "properties": {
    "gn:admin1_code":"1.0",
    "gn:admin2_code":"6511.0",
    "gn:asciiname":"Monsalvo",
    "gn:country_code":"AR",
    "gn:dem":7,
    "gn:feature_class":"P",
    "gn:feature_code":"PPL",
    "gn:name":"Monsalvo",
    "gn:population":0,
    "gn:timezone":"America/Argentina/Buenos_Aires",
    "iso:country":"AR",
    "wof:name":"Monsalvo",
    "wof:placetype":"locality"
},
  "geometry": {"coordinates":[-57.35,-36.86667],"type":"Point"}
}