{
  "type": "Feature",
  "properties": {
    "gn:admin1_code":"17",
    "gn:admin2_code":"66133.0",
    "gn:asciiname":"Coronel Juan Sola",
    "gn:cc2":"AR",
    "gn:country_code":"AR",
    "gn:dem":223,
    "gn:feature_class":"P",
    "gn:feature_code":"PPL",
    "gn:name":"Coronel Juan Sol\u00e1",
    "gn:population":0,
    "gn:timezone":"America/Argentina/Salta",
    "iso:country":"AR",
    "name:ceb_x_preferred":[
        "Coronel Juan Sol\u00e1"
    ],
    "name:spa_x_preferred":[
        "Coronel Juan Sol\u00e1"
    ],
    "name:swe_x_preferred":[
        "Coronel Juan Sol\u00e1"
    ],
    "name:und_x_variant":[
        "Morillo",
        "Juan Sol\u00e1",
        "Morrillo",
        "Coronel Juan Sol\u00e1 Morillo"
    ],
    "wof:name":"Coronel Juan Sola",
    "wof:placetype":"locality"
},
  "geometry": {"coordinates":[-62.88333000000001,-23.46667],"type":"Point"}
}