{
  "type": "Feature",
  "properties": {
    "iso:country":"AR",
    "name:ceb_x_preferred":[
        "San Agust\u00edn"
    ],
    "name:eng_x_preferred":[
        "San Agust\u00edn"
    ],
    "name:fra_x_preferred":[
        "San Agust\u00edn"
    ],
    "name:ita_x_preferred":[
        "San Agust\u00edn"
    ],
    "name:nld_x_preferred":[
        "San Agust\u00edn"
    ],
    "name:por_x_preferred":[
        "San Agust\u00edn"
    ],
    "name:rus_x_preferred":[
        "\u0421\u0430\u043d-\u0410\u0433\u0443\u0441\u0442\u0438\u043d"
    ],
    "name:spa_x_preferred":[
        "San Agust\u00edn"
    ],
    "name:swe_x_preferred":[
        "San Agust\u00edn"
    ],
    "name:tur_x_preferred":[
        "San Agust\u00edn"
    ],
    "name:ukr_x_preferred":[
        "\u0421\u0430\u043d-\u0410\u0433\u0443\u0441\u0442\u0456\u043d"
    ],
    "name:zho_x_preferred":[
        "\u8056\u5967\u65af\u6c40"
    ],
    "qs:gn_country":"AR",
    "qs:gn_fcode":"PPL",
    "qs:gn_pop":2870,
    "qs:name":"San Agust\u00edn",
    "qs:name_adm0":"Argentina",
    "qs:name_adm1":"C\u00f3rdoba",
    "qs:photos":30,
    "qs:photos_1k":6,
    "qs:photos_9k":1,
    "qs:photos_9r":2,
    "qs:photos_all":30,
    "qs:photos_sr":2,
    "qs:placetype":"Town",
    "qs:pop_sr":"4",
    "qs:woe_adm0":23424747,
    "wd:wordcount":69,
    "wof:name":"San Agust\u00edn",
    "wof:placetype":"locality",
    "wof:population":2870
},
  "geometry": {"coordinates":[-64.374,-31.97681],"type":"Point"}
}