{
  "type": "Feature",
  "properties": {
    "gn:admin1_code":"5.0",
    "gn:admin2_code":"14035.0",
    "gn:asciiname":"Los Alfalfares",
    "gn:country_code":"AR",
    "gn:dem":233,
    "gn:feature_class":"P",
    "gn:feature_code":"PPL",
    "gn:name":"Los Alfalfares",
    "gn:population":0,
    "gn:timezone":"America/Argentina/Cordoba",
    "iso:country":"AR",
    "wof:name":"Los Alfalfares",
    "wof:placetype":"locality"
},
  "geometry": {"coordinates":[-64.71793000000001,-34.80929],"type":"Point"}
}