{
  "type": "Feature",
  "properties": {
    "gn:admin1_code":"13.0",
    "gn:admin2_code":"50091.0",
    "gn:asciiname":"Pareditas",
    "gn:country_code":"AR",
    "gn:dem":1075,
    "gn:feature_class":"P",
    "gn:feature_code":"PPL",
    "gn:name":"Pareditas",
    "gn:population":0,
    "gn:timezone":"America/Argentina/Mendoza",
    "iso:country":"AR",
    "wof:name":"Pareditas",
    "wof:placetype":"locality"
},
  "geometry": {"coordinates":[-69.0784,-33.94107],"type":"Point"}
}