{
  "type": "Feature",
  "properties": {
    "gn:admin1_code":"24",
    "gn:admin2_code":"90077.0",
    "gn:asciiname":"Cebil Solo",
    "gn:country_code":"AR",
    "gn:dem":506,
    "gn:feature_class":"P",
    "gn:feature_code":"PPL",
    "gn:name":"Cebil Solo",
    "gn:population":0,
    "gn:timezone":"America/Argentina/Tucuman",
    "iso:country":"AR",
    "name:und_x_variant":[
        "Sebil Solo",
        "Cebil Solo"
    ],
    "wof:name":"Cebil Solo",
    "wof:placetype":"locality"
},
  "geometry": {"coordinates":[-65.74045,-27.36795],"type":"Point"}
}