{
  "type": "Feature",
  "properties": {
    "gn:admin1_code":"14.0",
    "gn:admin2_code":"54056.0",
    "gn:asciiname":"Fracran",
    "gn:country_code":"AR",
    "gn:dem":602,
    "gn:feature_class":"P",
    "gn:feature_code":"PPL",
    "gn:name":"Fracr\u00e1n",
    "gn:population":0,
    "gn:timezone":"America/Argentina/Cordoba",
    "iso:country":"AR",
    "name:und_x_variant":[
        "Fracrau",
        "Fracr\u00e1n"
    ],
    "wof:name":"Fracran",
    "wof:placetype":"locality"
},
  "geometry": {"coordinates":[-54.28388,-26.73555],"type":"Point"}
}