{
  "type": "Feature",
  "properties": {
    "gn:admin1_code":"1.0",
    "gn:admin2_code":"6861.0",
    "gn:asciiname":"Florida",
    "gn:country_code":"AR",
    "gn:dem":27,
    "gn:feature_class":"P",
    "gn:feature_code":"PPL",
    "gn:name":"Florida",
    "gn:population":0,
    "gn:timezone":"America/Argentina/Buenos_Aires",
    "iso:country":"AR",
    "name:heb_x_preferred":[
        "\u05e4\u05dc\u05d5\u05e8\u05d9\u05d3\u05d4"
    ],
    "name:hun_x_preferred":[
        "Florida"
    ],
    "wof:name":"Florida",
    "wof:placetype":"locality"
},
  "geometry": {"coordinates":[-58.49078,-34.53258],"type":"Point"}
}