{
  "type": "Feature",
  "properties": {
    "gn:admin1_code":"1.0",
    "gn:admin2_code":"6861.0",
    "gn:asciiname":"Florida",
    "gn:country_code":"AR",
    "gn:dem":27,
    "gn:feature_class":"P",
    "gn:feature_code":"PPL",
    "gn:name":"Florida",
    "gn:population":0,
    "gn:timezone":"America/Argentina/Buenos_Aires",
    "iso:country":"AR",
    "wof:name":"Florida",
    "wof:placetype":"locality"
},
  "geometry": {"coordinates":[-58.49078000000001,-34.53258],"type":"Point"}
}