{
  "type": "Feature",
  "properties": {
    "gn:admin1_code":"17",
    "gn:admin2_code":"66133.0",
    "gn:asciiname":"Aguas Muertas",
    "gn:country_code":"AR",
    "gn:dem":202,
    "gn:feature_class":"P",
    "gn:feature_code":"PPL",
    "gn:name":"Aguas Muertas",
    "gn:population":0,
    "gn:timezone":"America/Argentina/Salta",
    "iso:country":"AR",
    "wof:name":"Aguas Muertas",
    "wof:placetype":"locality"
},
  "geometry": {"coordinates":[-62.67694,-24.22154],"type":"Point"}
}