{
  "type": "Feature",
  "properties": {
    "iso:country":"AR",
    "name:ceb_x_preferred":[
        "La Mendieta"
    ],
    "name:dut_x_preferred":[
        "La Mendieta"
    ],
    "name:eng_x_preferred":[
        "La Mendieta"
    ],
    "name:fre_x_preferred":[
        "La Mendieta"
    ],
    "name:ita_x_preferred":[
        "La Mendieta"
    ],
    "name:spa_x_preferred":[
        "La Mendieta"
    ],
    "name:swe_x_preferred":[
        "La Mendieta"
    ],
    "name:ukr_x_preferred":[
        "\u041b\u0430-\u041c\u0435\u043d\u0434\u044c\u0454\u0442\u0430"
    ],
    "name:urd_x_preferred":[
        "\u0644\u0627 \u0645\u06cc\u0646\u0688\u06cc\u0679\u0627"
    ],
    "qs:gn_country":"AR",
    "qs:gn_fcode":"PPL",
    "qs:gn_pop":3812,
    "qs:name":"La Mendieta",
    "qs:name_adm0":"Argentina",
    "qs:name_adm1":"Jujuy",
    "qs:photos":0,
    "qs:photos_1k":0,
    "qs:photos_9k":1,
    "qs:photos_9r":1,
    "qs:photos_all":1,
    "qs:photos_sr":0,
    "qs:placetype":"Town",
    "qs:pop_sr":"6",
    "qs:woe_adm0":23424747,
    "wd:wordcount":33,
    "wof:name":"La Mendieta",
    "wof:placetype":"locality",
    "wof:population":3812
},
  "geometry": {"coordinates":[-64.96377,-24.31187],"type":"Point"}
}