{
  "type": "Feature",
  "properties": {
    "gn:admin1_code":"15.0",
    "gn:admin2_code":"58084.0",
    "gn:asciiname":"Ranquilon",
    "gn:country_code":"AR",
    "gn:dem":1268,
    "gn:feature_class":"P",
    "gn:feature_code":"PPL",
    "gn:name":"Ranquil\u00f3n",
    "gn:population":0,
    "gn:timezone":"America/Argentina/Salta",
    "iso:country":"AR",
    "wof:name":"Ranquilon",
    "wof:placetype":"locality"
},
  "geometry": {"coordinates":[-70.51863,-37.77256],"type":"Point"}
}