{
  "type": "Feature",
  "properties": {
    "gn:country":"AR",
    "gn:fcode":"PPL",
    "gn:population":28756,
    "iso:country":"AR",
    "name:ceb_x_preferred":[
        "Gobernador Ingeniero Valent\u00edn Virasoro"
    ],
    "name:deu_x_preferred":[
        "Gobernador Virasoro"
    ],
    "name:eng_x_preferred":[
        "Gobernador Virasoro"
    ],
    "name:fra_x_preferred":[
        "Gobernador Virasoro"
    ],
    "name:nld_x_preferred":[
        "Gobernador Virasoro"
    ],
    "name:pol_x_preferred":[
        "Gobernador Virasoro"
    ],
    "name:spa_x_preferred":[
        "Gobernador Virasoro"
    ],
    "name:swe_x_preferred":[
        "Gobernador Ingeniero Valent\u00edn Virasoro"
    ],
    "name:ukr_x_preferred":[
        "\u0413\u043e\u0431\u0435\u0440\u043d\u0430\u0434\u043e\u0440-\u0412\u0456\u0440\u0430\u0441\u043e\u0440\u043e"
    ],
    "name:und_x_variant":[
        "Vuelta del Omb\u00fa"
    ],
    "qs:name":"Gobernador Ingeniero Valent\u00edn Virasoro",
    "qs:photos_9r":0,
    "qs:photos_sr":0,
    "qs:pop_sr":"7",
    "wof:name":"Gobernador Ingeniero Valent\u00edn Virasoro",
    "wof:placetype":"locality",
    "wof:population":28756
},
  "geometry": {"coordinates":[-56.03333,-28.05],"type":"Point"}
}