{
  "type": "Feature",
  "properties": {
    "iso:country":"AR",
    "qs:gn_country":"AR",
    "qs:gn_fcode":"PPL",
    "qs:gn_pop":6411,
    "qs:name":"Salsipuedes",
    "qs:name_adm0":"Argentina",
    "qs:name_adm1":"C\u00f3rdoba",
    "qs:photos":38,
    "qs:photos_1k":8,
    "qs:photos_9k":1,
    "qs:photos_9r":2,
    "qs:photos_all":38,
    "qs:photos_sr":2,
    "qs:placetype":"Town",
    "qs:pop_sr":"5",
    "qs:woe_adm0":23424747,
    "wof:name":"Salsipuedes",
    "wof:placetype":"locality",
    "wof:population":6411
},
  "geometry": {"coordinates":[-64.29589,-31.13724],"type":"Point"}
}