{
  "type": "Feature",
  "properties": {
    "gn:admin1_code":"6.0",
    "gn:admin2_code":"18098.0",
    "gn:asciiname":"Manantiales",
    "gn:country_code":"AR",
    "gn:dem":79,
    "gn:feature_class":"P",
    "gn:feature_code":"PPL",
    "gn:name":"Manantiales",
    "gn:population":0,
    "gn:timezone":"America/Argentina/Cordoba",
    "iso:country":"AR",
    "name:ceb_x_preferred":[
        "Manantiales"
    ],
    "name:deu_x_preferred":[
        "Manantiales"
    ],
    "name:spa_x_preferred":[
        "Manantiales"
    ],
    "name:swe_x_preferred":[
        "Manantiales"
    ],
    "wof:name":"Manantiales",
    "wof:placetype":"locality"
},
  "geometry": {"coordinates":[-58.12103000000001,-27.94634000000001],"type":"Point"}
}