{
  "type": "Feature",
  "properties": {
    "iso:country":"AR",
    "name:fra_x_preferred":[
        "Carlos Tejedor"
    ],
    "name:hun_x_preferred":[
        "Carlos Tejedor partido"
    ],
    "name:ita_x_preferred":[
        "Partido di Carlos Tejedor"
    ],
    "name:nld_x_preferred":[
        "Carlos Tejedor"
    ],
    "name:por_x_preferred":[
        "Carlos Tejedor"
    ],
    "name:spa_x_preferred":[
        "Partido de Carlos Tejedor"
    ],
    "name:unk_x_variant":[
        "Tejedor"
    ],
    "qs:gn_country":"AR",
    "qs:gn_fcode":"PPL",
    "qs:gn_pop":0,
    "qs:name":"Carlos Tejedor",
    "qs:name_adm0":"Argentina",
    "qs:name_adm1":"Buenos Aires",
    "qs:photos":0,
    "qs:photos_1k":0,
    "qs:photos_9k":1,
    "qs:photos_9r":1,
    "qs:photos_all":11,
    "qs:photos_sr":0,
    "qs:placetype":"Town",
    "qs:pop_sr":"0",
    "qs:woe_adm0":23424747,
    "wd:wordcount":50,
    "wof:name":"Carlos Tejedor",
    "wof:placetype":"locality"
},
  "geometry": {"coordinates":[-62.42146,-35.39265],"type":"Point"}
}