{
  "type": "Feature",
  "properties": {
    "gn:admin1_code":"1.0",
    "gn:admin2_code":"6466.0",
    "gn:asciiname":"Monasterio",
    "gn:country_code":"AR",
    "gn:dem":12,
    "gn:feature_class":"P",
    "gn:feature_code":"PPL",
    "gn:name":"Monasterio",
    "gn:population":0,
    "gn:timezone":"America/Argentina/Buenos_Aires",
    "iso:country":"AR",
    "name:arg_x_preferred":[
        "Monasterio"
    ],
    "name:cat_x_preferred":[
        "Monasterio"
    ],
    "name:epo_x_preferred":[
        "Monasterio"
    ],
    "name:eus_x_preferred":[
        "Monasterio"
    ],
    "name:fra_x_preferred":[
        "Monasterio"
    ],
    "name:hun_x_preferred":[
        "Monasterio"
    ],
    "name:ina_x_preferred":[
        "Monasterio"
    ],
    "name:ita_x_preferred":[
        "Monasterio"
    ],
    "name:kaz_x_preferred":[
        "\u041c\u043e\u043d\u0430\u0441\u0442\u0435\u0440\u0438\u043e"
    ],
    "name:msa_x_preferred":[
        "Monasterio"
    ],
    "name:nld_x_preferred":[
        "Monasterio"
    ],
    "name:pol_x_preferred":[
        "Monasterio"
    ],
    "name:por_x_preferred":[
        "Monasterio"
    ],
    "name:rus_x_preferred":[
        "\u041c\u043e\u043d\u0430\u0441\u0442\u0435\u0440\u0438\u043e"
    ],
    "name:spa_x_preferred":[
        "Monasterio"
    ],
    "name:ukr_x_preferred":[
        "\u041c\u043e\u043d\u0430\u0441\u0442\u0435\u0440\u0456\u043e"
    ],
    "name:vie_x_preferred":[
        "Monasterio"
    ],
    "name:war_x_preferred":[
        "Monasterio"
    ],
    "name:zho_x_preferred":[
        "\u83ab\u7eb3\u65af\u7279\u91cc\u5965"
    ],
    "wof:name":"Monasterio",
    "wof:placetype":"locality"
},
  "geometry": {"coordinates":[-57.92283000000001,-35.76374000000001],"type":"Point"}
}