{
  "type": "Feature",
  "properties": {
    "gn:admin1_code":"1.0",
    "gn:admin2_code":"6466.0",
    "gn:asciiname":"Monasterio",
    "gn:country_code":"AR",
    "gn:dem":12,
    "gn:feature_class":"P",
    "gn:feature_code":"PPL",
    "gn:name":"Monasterio",
    "gn:population":0,
    "gn:timezone":"America/Argentina/Buenos_Aires",
    "iso:country":"AR",
    "wof:name":"Monasterio",
    "wof:placetype":"locality"
},
  "geometry": {"coordinates":[-57.92283000000001,-35.76374000000001],"type":"Point"}
}