{
  "type": "Feature",
  "properties": {
    "gn:admin1_code":"1.0",
    "gn:admin2_code":"6602.0",
    "gn:asciiname":"Jose B. Casas",
    "gn:country_code":"AR",
    "gn:dem":19,
    "gn:feature_class":"P",
    "gn:feature_code":"PPL",
    "gn:name":"Jos\u00e9 B. Cas\u00e1s",
    "gn:population":0,
    "gn:timezone":"America/Argentina/Buenos_Aires",
    "iso:country":"AR",
    "name:und_x_variant":[
        "Jos\u00e9 V. Casas",
        "Jos\u00e9 B. Cas\u00e1s"
    ],
    "wof:name":"Jose B. Casas",
    "wof:placetype":"locality"
},
  "geometry": {"coordinates":[-62.54441,-40.43516],"type":"Point"}
}