{
  "type": "Feature",
  "properties": {
    "gn:admin1_code":"1.0",
    "gn:admin2_code":"6588.0",
    "gn:asciiname":"French",
    "gn:country_code":"AR",
    "gn:dem":79,
    "gn:feature_class":"P",
    "gn:feature_code":"PPL",
    "gn:name":"French",
    "gn:population":0,
    "gn:timezone":"America/Argentina/Buenos_Aires",
    "iso:country":"AR",
    "name:ben_x_preferred":[
        "\u09ab\u09b0\u09be\u09b8\u09bf"
    ],
    "name:bih_x_preferred":[
        "\u092b\u094d\u0930\u093e\u0902\u0938\u0940\u0938\u0940"
    ],
    "name:bul_x_preferred":[
        "\u0424\u0440\u0435\u043d\u0441\u043a\u0438"
    ],
    "name:deu_x_preferred":[
        "French"
    ],
    "name:fas_x_preferred":[
        "\u0641\u0631\u0627\u0646\u0633\u0648\u06cc"
    ],
    "name:fra_x_preferred":[
        "French"
    ],
    "name:heb_x_preferred":[
        "\u05e4\u05e8\u05e0\u05e5'"
    ],
    "name:ita_x_preferred":[
        "French"
    ],
    "name:jpn_x_preferred":[
        "\u30d5\u30ec\u30f3\u30c1\u30fb\u30ea\u30d0\u30fc"
    ],
    "name:jpn_x_variant":[
        "\u30d5\u30ec\u30f3\u30c1"
    ],
    "name:kor_x_preferred":[
        "\ud504\ub80c\uce58"
    ],
    "name:nld_x_preferred":[
        "French"
    ],
    "name:pol_x_preferred":[
        "French"
    ],
    "name:por_x_preferred":[
        "French"
    ],
    "name:rus_x_preferred":[
        "\u0424\u0440\u0435\u043d\u0447"
    ],
    "name:sco_x_preferred":[
        "French"
    ],
    "name:spa_x_preferred":[
        "French"
    ],
    "name:srp_x_preferred":[
        "\u0424\u0440\u0430\u043d\u0446\u0443\u0441\u043a\u0438"
    ],
    "name:tur_x_preferred":[
        "French"
    ],
    "name:ukr_x_preferred":[
        "\u0424\u0440\u0435\u043d\u0447"
    ],
    "name:urd_x_preferred":[
        "\u0641\u0631\u0646\u0686"
    ],
    "name:vie_x_preferred":[
        "S\u00f4ng French"
    ],
    "name:zho_cn_x_preferred":[
        "\u5f17\u4f26\u5947\u6cb3"
    ],
    "name:zho_tw_x_preferred":[
        "\u6cd5\u862d\u897f\u6cb3"
    ],
    "wof:name":"French",
    "wof:placetype":"locality"
},
  "geometry": {"coordinates":[-60.9993,-35.51796],"type":"Point"}
}