{
  "type": "Feature",
  "properties": {
    "gn:admin1_code":"1.0",
    "gn:admin2_code":"6588.0",
    "gn:asciiname":"French",
    "gn:country_code":"AR",
    "gn:dem":79,
    "gn:feature_class":"P",
    "gn:feature_code":"PPL",
    "gn:name":"French",
    "gn:population":0,
    "gn:timezone":"America/Argentina/Buenos_Aires",
    "iso:country":"AR",
    "wof:name":"French",
    "wof:placetype":"locality"
},
  "geometry": {"coordinates":[-60.9993,-35.51795999999999],"type":"Point"}
}