{
  "type": "Feature",
  "properties": {
    "gn:admin1_code":"22.0",
    "gn:admin2_code":"86028.0",
    "gn:asciiname":"Percas",
    "gn:country_code":"AR",
    "gn:dem":121,
    "gn:feature_class":"P",
    "gn:feature_code":"PPL",
    "gn:name":"Percas",
    "gn:population":0,
    "gn:timezone":"America/Argentina/Cordoba",
    "iso:country":"AR",
    "wof:name":"Percas",
    "wof:placetype":"locality"
},
  "geometry": {"coordinates":[-63.55789,-28.37141],"type":"Point"}
}