{
  "type": "Feature",
  "properties": {
    "gn:admin1_code":"18.0",
    "gn:admin2_code":"70084.0",
    "gn:asciiname":"La Bebida",
    "gn:country_code":"AR",
    "gn:dem":702,
    "gn:feature_class":"P",
    "gn:feature_code":"PPL",
    "gn:name":"La Bebida",
    "gn:population":0,
    "gn:timezone":"America/Argentina/San_Juan",
    "iso:country":"AR",
    "wof:name":"La Bebida",
    "wof:placetype":"locality"
},
  "geometry": {"coordinates":[-68.61667,-31.53333],"type":"Point"}
}