{
  "type": "Feature",
  "properties": {
    "gn:admin1_code":"12",
    "gn:admin2_code":"46105.0",
    "gn:asciiname":"Amana",
    "gn:country_code":"AR",
    "gn:dem":1246,
    "gn:feature_class":"P",
    "gn:feature_code":"PPL",
    "gn:name":"Aman\u00e1",
    "gn:population":0,
    "gn:timezone":"America/Argentina/La_Rioja",
    "iso:country":"AR",
    "name:ceb_x_preferred":[
        "Aman\u00e1"
    ],
    "name:fas_x_preferred":[
        "\u0627\u0645\u0627\u0646\u0627"
    ],
    "name:spa_x_preferred":[
        "Aman\u00e1"
    ],
    "name:swe_x_preferred":[
        "Aman\u00e1"
    ],
    "name:und_x_variant":[
        "Aman\u00e1"
    ],
    "wof:name":"Amana",
    "wof:placetype":"locality"
},
  "geometry": {"coordinates":[-67.50575000000001,-30.0564],"type":"Point"}
}