{
  "type": "Feature",
  "properties": {
    "gn:admin1_code":"17",
    "gn:admin2_code":"66056.0",
    "gn:asciiname":"Coronel Cornejo",
    "gn:country_code":"AR",
    "gn:dem":407,
    "gn:feature_class":"P",
    "gn:feature_code":"PPL",
    "gn:name":"Coronel Cornejo",
    "gn:population":0,
    "gn:timezone":"America/Argentina/Salta",
    "iso:country":"AR",
    "name:ceb_x_preferred":[
        "Coronel Cornejo"
    ],
    "name:spa_x_preferred":[
        "Coronel Cornejo"
    ],
    "name:swe_x_preferred":[
        "Coronel Cornejo"
    ],
    "wof:name":"Coronel Cornejo",
    "wof:placetype":"locality"
},
  "geometry": {"coordinates":[-63.82326,-22.73479],"type":"Point"}
}