{
  "type": "Feature",
  "properties": {
    "gn:admin1_code":"16",
    "gn:admin2_code":"62042.0",
    "gn:asciiname":"Contraalmirante Martin Guerrico",
    "gn:cc2":"AR",
    "gn:country_code":"AR",
    "gn:dem":246,
    "gn:feature_class":"P",
    "gn:feature_code":"PPL",
    "gn:name":"Contraalmirante Mart\u00edn Guerrico",
    "gn:population":0,
    "gn:timezone":"America/Argentina/Salta",
    "iso:country":"AR",
    "name:und_x_variant":[
        "M. Guerrico",
        "Contralmirante Mart\u00edn Guerrico",
        "Mart\u00edn Guerrico",
        "Contraalmirante Mart\u00edn Guerrico"
    ],
    "wof:name":"Contraalmirante Martin Guerrico",
    "wof:placetype":"locality"
},
  "geometry": {"coordinates":[-67.73333000000001,-39.01667],"type":"Point"}
}