{
  "type": "Feature",
  "properties": {
    "gn:admin1_code":"22",
    "gn:admin2_code":"86147.0",
    "gn:asciiname":"Bahoma",
    "gn:country_code":"AR",
    "gn:dem":304,
    "gn:feature_class":"P",
    "gn:feature_code":"PPL",
    "gn:name":"Bahoma",
    "gn:population":0,
    "gn:timezone":"America/Argentina/Cordoba",
    "iso:country":"AR",
    "wof:name":"Bahoma",
    "wof:placetype":"locality"
},
  "geometry": {"coordinates":[-64.85677,-27.62662000000001],"type":"Point"}
}