{
  "type": "Feature",
  "properties": {
    "gn:admin1_code":"19.0",
    "gn:admin2_code":"74056.0",
    "gn:asciiname":"San Martin del Alto Negro",
    "gn:country_code":"AR",
    "gn:dem":535,
    "gn:feature_class":"P",
    "gn:feature_code":"PPL",
    "gn:name":"San Mart\u00edn del Alto Negro",
    "gn:population":0,
    "gn:timezone":"America/Argentina/San_Luis",
    "iso:country":"AR",
    "wof:name":"San Martin del Alto Negro",
    "wof:placetype":"locality"
},
  "geometry": {"coordinates":[-66.08797,-34.14219],"type":"Point"}
}