{
  "type": "Feature",
  "properties": {
    "gn:admin1_code":"17.0",
    "gn:admin2_code":"66049.0",
    "gn:asciiname":"Palomitas",
    "gn:country_code":"AR",
    "gn:dem":883,
    "gn:feature_class":"P",
    "gn:feature_code":"PPL",
    "gn:name":"Palomitas",
    "gn:population":0,
    "gn:timezone":"America/Argentina/Salta",
    "iso:country":"AR",
    "wof:name":"Palomitas",
    "wof:placetype":"locality"
},
  "geometry": {"coordinates":[-64.97534,-24.90198],"type":"Point"}
}