{
  "type": "Feature",
  "properties": {
    "gn:admin1_code":"24.0",
    "gn:admin2_code":"90112.0",
    "gn:asciiname":"Vipos",
    "gn:country_code":"AR",
    "gn:dem":782,
    "gn:feature_class":"P",
    "gn:feature_code":"PPL",
    "gn:name":"Vipos",
    "gn:population":0,
    "gn:timezone":"America/Argentina/Tucuman",
    "iso:country":"AR",
    "wof:name":"Vipos",
    "wof:placetype":"locality"
},
  "geometry": {"coordinates":[-65.34581999999999,-26.48072],"type":"Point"}
}