{
  "type": "Feature",
  "properties": {
    "gn:admin1_code":"5.0",
    "gn:admin2_code":"14133.0",
    "gn:asciiname":"Los Manantiales",
    "gn:country_code":"AR",
    "gn:dem":776,
    "gn:feature_class":"P",
    "gn:feature_code":"PPL",
    "gn:name":"Los Manantiales",
    "gn:population":0,
    "gn:timezone":"America/Argentina/Cordoba",
    "iso:country":"AR",
    "wof:name":"Los Manantiales",
    "wof:placetype":"locality"
},
  "geometry": {"coordinates":[-65.04167,-32.23581],"type":"Point"}
}