{
  "type": "Feature",
  "properties": {
    "gn:country":"AR",
    "gn:fcode":"PPL",
    "gn:population":930,
    "iso:country":"AR",
    "name:ceb_x_preferred":[
        "Ataliva Roca"
    ],
    "name:eng_x_preferred":[
        "Ataliva Roca"
    ],
    "name:nld_x_preferred":[
        "Ataliva Roca"
    ],
    "name:por_x_preferred":[
        "Ataliva Roca"
    ],
    "name:spa_x_preferred":[
        "Ataliva Roca"
    ],
    "name:swe_x_preferred":[
        "Ataliva Roca"
    ],
    "qs:name":"Ataliva Roca",
    "qs:photos_9r":0,
    "qs:photos_sr":0,
    "qs:pop_sr":"2",
    "wd:wordcount":85,
    "wof:name":"Ataliva Roca",
    "wof:placetype":"locality",
    "wof:population":930
},
  "geometry": {"coordinates":[-64.28333000000001,-37.01667],"type":"Point"}
}