{
  "type": "Feature",
  "properties": {
    "gn:admin1_code":"8.0",
    "gn:admin2_code":"30091.0",
    "gn:asciiname":"Altamirano Sur",
    "gn:country_code":"AR",
    "gn:dem":43,
    "gn:feature_class":"P",
    "gn:feature_code":"PPL",
    "gn:name":"Altamirano Sur",
    "gn:population":0,
    "gn:timezone":"America/Argentina/Cordoba",
    "iso:country":"AR",
    "name:und_x_variant":[
        "Altamirano Sud",
        "Altamirano Sur"
    ],
    "wof:name":"Altamirano Sur",
    "wof:placetype":"locality"
},
  "geometry": {"coordinates":[-59.17862,-32.08949],"type":"Point"}
}