{
  "type": "Feature",
  "properties": {
    "iso:country":"AR",
    "qs:gn_country":"AR",
    "qs:gn_fcode":"PPL",
    "qs:gn_pop":0,
    "qs:name":"Villalonga",
    "qs:name_adm0":"Argentina",
    "qs:name_adm1":"Buenos Aires",
    "qs:photos":0,
    "qs:photos_1k":0,
    "qs:photos_9k":1,
    "qs:photos_9r":1,
    "qs:photos_all":7,
    "qs:photos_sr":0,
    "qs:placetype":"Town",
    "qs:pop_sr":"0",
    "qs:woe_adm0":23424747,
    "wd:wordcount":26,
    "wof:name":"Villalonga",
    "wof:placetype":"locality"
},
  "geometry": {"coordinates":[-62.61782,-39.91614],"type":"Point"}
}