{
  "type": "Feature",
  "properties": {
    "iso:country":"AR",
    "name:arg_x_preferred":[
        "Vilallonga"
    ],
    "name:cat_x_preferred":[
        "Vilallonga"
    ],
    "name:ceb_x_preferred":[
        "Villalonga"
    ],
    "name:deu_x_preferred":[
        "Villalonga"
    ],
    "name:eng_x_preferred":[
        "Villalonga"
    ],
    "name:eus_x_preferred":[
        "Vilallonga"
    ],
    "name:fra_x_preferred":[
        "Villalonga"
    ],
    "name:fra_x_variant":[
        "Vilallonga"
    ],
    "name:hun_x_preferred":[
        "Villalonga"
    ],
    "name:hye_x_preferred":[
        "\u054e\u056b\u056c\u0575\u0561\u056c\u0578\u0576\u0563\u0561"
    ],
    "name:ita_x_preferred":[
        "Villalonga"
    ],
    "name:nan_x_preferred":[
        "Villalonga"
    ],
    "name:nld_x_preferred":[
        "Villalonga"
    ],
    "name:oci_x_preferred":[
        "Villalonga"
    ],
    "name:pol_x_preferred":[
        "Villalonga"
    ],
    "name:por_x_preferred":[
        "Villalonga"
    ],
    "name:rus_x_preferred":[
        "\u0412\u0438\u043b\u044c\u044f\u043b\u043e\u043d\u0433\u0430"
    ],
    "name:spa_x_preferred":[
        "Villalonga"
    ],
    "name:sqi_x_preferred":[
        "Villalonga"
    ],
    "name:swe_x_preferred":[
        "Villalonga"
    ],
    "name:ukr_x_preferred":[
        "\u0412\u0456\u043b\u044c\u044f\u043b\u043e\u043d\u0433\u0430"
    ],
    "name:war_x_preferred":[
        "Villalonga"
    ],
    "name:zho_x_preferred":[
        "\u6bd4\u5229\u4e9a\u9686\u52a0"
    ],
    "qs:gn_country":"AR",
    "qs:gn_fcode":"PPL",
    "qs:gn_pop":0,
    "qs:name":"Villalonga",
    "qs:name_adm0":"Argentina",
    "qs:name_adm1":"Buenos Aires",
    "qs:photos":0,
    "qs:photos_1k":0,
    "qs:photos_9k":1,
    "qs:photos_9r":1,
    "qs:photos_all":7,
    "qs:photos_sr":0,
    "qs:placetype":"Town",
    "qs:pop_sr":"0",
    "qs:woe_adm0":23424747,
    "wd:wordcount":26,
    "wof:name":"Villalonga",
    "wof:placetype":"locality"
},
  "geometry": {"coordinates":[-62.61782,-39.91614],"type":"Point"}
}