{
  "type": "Feature",
  "properties": {
    "gn:admin1_code":"22",
    "gn:admin2_code":"86084.0",
    "gn:asciiname":"Cerrillos",
    "gn:country_code":"AR",
    "gn:dem":388,
    "gn:feature_class":"P",
    "gn:feature_code":"PPL",
    "gn:name":"Cerrillos",
    "gn:population":0,
    "gn:timezone":"America/Argentina/Cordoba",
    "iso:country":"AR",
    "name:cat_x_preferred":[
        "Cerrillos"
    ],
    "name:ceb_x_preferred":[
        "Cerrillos"
    ],
    "name:deu_x_preferred":[
        "Cerrillos"
    ],
    "name:fra_x_preferred":[
        "Cerrillos"
    ],
    "name:nld_x_preferred":[
        "Cerrillos"
    ],
    "name:por_x_preferred":[
        "Cerrillos"
    ],
    "name:rus_x_preferred":[
        "\u0421\u0435\u0440\u0440\u0438\u043b\u044c\u043e\u0441"
    ],
    "name:spa_x_preferred":[
        "Cerrillos"
    ],
    "name:swe_x_preferred":[
        "Cerrillos"
    ],
    "wof:name":"Cerrillos",
    "wof:placetype":"locality"
},
  "geometry": {"coordinates":[-64.63531999999999,-28.06708],"type":"Point"}
}