{
  "type": "Feature",
  "properties": {
    "gn:admin1_code":"16.0",
    "gn:admin2_code":"62007.0",
    "gn:asciiname":"General Liborio Bernal",
    "gn:country_code":"AR",
    "gn:dem":64,
    "gn:feature_class":"P",
    "gn:feature_code":"PPL",
    "gn:name":"General Liborio Bernal",
    "gn:population":0,
    "gn:timezone":"America/Argentina/Salta",
    "iso:country":"AR",
    "wof:name":"General Liborio Bernal",
    "wof:placetype":"locality"
},
  "geometry": {"coordinates":[-63.65,-40.83333],"type":"Point"}
}